Workbook

Sheet Exec Summary
A1: Space Exploration Technologies Corp. (SpaceX) | $SPCX | Valuation Executive Summary
A2: ="Prepared: "&TEXT(TODAY(),"d-mmm-yyyy")&" | Source: SpaceX S-1 (Filed 20-May-2026) " -> Prepared: 24-Jun-2026 | Source: SpaceX S-1 (Filed 20-May-2026)
A4: INVESTMENT THESIS
A6: SpaceX is pursuing an IPO at $135/share, implying a fully diluted market cap of ~$1.75T. The company operates three segments:
A7: (1) Connectivity (Starlink) – satellite broadband, ~60% of FY2025 revenue, highest margin segment growing 50%+ YoY
A8: (2) Space (Launch + Starship) – launch services and government contracts, ~22% of revenue, steady growth anchored by Falcon 9 cadence
A9: (3) AI (X / xAI / Grok) – social media and AI compute infrastructure, ~17% of revenue, pre-profit but scaling rapidly
A11: Our 3-segment SOTP DCF analysis uses 20-year explicit forecasts per segment with comp-driven WACCs and terminal values.
A12: Two methodologies are applied: (1) Gordon Growth / EV-Revenue and (2) Exit Multiple / Gordon cross-check.
A14: VALUATION CONCLUSION
A16: Measure | B16: Method 1 ¹ | C16: Method 2 ² | D16: Average | G16: Notes
A17: Total Enterprise Value ($M) | B17: =SOTP!B12 -> 609915.35 | C17: =SOTP!C12 -> 410450.07 | D17: =SOTP!D12 -> 615495.19 | G17: ¹ Gordon Growth (Conn/Space) + EV/Revenue (AI)
A18: Equity Value ($M) | B18: =SOTP!B23 -> 692766.35 | C18: =SOTP!C23 -> 493301.07 | D18: =SOTP!D23 -> 698346.19 | G18: ² Exit Multiple (Conn/Space) + Gordon (AI cross-check)
A19: Implied Price / Share (fully diluted) | B19: =B18/SOTP!B29 -> 53.12218 | C19: =C18/SOTP!C29 -> 37.826936 | D19: =D18/SOTP!D29 -> 53.550049 | G19: Fully diluted: 12,960M shares (preferred conversion + xAI merger + RSUs + IPO)
A20: IPO Reference Price | B20: =Dashboard!B5 -> 154 | C20: =B20 -> 154 | D20: =B20 -> 154
A21: Upside / (Downside) to IPO | B21: =B19/B20-1 -> -0.65505078 | C21: =C19/C20-1 -> -0.75437055 | D21: =D19/D20-1 -> -0.65227241
A22: Shares Outstanding – Fully Diluted (M) | B22: =SOTP!B29 -> 13041
A24: SEGMENT VALUATION BREAKDOWN
A26: Segment | B26: Avg EV ($M) | C26: % of SOTP | D26: WACC | E26: Tg | G26: Primary Methodology
A27: Connectivity (Starlink) | B27: =SOTP!D9 -> 558405.91 | C27: =SOTP!E9 -> 0.90724658 | D27: =WACC!B42 -> 0.063906891 | E27: =WACC!C42 -> 0.03 | G27: Gordon Growth perpetuity + EV/EBITDA exit cross-check
A28: Space (Launch + Starship) | B28: =SOTP!D10 -> 52422.72 | C28: =SOTP!E10 -> 0.085171616 | D28: =WACC!B43 -> 0.068984004 | E28: =WACC!C43 -> 0.025 | G28: Gordon Growth perpetuity + EV/EBITDA exit cross-check
A29: AI (X / xAI / Grok) | B29: =SOTP!D11 -> 4666.5647 | C29: =SOTP!E11 -> 0.0075818052 | D29: =WACC!B44 -> 0.10385358 | E29: =WACC!C44 -> 0.035 | G29: EV/Revenue multiple (primary) – Gordon distorts on loss-making FCF
A30: Total SOTP | B30: =SOTP!D12 -> 615495.19 | C30: =SOTP!E12 -> 1
A32: KEY ASSUMPTIONS (Base Case)
A34: Item | B34: Connectivity | C34: Space | D34: AI | G34: Source
A35: Forecast Horizon | B35: 20 years | C35: 20 years | D35: 20 years | G35: DCF sheet assumptions
A36: WACC | B36: =WACC!B42 -> 0.063906891 | C36: =WACC!B43 -> 0.068984004 | D36: =WACC!B44 -> 0.10385358 | G36: Comp-driven; WACC sheet
A37: Terminal Growth Rate | B37: =WACC!C42 -> 0.03 | C37: =WACC!C43 -> 0.025 | D37: =WACC!C44 -> 0.035 | G37: WACC sheet
A38: Risk-Free Rate | B38: =WACC!B7 -> 0.0435 | G38: 10Y UST, Jun 2026
A39: Equity Risk Premium | B39: =WACC!B8 -> 0.055 | G39: Damodaran implied ERP, Jan 2026
A40: Tax Rate | B40: =WACC!B9 -> 0.21 | G40: US statutory; large NOL carryforwards
A42: FY2025 ACTUALS (S-1 Source)
A44: Metric | B44: FY2025 | C44: YoY | G44: Note
A45: Total Revenue ($M) | B45: =SOTP!D50 -> 18674 | C45: =SOTP!D50/SOTP!C50-1 -> 0.33242954 | G45: Consolidated – 3 segments
A46: Connectivity | B46: =SOTP!D51 -> 11387 | C46: =SOTP!D51/SOTP!C51-1 -> 0.49848664 | G46: 60.9% of total; 63% EBITDA margin
A47: Space | B47: =SOTP!D52 -> 4086 | C47: =SOTP!D52/SOTP!C52-1 -> 0.076396207 | G47: 21.9% of total; Falcon 9 cadence + Starship
A48: AI | B48: =SOTP!D53 -> 3201 | C48: =SOTP!D53/SOTP!C53-1 -> 0.22175573 | G48: 17.1% of total; X ads + xAI compute
A49: Net Income ($M) | B49: =SOTP!D56 -> -4937 | G49: AI segment losses dominate; R&D $8.6B
A50: Operating Cash Flow ($M) | B50: =SOTP!D55 -> 6785 | G50: Cash-generative despite heavy capex cycle
A51: Total Capex ($M) | B51: =SOTP!D54 -> -20737 | G51: AI infra $12.7B = 61% of total capex
A52: Connectivity EBITDA Margin | B52: =SOTP!D57 -> 0.62948977 | G52: Up from 46.2% in FY2024 – scale leverage
A54: KEY RISKS & SENSITIVITIES
A56: Sensitivity Range (SOTP, fully diluted):
A57: Method 1 (Gordon + EV/Rev): | B57: =B19 -> 53.12218 | G57: per share
A58: Method 2 (Exit Mult + Gordon): | B58: =C19 -> 37.826936 | G58: per share
A59: WACC sensitivity range (±2% Conn WACC): | B59: =TEXT(MIN(SOTP!C65:I71),"$#,##0")&" – "&TEXT(MAX(SOTP!C65:I71),"$#,##0") -> $48 – $101 | G59: per share (Method 1)
A61: Risk | G61: Impact | I61: Segment
A62: AI capex burn exceeds forecasts; xAI margin ramp delayed | G62: High – AI is 45% of avg SOTP EV | I62: AI
A63: Starlink subscriber growth stalls; enterprise adoption slower than modelled | G63: High – Conn is 46% of avg SOTP EV | I63: Connectivity
A64: Regulatory / spectrum risk; international market access restrictions | G64: Medium – affects both Conn & Space | I64: Conn / Space
A65: Method 1 vs Method 2 divergence ($184 vs $56) flags terminal-value sensitivity | G65: High – 3.3x range in implied price | I65: All
A66: Dual-class + Musk governance concentration; key-person dependence | G66: Medium – discount to intrinsic value | I66: All
A67: Starship development delays or cost overruns; launch cadence miss | G67: Medium – capex normalisation thesis | I67: Space
A69: MODEL MAP
A71: Sheet | G71: Purpose
A72: COVER | G72: Price input, valuation summary dashboard, scenario selector, upside/downside
A73: SOTP | G73: Sum-of-the-parts roll-up, EV bridge, implied share price, WACC sensitivity tables
A74: Conn DCF | G74: Connectivity (Starlink) 20-year segment DCF – IS, FCF, Gordon + exit multiple
A75: Space DCF | G75: Space (Launch + Starship) 20-year segment DCF – IS, FCF, Gordon + exit multiple
A76: AI DCF | G76: AI (X/xAI/Grok) 20-year segment DCF – IS, FCF, EV/Revenue primary + Gordon cross-check
A77: WACC | G77: Comp-driven betas, CAPM cost of equity, segment WACCs, capital structure
A78: Ratios | G78: Historical financial ratios – profitability, leverage, liquidity, efficiency
A79: Conn/Space/AI Comps | G79: Comparable company data for each segment – trading multiples, betas, benchmarking
A80: Actuals | G80: FY2023–FY2025 actual financials by segment (source: S-1)
A81: Historicals | G81: Extended historical data – balance sheet, cash flow, segment detail from S-1
A83: All financial data sourced from SpaceX S-1 (SEC EDGAR, filed 20-May-2026). Comparable company data from public filings.
A100: Property of Rifat Tahmid®™

Sheet Dashboard
A1: Space Exploration Technologies Corp. (SpaceX) | $SPCX | Sum-of-the-Parts DCF Valuation
A2: 3-Segment SOTP (Connectivity + Space + AI) | 20-Year Explicit DCF | S-1 Filed May 20, 2026 | $ in Millions (except per share)
A4: ① ENTER PRICE TO SEE UPSIDE / DOWNSIDE
A5: Current Share Price ($) | B5: 154 | C5: ← Enter the current trading price here
A7: ② VALUATION SUMMARY (Base Case)
B9: Gordon Growth | C9: Exit Multiple | D9: Average | H9: Note
A10: Total SOTP Enterprise Value ($M) | B10: =SOTP!B12 -> 609915.35 | C10: =SOTP!C12 -> 410450.07 | D10: =SOTP!D12 -> 615495.19
A11: (+) Net Cash (Cash − Total Debt) ($M) | B11: =SOTP!B18+SOTP!B19 -> -3149 | C11: =SOTP!C18+SOTP!C19 -> -3149 | D11: =SOTP!D18+SOTP!D19 -> -3149
A12: Connectivity Segment EV ($M) | B12: =SOTP!B9 -> 558405.91 | C12: =SOTP!C9 -> 340341.16 | D12: =SOTP!D9 -> 558405.91 | H12: =TEXT(D12/D10,"0%")&" of avg SOTP EV" -> 91% of avg SOTP EV
A13: Space Segment EV ($M) | B13: =SOTP!B10 -> 49217.277 | C13: =SOTP!C10 -> 59902.088 | D13: =SOTP!D10 -> 52422.72 | H13: =TEXT(D13/D10,"0%")&" of avg SOTP EV" -> 9% of avg SOTP EV
A14: AI Segment EV ($M) | B14: =SOTP!B11 -> 2292.1662 | C14: =SOTP!C11 -> 10206.828 | D14: =SOTP!D11 -> 4666.5647 | H14: =TEXT(D14/D10,"0%")&" of avg SOTP EV – wide range" -> 1% of avg SOTP EV – wide range
A15: Equity Value ($M) | B15: =SOTP!B23 -> 692766.35 | C15: =SOTP!C23 -> 493301.07 | D15: =SOTP!D23 -> 698346.19 | H15: After debt, cash, pref conversion
A17: Implied Share Price | B17: Gordon Growth | C17: Exit Multiple | D17: Average | H17: Shares Basis
A18: Basic – Common only (5,798M) | B18: =SOTP!B30 -> 119.48368 | C18: =SOTP!C30 -> 85.081247 | D18: =SOTP!D30 -> 120.44605 | H18: Understates: excludes converted pref + xAI shares
A19: Fully Diluted, Post-IPO (12,960M) | B19: =SOTP!B31 -> 53.12218 | C19: =SOTP!C31 -> 37.826936 | D19: =SOTP!D31 -> 53.550049 | H19: Reconciled to actual $135 IPO / $1.75T – primary metric
A21: ③ UPSIDE / (DOWNSIDE) vs. ENTERED PRICE (Fully-Diluted shares – primary)
B23: Gordon Growth | C23: Exit Multiple | D23: Average
A24: Our Implied Price (Fully-Diluted) | B24: =B19 -> 53.12218 | C24: =C19 -> 37.826936 | D24: =D19 -> 53.550049
A25: Current / IPO Price | B25: =IF(B5="","—",B5) -> 154 | C25: =IF(B5="","—",B5) -> 154 | D25: =IF(B5="","—",B5) -> 154
A26: Implied Upside / (Downside) | B26: =IF(B5="","← Enter price",(B19/B5)-1) -> -0.65505078 | C26: =IF(B5="","← Enter price",(C19/B5)-1) -> -0.75437055 | D26: =IF(B5="","← Enter price",(D19/B5)-1) -> -0.65227241
A28: ④ SCENARIO SELECTORS (1=Bear, 2=Base, 3=Bull – changes all 3 segment DCFs simultaneously)
A30: Segment | B30: Scenario (1/2/3) | C30: Selected | D30: WACC | E30: Terminal Growth (Base) | F30: Time-Varying WACC | G30: → Terminal
A31: Connectivity (Starlink) | B31: 2 | C31: =IF(B31=1,"◀ BEAR",IF(B31=2,"◀ BASE","◀ BULL")) -> ◀ BASE | D31: =WACC!B37 -> 0.063906891 | E31: =WACC!C42 -> 0.03 | F31: ='Conn DCF'!E77 -> 0.076352699 | G31: ='Conn DCF'!X77 -> 0.068413495
A32: Space (Launch + Starship) | B32: 2 | C32: =IF(B32=1,"◀ BEAR",IF(B32=2,"◀ BASE","◀ BULL")) -> ◀ BASE | D32: =WACC!C37 -> 0.068984004 | E32: =WACC!C43 -> 0.025 | F32: ='Space DCF'!E85 -> 0.12008989 | G32: ='Space DCF'!X85 -> 0.081760475
A33: AI (X / xAI / Grok) | B33: 2 | C33: =IF(B33=1,"◀ BEAR",IF(B33=2,"◀ BASE","◀ BULL")) -> ◀ BASE | D33: =WACC!D37 -> 0.10385358 | E33: =WACC!C44 -> 0.035 | F33: ='AI DCF'!E77 -> 0.15398861 | G33: ='AI DCF'!X77 -> 0.12056526
A34: ✓ Set scenarios here (B28:B30). 1=Bear, 2=Base, 3=Bull. Segment tabs follow automatically – whole valuation controlled from this page.
A36: ⑤ VALUATION SUMMARY (Implied Price/Share, Basic | Selected Scenario)
A38: Method | B38: Per Share (Basic) | H38: Note
A39: Gordon Growth (Perpetuity) | B39: =SOTP!B30 -> 119.48368 | C39: =SOTP!B30 -> 119.48368 | D39: =SOTP!B30 -> 119.48368 | H39: Changes with Scenario Selector (B28:B30 above)
A40: Exit Multiple | B40: =SOTP!C30 -> 85.081247 | C40: =SOTP!C30 -> 85.081247 | D40: =SOTP!C30 -> 85.081247
A41: Average (Gordon & Exit) | B41: =SOTP!D30 -> 120.44605 | C41: =SOTP!D30 -> 120.44605 | D41: =SOTP!D30 -> 120.44605
A43: ⑥ SENSITIVITY: Implied Price/Share (Fully-Diluted) – Connectivity WACC vs. Terminal Growth Rate (Base Case)
A45: WACC ↓ \ Terminal Growth Rate → | B45: =SOTP!C64 -> 0.0225 | C45: =SOTP!D64 -> 0.025 | D45: =SOTP!E64 -> 0.0275 | E45: =SOTP!F64 -> 0.03 | F45: =SOTP!G64 -> 0.0325 | G45: =SOTP!H64 -> 0.035 | H45: =SOTP!I64 -> 0.0375
A46: =SOTP!B65 -> 0.056406891 | B46: =SOTP!C65 -> 69.659843 | C46: =SOTP!D65 -> 72.757125 | D46: =SOTP!E65 -> 76.390142 | E46: =SOTP!F65 -> 80.711051 | F46: =SOTP!G65 -> 85.935655 | G46: =SOTP!H65 -> 92.380568 | H46: =SOTP!I65 -> 100.52986
A47: =SOTP!B66 -> 0.058906891 | B47: =SOTP!C66 -> 64.866783 | C47: =SOTP!D66 -> 67.421352 | D47: =SOTP!E66 -> 70.382611 | E47: =SOTP!F66 -> 73.856077 | F47: =SOTP!G66 -> 77.987224 | G47: =SOTP!H66 -> 82.982379 | H47: =SOTP!I66 -> 89.14425
A48: =SOTP!B67 -> 0.061406891 | B48: =SOTP!C67 -> 60.70767 | C48: =SOTP!D67 -> 62.836401 | D48: =SOTP!E67 -> 65.27904 | E48: =SOTP!F67 -> 68.110549 | F48: =SOTP!G67 -> 71.431822 | G48: =SOTP!H67 -> 75.38196 | H48: =SOTP!I67 -> 80.158248
A49: =SOTP!B68 -> 0.063906891 | B49: =SOTP!C68 -> 57.067054 | C49: =SOTP!D68 -> 58.856914 | D49: =SOTP!E68 -> 60.892587 | E49: =SOTP!F68 -> 63.228446 | F49: =SOTP!G68 -> 65.936176 | G49: =SOTP!H68 -> 69.112259 | H49: =SOTP!I68 -> 72.889717
A50: =SOTP!B69 -> 0.066406891 | B50: =SOTP!C69 -> 53.855805 | C50: =SOTP!D69 -> 55.372666 | D50: =SOTP!E69 -> 57.084462 | E50: =SOTP!F69 -> 59.03135 | F50: =SOTP!G69 -> 61.265331 | G50: =SOTP!H69 -> 63.854964 | H50: =SOTP!I69 -> 66.892524
A51: =SOTP!B70 -> 0.068906891 | B51: =SOTP!C70 -> 51.004024 | C51: =SOTP!D70 -> 52.29856 | D51: =SOTP!E70 -> 53.749415 | E51: =SOTP!F70 -> 55.386723 | F51: =SOTP!G70 -> 57.248892 | G51: =SOTP!H70 -> 59.385662 | H51: =SOTP!I70 -> 61.862608
A52: =SOTP!B71 -> 0.071406891 | B52: =SOTP!C71 -> 48.456126 | C52: =SOTP!D71 -> 49.567858 | D52: =SOTP!E71 -> 50.806191 | E52: =SOTP!F71 -> 52.194057 | F52: =SOTP!G71 -> 53.76028 | G52: =SOTP!H71 -> 55.541603 | H52: =SOTP!I71 -> 57.585605
A54: ⑦ KEY SEGMENT FINANCIALS (FY2025 Actuals | Source: SpaceX S-1)
A56: Metric ($M) | B56: FY2023A | C56: FY2024A | D56: FY2025A | E56: Q1 2026A
A57: Total Revenue | B57: =Actuals!B7 -> 10387 | C57: =Actuals!C7 -> 14015 | D57: =Actuals!D7 -> 18674 | E57: =Actuals!B27 -> 4694
A58: Connectivity Revenue | B58: =Actuals!B8 -> 3869 | C58: =Actuals!C8 -> 7599 | D58: =Actuals!D8 -> 11387 | E58: =Actuals!B28 -> 3257
A59: Space Revenue | B59: =Actuals!B9 -> 3557 | C59: =Actuals!C9 -> 3796 | D59: =Actuals!D9 -> 4086 | E59: =Actuals!B29 -> 619
A60: AI Revenue | B60: =Actuals!B10 -> 2961 | C60: =Actuals!C10 -> 2620 | D60: =Actuals!D10 -> 3201 | E60: =Actuals!B30 -> 818
A61: Connectivity Op. Income | B61: =Historicals!B43 -> 469 | C61: =Historicals!C43 -> 2006 | D61: =Historicals!D43 -> 4423 | E61: =Historicals!J43 -> 1188
A62: Space Op. Income | B62: =Historicals!B42 -> -1 | C62: =Historicals!C42 -> 21 | D62: =Historicals!D42 -> -657 | E62: =Historicals!J42 -> -662
A63: AI Op. Income | B63: =Historicals!B44 -> -3973 | C63: =Historicals!C44 -> -1561 | D63: =Historicals!D44 -> -6355 | E63: =Historicals!J44 -> -2469
A64: Total Operating Cash Flow | B64: =Historicals!B85 -> 4520 | C64: =Historicals!C85 -> 5776 | D64: =Historicals!D85 -> 6785 | E64: =Historicals!J85 -> 1047
A65: Total Capex | B65: =Actuals!B21 -> -4415 | C65: =Actuals!C21 -> -11163 | D65: =Actuals!D21 -> -20737 | E65: =Historicals!J86 -> -10107
A66: Net Income (Loss) | B66: =Actuals!B22 -> -4628 | C66: =Actuals!C22 -> 791 | D66: =Actuals!D22 -> -4937 | E66: =Historicals!J25 -> -4276
A68: ⑧ RECONCILIATION BRIDGE – Intrinsic Value → Market Price ($B)
A70: Layer | B70: Value ($B) | C70: Cumulative ($B) | D70: Target Mkt Val ($B) | H70: Note
A71: Our DCF Intrinsic Equity (avg) | B71: =SOTP!D23/1000 -> 698.34619 | C71: =B71 -> 698.34619 | D71: 1750 | H71: 20-yr SOTP DCF, base case – validated by M&I ($429B) & Morningstar ($780B)
A72: (+) AI Optionality | B72: 210 | C72: =C71+B72 -> 908.34619 | H72: xAI/Grok priced at ~$250B in Feb'26 deal vs our ~$64B DCF – market optionality premium
A73: (+) Orbital Data Centers / Compute | B73: 350 | C73: =C72+B73 -> 1258.3462 | H73: S-1 AI compute-in-space thesis; not in our cash-flow base
A74: (+) Mars / Starshield Upside | B74: 250 | C74: =C73+B74 -> 1508.3462 | H74: ARK/Mach33 value Mars by accumulated book value; long-dated optionality
A75: (+) Terafab + Other Future Markets | B75: 120 | C75: =C74+B75 -> 1628.3462 | H75: Semiconductor fab ($119B, Sacra); not modeled in base
A76: (+) Hype / Index-Inclusion / Scarcity | B76: =$D$71-C75 -> 121.65381 | C76: =C75+B76 -> 1750 | H76: Residual – 2x oversubscribed IPO, Nasdaq fast-track, Musk premium
A77: Market IPO Valuation (= total) | B77: =$D$71 -> 1750 | C77: =$D$71 -> 1750 | H77: Reuters: $135/share × ~12.96B shares = $1.75T

Sheet SOTP
A1: SpaceX – Sum-of-the-Parts Valuation
A2: Sum-of-the-Parts DCF Valuation | S-1 Filed May 20, 2026 | $ in Millions (except per share)
A3: Segments: Connectivity (Starlink) + Space (Launch/Starship) + AI (X/xAI/Grok) | 20-Year DCF with Gordon Growth & Exit Multiple cross-check
A5: Scenarios are controlled on the COVER tab (B28:B30). This sheet reflects the selected case live.
A6: SEGMENT ENTERPRISE VALUE SUMMARY ($M)
A8: Segment | B8: Method 1 EV ¹ | C8: Method 2 EV ² | D8: Selected EV | E8: % of Total SOTP | F8: GG Weight | H8: Comp Data Status
A9: Connectivity (Starlink) | B9: ='Conn DCF'!B103 -> 558405.91 | C9: ='Conn DCF'!C103 -> 340341.16 | D9: =F9*B9+(1-F9)*C9 -> 558405.91 | E9: =D9/$D$12 -> 0.90724658 | F9: 1 | H9: =IF(N('Conn Comps'!K54)>0,"✓ LIVE "&TEXT('Conn Comps'!K54,"0.0x")&" EV/EBITDA","⚠ FALLBACK") -> ✓ LIVE 5.9x EV/EBITDA
A10: Space (Launch + Starship) | B10: ='Space DCF'!B111 -> 49217.277 | C10: ='Space DCF'!C111 -> 59902.088 | D10: =F10*B10+(1-F10)*C10 -> 52422.72 | E10: =D10/$D$12 -> 0.085171616 | F10: 0.7 | H10: =IF(N('Space Comps'!K35)>0,"✓ LIVE "&TEXT('Space Comps'!K35,"0.0x")&" EV/EBITDA","⚠ FALLBACK") -> ✓ LIVE 15.1x EV/EBITDA
A11: AI (X / xAI / Grok) | B11: ='AI DCF'!B103 -> 2292.1662 | C11: ='AI DCF'!C103 -> 10206.828 | D11: =F11*B11+(1-F11)*C11 -> 4666.5647 | E11: =D11/$D$12 -> 0.0075818052 | F11: 0.7 | H11: =IF(N('AI Comps'!J43)>0,"✓ LIVE "&TEXT('AI Comps'!J43,"0.0x")&" EV/Rev (Tier 3)","⚠ FALLBACK") -> ✓ LIVE 3.2x EV/Rev (Tier 3)
A12: Total Enterprise Value (SOTP) | B12: =B9+B10+B11 -> 609915.35 | C12: =C9+C10+C11 -> 410450.07 | D12: =D9+D10+D11 -> 615495.19 | E12: =D12/$D$12 -> 1
B16: Gordon Growth | C16: Exit Multiple | D16: Average | H16: Note
A17: Total Enterprise Value (SOTP) | B17: =B12 -> 609915.35 | C17: =C12 -> 410450.07 | D17: =D12 -> 615495.19
A18: (–) Total Debt & Finance Leases | B18: =-Historicals!D81-5000 -> -27896 | C18: =$B$18 -> -27896 | D18: =$B$18 -> -27896 | H18: S-1 Dec'25 BS
A19: (+) Cash & Marketable Securities | B19: =Historicals!D68 -> 24747 | C19: =$B$19 -> 24747 | D19: =$B$19 -> 24747 | H19: S-1 Dec'25 BS
A20: (–) Redeemable Preferred Stock | B20: =-Historicals!D79 -> -38752 | C20: =$B$20 -> -38752 | D20: =$B$20 -> -38752 | H20: Pre-IPO; converts at IPO
A21: Post-IPO Preferred Conversion Adjustment | B21: =-B20 -> 38752 | C21: =$B$21 -> 38752 | D21: =$B$21 -> 38752
A22: (+) IPO Proceeds (555.6M shares @ $135) | B22: 86000 | C22: =$B$22 -> 86000 | D22: =$B$22 -> 86000 | H22: 555.6M primary × $135
A23: Equity Value | B23: =B17+B18+B19+B20+B21+B22 -> 692766.35 | C23: =C17+C18+C19+C20+C21+C22 -> 493301.07 | D23: =D17+D18+D19+D20+D21+D22 -> 698346.19
A25: IMPLIED PRICE PER SHARE (Post-IPO Fully Diluted)
A27: Item | B27: Gordon Growth | C27: Exit Multiple | D27: Average | H27: Note
A28: Common Shares – Basic (Class A+B+C, S-1 Q1'26) | B28: 5798 | C28: =$B$28 -> 5798 | D28: =$B$28 -> 5798 | H28: Cl. A+B+C (S-1 Q1'26)
A29: Total Shares – Fully Diluted, Post-IPO | B29: =B93 -> 13041 | C29: =$B$29 -> 13041 | D29: =$B$29 -> 13041 | H29: $1.75T ÷ $135 reconciled
A30: Implied Price/Share – on Basic (understates) | B30: =B23/$B$28 -> 119.48368 | C30: =C23/$B$28 -> 85.081247 | D30: =D23/$B$28 -> 120.44605
A31: Implied Price/Share – Fully Diluted (primary) | B31: =B23/$B$29 -> 53.12218 | C31: =C23/$B$29 -> 37.826936 | D31: =D23/$B$29 -> 53.550049
A33: CURSOR PRO-FORMA (all-stock acquisition, pending Q3'26 close)
A34: (+) Cursor Acquisition EV (444M shares @ ~$135) | B34: 60000 | C34: =$B$34 -> 60000 | D34: =$B$34 -> 60000 | H34: All-stock; 3.4% dilution at IPO val
A35: Pro-Forma Equity Value | B35: =B23+B34 -> 752766.35 | C35: =C23+C34 -> 553301.07 | D35: =D23+D34 -> 758346.19
A36: Pro-Forma FD Shares (12,960 + 444M Cursor) | B36: =B29+444 -> 13485 | C36: =$B$36 -> 13485 | D36: =$B$36 -> 13485 | H36: $60B ÷ $135 = 444M new shares
A37: Pro-Forma Price/Share – Fully Diluted | B37: =B35/B36 -> 55.822495 | C37: =C35/C36 -> 41.030854 | D37: =D35/D36 -> 56.236277
A39: SOTP COMPONENT BREAKDOWN ($M)
A41: Segment | B41: EV (Avg) | C41: Per Share (Basic) | D41: % of Total EV | E41: Segment WACC | H41: Key Value Driver
A42: Connectivity (Starlink) | B42: =D9 -> 558405.91 | C42: =B42/$B$28 -> 96.310091 | D42: =B42/$B$45 -> 0.90724658 | E42: ='Conn DCF'!B46 -> 0.063906891 | H42: Subscriber growth + enterprise adoption; 63%+ EBITDA margins
A43: Space (Launch + Starship) | B43: =D10 -> 52422.72 | C43: =B43/$B$28 -> 9.0415178 | D43: =B43/$B$45 -> 0.085171616 | E43: ='Space DCF'!B50 -> 0.068984004 | H43: Starship cost curve + reusability; long-term capex normalization
A44: AI (X / xAI) | B44: =D11 -> 4666.5647 | C44: =B44/$B$28 -> 0.80485765 | D44: =B44/$B$45 -> 0.0075818052 | E44: ='AI DCF'!B42 -> 0.10385358 | H44: Grok monetization + compute infra; margin ramp from -39% to +46%
A45: Total | B45: =D12 -> 615495.19 | C45: =B45/$B$28 -> 106.15647 | D45: =SUM(D42:D44) -> 1
A47: KEY METRICS SNAPSHOT (FY2025 Actuals | Source: SpaceX S-1)
A49: Metric | B49: FY2023A | C49: FY2024A | D49: FY2025A | E49: Q1 2026 | H49: Note
A50: Total Revenue ($M) | B50: =Historicals!B8 -> 10387 | C50: =Historicals!C8 -> 14015 | D50: =Historicals!D8 -> 18674 | E50: =Historicals!J8 -> 4694 | H50: S-1 Consolidated Statements of Operations
A51: Connectivity ($M) | B51: =Historicals!B32 -> 3869 | C51: =Historicals!C32 -> 7599 | D51: =Historicals!D32 -> 11387 | E51: =Historicals!J32 -> 3257 | H51: Starlink Consumer + Enterprise/Gov't
A52: Space ($M) | B52: =Historicals!B29 -> 3557 | C52: =Historicals!C29 -> 3796 | D52: =Historicals!D29 -> 4086 | E52: =Historicals!J29 -> 619 | H52: Launch Services + Launch & Development
A53: AI ($M) | B53: =Historicals!B35 -> 2961 | C53: =Historicals!C35 -> 2620 | D53: =Historicals!D35 -> 3201 | E53: =Historicals!J35 -> 818 | H53: X advertising + AI Solutions & Infrastructure
A54: Total Capex ($M) | B54: =-Historicals!B64 -> -4415 | C54: =-Historicals!C64 -> -11163 | D54: =-Historicals!D64 -> -20737 | E54: =-Historicals!J64 -> -10107 | H54: Massive AI infra build (xAI: $12.7B in 2025)
A55: Operating Cash Flow ($M) | B55: =Historicals!B85 -> 4520 | C55: =Historicals!C85 -> 5776 | D55: =Historicals!D85 -> 6785 | E55: =Historicals!J85 -> 1047
A56: Net Income (Loss) ($M) | B56: =Historicals!B25 -> -4628 | C56: =Historicals!C25 -> 791 | D56: =Historicals!D25 -> -4937 | E56: =Historicals!J25 -> -4276 | H56: R&D ($8.6B) + AI losses dominate 2025
A57: Connectivity EBITDA Margin | B57: =Historicals!B49/Historicals!B32 -> 0.41406048 | C57: =Historicals!C49/Historicals!C32 -> 0.50651402 | D57: =Historicals!D49/Historicals!D32 -> 0.62948977 | E57: =Historicals!J49/Historicals!J32 -> 0.64077372 | H57: From S-1 Segment Adjusted EBITDA disclosure
A58: ¹ Method 1 = Gordon Growth (perpetuity) for Connectivity & Space; EV/Revenue multiple (PRIMARY) for AI – Gordon distorts on AI's loss-making early FCF.
A59: ² Method 2 = EV/EBITDA Exit Multiple for Connectivity & Space; Gordon Growth (cross-check only) for AI.
A61: VALUATION SENSITIVITY ANALYSIS (Method 1: Gordon Growth for Connectivity & Space, EV/Revenue for AI)
A63: Table 1: SOTP Implied Price/Share (Fully-Diluted) – Connectivity WACC vs. Terminal Growth Rate (Base Case)
B64: Connectivity WACC ↓ \ Terminal Growth Rate → | C64: ='Conn DCF'!B45-0.0075 -> 0.0225 | D64: ='Conn DCF'!B45-0.005 -> 0.025 | E64: ='Conn DCF'!B45-0.0025 -> 0.0275 | F64: ='Conn DCF'!B45 -> 0.03 | G64: ='Conn DCF'!B45+0.0025 -> 0.0325 | H64: ='Conn DCF'!B45+0.005 -> 0.035 | I64: ='Conn DCF'!B45+0.0075 -> 0.0375
B65: ='Conn DCF'!B46-0.0075 -> 0.056406891 | C65: =((SUMPRODUCT('Conn DCF'!$E$62:$X$62,1/(1+$B65)^'Conn DCF'!$E$79:$X$79)+'Conn DCF'!$X$62*(1+C$64)/($B65-C$64)/(1+$B65)^20)+'Space DCF'!$B$111+'AI DCF'!$B$103+$B$18+$B$19+$B$20+$B$21+$B$22)/$B$29 -> 69.659843 | D65: =((SUMPRODUCT('Conn DCF'!$E$62:$X$62,1/(1+$B65)^'Conn DCF'!$E$79:$X$79)+'Conn DCF'!$X$62*(1+D$64)/($B65-D$64)/(1+$B65)^20)+'Space DCF'!$B$111+'AI DCF'!$B$103+$B$18+$B$19+$B$20+$B$21+$B$22)/$B$29 -> 72.757125 | E65: =((SUMPRODUCT('Conn DCF'!$E$62:$X$62,1/(1+$B65)^'Conn DCF'!$E$79:$X$79)+'Conn DCF'!$X$62*(1+E$64)/($B65-E$64)/(1+$B65)^20)+'Space DCF'!$B$111+'AI DCF'!$B$103+$B$18+$B$19+$B$20+$B$21+$B$22)/$B$29 -> 76.390142 | F65: =((SUMPRODUCT('Conn DCF'!$E$62:$X$62,1/(1+$B65)^'Conn DCF'!$E$79:$X$79)+'Conn DCF'!$X$62*(1+F$64)/($B65-F$64)/(1+$B65)^20)+'Space DCF'!$B$111+'AI DCF'!$B$103+$B$18+$B$19+$B$20+$B$21+$B$22)/$B$29 -> 80.711051 | G65: =((SUMPRODUCT('Conn DCF'!$E$62:$X$62,1/(1+$B65)^'Conn DCF'!$E$79:$X$79)+'Conn DCF'!$X$62*(1+G$64)/($B65-G$64)/(1+$B65)^20)+'Space DCF'!$B$111+'AI DCF'!$B$103+$B$18+$B$19+$B$20+$B$21+$B$22)/$B$29 -> 85.935655 | H65: =((SUMPRODUCT('Conn DCF'!$E$62:$X$62,1/(1+$B65)^'Conn DCF'!$E$79:$X$79)+'Conn DCF'!$X$62*(1+H$64)/($B65-H$64)/(1+$B65)^20)+'Space DCF'!$B$111+'AI DCF'!$B$103+$B$18+$B$19+$B$20+$B$21+$B$22)/$B$29 -> 92.380568 | I65: =((SUMPRODUCT('Conn DCF'!$E$62:$X$62,1/(1+$B65)^'Conn DCF'!$E$79:$X$79)+'Conn DCF'!$X$62*(1+I$64)/($B65-I$64)/(1+$B65)^20)+'Space DCF'!$B$111+'AI DCF'!$B$103+$B$18+$B$19+$B$20+$B$21+$B$22)/$B$29 -> 100.52986
B66: ='Conn DCF'!B46-0.005 -> 0.058906891 | C66: =((SUMPRODUCT('Conn DCF'!$E$62:$X$62,1/(1+$B66)^'Conn DCF'!$E$79:$X$79)+'Conn DCF'!$X$62*(1+C$64)/($B66-C$64)/(1+$B66)^20)+'Space DCF'!$B$111+'AI DCF'!$B$103+$B$18+$B$19+$B$20+$B$21+$B$22)/$B$29 -> 64.866783 | D66: =((SUMPRODUCT('Conn DCF'!$E$62:$X$62,1/(1+$B66)^'Conn DCF'!$E$79:$X$79)+'Conn DCF'!$X$62*(1+D$64)/($B66-D$64)/(1+$B66)^20)+'Space DCF'!$B$111+'AI DCF'!$B$103+$B$18+$B$19+$B$20+$B$21+$B$22)/$B$29 -> 67.421352 | E66: =((SUMPRODUCT('Conn DCF'!$E$62:$X$62,1/(1+$B66)^'Conn DCF'!$E$79:$X$79)+'Conn DCF'!$X$62*(1+E$64)/($B66-E$64)/(1+$B66)^20)+'Space DCF'!$B$111+'AI DCF'!$B$103+$B$18+$B$19+$B$20+$B$21+$B$22)/$B$29 -> 70.382611 | F66: =((SUMPRODUCT('Conn DCF'!$E$62:$X$62,1/(1+$B66)^'Conn DCF'!$E$79:$X$79)+'Conn DCF'!$X$62*(1+F$64)/($B66-F$64)/(1+$B66)^20)+'Space DCF'!$B$111+'AI DCF'!$B$103+$B$18+$B$19+$B$20+$B$21+$B$22)/$B$29 -> 73.856077 | G66: =((SUMPRODUCT('Conn DCF'!$E$62:$X$62,1/(1+$B66)^'Conn DCF'!$E$79:$X$79)+'Conn DCF'!$X$62*(1+G$64)/($B66-G$64)/(1+$B66)^20)+'Space DCF'!$B$111+'AI DCF'!$B$103+$B$18+$B$19+$B$20+$B$21+$B$22)/$B$29 -> 77.987224 | H66: =((SUMPRODUCT('Conn DCF'!$E$62:$X$62,1/(1+$B66)^'Conn DCF'!$E$79:$X$79)+'Conn DCF'!$X$62*(1+H$64)/($B66-H$64)/(1+$B66)^20)+'Space DCF'!$B$111+'AI DCF'!$B$103+$B$18+$B$19+$B$20+$B$21+$B$22)/$B$29 -> 82.982379 | I66: =((SUMPRODUCT('Conn DCF'!$E$62:$X$62,1/(1+$B66)^'Conn DCF'!$E$79:$X$79)+'Conn DCF'!$X$62*(1+I$64)/($B66-I$64)/(1+$B66)^20)+'Space DCF'!$B$111+'AI DCF'!$B$103+$B$18+$B$19+$B$20+$B$21+$B$22)/$B$29 -> 89.14425
B67: ='Conn DCF'!B46-0.0025 -> 0.061406891 | C67: =((SUMPRODUCT('Conn DCF'!$E$62:$X$62,1/(1+$B67)^'Conn DCF'!$E$79:$X$79)+'Conn DCF'!$X$62*(1+C$64)/($B67-C$64)/(1+$B67)^20)+'Space DCF'!$B$111+'AI DCF'!$B$103+$B$18+$B$19+$B$20+$B$21+$B$22)/$B$29 -> 60.70767 | D67: =((SUMPRODUCT('Conn DCF'!$E$62:$X$62,1/(1+$B67)^'Conn DCF'!$E$79:$X$79)+'Conn DCF'!$X$62*(1+D$64)/($B67-D$64)/(1+$B67)^20)+'Space DCF'!$B$111+'AI DCF'!$B$103+$B$18+$B$19+$B$20+$B$21+$B$22)/$B$29 -> 62.836401 | E67: =((SUMPRODUCT('Conn DCF'!$E$62:$X$62,1/(1+$B67)^'Conn DCF'!$E$79:$X$79)+'Conn DCF'!$X$62*(1+E$64)/($B67-E$64)/(1+$B67)^20)+'Space DCF'!$B$111+'AI DCF'!$B$103+$B$18+$B$19+$B$20+$B$21+$B$22)/$B$29 -> 65.27904 | F67: =((SUMPRODUCT('Conn DCF'!$E$62:$X$62,1/(1+$B67)^'Conn DCF'!$E$79:$X$79)+'Conn DCF'!$X$62*(1+F$64)/($B67-F$64)/(1+$B67)^20)+'Space DCF'!$B$111+'AI DCF'!$B$103+$B$18+$B$19+$B$20+$B$21+$B$22)/$B$29 -> 68.110549 | G67: =((SUMPRODUCT('Conn DCF'!$E$62:$X$62,1/(1+$B67)^'Conn DCF'!$E$79:$X$79)+'Conn DCF'!$X$62*(1+G$64)/($B67-G$64)/(1+$B67)^20)+'Space DCF'!$B$111+'AI DCF'!$B$103+$B$18+$B$19+$B$20+$B$21+$B$22)/$B$29 -> 71.431822 | H67: =((SUMPRODUCT('Conn DCF'!$E$62:$X$62,1/(1+$B67)^'Conn DCF'!$E$79:$X$79)+'Conn DCF'!$X$62*(1+H$64)/($B67-H$64)/(1+$B67)^20)+'Space DCF'!$B$111+'AI DCF'!$B$103+$B$18+$B$19+$B$20+$B$21+$B$22)/$B$29 -> 75.38196 | I67: =((SUMPRODUCT('Conn DCF'!$E$62:$X$62,1/(1+$B67)^'Conn DCF'!$E$79:$X$79)+'Conn DCF'!$X$62*(1+I$64)/($B67-I$64)/(1+$B67)^20)+'Space DCF'!$B$111+'AI DCF'!$B$103+$B$18+$B$19+$B$20+$B$21+$B$22)/$B$29 -> 80.158248
B68: ='Conn DCF'!B46 -> 0.063906891 | C68: =((SUMPRODUCT('Conn DCF'!$E$62:$X$62,1/(1+$B68)^'Conn DCF'!$E$79:$X$79)+'Conn DCF'!$X$62*(1+C$64)/($B68-C$64)/(1+$B68)^20)+'Space DCF'!$B$111+'AI DCF'!$B$103+$B$18+$B$19+$B$20+$B$21+$B$22)/$B$29 -> 57.067054 | D68: =((SUMPRODUCT('Conn DCF'!$E$62:$X$62,1/(1+$B68)^'Conn DCF'!$E$79:$X$79)+'Conn DCF'!$X$62*(1+D$64)/($B68-D$64)/(1+$B68)^20)+'Space DCF'!$B$111+'AI DCF'!$B$103+$B$18+$B$19+$B$20+$B$21+$B$22)/$B$29 -> 58.856914 | E68: =((SUMPRODUCT('Conn DCF'!$E$62:$X$62,1/(1+$B68)^'Conn DCF'!$E$79:$X$79)+'Conn DCF'!$X$62*(1+E$64)/($B68-E$64)/(1+$B68)^20)+'Space DCF'!$B$111+'AI DCF'!$B$103+$B$18+$B$19+$B$20+$B$21+$B$22)/$B$29 -> 60.892587 | F68: =((SUMPRODUCT('Conn DCF'!$E$62:$X$62,1/(1+$B68)^'Conn DCF'!$E$79:$X$79)+'Conn DCF'!$X$62*(1+F$64)/($B68-F$64)/(1+$B68)^20)+'Space DCF'!$B$111+'AI DCF'!$B$103+$B$18+$B$19+$B$20+$B$21+$B$22)/$B$29 -> 63.228446 | G68: =((SUMPRODUCT('Conn DCF'!$E$62:$X$62,1/(1+$B68)^'Conn DCF'!$E$79:$X$79)+'Conn DCF'!$X$62*(1+G$64)/($B68-G$64)/(1+$B68)^20)+'Space DCF'!$B$111+'AI DCF'!$B$103+$B$18+$B$19+$B$20+$B$21+$B$22)/$B$29 -> 65.936176 | H68: =((SUMPRODUCT('Conn DCF'!$E$62:$X$62,1/(1+$B68)^'Conn DCF'!$E$79:$X$79)+'Conn DCF'!$X$62*(1+H$64)/($B68-H$64)/(1+$B68)^20)+'Space DCF'!$B$111+'AI DCF'!$B$103+$B$18+$B$19+$B$20+$B$21+$B$22)/$B$29 -> 69.112259 | I68: =((SUMPRODUCT('Conn DCF'!$E$62:$X$62,1/(1+$B68)^'Conn DCF'!$E$79:$X$79)+'Conn DCF'!$X$62*(1+I$64)/($B68-I$64)/(1+$B68)^20)+'Space DCF'!$B$111+'AI DCF'!$B$103+$B$18+$B$19+$B$20+$B$21+$B$22)/$B$29 -> 72.889717
B69: ='Conn DCF'!B46+0.0025 -> 0.066406891 | C69: =((SUMPRODUCT('Conn DCF'!$E$62:$X$62,1/(1+$B69)^'Conn DCF'!$E$79:$X$79)+'Conn DCF'!$X$62*(1+C$64)/($B69-C$64)/(1+$B69)^20)+'Space DCF'!$B$111+'AI DCF'!$B$103+$B$18+$B$19+$B$20+$B$21+$B$22)/$B$29 -> 53.855805 | D69: =((SUMPRODUCT('Conn DCF'!$E$62:$X$62,1/(1+$B69)^'Conn DCF'!$E$79:$X$79)+'Conn DCF'!$X$62*(1+D$64)/($B69-D$64)/(1+$B69)^20)+'Space DCF'!$B$111+'AI DCF'!$B$103+$B$18+$B$19+$B$20+$B$21+$B$22)/$B$29 -> 55.372666 | E69: =((SUMPRODUCT('Conn DCF'!$E$62:$X$62,1/(1+$B69)^'Conn DCF'!$E$79:$X$79)+'Conn DCF'!$X$62*(1+E$64)/($B69-E$64)/(1+$B69)^20)+'Space DCF'!$B$111+'AI DCF'!$B$103+$B$18+$B$19+$B$20+$B$21+$B$22)/$B$29 -> 57.084462 | F69: =((SUMPRODUCT('Conn DCF'!$E$62:$X$62,1/(1+$B69)^'Conn DCF'!$E$79:$X$79)+'Conn DCF'!$X$62*(1+F$64)/($B69-F$64)/(1+$B69)^20)+'Space DCF'!$B$111+'AI DCF'!$B$103+$B$18+$B$19+$B$20+$B$21+$B$22)/$B$29 -> 59.03135 | G69: =((SUMPRODUCT('Conn DCF'!$E$62:$X$62,1/(1+$B69)^'Conn DCF'!$E$79:$X$79)+'Conn DCF'!$X$62*(1+G$64)/($B69-G$64)/(1+$B69)^20)+'Space DCF'!$B$111+'AI DCF'!$B$103+$B$18+$B$19+$B$20+$B$21+$B$22)/$B$29 -> 61.265331 | H69: =((SUMPRODUCT('Conn DCF'!$E$62:$X$62,1/(1+$B69)^'Conn DCF'!$E$79:$X$79)+'Conn DCF'!$X$62*(1+H$64)/($B69-H$64)/(1+$B69)^20)+'Space DCF'!$B$111+'AI DCF'!$B$103+$B$18+$B$19+$B$20+$B$21+$B$22)/$B$29 -> 63.854964 | I69: =((SUMPRODUCT('Conn DCF'!$E$62:$X$62,1/(1+$B69)^'Conn DCF'!$E$79:$X$79)+'Conn DCF'!$X$62*(1+I$64)/($B69-I$64)/(1+$B69)^20)+'Space DCF'!$B$111+'AI DCF'!$B$103+$B$18+$B$19+$B$20+$B$21+$B$22)/$B$29 -> 66.892524
B70: ='Conn DCF'!B46+0.005 -> 0.068906891 | C70: =((SUMPRODUCT('Conn DCF'!$E$62:$X$62,1/(1+$B70)^'Conn DCF'!$E$79:$X$79)+'Conn DCF'!$X$62*(1+C$64)/($B70-C$64)/(1+$B70)^20)+'Space DCF'!$B$111+'AI DCF'!$B$103+$B$18+$B$19+$B$20+$B$21+$B$22)/$B$29 -> 51.004024 | D70: =((SUMPRODUCT('Conn DCF'!$E$62:$X$62,1/(1+$B70)^'Conn DCF'!$E$79:$X$79)+'Conn DCF'!$X$62*(1+D$64)/($B70-D$64)/(1+$B70)^20)+'Space DCF'!$B$111+'AI DCF'!$B$103+$B$18+$B$19+$B$20+$B$21+$B$22)/$B$29 -> 52.29856 | E70: =((SUMPRODUCT('Conn DCF'!$E$62:$X$62,1/(1+$B70)^'Conn DCF'!$E$79:$X$79)+'Conn DCF'!$X$62*(1+E$64)/($B70-E$64)/(1+$B70)^20)+'Space DCF'!$B$111+'AI DCF'!$B$103+$B$18+$B$19+$B$20+$B$21+$B$22)/$B$29 -> 53.749415 | F70: =((SUMPRODUCT('Conn DCF'!$E$62:$X$62,1/(1+$B70)^'Conn DCF'!$E$79:$X$79)+'Conn DCF'!$X$62*(1+F$64)/($B70-F$64)/(1+$B70)^20)+'Space DCF'!$B$111+'AI DCF'!$B$103+$B$18+$B$19+$B$20+$B$21+$B$22)/$B$29 -> 55.386723 | G70: =((SUMPRODUCT('Conn DCF'!$E$62:$X$62,1/(1+$B70)^'Conn DCF'!$E$79:$X$79)+'Conn DCF'!$X$62*(1+G$64)/($B70-G$64)/(1+$B70)^20)+'Space DCF'!$B$111+'AI DCF'!$B$103+$B$18+$B$19+$B$20+$B$21+$B$22)/$B$29 -> 57.248892 | H70: =((SUMPRODUCT('Conn DCF'!$E$62:$X$62,1/(1+$B70)^'Conn DCF'!$E$79:$X$79)+'Conn DCF'!$X$62*(1+H$64)/($B70-H$64)/(1+$B70)^20)+'Space DCF'!$B$111+'AI DCF'!$B$103+$B$18+$B$19+$B$20+$B$21+$B$22)/$B$29 -> 59.385662 | I70: =((SUMPRODUCT('Conn DCF'!$E$62:$X$62,1/(1+$B70)^'Conn DCF'!$E$79:$X$79)+'Conn DCF'!$X$62*(1+I$64)/($B70-I$64)/(1+$B70)^20)+'Space DCF'!$B$111+'AI DCF'!$B$103+$B$18+$B$19+$B$20+$B$21+$B$22)/$B$29 -> 61.862608
B71: ='Conn DCF'!B46+0.0075 -> 0.071406891 | C71: =((SUMPRODUCT('Conn DCF'!$E$62:$X$62,1/(1+$B71)^'Conn DCF'!$E$79:$X$79)+'Conn DCF'!$X$62*(1+C$64)/($B71-C$64)/(1+$B71)^20)+'Space DCF'!$B$111+'AI DCF'!$B$103+$B$18+$B$19+$B$20+$B$21+$B$22)/$B$29 -> 48.456126 | D71: =((SUMPRODUCT('Conn DCF'!$E$62:$X$62,1/(1+$B71)^'Conn DCF'!$E$79:$X$79)+'Conn DCF'!$X$62*(1+D$64)/($B71-D$64)/(1+$B71)^20)+'Space DCF'!$B$111+'AI DCF'!$B$103+$B$18+$B$19+$B$20+$B$21+$B$22)/$B$29 -> 49.567858 | E71: =((SUMPRODUCT('Conn DCF'!$E$62:$X$62,1/(1+$B71)^'Conn DCF'!$E$79:$X$79)+'Conn DCF'!$X$62*(1+E$64)/($B71-E$64)/(1+$B71)^20)+'Space DCF'!$B$111+'AI DCF'!$B$103+$B$18+$B$19+$B$20+$B$21+$B$22)/$B$29 -> 50.806191 | F71: =((SUMPRODUCT('Conn DCF'!$E$62:$X$62,1/(1+$B71)^'Conn DCF'!$E$79:$X$79)+'Conn DCF'!$X$62*(1+F$64)/($B71-F$64)/(1+$B71)^20)+'Space DCF'!$B$111+'AI DCF'!$B$103+$B$18+$B$19+$B$20+$B$21+$B$22)/$B$29 -> 52.194057 | G71: =((SUMPRODUCT('Conn DCF'!$E$62:$X$62,1/(1+$B71)^'Conn DCF'!$E$79:$X$79)+'Conn DCF'!$X$62*(1+G$64)/($B71-G$64)/(1+$B71)^20)+'Space DCF'!$B$111+'AI DCF'!$B$103+$B$18+$B$19+$B$20+$B$21+$B$22)/$B$29 -> 53.76028 | H71: =((SUMPRODUCT('Conn DCF'!$E$62:$X$62,1/(1+$B71)^'Conn DCF'!$E$79:$X$79)+'Conn DCF'!$X$62*(1+H$64)/($B71-H$64)/(1+$B71)^20)+'Space DCF'!$B$111+'AI DCF'!$B$103+$B$18+$B$19+$B$20+$B$21+$B$22)/$B$29 -> 55.541603 | I71: =((SUMPRODUCT('Conn DCF'!$E$62:$X$62,1/(1+$B71)^'Conn DCF'!$E$79:$X$79)+'Conn DCF'!$X$62*(1+I$64)/($B71-I$64)/(1+$B71)^20)+'Space DCF'!$B$111+'AI DCF'!$B$103+$B$18+$B$19+$B$20+$B$21+$B$22)/$B$29 -> 57.585605
A73: Table 2: Total SOTP Enterprise Value ($B) – Connectivity WACC vs. Terminal Growth Rate (Base Case)
B74: Connectivity WACC ↓ \ Terminal Growth Rate → | C74: ='Conn DCF'!B45-0.0075 -> 0.0225 | D74: ='Conn DCF'!B45-0.005 -> 0.025 | E74: ='Conn DCF'!B45-0.0025 -> 0.0275 | F74: ='Conn DCF'!B45 -> 0.03 | G74: ='Conn DCF'!B45+0.0025 -> 0.0325 | H74: ='Conn DCF'!B45+0.005 -> 0.035 | I74: ='Conn DCF'!B45+0.0075 -> 0.0375
B75: ='Conn DCF'!B46-0.0075 -> 0.056406891 | C75: =(SUMPRODUCT('Conn DCF'!$E$62:$X$62,1/(1+$B75)^'Conn DCF'!$E$79:$X$79)+'Conn DCF'!$X$62*(1+C$74)/($B75-C$74)/(1+$B75)^20)+'Space DCF'!$B$111+'AI DCF'!$B$103 -> 825583.01 | D75: =(SUMPRODUCT('Conn DCF'!$E$62:$X$62,1/(1+$B75)^'Conn DCF'!$E$79:$X$79)+'Conn DCF'!$X$62*(1+D$74)/($B75-D$74)/(1+$B75)^20)+'Space DCF'!$B$111+'AI DCF'!$B$103 -> 865974.67 | E75: =(SUMPRODUCT('Conn DCF'!$E$62:$X$62,1/(1+$B75)^'Conn DCF'!$E$79:$X$79)+'Conn DCF'!$X$62*(1+E$74)/($B75-E$74)/(1+$B75)^20)+'Space DCF'!$B$111+'AI DCF'!$B$103 -> 913352.84 | F75: =(SUMPRODUCT('Conn DCF'!$E$62:$X$62,1/(1+$B75)^'Conn DCF'!$E$79:$X$79)+'Conn DCF'!$X$62*(1+F$74)/($B75-F$74)/(1+$B75)^20)+'Space DCF'!$B$111+'AI DCF'!$B$103 -> 969701.81 | G75: =(SUMPRODUCT('Conn DCF'!$E$62:$X$62,1/(1+$B75)^'Conn DCF'!$E$79:$X$79)+'Conn DCF'!$X$62*(1+G$74)/($B75-G$74)/(1+$B75)^20)+'Space DCF'!$B$111+'AI DCF'!$B$103 -> 1037835.9 | H75: =(SUMPRODUCT('Conn DCF'!$E$62:$X$62,1/(1+$B75)^'Conn DCF'!$E$79:$X$79)+'Conn DCF'!$X$62*(1+H$74)/($B75-H$74)/(1+$B75)^20)+'Space DCF'!$B$111+'AI DCF'!$B$103 -> 1121884 | I75: =(SUMPRODUCT('Conn DCF'!$E$62:$X$62,1/(1+$B75)^'Conn DCF'!$E$79:$X$79)+'Conn DCF'!$X$62*(1+I$74)/($B75-I$74)/(1+$B75)^20)+'Space DCF'!$B$111+'AI DCF'!$B$103 -> 1228158.9
B76: ='Conn DCF'!B46-0.005 -> 0.058906891 | C76: =(SUMPRODUCT('Conn DCF'!$E$62:$X$62,1/(1+$B76)^'Conn DCF'!$E$79:$X$79)+'Conn DCF'!$X$62*(1+C$74)/($B76-C$74)/(1+$B76)^20)+'Space DCF'!$B$111+'AI DCF'!$B$103 -> 763076.71 | D76: =(SUMPRODUCT('Conn DCF'!$E$62:$X$62,1/(1+$B76)^'Conn DCF'!$E$79:$X$79)+'Conn DCF'!$X$62*(1+D$74)/($B76-D$74)/(1+$B76)^20)+'Space DCF'!$B$111+'AI DCF'!$B$103 -> 796390.86 | E76: =(SUMPRODUCT('Conn DCF'!$E$62:$X$62,1/(1+$B76)^'Conn DCF'!$E$79:$X$79)+'Conn DCF'!$X$62*(1+E$74)/($B76-E$74)/(1+$B76)^20)+'Space DCF'!$B$111+'AI DCF'!$B$103 -> 835008.64 | F76: =(SUMPRODUCT('Conn DCF'!$E$62:$X$62,1/(1+$B76)^'Conn DCF'!$E$79:$X$79)+'Conn DCF'!$X$62*(1+F$74)/($B76-F$74)/(1+$B76)^20)+'Space DCF'!$B$111+'AI DCF'!$B$103 -> 880306.1 | G76: =(SUMPRODUCT('Conn DCF'!$E$62:$X$62,1/(1+$B76)^'Conn DCF'!$E$79:$X$79)+'Conn DCF'!$X$62*(1+G$74)/($B76-G$74)/(1+$B76)^20)+'Space DCF'!$B$111+'AI DCF'!$B$103 -> 934180.39 | H76: =(SUMPRODUCT('Conn DCF'!$E$62:$X$62,1/(1+$B76)^'Conn DCF'!$E$79:$X$79)+'Conn DCF'!$X$62*(1+H$74)/($B76-H$74)/(1+$B76)^20)+'Space DCF'!$B$111+'AI DCF'!$B$103 -> 999322.2 | I76: =(SUMPRODUCT('Conn DCF'!$E$62:$X$62,1/(1+$B76)^'Conn DCF'!$E$79:$X$79)+'Conn DCF'!$X$62*(1+I$74)/($B76-I$74)/(1+$B76)^20)+'Space DCF'!$B$111+'AI DCF'!$B$103 -> 1079679.2
B77: ='Conn DCF'!B46-0.0025 -> 0.061406891 | C77: =(SUMPRODUCT('Conn DCF'!$E$62:$X$62,1/(1+$B77)^'Conn DCF'!$E$79:$X$79)+'Conn DCF'!$X$62*(1+C$74)/($B77-C$74)/(1+$B77)^20)+'Space DCF'!$B$111+'AI DCF'!$B$103 -> 708837.73 | D77: =(SUMPRODUCT('Conn DCF'!$E$62:$X$62,1/(1+$B77)^'Conn DCF'!$E$79:$X$79)+'Conn DCF'!$X$62*(1+D$74)/($B77-D$74)/(1+$B77)^20)+'Space DCF'!$B$111+'AI DCF'!$B$103 -> 736598.51 | E77: =(SUMPRODUCT('Conn DCF'!$E$62:$X$62,1/(1+$B77)^'Conn DCF'!$E$79:$X$79)+'Conn DCF'!$X$62*(1+E$74)/($B77-E$74)/(1+$B77)^20)+'Space DCF'!$B$111+'AI DCF'!$B$103 -> 768452.96 | F77: =(SUMPRODUCT('Conn DCF'!$E$62:$X$62,1/(1+$B77)^'Conn DCF'!$E$79:$X$79)+'Conn DCF'!$X$62*(1+F$74)/($B77-F$74)/(1+$B77)^20)+'Space DCF'!$B$111+'AI DCF'!$B$103 -> 805378.67 | G77: =(SUMPRODUCT('Conn DCF'!$E$62:$X$62,1/(1+$B77)^'Conn DCF'!$E$79:$X$79)+'Conn DCF'!$X$62*(1+G$74)/($B77-G$74)/(1+$B77)^20)+'Space DCF'!$B$111+'AI DCF'!$B$103 -> 848691.39 | H77: =(SUMPRODUCT('Conn DCF'!$E$62:$X$62,1/(1+$B77)^'Conn DCF'!$E$79:$X$79)+'Conn DCF'!$X$62*(1+H$74)/($B77-H$74)/(1+$B77)^20)+'Space DCF'!$B$111+'AI DCF'!$B$103 -> 900205.13 | I77: =(SUMPRODUCT('Conn DCF'!$E$62:$X$62,1/(1+$B77)^'Conn DCF'!$E$79:$X$79)+'Conn DCF'!$X$62*(1+I$74)/($B77-I$74)/(1+$B77)^20)+'Space DCF'!$B$111+'AI DCF'!$B$103 -> 962492.71
B78: ='Conn DCF'!B46 -> 0.063906891 | C78: =(SUMPRODUCT('Conn DCF'!$E$62:$X$62,1/(1+$B78)^'Conn DCF'!$E$79:$X$79)+'Conn DCF'!$X$62*(1+C$74)/($B78-C$74)/(1+$B78)^20)+'Space DCF'!$B$111+'AI DCF'!$B$103 -> 661360.45 | D78: =(SUMPRODUCT('Conn DCF'!$E$62:$X$62,1/(1+$B78)^'Conn DCF'!$E$79:$X$79)+'Conn DCF'!$X$62*(1+D$74)/($B78-D$74)/(1+$B78)^20)+'Space DCF'!$B$111+'AI DCF'!$B$103 -> 684702.01 | E78: =(SUMPRODUCT('Conn DCF'!$E$62:$X$62,1/(1+$B78)^'Conn DCF'!$E$79:$X$79)+'Conn DCF'!$X$62*(1+E$74)/($B78-E$74)/(1+$B78)^20)+'Space DCF'!$B$111+'AI DCF'!$B$103 -> 711249.23 | F78: =(SUMPRODUCT('Conn DCF'!$E$62:$X$62,1/(1+$B78)^'Conn DCF'!$E$79:$X$79)+'Conn DCF'!$X$62*(1+F$74)/($B78-F$74)/(1+$B78)^20)+'Space DCF'!$B$111+'AI DCF'!$B$103 -> 741711.17 | G78: =(SUMPRODUCT('Conn DCF'!$E$62:$X$62,1/(1+$B78)^'Conn DCF'!$E$79:$X$79)+'Conn DCF'!$X$62*(1+G$74)/($B78-G$74)/(1+$B78)^20)+'Space DCF'!$B$111+'AI DCF'!$B$103 -> 777022.67 | H78: =(SUMPRODUCT('Conn DCF'!$E$62:$X$62,1/(1+$B78)^'Conn DCF'!$E$79:$X$79)+'Conn DCF'!$X$62*(1+H$74)/($B78-H$74)/(1+$B78)^20)+'Space DCF'!$B$111+'AI DCF'!$B$103 -> 818441.98 | I78: =(SUMPRODUCT('Conn DCF'!$E$62:$X$62,1/(1+$B78)^'Conn DCF'!$E$79:$X$79)+'Conn DCF'!$X$62*(1+I$74)/($B78-I$74)/(1+$B78)^20)+'Space DCF'!$B$111+'AI DCF'!$B$103 -> 867703.8
B79: ='Conn DCF'!B46+0.0025 -> 0.066406891 | C79: =(SUMPRODUCT('Conn DCF'!$E$62:$X$62,1/(1+$B79)^'Conn DCF'!$E$79:$X$79)+'Conn DCF'!$X$62*(1+C$74)/($B79-C$74)/(1+$B79)^20)+'Space DCF'!$B$111+'AI DCF'!$B$103 -> 619482.55 | D79: =(SUMPRODUCT('Conn DCF'!$E$62:$X$62,1/(1+$B79)^'Conn DCF'!$E$79:$X$79)+'Conn DCF'!$X$62*(1+D$74)/($B79-D$74)/(1+$B79)^20)+'Space DCF'!$B$111+'AI DCF'!$B$103 -> 639263.94 | E79: =(SUMPRODUCT('Conn DCF'!$E$62:$X$62,1/(1+$B79)^'Conn DCF'!$E$79:$X$79)+'Conn DCF'!$X$62*(1+E$74)/($B79-E$74)/(1+$B79)^20)+'Space DCF'!$B$111+'AI DCF'!$B$103 -> 661587.47 | F79: =(SUMPRODUCT('Conn DCF'!$E$62:$X$62,1/(1+$B79)^'Conn DCF'!$E$79:$X$79)+'Conn DCF'!$X$62*(1+F$74)/($B79-F$74)/(1+$B79)^20)+'Space DCF'!$B$111+'AI DCF'!$B$103 -> 686976.83 | G79: =(SUMPRODUCT('Conn DCF'!$E$62:$X$62,1/(1+$B79)^'Conn DCF'!$E$79:$X$79)+'Conn DCF'!$X$62*(1+G$74)/($B79-G$74)/(1+$B79)^20)+'Space DCF'!$B$111+'AI DCF'!$B$103 -> 716110.19 | H79: =(SUMPRODUCT('Conn DCF'!$E$62:$X$62,1/(1+$B79)^'Conn DCF'!$E$79:$X$79)+'Conn DCF'!$X$62*(1+H$74)/($B79-H$74)/(1+$B79)^20)+'Space DCF'!$B$111+'AI DCF'!$B$103 -> 749881.59 | I79: =(SUMPRODUCT('Conn DCF'!$E$62:$X$62,1/(1+$B79)^'Conn DCF'!$E$79:$X$79)+'Conn DCF'!$X$62*(1+I$74)/($B79-I$74)/(1+$B79)^20)+'Space DCF'!$B$111+'AI DCF'!$B$103 -> 789494.4
B80: ='Conn DCF'!B46+0.005 -> 0.068906891 | C80: =(SUMPRODUCT('Conn DCF'!$E$62:$X$62,1/(1+$B80)^'Conn DCF'!$E$79:$X$79)+'Conn DCF'!$X$62*(1+C$74)/($B80-C$74)/(1+$B80)^20)+'Space DCF'!$B$111+'AI DCF'!$B$103 -> 582292.47 | D80: =(SUMPRODUCT('Conn DCF'!$E$62:$X$62,1/(1+$B80)^'Conn DCF'!$E$79:$X$79)+'Conn DCF'!$X$62*(1+D$74)/($B80-D$74)/(1+$B80)^20)+'Space DCF'!$B$111+'AI DCF'!$B$103 -> 599174.52 | E80: =(SUMPRODUCT('Conn DCF'!$E$62:$X$62,1/(1+$B80)^'Conn DCF'!$E$79:$X$79)+'Conn DCF'!$X$62*(1+E$74)/($B80-E$74)/(1+$B80)^20)+'Space DCF'!$B$111+'AI DCF'!$B$103 -> 618095.12 | F80: =(SUMPRODUCT('Conn DCF'!$E$62:$X$62,1/(1+$B80)^'Conn DCF'!$E$79:$X$79)+'Conn DCF'!$X$62*(1+F$74)/($B80-F$74)/(1+$B80)^20)+'Space DCF'!$B$111+'AI DCF'!$B$103 -> 639447.25 | G80: =(SUMPRODUCT('Conn DCF'!$E$62:$X$62,1/(1+$B80)^'Conn DCF'!$E$79:$X$79)+'Conn DCF'!$X$62*(1+G$74)/($B80-G$74)/(1+$B80)^20)+'Space DCF'!$B$111+'AI DCF'!$B$103 -> 663731.8 | H80: =(SUMPRODUCT('Conn DCF'!$E$62:$X$62,1/(1+$B80)^'Conn DCF'!$E$79:$X$79)+'Conn DCF'!$X$62*(1+H$74)/($B80-H$74)/(1+$B80)^20)+'Space DCF'!$B$111+'AI DCF'!$B$103 -> 691597.42 | I80: =(SUMPRODUCT('Conn DCF'!$E$62:$X$62,1/(1+$B80)^'Conn DCF'!$E$79:$X$79)+'Conn DCF'!$X$62*(1+I$74)/($B80-I$74)/(1+$B80)^20)+'Space DCF'!$B$111+'AI DCF'!$B$103 -> 723899.27
B81: ='Conn DCF'!B46+0.0075 -> 0.071406891 | C81: =(SUMPRODUCT('Conn DCF'!$E$62:$X$62,1/(1+$B81)^'Conn DCF'!$E$79:$X$79)+'Conn DCF'!$X$62*(1+C$74)/($B81-C$74)/(1+$B81)^20)+'Space DCF'!$B$111+'AI DCF'!$B$103 -> 549065.34 | D81: =(SUMPRODUCT('Conn DCF'!$E$62:$X$62,1/(1+$B81)^'Conn DCF'!$E$79:$X$79)+'Conn DCF'!$X$62*(1+D$74)/($B81-D$74)/(1+$B81)^20)+'Space DCF'!$B$111+'AI DCF'!$B$103 -> 563563.44 | E81: =(SUMPRODUCT('Conn DCF'!$E$62:$X$62,1/(1+$B81)^'Conn DCF'!$E$79:$X$79)+'Conn DCF'!$X$62*(1+E$74)/($B81-E$74)/(1+$B81)^20)+'Space DCF'!$B$111+'AI DCF'!$B$103 -> 579712.54 | F81: =(SUMPRODUCT('Conn DCF'!$E$62:$X$62,1/(1+$B81)^'Conn DCF'!$E$79:$X$79)+'Conn DCF'!$X$62*(1+F$74)/($B81-F$74)/(1+$B81)^20)+'Space DCF'!$B$111+'AI DCF'!$B$103 -> 597811.7 | G81: =(SUMPRODUCT('Conn DCF'!$E$62:$X$62,1/(1+$B81)^'Conn DCF'!$E$79:$X$79)+'Conn DCF'!$X$62*(1+G$74)/($B81-G$74)/(1+$B81)^20)+'Space DCF'!$B$111+'AI DCF'!$B$103 -> 618236.81 | H81: =(SUMPRODUCT('Conn DCF'!$E$62:$X$62,1/(1+$B81)^'Conn DCF'!$E$79:$X$79)+'Conn DCF'!$X$62*(1+H$74)/($B81-H$74)/(1+$B81)^20)+'Space DCF'!$B$111+'AI DCF'!$B$103 -> 641467.05 | I81: =(SUMPRODUCT('Conn DCF'!$E$62:$X$62,1/(1+$B81)^'Conn DCF'!$E$79:$X$79)+'Conn DCF'!$X$62*(1+I$74)/($B81-I$74)/(1+$B81)^20)+'Space DCF'!$B$111+'AI DCF'!$B$103 -> 668122.87
A83: FULLY DILUTED SHARE COUNT RECONCILIATION
B85: Shares (M) | H85: Source / Note
A86: Class A Common Stock (pro forma) | B86: 6906 | H86: S-1 Cap Table: 6,824,581,339 shares
A87: Class B Common Stock (pro forma) | B87: 5696 | H87: S-1 Cap Table: 5,695,729,430 shares
A88: Class C (reclassified to A pre-IPO) | B88: 0 | H88: 494M pre-reclass shares converted to Class A
A89: Total Basic Pro Forma | B89: =B86+B87+B88 -> 12602 | H89: = 12,520,310,769 shares
A90: Dilutive: Stock Options | B90: 292 | H90: S-1 EPS Note: FY2024 diluted denominator
A91: Dilutive: RSUs | B91: 45 | H91: S-1 EPS Note: FY2024 diluted denominator
A92: Dilutive: Other (ESPP + est.) | B92: 102 | H92: Residual to reconcile to model FD count
A93: Total Fully Diluted (Model) | B93: =B89+B90+B91+B92 -> 13041 | H93: = SOTP B25 (12,960M shares)
A94: Musk Performance Shares (not in FD) | B94: 800 | H94: 12 tranches x 66.7M; vest at $500B-$6.5T mkt cap
A95: IPO Terms (Reuters, pre-final) | H95: $135/sh | 555.6M shares | ~$75B gross | ~$1.75T
A97: LOCK-UP & FLOAT SCHEDULE (Source: SEC Filing, Jun 17 2026 | Boyan Girginov analysis)
A99: Date | B99: Event | C99: Cumulative % Float | D99: Shares Tradeable (M) | E99: Float-Adj Mkt Cap ($M)
A100: 46185 | B100: IPO – Initial Float | C100: 0.049 | D100: =C100*$B$29 -> 639.009 | E100: =D100*$D$31 -> 34218.963
A101: 46242 | B101: Accelerated Early Unlock Begins | C101: 0.118 | D101: =C101*$B$29 -> 1538.838 | E101: =D101*$D$31 -> 82404.851
A102: 46274 | B102: Early Release Window | C102: 0.177 | D102: =C102*$B$29 -> 2308.257 | E102: =D102*$D$31 -> 123607.28
A103: 46319 | B103: Early Release Window | C103: 0.251 | D103: =C103*$B$29 -> 3273.291 | E103: =D103*$D$31 -> 175284.89
A104: 46364 | B104: Accelerated Window Closes | C104: 0.375 | D104: =C104*$B$29 -> 4890.375 | E104: =D104*$D$31 -> 261879.82
A105: 46388 | B105: Normal Unlock Schedule Begins | C105: 0.4 | D105: =C105*$B$29 -> 5216.4 | E105: =D105*$D$31 -> 279338.48
A106: 46464 | B106: Extended Lock-Up Pool | C106: 0.441 | D106: =C106*$B$29 -> 5751.081 | E106: =D106*$D$31 -> 307970.67
A107: 46550 | B107: ⚠ MUSK DAY 366 (+46.1% in ONE day) | C107: 0.969 | D107: =C107*$B$29 -> 12636.729 | E107: =D107*$D$31 -> 676697.46
A108: 46600 | B108: Musk Lock-Up Ends | C108: 0.995 | D108: =C108*$B$29 -> 12975.795 | E108: =D108*$D$31 -> 694854.46
A109: 46631 | B109: Full Unlock – 100% | C109: 1 | D109: =C109*$B$29 -> 13041 | E109: =D109*$D$31 -> 698346.19
A110: 4.9% IPO float (incl. greenshoe) | Musk 46.1% stake unlocks Day 366 (Jun 12, 2027) | Full unlock ~Sep 2027
A111: Cursor option scenario: +444M (new) shares if exercised at IPO price – see Pro-Forma section above

Sheet Conn DCF
A1: SpaceX – Connectivity Segment DCF (Starlink)
A2: S-1 Filed May 20, 2026 | 20-Year Explicit Forecast FY2026E–FY2045E | $ in Millions
A5: SCENARIO SELECTOR | B5: =Dashboard!B31 -> 2 | C5: =IF(B5=1,"◀ BEAR",IF(B5=2,"◀ BASE","◀ BULL")) -> ◀ BASE | D5: (1 = Bear | 2 = Base | 3 = Bull)
B6: FY2023A | C6: FY2024A | D6: FY2025A | E6: FY2026E | F6: FY2027E | G6: FY2028E | H6: FY2029E | I6: FY2030E | J6: FY2031E | K6: FY2032E | L6: FY2033E | M6: FY2034E | N6: FY2035E | O6: FY2036E | P6: FY2037E | Q6: FY2038E | R6: FY2039E | S6: FY2040E | T6: FY2041E | U6: FY2042E | V6: FY2043E | W6: FY2044E | X6: FY2045E
A8: BEAR CASE ASSUMPTIONS
A9: Revenue Growth % (YoY) | E9: 0.28 | F9: 0.24 | G9: 0.2 | H9: 0.18 | I9: 0.15 | J9: 0.13 | K9: 0.11 | L9: 0.09 | M9: 0.08 | N9: 0.07 | O9: 0.06 | P9: 0.055 | Q9: 0.05 | R9: 0.045 | S9: 0.04 | T9: 0.038 | U9: 0.035 | V9: 0.032 | W9: 0.03 | X9: 0.025
A10: EBITDA Margin % | E10: 0.6 | F10: 0.61 | G10: 0.62 | H10: 0.63 | I10: 0.64 | J10: 0.64 | K10: 0.65 | L10: 0.65 | M10: 0.65 | N10: 0.65 | O10: 0.655 | P10: 0.655 | Q10: 0.66 | R10: 0.66 | S10: 0.66 | T10: 0.665 | U10: 0.665 | V10: 0.67 | W10: 0.67 | X10: 0.67
A11: Capex % of Revenue | E11: 0.34 | F11: 0.3 | G11: 0.26 | H11: 0.23 | I11: 0.2 | J11: 0.18 | K11: 0.16 | L11: 0.14 | M11: 0.12 | N11: 0.11 | O11: 0.105 | P11: 0.1 | Q11: 0.1 | R11: 0.095 | S11: 0.095 | T11: 0.09 | U11: 0.09 | V11: 0.09 | W11: 0.09 | X11: 0.09
A12: ΔNW Cap % of ΔRevenue | E12: 0.05 | F12: 0.05 | G12: 0.05 | H12: 0.05 | I12: 0.04 | J12: 0.04 | K12: 0.04 | L12: 0.03 | M12: 0.03 | N12: 0.03 | O12: 0.03 | P12: 0.03 | Q12: 0.03 | R12: 0.025 | S12: 0.025 | T12: 0.025 | U12: 0.025 | V12: 0.025 | W12: 0.025 | X12: 0.025
A13: Active Fleet (End of Period) | E13: 10200 | F13: 11400 | G13: 12800 | H13: 13850 | I13: 14950 | J13: 16000 | K13: 16800 | L13: 17400 | M13: 18000 | N13: 18600 | O13: 18950 | P13: 19300 | Q13: 19650 | R13: 20000 | S13: 20350 | T13: 20550 | U13: 20750 | V13: 20950 | W13: 21150 | X13: 21350
A14: SBC (% of Revenue) | E14: 0.03 | F14: 0.03 | G14: 0.029 | H14: 0.029 | I14: 0.028 | J14: 0.028 | K14: 0.027 | L14: 0.027 | M14: 0.026 | N14: 0.026 | O14: 0.025 | P14: 0.025 | Q14: 0.024 | R14: 0.024 | S14: 0.023 | T14: 0.023 | U14: 0.022 | V14: 0.022 | W14: 0.021 | X14: 0.02
A15: Terminal Growth Rate | B15: =WACC!D42 -> 0.025
A16: WACC | B16: =WACC!B42 -> 0.063906891
A18: BASE CASE ASSUMPTIONS
A19: Revenue Growth % (YoY) | E19: 0.38 | F19: 0.32 | G19: 0.26 | H19: 0.22 | I19: 0.18 | J19: 0.15 | K19: 0.13 | L19: 0.11 | M19: 0.09 | N19: 0.08 | O19: 0.07 | P19: 0.065 | Q19: 0.06 | R19: 0.055 | S19: 0.05 | T19: 0.045 | U19: 0.04 | V19: 0.038 | W19: 0.035 | X19: 0.03
A20: EBITDA Margin % | E20: 0.63 | F20: 0.65 | G20: 0.66 | H20: 0.67 | I20: 0.68 | J20: 0.68 | K20: 0.68 | L20: 0.68 | M20: 0.68 | N20: 0.68 | O20: 0.685 | P20: 0.685 | Q20: 0.69 | R20: 0.69 | S20: 0.69 | T20: 0.695 | U20: 0.695 | V20: 0.7 | W20: 0.7 | X20: 0.7
A21: Capex % of Revenue | E21: 0.32 | F21: 0.27 | G21: 0.23 | H21: 0.2 | I21: 0.17 | J21: 0.15 | K21: 0.13 | L21: 0.12 | M21: 0.11 | N21: 0.1 | O21: 0.095 | P21: 0.09 | Q21: 0.088 | R21: 0.085 | S21: 0.082 | T21: 0.08 | U21: 0.08 | V21: 0.08 | W21: 0.08 | X21: 0.08
A22: ΔNW Cap % of ΔRevenue | E22: 0.04 | F22: 0.04 | G22: 0.04 | H22: 0.04 | I22: 0.03 | J22: 0.03 | K22: 0.03 | L22: 0.03 | M22: 0.02 | N22: 0.02 | O22: 0.02 | P22: 0.02 | Q22: 0.02 | R22: 0.02 | S22: 0.02 | T22: 0.015 | U22: 0.015 | V22: 0.015 | W22: 0.015 | X22: 0.015
A23: Active Fleet (End of Period) | E23: 11040 | F23: 12696 | G23: 14600 | H23: 16060 | I23: 17666 | J23: 19433 | K23: 20405 | L23: 21425 | M23: 22496 | N23: 23621 | O23: 24093 | P23: 24575 | Q23: 25067 | R23: 25568 | S23: 26079 | T23: 26340 | U23: 26603 | V23: 26869 | W23: 27138 | X23: 27409
A24: SBC (% of Revenue) | E24: 0.025 | F24: 0.025 | G24: 0.024 | H24: 0.024 | I24: 0.023 | J24: 0.023 | K24: 0.022 | L24: 0.022 | M24: 0.021 | N24: 0.021 | O24: 0.02 | P24: 0.02 | Q24: 0.019 | R24: 0.019 | S24: 0.018 | T24: 0.018 | U24: 0.017 | V24: 0.017 | W24: 0.016 | X24: 0.015
A25: Terminal Growth Rate | B25: =WACC!C42 -> 0.03
A26: WACC | B26: =WACC!B42 -> 0.063906891
A28: BULL CASE ASSUMPTIONS
A29: Revenue Growth % (YoY) | E29: 0.48 | F29: 0.4 | G29: 0.33 | H29: 0.27 | I29: 0.22 | J29: 0.18 | K29: 0.15 | L29: 0.13 | M29: 0.11 | N29: 0.09 | O29: 0.085 | P29: 0.08 | Q29: 0.075 | R29: 0.07 | S29: 0.065 | T29: 0.06 | U29: 0.055 | V29: 0.05 | W29: 0.045 | X29: 0.04
A30: EBITDA Margin % | E30: 0.65 | F30: 0.67 | G30: 0.69 | H30: 0.7 | I30: 0.71 | J30: 0.71 | K30: 0.72 | L30: 0.72 | M30: 0.72 | N30: 0.72 | O30: 0.72 | P30: 0.72 | Q30: 0.725 | R30: 0.725 | S30: 0.73 | T30: 0.73 | U30: 0.73 | V30: 0.73 | W30: 0.73 | X30: 0.73
A31: Capex % of Revenue | E31: 0.3 | F31: 0.25 | G31: 0.21 | H31: 0.18 | I31: 0.15 | J31: 0.13 | K31: 0.11 | L31: 0.1 | M31: 0.09 | N31: 0.09 | O31: 0.085 | P31: 0.082 | Q31: 0.08 | R31: 0.078 | S31: 0.075 | T31: 0.072 | U31: 0.07 | V31: 0.07 | W31: 0.07 | X31: 0.07
A32: ΔNW Cap % of ΔRevenue | E32: 0.03 | F32: 0.03 | G32: 0.03 | H32: 0.03 | I32: 0.02 | J32: 0.02 | K32: 0.02 | L32: 0.02 | M32: 0.02 | N32: 0.02 | O32: 0.02 | P32: 0.02 | Q32: 0.015 | R32: 0.015 | S32: 0.015 | T32: 0.015 | U32: 0.015 | V32: 0.015 | W32: 0.015 | X32: 0.015
A33: Active Fleet (End of Period) | E33: 12100 | F33: 14400 | G33: 17000 | H33: 19200 | I33: 21600 | J33: 24200 | K33: 25800 | L33: 27500 | M33: 29100 | N33: 30800 | O33: 31600 | P33: 32400 | Q33: 33250 | R33: 34100 | S33: 35000 | T33: 35500 | U33: 36000 | V33: 36500 | W33: 37000 | X33: 37500
A34: SBC (% of Revenue) | E34: 0.02 | F34: 0.02 | G34: 0.019 | H34: 0.019 | I34: 0.018 | J34: 0.018 | K34: 0.017 | L34: 0.017 | M34: 0.016 | N34: 0.016 | O34: 0.015 | P34: 0.015 | Q34: 0.014 | R34: 0.014 | S34: 0.013 | T34: 0.013 | U34: 0.012 | V34: 0.012 | W34: 0.011 | X34: 0.01
A35: Terminal Growth Rate | B35: =WACC!E42 -> 0.035
A36: WACC | B36: =WACC!B42 -> 0.063906891
A38: SELECTED CASE ASSUMPTIONS (auto-updates with Scenario Selector)
A39: Revenue Growth % (YoY) | E39: =IF($B$5=1,E9,IF($B$5=2,E19,E29)) -> 0.38 | F39: =IF($B$5=1,F9,IF($B$5=2,F19,F29)) -> 0.32 | G39: =IF($B$5=1,G9,IF($B$5=2,G19,G29)) -> 0.26 | H39: =IF($B$5=1,H9,IF($B$5=2,H19,H29)) -> 0.22 | I39: =IF($B$5=1,I9,IF($B$5=2,I19,I29)) -> 0.18 | J39: =IF($B$5=1,J9,IF($B$5=2,J19,J29)) -> 0.15 | K39: =IF($B$5=1,K9,IF($B$5=2,K19,K29)) -> 0.13 | L39: =IF($B$5=1,L9,IF($B$5=2,L19,L29)) -> 0.11 | ... X39: =IF($B$5=1,X9,IF($B$5=2,X19,X29)) -> 0.03
A40: EBITDA Margin % | E40: =IF($B$5=1,E10,IF($B$5=2,E20,E30)) -> 0.63 | F40: =IF($B$5=1,F10,IF($B$5=2,F20,F30)) -> 0.65 | G40: =IF($B$5=1,G10,IF($B$5=2,G20,G30)) -> 0.66 | H40: =IF($B$5=1,H10,IF($B$5=2,H20,H30)) -> 0.67 | I40: =IF($B$5=1,I10,IF($B$5=2,I20,I30)) -> 0.68 | J40: =IF($B$5=1,J10,IF($B$5=2,J20,J30)) -> 0.68 | K40: =IF($B$5=1,K10,IF($B$5=2,K20,K30)) -> 0.68 | L40: =IF($B$5=1,L10,IF($B$5=2,L20,L30)) -> 0.68 | ... X40: =IF($B$5=1,X10,IF($B$5=2,X20,X30)) -> 0.7
A41: Capex % of Revenue | E41: =IF($B$5=1,E11,IF($B$5=2,E21,E31)) -> 0.32 | F41: =IF($B$5=1,F11,IF($B$5=2,F21,F31)) -> 0.27 | G41: =IF($B$5=1,G11,IF($B$5=2,G21,G31)) -> 0.23 | H41: =IF($B$5=1,H11,IF($B$5=2,H21,H31)) -> 0.2 | I41: =IF($B$5=1,I11,IF($B$5=2,I21,I31)) -> 0.17 | J41: =IF($B$5=1,J11,IF($B$5=2,J21,J31)) -> 0.15 | K41: =IF($B$5=1,K11,IF($B$5=2,K21,K31)) -> 0.13 | L41: =IF($B$5=1,L11,IF($B$5=2,L21,L31)) -> 0.12 | ... X41: =IF($B$5=1,X11,IF($B$5=2,X21,X31)) -> 0.08
A42: ΔNW Cap % of ΔRevenue | E42: =IF($B$5=1,E12,IF($B$5=2,E22,E32)) -> 0.04 | F42: =IF($B$5=1,F12,IF($B$5=2,F22,F32)) -> 0.04 | G42: =IF($B$5=1,G12,IF($B$5=2,G22,G32)) -> 0.04 | H42: =IF($B$5=1,H12,IF($B$5=2,H22,H32)) -> 0.04 | I42: =IF($B$5=1,I12,IF($B$5=2,I22,I32)) -> 0.03 | J42: =IF($B$5=1,J12,IF($B$5=2,J22,J32)) -> 0.03 | K42: =IF($B$5=1,K12,IF($B$5=2,K22,K32)) -> 0.03 | L42: =IF($B$5=1,L12,IF($B$5=2,L22,L32)) -> 0.03 | ... X42: =IF($B$5=1,X12,IF($B$5=2,X22,X32)) -> 0.015
A43: Active Fleet (End of Period) | E43: =IF($B$5=1,E13,IF($B$5=2,E23,E33)) -> 11040 | F43: =IF($B$5=1,F13,IF($B$5=2,F23,F33)) -> 12696 | G43: =IF($B$5=1,G13,IF($B$5=2,G23,G33)) -> 14600 | H43: =IF($B$5=1,H13,IF($B$5=2,H23,H33)) -> 16060 | I43: =IF($B$5=1,I13,IF($B$5=2,I23,I33)) -> 17666 | J43: =IF($B$5=1,J13,IF($B$5=2,J23,J33)) -> 19433 | K43: =IF($B$5=1,K13,IF($B$5=2,K23,K33)) -> 20405 | L43: =IF($B$5=1,L13,IF($B$5=2,L23,L33)) -> 21425 | ... X43: =IF($B$5=1,X13,IF($B$5=2,X23,X33)) -> 27409
A44: SBC (% of Revenue) | E44: =IF($B$5=1,E14,IF($B$5=2,E24,E34)) -> 0.025 | F44: =IF($B$5=1,F14,IF($B$5=2,F24,F34)) -> 0.025 | G44: =IF($B$5=1,G14,IF($B$5=2,G24,G34)) -> 0.024 | H44: =IF($B$5=1,H14,IF($B$5=2,H24,H34)) -> 0.024 | I44: =IF($B$5=1,I14,IF($B$5=2,I24,I34)) -> 0.023 | J44: =IF($B$5=1,J14,IF($B$5=2,J24,J34)) -> 0.023 | K44: =IF($B$5=1,K14,IF($B$5=2,K24,K34)) -> 0.022 | L44: =IF($B$5=1,L14,IF($B$5=2,L24,L34)) -> 0.022 | ... X44: =IF($B$5=1,X14,IF($B$5=2,X24,X34)) -> 0.015
A45: Terminal Growth Rate | B45: =IF($B$5=1,B15,IF($B$5=2,B25,B35)) -> 0.03
A46: WACC | B46: =IF($B$5=1,B16,IF($B$5=2,B26,B36)) -> 0.063906891
A47: Blended WACC (Sensitivity Center) | B47: =AVERAGE(E77:X77) -> 0.072383097
A49: CONNECTIVITY SEGMENT – INCOME STATEMENT & FREE CASH FLOW ($M)
A50: Revenue | B50: =Actuals!B8 -> 3869 | C50: =Actuals!C8 -> 7599 | D50: =Actuals!D8 -> 11387 | E50: =D50*(1+E39) -> 15714.06 | F50: =E50*(1+F39) -> 20742.559 | G50: =F50*(1+G39) -> 26135.625 | H50: =G50*(1+H39) -> 31885.462 | I50: =H50*(1+I39) -> 37624.845 | J50: =I50*(1+J39) -> 43268.572 | K50: =J50*(1+K39) -> 48893.486 | L50: =K50*(1+L39) -> 54271.77 | ... X50: =W50*(1+X39) -> 102808.69
A51: % YoY Growth | B51: – | C51: =C50/B50-1 -> 0.9640734 | D51: =D50/C50-1 -> 0.49848664 | E51: =E50/D50-1 -> 0.38 | F51: =F50/E50-1 -> 0.32 | G51: =G50/F50-1 -> 0.26 | H51: =H50/G50-1 -> 0.22 | I51: =I50/H50-1 -> 0.18 | J51: =J50/I50-1 -> 0.15 | ... X51: =X50/W50-1 -> 0.03
A52: EBITDA | B52: =Actuals!B11 -> 1602 | C52: =Actuals!C11 -> 3849 | D52: =Actuals!D11 -> 7168 | E52: =E50*E40 -> 9899.8578 | F52: =F50*F40 -> 13482.663 | G52: =G50*G40 -> 17249.512 | H52: =H50*H40 -> 21363.26 | I52: =I50*I40 -> 25584.895 | J52: =J50*J40 -> 29422.629 | K52: =K50*K40 -> 33247.571 | L52: =L50*L40 -> 36904.803 | ... X52: =X50*X40 -> 71966.08
A53: EBITDA Margin % | B53: =B52/B50 -> 0.41406048 | C53: =C52/C50 -> 0.50651402 | D53: =D52/D50 -> 0.62948977 | E53: =E52/E50 -> 0.63 | F53: =F52/F50 -> 0.65 | G53: =G52/G50 -> 0.66 | H53: =H52/H50 -> 0.67 | I53: =I52/I50 -> 0.68 | ... X53: =X52/X50 -> 0.7
A54: D&A (Physical Fleet Model) | B54: =Actuals!B14 -> 884 | C54: =Actuals!C14 -> 1508 | D54: =Actuals!D14 -> 2376 | E54: =E171 -> 2760 | F54: =F171 -> 3174 | G54: =G171 -> 3650 | H54: =H171 -> 4015 | I54: =I171 -> 4416.5 | J54: =J171 -> 4858.25 | K54: =K171 -> 5101.25 | L54: =L171 -> 5356.25 | ... X54: =X171 -> 6852.25
A55: EBIT (EBITDA − D&A) | B55: =B52-B54 -> 718 | C55: =C52-C54 -> 2341 | D55: =D52-D54 -> 4792 | E55: =E52-E54 -> 7139.8578 | F55: =F52-F54 -> 10308.663 | G55: =G52-G54 -> 13599.512 | H55: =H52-H54 -> 17348.26 | I55: =I52-I54 -> 21168.395 | ... X55: =X52-X54 -> 65113.83
A56: EBIT Margin % | B56: =B55/B50 -> 0.18557767 | C56: =C55/C50 -> 0.30806685 | D56: =D55/D50 -> 0.42083077 | E56: =E55/E50 -> 0.45436111 | F56: =F55/F50 -> 0.49698127 | G56: =G55/G50 -> 0.52034388 | H56: =H55/H50 -> 0.54408054 | I56: =I55/I50 -> 0.56261746 | ... X56: =X55/X50 -> 0.6333495
A57: (–) Tax on EBIT | B57: =MAX(B55,0)*WACC!$B$9 -> 150.78 | C57: =MAX(C55,0)*WACC!$B$9 -> 491.61 | D57: =MAX(D55,0)*WACC!$B$9 -> 1006.32 | E57: =MAX(E55,0)*WACC!$B$9 -> 1499.3701 | F57: =MAX(F55,0)*WACC!$B$9 -> 2164.8193 | G57: =MAX(G55,0)*WACC!$B$9 -> 2855.8976 | H57: =MAX(H55,0)*WACC!$B$9 -> 3643.1345 | I57: =MAX(I55,0)*WACC!$B$9 -> 4445.3629 | ... X57: =MAX(X55,0)*WACC!$B$9 -> 13673.904
A58: NOPAT | B58: =B55-B57 -> 567.22 | C58: =C55-C57 -> 1849.39 | D58: =D55-D57 -> 3785.68 | E58: =E55-E57 -> 5640.4877 | F58: =F55-F57 -> 8143.8441 | G58: =G55-G57 -> 10743.615 | H58: =H55-H57 -> 13705.125 | I58: =I55-I57 -> 16723.032 | ... X58: =X55-X57 -> 51439.925
A59: (+) D&A | B59: =B54 -> 884 | C59: =C54 -> 1508 | D59: =D54 -> 2376 | E59: =E54 -> 2760 | F59: =F54 -> 3174 | G59: =G54 -> 3650 | H59: =H54 -> 4015 | I59: =I54 -> 4416.5 | ... X59: =X54 -> 6852.25
A60: (–) Capital Expenditures | B60: =Actuals!B18 -> -2455 | C60: =Actuals!C18 -> -3498 | D60: =Actuals!D18 -> -4178 | E60: =-E50*E41 -> -5028.4992 | F60: =-F50*F41 -> -5600.491 | G60: =-G50*G41 -> -6011.1937 | H60: =-H50*H41 -> -6377.0924 | I60: =-I50*I41 -> -6396.2237 | J60: =-J50*J41 -> -6490.2858 | K60: =-K50*K41 -> -6356.1532 | L60: =-L50*L41 -> -6512.6124 | ... X60: =-X50*X41 -> -8224.6948
A61: (–) Increase in Net Working Capital | B61: 0 | C61: 0 | D61: 0 | E61: =-(E50-D50)*E42 -> -173.0824 | F61: =-(F50-E50)*F42 -> -201.13997 | G61: =-(G50-F50)*G42 -> -215.72262 | H61: =-(H50-G50)*H42 -> -229.9935 | I61: =-(I50-H50)*I42 -> -172.18149 | J61: =-(J50-I50)*J42 -> -169.3118 | K61: =-(K50-J50)*K42 -> -168.74743 | L61: =-(L50-K50)*L42 -> -161.3485 | ... X61: =-(X50-W50)*X42 -> -44.916416
A62: Unlevered Free Cash Flow | B62: =B58+B59+B60+B61 -> -1003.78 | C62: =C58+C59+C60+C61 -> -140.61 | D62: =D58+D59+D60+D61 -> 1983.68 | E62: =E58+E59+E60+E61-E50*E44*(1-WACC!$B$9) -> 2888.5534 | F62: =F58+F59+F60+F61-F50*F44*(1-WACC!$B$9) -> 5106.5477 | G62: =G58+G59+G60+G61-G50*G44*(1-WACC!$B$9) -> 7671.1669 | H62: =H58+H59+H60+H61-H50*H44*(1-WACC!$B$9) -> 10508.491 | I62: =I58+I59+I60+I61-I50*I44*(1-WACC!$B$9) -> 13887.483 | J62: =J58+J59+J60+J61-J50*J44*(1-WACC!$B$9) -> 16818.322 | K62: =K58+K59+K60+K61-K50*K44*(1-WACC!$B$9) -> 19962.174 | L62: =L58+L59+L60+L61-L50*L44*(1-WACC!$B$9) -> 22662.403 | ... X62: =X58+X59+X60+X61-X50*X44*(1-WACC!$B$9) -> 48804.281
A63: FCF Margin % | B63: =B62/B50 -> -0.25944172 | C63: =C62/C50 -> -0.01850375 | D63: =D62/D50 -> 0.17420567 | E63: =E62/E50 -> 0.18381967 | F63: =F62/F50 -> 0.24618696 | G63: =G62/G50 -> 0.29351382 | H63: =H62/H50 -> 0.32956997 | I63: =I62/I50 -> 0.36910406 | ... X63: =X62/X50 -> 0.47470971
A65: DCF – DISCOUNT FACTORS & PRESENT VALUES (Mid-Year Convention)
A67: TIME-WEIGHTED BETA & WACC
A68: Tier 1 (Satellite) Unlevered β | B68: ='Conn Comps'!X20 -> 0.51874806 | C68: Satellite Operators | E68: =$B$68 -> 0.51874806 | F68: =$B$68 -> 0.51874806 | G68: =$B$68 -> 0.51874806 | H68: =$B$68 -> 0.51874806 | I68: =$B$68 -> 0.51874806 | J68: =$B$68 -> 0.51874806 | K68: =$B$68 -> 0.51874806 | L68: =$B$68 -> 0.51874806 | ... X68: =$B$68 -> 0.51874806
A69: Tier 2 (EM Telecom) Unlevered β | B69: ='Conn Comps'!X37 -> 0.48368268 | C69: EM Telecom | E69: =$B$69 -> 0.48368268 | F69: =$B$69 -> 0.48368268 | G69: =$B$69 -> 0.48368268 | H69: =$B$69 -> 0.48368268 | I69: =$B$69 -> 0.48368268 | J69: =$B$69 -> 0.48368268 | K69: =$B$69 -> 0.48368268 | L69: =$B$69 -> 0.48368268 | ... X69: =$B$69 -> 0.48368268
A70: Tier 3 (Mature Wireless) Unlevered β | B70: ='Conn Comps'!X54 -> 0.20833333 | C70: Mature Wireless | E70: =$B$70 -> 0.20833333 | F70: =$B$70 -> 0.20833333 | G70: =$B$70 -> 0.20833333 | H70: =$B$70 -> 0.20833333 | I70: =$B$70 -> 0.20833333 | J70: =$B$70 -> 0.20833333 | K70: =$B$70 -> 0.20833333 | L70: =$B$70 -> 0.20833333 | ... X70: =$B$70 -> 0.20833333
A71: Tier 1 Weight | B71: =IF($B$5=1,0.6,IF($B$5=2,0.5,0.4)) -> 0.5 | C71: =IF($B$5=1,0.15,IF($B$5=2,0.1,0.05)) -> 0.1 | D71: B = Yr 1, C = Yr 20 | E71: =$B71+($C71-$B71)*(COLUMN()-5)/19 -> 0.5 | F71: =$B71+($C71-$B71)*(COLUMN()-5)/19 -> 0.47894737 | G71: =$B71+($C71-$B71)*(COLUMN()-5)/19 -> 0.45789474 | H71: =$B71+($C71-$B71)*(COLUMN()-5)/19 -> 0.43684211 | I71: =$B71+($C71-$B71)*(COLUMN()-5)/19 -> 0.41578947 | J71: =$B71+($C71-$B71)*(COLUMN()-5)/19 -> 0.39473684 | K71: =$B71+($C71-$B71)*(COLUMN()-5)/19 -> 0.37368421 | L71: =$B71+($C71-$B71)*(COLUMN()-5)/19 -> 0.35263158 | ... X71: =$B71+($C71-$B71)*(COLUMN()-5)/19 -> 0.1
A72: Tier 2 Weight | B72: =IF($B$5=1,0.25,IF($B$5=2,0.3,0.35)) -> 0.3 | C72: =IF($B$5=1,0.25,IF($B$5=2,0.2,0.15)) -> 0.2 | D72: (see E→X for glide) | E72: =$B72+($C72-$B72)*(COLUMN()-5)/19 -> 0.3 | F72: =$B72+($C72-$B72)*(COLUMN()-5)/19 -> 0.29473684 | G72: =$B72+($C72-$B72)*(COLUMN()-5)/19 -> 0.28947368 | H72: =$B72+($C72-$B72)*(COLUMN()-5)/19 -> 0.28421053 | I72: =$B72+($C72-$B72)*(COLUMN()-5)/19 -> 0.27894737 | J72: =$B72+($C72-$B72)*(COLUMN()-5)/19 -> 0.27368421 | K72: =$B72+($C72-$B72)*(COLUMN()-5)/19 -> 0.26842105 | L72: =$B72+($C72-$B72)*(COLUMN()-5)/19 -> 0.26315789 | ... X72: =$B72+($C72-$B72)*(COLUMN()-5)/19 -> 0.2
A73: Tier 3 Weight (= 1 – T1 – T2) | B73: =1-B71-B72 -> 0.2 | C73: =1-C71-C72 -> 0.7 | E73: =1-E71-E72 -> 0.2 | F73: =1-F71-F72 -> 0.22631579 | G73: =1-G71-G72 -> 0.25263158 | H73: =1-H71-H72 -> 0.27894737 | I73: =1-I71-I72 -> 0.30526316 | J73: =1-J71-J72 -> 0.33157895 | K73: =1-K71-K72 -> 0.35789474 | L73: =1-L71-L72 -> 0.38421053 | ... X73: =1-X71-X72 -> 0.7
A74: Blended Unlevered β | E74: =E68*E71+E69*E72+E70*E73 -> 0.4461455 | F74: =F68*F71+F69*F72+F70*F73 -> 0.43816125 | G74: =G68*G71+G69*G72+G70*G73 -> 0.43017699 | H74: =H68*H71+H69*H72+H70*H73 -> 0.42219274 | I74: =I68*I71+I69*I72+I70*I73 -> 0.41420848 | J74: =J68*J71+J69*J72+J70*J73 -> 0.40622423 | K74: =K68*K71+K69*K72+K70*K73 -> 0.39823998 | L74: =L68*L71+L69*L72+L70*L73 -> 0.39025572 | ... X74: =X68*X71+X69*X72+X70*X73 -> 0.29444467
A75: Relevered β (Hamada) | E75: =E74*(1+(1-WACC!$B$9)*WACC!$B$22) -> 0.55188198 | F75: =F74*(1+(1-WACC!$B$9)*WACC!$B$22) -> 0.54200546 | G75: =G74*(1+(1-WACC!$B$9)*WACC!$B$22) -> 0.53212894 | H75: =H74*(1+(1-WACC!$B$9)*WACC!$B$22) -> 0.52225242 | I75: =I74*(1+(1-WACC!$B$9)*WACC!$B$22) -> 0.5123759 | J75: =J74*(1+(1-WACC!$B$9)*WACC!$B$22) -> 0.50249937 | K75: =K74*(1+(1-WACC!$B$9)*WACC!$B$22) -> 0.49262285 | L75: =L74*(1+(1-WACC!$B$9)*WACC!$B$22) -> 0.48274633 | ... X75: =X74*(1+(1-WACC!$B$9)*WACC!$B$22) -> 0.36422806
A76: Cost of Equity (Ke) | E76: =WACC!$B$7+E75*WACC!$B$8+WACC!$B$10 -> 0.083853509 | F76: =WACC!$B$7+F75*WACC!$B$8+WACC!$B$10 -> 0.0833103 | G76: =WACC!$B$7+G75*WACC!$B$8+WACC!$B$10 -> 0.082767092 | H76: =WACC!$B$7+H75*WACC!$B$8+WACC!$B$10 -> 0.082223883 | I76: =WACC!$B$7+I75*WACC!$B$8+WACC!$B$10 -> 0.081680674 | J76: =WACC!$B$7+J75*WACC!$B$8+WACC!$B$10 -> 0.081137466 | K76: =WACC!$B$7+K75*WACC!$B$8+WACC!$B$10 -> 0.080594257 | L76: =WACC!$B$7+L75*WACC!$B$8+WACC!$B$10 -> 0.080051048 | ... X76: =WACC!$B$7+X75*WACC!$B$8+WACC!$B$10 -> 0.073532543
A77: Time-Varying WACC | B77: =E77 -> 0.076352699 | C77: → | D77: =X77 -> 0.068413495 | E77: =E76*WACC!$B$35+WACC!$B$30*WACC!$B$36 -> 0.076352699 | F77: =F76*WACC!$B$35+WACC!$B$30*WACC!$B$36 -> 0.075934846 | G77: =G76*WACC!$B$35+WACC!$B$30*WACC!$B$36 -> 0.075516994 | H77: =H76*WACC!$B$35+WACC!$B$30*WACC!$B$36 -> 0.075099141 | I77: =I76*WACC!$B$35+WACC!$B$30*WACC!$B$36 -> 0.074681288 | J77: =J76*WACC!$B$35+WACC!$B$30*WACC!$B$36 -> 0.074263435 | K77: =K76*WACC!$B$35+WACC!$B$30*WACC!$B$36 -> 0.073845582 | L77: =L76*WACC!$B$35+WACC!$B$30*WACC!$B$36 -> 0.073427729 | ... X77: =X76*WACC!$B$35+WACC!$B$30*WACC!$B$36 -> 0.068413495
A79: Discount Period (mid-year) | E79: 0.5 | F79: 1.5 | G79: 2.5 | H79: 3.5 | I79: 4.5 | J79: 5.5 | K79: 6.5 | L79: 7.5 | M79: 8.5 | N79: 9.5 | O79: 10.5 | P79: 11.5 | Q79: 12.5 | R79: 13.5 | S79: 14.5 | T79: 15.5 | U79: 16.5 | V79: 17.5 | W79: 18.5 | X79: 19.5
A80: Discount Factor | E80: =1/(1+E77)^0.5 -> 0.9638794 | F80: =E80/((1+E77)^0.5*(1+F77)^0.5) -> 0.89567904 | G80: =F80/((1+F77)^0.5*(1+G77)^0.5) -> 0.83262756 | H80: =G80/((1+G77)^0.5*(1+H77)^0.5) -> 0.77431538 | I80: =H80/((1+H77)^0.5*(1+I77)^0.5) -> 0.72036696 | J80: =I80/((1+I77)^0.5*(1+J77)^0.5) -> 0.67043788 | K80: =J80/((1+J77)^0.5*(1+K77)^0.5) -> 0.62421217 | L80: =K80/((1+K77)^0.5*(1+L77)^0.5) -> 0.58139984 | M80: =L80/((1+L77)^0.5*(1+M77)^0.5) -> 0.54173469 | ... X80: =W80/((1+W77)^0.5*(1+X77)^0.5) -> 0.25550088
A81: Unlevered FCF ($M) | E81: =E62 -> 2888.5534 | F81: =F62 -> 5106.5477 | G81: =G62 -> 7671.1669 | H81: =H62 -> 10508.491 | I81: =I62 -> 13887.483 | J81: =J62 -> 16818.322 | K81: =K62 -> 19962.174 | L81: =L62 -> 22662.403 | ... X81: =X62 -> 48804.281
A82: PV of FCF ($M) | E82: =E81*E80 -> 2784.2171 | F82: =F81*F80 -> 4573.8277 | G82: =G81*G80 -> 6387.225 | H82: =H81*H80 -> 8136.8861 | I82: =I81*I80 -> 10004.084 | J82: =J81*J80 -> 11275.64 | K82: =K81*K80 -> 12460.632 | L82: =L81*L80 -> 13175.918 | ... X82: =X81*X80 -> 12469.537
A84: TERMINAL VALUE
A85: Gordon Growth Model
A86: Terminal Year FCF ($M) | B86: =X62 -> 48804.281
A87: Terminal FCF × (1+g) | B87: =X62*(1+$B$45) -> 50268.41
A88: Terminal Value (Gordon Growth) | B88: =B87/($X$77-$B$45) -> 1308613.3
A89: PV of Terminal Value (Gordon Growth) | B89: =B88*$X$80/(1+$X$77)^0.5 -> 323470.03
A90: GG-Implied Exit EV/EBITDA | B90: =B88/B94 -> 18.183751
A92: EV/EBITDA Exit Multiple Method
A93: Exit EV/EBITDA Multiple | B93: =IF(N('Conn Comps'!K54)>0,'Conn Comps'!K54,25) -> 5.9253197 | D93: =IF(N('Conn Comps'!K54)>0,"✓ LIVE – "&TEXT('Conn Comps'!K54,"0.0x")&" from Conn Comps mature tier","⚠ FALLBACK – using 25x default") -> ✓ LIVE – 5.9x from Conn Comps mature tier
A94: Terminal Year EBITDA ($M) | B94: =X52 -> 71966.08
A95: Terminal Value (Exit Multiple) | B95: =B93*B94 -> 426422.03
A96: PV of Terminal Value (Exit Multiple) | B96: =B95*$X$80/(1+$X$77)^0.5 -> 105405.28
A98: CONNECTIVITY SEGMENT VALUATION SUMMARY
B100: Gordon Growth | C100: Exit Multiple
A101: Sum of PV of FCFs ($M) | B101: =SUM(E82:X82) -> 234935.88 | C101: =SUM(E82:X82) -> 234935.88
A102: PV of Terminal Value ($M) | B102: =B89 -> 323470.03 | C102: =B96 -> 105405.28
A103: Enterprise Value ($M) | B103: =B101+B102 -> 558405.91 | C103: =C101+C102 -> 340341.16
A105: TV % of Enterprise Value | B105: =B102/B103 -> 0.57927401 | C105: =C102/C103 -> 0.30970476
A107: SENSITIVITY ANALYSIS – CONNECTIVITY SEGMENT EV ($M)
A109: Table 1: EV ($M) – WACC vs. Terminal Growth Rate (Gordon Growth)
B110: WACC ↓ \ Tg → | C110: =$B$45-0.0075 -> 0.0225 | D110: =$B$45-0.005 -> 0.025 | E110: =$B$45-0.0025 -> 0.0275 | F110: =$B$45 -> 0.03 | G110: =$B$45+0.0025 -> 0.0325 | H110: =$B$45+0.005 -> 0.035 | I110: =$B$45+0.0075 -> 0.0375
B111: =$B$47-0.0075 -> 0.064883097 | C111: =SUMPRODUCT($E$62:$X$62,1/(1+$B111)^$E$79:$X$79)+($X$62*(1+C$110)/($B111-C$110))/(1+$B111)^20 -> 592887.14 | D111: =SUMPRODUCT($E$62:$X$62,1/(1+$B111)^$E$79:$X$79)+($X$62*(1+D$110)/($B111-D$110))/(1+$B111)^20 -> 614748.62 | E111: =SUMPRODUCT($E$62:$X$62,1/(1+$B111)^$E$79:$X$79)+($X$62*(1+E$110)/($B111-E$110))/(1+$B111)^20 -> 639534.09 | F111: =SUMPRODUCT($E$62:$X$62,1/(1+$B111)^$E$79:$X$79)+($X$62*(1+F$110)/($B111-F$110))/(1+$B111)^20 -> 667872.2 | G111: =SUMPRODUCT($E$62:$X$62,1/(1+$B111)^$E$79:$X$79)+($X$62*(1+G$110)/($B111-G$110))/(1+$B111)^20 -> 700585.75 | H111: =SUMPRODUCT($E$62:$X$62,1/(1+$B111)^$E$79:$X$79)+($X$62*(1+H$110)/($B111-H$110))/(1+$B111)^20 -> 738772.9 | I111: =SUMPRODUCT($E$62:$X$62,1/(1+$B111)^$E$79:$X$79)+($X$62*(1+I$110)/($B111-I$110))/(1+$B111)^20 -> 783932.8
B112: =$B$47-0.005 -> 0.067383097 | C112: =SUMPRODUCT($E$62:$X$62,1/(1+$B112)^$E$79:$X$79)+($X$62*(1+C$110)/($B112-C$110))/(1+$B112)^20 -> 552936.74 | D112: =SUMPRODUCT($E$62:$X$62,1/(1+$B112)^$E$79:$X$79)+($X$62*(1+D$110)/($B112-D$110))/(1+$B112)^20 -> 571516.34 | E112: =SUMPRODUCT($E$62:$X$62,1/(1+$B112)^$E$79:$X$79)+($X$62*(1+E$110)/($B112-E$110))/(1+$B112)^20 -> 592425.2 | F112: =SUMPRODUCT($E$62:$X$62,1/(1+$B112)^$E$79:$X$79)+($X$62*(1+F$110)/($B112-F$110))/(1+$B112)^20 -> 616130.62 | G112: =SUMPRODUCT($E$62:$X$62,1/(1+$B112)^$E$79:$X$79)+($X$62*(1+G$110)/($B112-G$110))/(1+$B112)^20 -> 643233.88 | H112: =SUMPRODUCT($E$62:$X$62,1/(1+$B112)^$E$79:$X$79)+($X$62*(1+H$110)/($B112-H$110))/(1+$B112)^20 -> 674521.92 | I112: =SUMPRODUCT($E$62:$X$62,1/(1+$B112)^$E$79:$X$79)+($X$62*(1+I$110)/($B112-I$110))/(1+$B112)^20 -> 711045.04
B113: =$B$47-0.0025 -> 0.069883097 | C113: =SUMPRODUCT($E$62:$X$62,1/(1+$B113)^$E$79:$X$79)+($X$62*(1+C$110)/($B113-C$110))/(1+$B113)^20 -> 517371.74 | D113: =SUMPRODUCT($E$62:$X$62,1/(1+$B113)^$E$79:$X$79)+($X$62*(1+D$110)/($B113-D$110))/(1+$B113)^20 -> 533268.24 | E113: =SUMPRODUCT($E$62:$X$62,1/(1+$B113)^$E$79:$X$79)+($X$62*(1+E$110)/($B113-E$110))/(1+$B113)^20 -> 551040.08 | F113: =SUMPRODUCT($E$62:$X$62,1/(1+$B113)^$E$79:$X$79)+($X$62*(1+F$110)/($B113-F$110))/(1+$B113)^20 -> 571039.9 | G113: =SUMPRODUCT($E$62:$X$62,1/(1+$B113)^$E$79:$X$79)+($X$62*(1+G$110)/($B113-G$110))/(1+$B113)^20 -> 593714.71 | H113: =SUMPRODUCT($E$62:$X$62,1/(1+$B113)^$E$79:$X$79)+($X$62*(1+H$110)/($B113-H$110))/(1+$B113)^20 -> 619639.62 | I113: =SUMPRODUCT($E$62:$X$62,1/(1+$B113)^$E$79:$X$79)+($X$62*(1+I$110)/($B113-I$110))/(1+$B113)^20 -> 649567.39
B114: =$B$47 -> 0.072383097 | C114: =SUMPRODUCT($E$62:$X$62,1/(1+$B114)^$E$79:$X$79)+($X$62*(1+C$110)/($B114-C$110))/(1+$B114)^20 -> 485527.02 | D114: =SUMPRODUCT($E$62:$X$62,1/(1+$B114)^$E$79:$X$79)+($X$62*(1+D$110)/($B114-D$110))/(1+$B114)^20 -> 499209.72 | E114: =SUMPRODUCT($E$62:$X$62,1/(1+$B114)^$E$79:$X$79)+($X$62*(1+E$110)/($B114-E$110))/(1+$B114)^20 -> 514416.68 | F114: =SUMPRODUCT($E$62:$X$62,1/(1+$B114)^$E$79:$X$79)+($X$62*(1+F$110)/($B114-F$110))/(1+$B114)^20 -> 531417.63 | G114: =SUMPRODUCT($E$62:$X$62,1/(1+$B114)^$E$79:$X$79)+($X$62*(1+G$110)/($B114-G$110))/(1+$B114)^20 -> 550549.93 | H114: =SUMPRODUCT($E$62:$X$62,1/(1+$B114)^$E$79:$X$79)+($X$62*(1+H$110)/($B114-H$110))/(1+$B114)^20 -> 572241.18 | I114: =SUMPRODUCT($E$62:$X$62,1/(1+$B114)^$E$79:$X$79)+($X$62*(1+I$110)/($B114-I$110))/(1+$B114)^20 -> 597041.56
B115: =$B$47+0.0025 -> 0.074883097 | C115: =SUMPRODUCT($E$62:$X$62,1/(1+$B115)^$E$79:$X$79)+($X$62*(1+C$110)/($B115-C$110))/(1+$B115)^20 -> 456864.66 | D115: =SUMPRODUCT($E$62:$X$62,1/(1+$B115)^$E$79:$X$79)+($X$62*(1+D$110)/($B115-D$110))/(1+$B115)^20 -> 468705.7 | E115: =SUMPRODUCT($E$62:$X$62,1/(1+$B115)^$E$79:$X$79)+($X$62*(1+E$110)/($B115-E$110))/(1+$B115)^20 -> 481796.25 | F115: =SUMPRODUCT($E$62:$X$62,1/(1+$B115)^$E$79:$X$79)+($X$62*(1+F$110)/($B115-F$110))/(1+$B115)^20 -> 496345.08 | G115: =SUMPRODUCT($E$62:$X$62,1/(1+$B115)^$E$79:$X$79)+($X$62*(1+G$110)/($B115-G$110))/(1+$B115)^20 -> 512610.27 | H115: =SUMPRODUCT($E$62:$X$62,1/(1+$B115)^$E$79:$X$79)+($X$62*(1+H$110)/($B115-H$110))/(1+$B115)^20 -> 530914.56 | I115: =SUMPRODUCT($E$62:$X$62,1/(1+$B115)^$E$79:$X$79)+($X$62*(1+I$110)/($B115-I$110))/(1+$B115)^20 -> 551667.05
B116: =$B$47+0.005 -> 0.077383097 | C116: =SUMPRODUCT($E$62:$X$62,1/(1+$B116)^$E$79:$X$79)+($X$62*(1+C$110)/($B116-C$110))/(1+$B116)^20 -> 430945 | D116: =SUMPRODUCT($E$62:$X$62,1/(1+$B116)^$E$79:$X$79)+($X$62*(1+D$110)/($B116-D$110))/(1+$B116)^20 -> 441242.58 | E116: =SUMPRODUCT($E$62:$X$62,1/(1+$B116)^$E$79:$X$79)+($X$62*(1+E$110)/($B116-E$110))/(1+$B116)^20 -> 452572.33 | F116: =SUMPRODUCT($E$62:$X$62,1/(1+$B116)^$E$79:$X$79)+($X$62*(1+F$110)/($B116-F$110))/(1+$B116)^20 -> 465097.63 | G116: =SUMPRODUCT($E$62:$X$62,1/(1+$B116)^$E$79:$X$79)+($X$62*(1+G$110)/($B116-G$110))/(1+$B116)^20 -> 479018.25 | H116: =SUMPRODUCT($E$62:$X$62,1/(1+$B116)^$E$79:$X$79)+($X$62*(1+H$110)/($B116-H$110))/(1+$B116)^20 -> 494581.12 | I116: =SUMPRODUCT($E$62:$X$62,1/(1+$B116)^$E$79:$X$79)+($X$62*(1+I$110)/($B116-I$110))/(1+$B116)^20 -> 512095.04
B117: =$B$47+0.0075 -> 0.079883097 | C117: =SUMPRODUCT($E$62:$X$62,1/(1+$B117)^$E$79:$X$79)+($X$62*(1+C$110)/($B117-C$110))/(1+$B117)^20 -> 407405.19 | D117: =SUMPRODUCT($E$62:$X$62,1/(1+$B117)^$E$79:$X$79)+($X$62*(1+D$110)/($B117-D$110))/(1+$B117)^20 -> 416400.52 | E117: =SUMPRODUCT($E$62:$X$62,1/(1+$B117)^$E$79:$X$79)+($X$62*(1+E$110)/($B117-E$110))/(1+$B117)^20 -> 426254.47 | F117: =SUMPRODUCT($E$62:$X$62,1/(1+$B117)^$E$79:$X$79)+($X$62*(1+F$110)/($B117-F$110))/(1+$B117)^20 -> 437096.11 | G117: =SUMPRODUCT($E$62:$X$62,1/(1+$B117)^$E$79:$X$79)+($X$62*(1+G$110)/($B117-G$110))/(1+$B117)^20 -> 449081.8 | H117: =SUMPRODUCT($E$62:$X$62,1/(1+$B117)^$E$79:$X$79)+($X$62*(1+H$110)/($B117-H$110))/(1+$B117)^20 -> 462402.7 | I117: =SUMPRODUCT($E$62:$X$62,1/(1+$B117)^$E$79:$X$79)+($X$62*(1+I$110)/($B117-I$110))/(1+$B117)^20 -> 477295.09
...

Sheet Space DCF
A1: SpaceX – Space Segment DCF (Launch & Starship)
A2: S-1 Filed May 20, 2026 | 20-Year Explicit Forecast FY2026E–FY2045E | $ in Millions
A5: SCENARIO SELECTOR | B5: =Dashboard!B32 -> 2 | C5: =IF(B5=1,"◀ BEAR",IF(B5=2,"◀ BASE","◀ BULL")) -> ◀ BASE | D5: (1 = Bear | 2 = Base | 3 = Bull)
B6: FY2023A | C6: FY2024A | D6: FY2025A | E6: FY2026E | F6: FY2027E | G6: FY2028E | H6: FY2029E | I6: FY2030E | J6: FY2031E | K6: FY2032E | L6: FY2033E | M6: FY2034E | N6: FY2035E | O6: FY2036E | P6: FY2037E | Q6: FY2038E | R6: FY2039E | S6: FY2040E | T6: FY2041E | U6: FY2042E | V6: FY2043E | W6: FY2044E | X6: FY2045E
A8: BEAR CASE ASSUMPTIONS
A9: Revenue Growth % (YoY) | E9: 0.06 | F9: 0.08 | G9: 0.1 | H9: 0.12 | I9: 0.15 | J9: 0.15 | K9: 0.13 | L9: 0.12 | M9: 0.1 | N9: 0.08 | O9: 0.07 | P9: 0.06 | Q9: 0.05 | R9: 0.045 | S9: 0.04 | T9: 0.035 | U9: 0.03 | V9: 0.03 | W9: 0.028 | X9: 0.025
A10: EBITDA Margin % | E10: 0.1 | F10: 0.12 | G10: 0.15 | H10: 0.18 | I10: 0.22 | J10: 0.25 | K10: 0.27 | L10: 0.28 | M10: 0.29 | N10: 0.3 | O10: 0.31 | P10: 0.32 | Q10: 0.33 | R10: 0.34 | S10: 0.34 | T10: 0.35 | U10: 0.36 | V10: 0.37 | W10: 0.37 | X10: 0.38
A11: Capex % of Revenue | E11: 0.85 | F11: 0.75 | G11: 0.65 | H11: 0.55 | I11: 0.45 | J11: 0.38 | K11: 0.32 | L11: 0.28 | M11: 0.24 | N11: 0.22 | O11: 0.21 | P11: 0.2 | Q11: 0.19 | R11: 0.18 | S11: 0.17 | T11: 0.16 | U11: 0.15 | V11: 0.14 | W11: 0.13 | X11: 0.12
A12: ΔNW Cap % of ΔRevenue | E12: 0.06 | F12: 0.06 | G12: 0.05 | H12: 0.05 | I12: 0.05 | J12: 0.04 | K12: 0.04 | L12: 0.03 | M12: 0.03 | N12: 0.03 | O12: 0.03 | P12: 0.03 | Q12: 0.025 | R12: 0.025 | S12: 0.025 | T12: 0.025 | U12: 0.02 | V12: 0.02 | W12: 0.02 | X12: 0.02
A13: Total Falcon 9 Launches | E13: 180 | F13: 185 | G13: 185 | H13: 180 | I13: 165 | J13: 140 | K13: 110 | L13: 80 | M13: 55 | N13: 35 | O13: 22 | P13: 14 | Q13: 8 | R13: 5 | S13: 3 | T13: 0 | U13: 0 | V13: 0 | W13: 0 | X13: 0
A14: Total Starship Launches | E14: 5 | F14: 10 | G14: 25 | H14: 45 | I14: 70 | J14: 110 | K14: 155 | L14: 200 | M14: 250 | N14: 300 | O14: 340 | P14: 370 | Q14: 395 | R14: 415 | S14: 430 | T14: 440 | U14: 450 | V14: 460 | W14: 465 | X14: 470
A15: Starship D&A / Launch ($M) | E15: 2.5 | F15: 2.2 | G15: 2 | H15: 1.8 | I15: 1.5 | J15: 1.3 | K15: 1.15 | L15: 1.05 | M15: 0.95 | N15: 0.9 | O15: 0.85 | P15: 0.82 | Q15: 0.78 | R15: 0.75 | S15: 0.72 | T15: 0.7 | U15: 0.68 | V15: 0.67 | W15: 0.66 | X15: 0.65
A16: Terminal Growth Rate | B16: =WACC!D43 -> 0.02
A17: WACC | B17: =WACC!B43 -> 0.068984004
A19: BASE CASE ASSUMPTIONS
A20: Revenue Growth % (YoY) | E20: 0.1 | F20: 0.14 | G20: 0.18 | H20: 0.22 | I20: 0.26 | J20: 0.22 | K20: 0.18 | L20: 0.15 | M20: 0.13 | N20: 0.11 | O20: 0.1 | P20: 0.09 | Q20: 0.08 | R20: 0.07 | S20: 0.06 | T20: 0.05 | U20: 0.045 | V20: 0.04 | W20: 0.035 | X20: 0.03
A21: EBITDA Margin % | E21: 0.18 | F21: 0.18 | G21: 0.24 | H21: 0.3 | I21: 0.36 | J21: 0.41 | K21: 0.45 | L21: 0.47 | M21: 0.48 | N21: 0.49 | O21: 0.5 | P21: 0.51 | Q21: 0.52 | R21: 0.52 | S21: 0.53 | T21: 0.54 | U21: 0.54 | V21: 0.55 | W21: 0.55 | X21: 0.56
A22: Capex % of Revenue | E22: 0.75 | F22: 0.65 | G22: 0.55 | H22: 0.45 | I22: 0.36 | J22: 0.28 | K22: 0.22 | L22: 0.18 | M22: 0.15 | N22: 0.13 | O22: 0.125 | P22: 0.12 | Q22: 0.115 | R22: 0.11 | S22: 0.105 | T22: 0.1 | U22: 0.098 | V22: 0.095 | W22: 0.092 | X22: 0.09
A23: ΔNW Cap % of ΔRevenue | E23: 0.05 | F23: 0.05 | G23: 0.05 | H23: 0.04 | I23: 0.04 | J23: 0.04 | K23: 0.03 | L23: 0.03 | M23: 0.02 | N23: 0.02 | O23: 0.02 | P23: 0.02 | Q23: 0.02 | R23: 0.018 | S23: 0.018 | T23: 0.015 | U23: 0.015 | V23: 0.015 | W23: 0.015 | X23: 0.015
A24: Total Falcon 9 Launches | E24: 175 | F24: 180 | G24: 175 | H24: 160 | I24: 130 | J24: 100 | K24: 70 | L24: 45 | M24: 25 | N24: 15 | O24: 8 | P24: 5 | Q24: 3 | R24: 0 | S24: 0 | T24: 0 | U24: 0 | V24: 0 | W24: 0 | X24: 0
A25: Total Starship Launches | E25: 10 | F25: 24 | G25: 50 | H25: 80 | I25: 100 | J25: 150 | K25: 210 | L25: 280 | M25: 340 | N25: 400 | O25: 440 | P25: 470 | Q25: 490 | R25: 510 | S25: 520 | T25: 530 | U25: 540 | V25: 545 | W25: 550 | X25: 555
A26: Starship D&A / Launch ($M) | E26: 2 | F26: 1.8 | G26: 1.6 | H26: 1.4 | I26: 1.2 | J26: 1.1 | K26: 1 | L26: 0.9 | M26: 0.8 | N26: 0.76 | O26: 0.72 | P26: 0.68 | Q26: 0.64 | R26: 0.62 | S26: 0.6 | T26: 0.6 | U26: 0.6 | V26: 0.6 | W26: 0.6 | X26: 0.6
A27: Terminal Growth Rate | B27: =WACC!C43 -> 0.025
A28: WACC | B28: =WACC!B43 -> 0.068984004
A30: BULL CASE ASSUMPTIONS
A31: Revenue Growth % (YoY) | E31: 0.16 | F31: 0.22 | G31: 0.28 | H31: 0.32 | I31: 0.36 | J31: 0.3 | K31: 0.25 | L31: 0.2 | M31: 0.17 | N31: 0.14 | O31: 0.13 | P31: 0.12 | Q31: 0.11 | R31: 0.1 | S31: 0.09 | T31: 0.08 | U31: 0.07 | V31: 0.06 | W31: 0.05 | X31: 0.04
A32: EBITDA Margin % | E32: 0.18 | F32: 0.24 | G32: 0.32 | H32: 0.4 | I32: 0.46 | J32: 0.5 | K32: 0.52 | L32: 0.53 | M32: 0.54 | N32: 0.55 | O32: 0.56 | P32: 0.57 | Q32: 0.58 | R32: 0.59 | S32: 0.59 | T32: 0.6 | U32: 0.61 | V32: 0.61 | W32: 0.62 | X32: 0.62
A33: Capex % of Revenue | E33: 0.7 | F33: 0.6 | G33: 0.5 | H33: 0.4 | I33: 0.31 | J33: 0.24 | K33: 0.19 | L33: 0.16 | M33: 0.13 | N33: 0.11 | O33: 0.11 | P33: 0.105 | Q33: 0.1 | R33: 0.098 | S33: 0.095 | T33: 0.092 | U33: 0.09 | V33: 0.088 | W33: 0.085 | X33: 0.08
A34: ΔNW Cap % of ΔRevenue | E34: 0.04 | F34: 0.04 | G34: 0.04 | H34: 0.03 | I34: 0.03 | J34: 0.03 | K34: 0.02 | L34: 0.02 | M34: 0.02 | N34: 0.02 | O34: 0.02 | P34: 0.018 | Q34: 0.018 | R34: 0.015 | S34: 0.015 | T34: 0.015 | U34: 0.012 | V34: 0.012 | W34: 0.012 | X34: 0.012
A35: Total Falcon 9 Launches | E35: 170 | F35: 165 | G35: 150 | H35: 130 | I35: 100 | J35: 70 | K35: 45 | L35: 25 | M35: 12 | N35: 6 | O35: 3 | P35: 2 | Q35: 0 | R35: 0 | S35: 0 | T35: 0 | U35: 0 | V35: 0 | W35: 0 | X35: 0
A36: Total Starship Launches | E36: 15 | F36: 40 | G36: 80 | H36: 130 | I36: 180 | J36: 240 | K36: 310 | L36: 380 | M36: 450 | N36: 510 | O36: 560 | P36: 600 | Q36: 630 | R36: 650 | S36: 670 | T36: 685 | U36: 700 | V36: 710 | W36: 720 | X36: 730
A37: Starship D&A / Launch ($M) | E37: 1.8 | F37: 1.5 | G37: 1.2 | H37: 1 | I37: 0.85 | J37: 0.75 | K37: 0.68 | L37: 0.62 | M37: 0.57 | N37: 0.53 | O37: 0.5 | P37: 0.47 | Q37: 0.45 | R37: 0.43 | S37: 0.42 | T37: 0.41 | U37: 0.4 | V37: 0.39 | W37: 0.38 | X37: 0.37
A38: Terminal Growth Rate | B38: =WACC!E43 -> 0.03
A39: WACC | B39: =WACC!B43 -> 0.068984004
A41: SELECTED CASE ASSUMPTIONS (auto-updates with Scenario Selector)
A42: Revenue Growth % (YoY) | E42: =IF($B$5=1,E9,IF($B$5=2,E20,E31)) -> 0.1 | F42: =IF($B$5=1,F9,IF($B$5=2,F20,F31)) -> 0.14 | G42: =IF($B$5=1,G9,IF($B$5=2,G20,G31)) -> 0.18 | H42: =IF($B$5=1,H9,IF($B$5=2,H20,H31)) -> 0.22 | I42: =IF($B$5=1,I9,IF($B$5=2,I20,I31)) -> 0.26 | J42: =IF($B$5=1,J9,IF($B$5=2,J20,J31)) -> 0.22 | K42: =IF($B$5=1,K9,IF($B$5=2,K20,K31)) -> 0.18 | L42: =IF($B$5=1,L9,IF($B$5=2,L20,L31)) -> 0.15 | ... X42: =IF($B$5=1,X9,IF($B$5=2,X20,X31)) -> 0.03
A43: EBITDA Margin % | E43: =IF($B$5=1,E10,IF($B$5=2,E21,E32)) -> 0.18 | F43: =IF($B$5=1,F10,IF($B$5=2,F21,F32)) -> 0.18 | G43: =IF($B$5=1,G10,IF($B$5=2,G21,G32)) -> 0.24 | H43: =IF($B$5=1,H10,IF($B$5=2,H21,H32)) -> 0.3 | I43: =IF($B$5=1,I10,IF($B$5=2,I21,I32)) -> 0.36 | J43: =IF($B$5=1,J10,IF($B$5=2,J21,J32)) -> 0.41 | K43: =IF($B$5=1,K10,IF($B$5=2,K21,K32)) -> 0.45 | L43: =IF($B$5=1,L10,IF($B$5=2,L21,L32)) -> 0.47 | ... X43: =IF($B$5=1,X10,IF($B$5=2,X21,X32)) -> 0.56
A44: Capex % of Revenue | E44: =IF($B$5=1,E11,IF($B$5=2,E22,E33)) -> 0.75 | F44: =IF($B$5=1,F11,IF($B$5=2,F22,F33)) -> 0.65 | G44: =IF($B$5=1,G11,IF($B$5=2,G22,G33)) -> 0.55 | H44: =IF($B$5=1,H11,IF($B$5=2,H22,H33)) -> 0.45 | I44: =IF($B$5=1,I11,IF($B$5=2,I22,I33)) -> 0.36 | J44: =IF($B$5=1,J11,IF($B$5=2,J22,J33)) -> 0.28 | K44: =IF($B$5=1,K11,IF($B$5=2,K22,K33)) -> 0.22 | L44: =IF($B$5=1,L11,IF($B$5=2,L22,L33)) -> 0.18 | ... X44: =IF($B$5=1,X11,IF($B$5=2,X22,X33)) -> 0.09
A45: ΔNW Cap % of ΔRevenue | E45: =IF($B$5=1,E12,IF($B$5=2,E23,E34)) -> 0.05 | F45: =IF($B$5=1,F12,IF($B$5=2,F23,F34)) -> 0.05 | G45: =IF($B$5=1,G12,IF($B$5=2,G23,G34)) -> 0.05 | H45: =IF($B$5=1,H12,IF($B$5=2,H23,H34)) -> 0.04 | I45: =IF($B$5=1,I12,IF($B$5=2,I23,I34)) -> 0.04 | J45: =IF($B$5=1,J12,IF($B$5=2,J23,J34)) -> 0.04 | K45: =IF($B$5=1,K12,IF($B$5=2,K23,K34)) -> 0.03 | L45: =IF($B$5=1,L12,IF($B$5=2,L23,L34)) -> 0.03 | ... X45: =IF($B$5=1,X12,IF($B$5=2,X23,X34)) -> 0.015
A46: Total Falcon 9 Launches | E46: =IF($B$5=1,E13,IF($B$5=2,E24,E35)) -> 175 | F46: =IF($B$5=1,F13,IF($B$5=2,F24,F35)) -> 180 | G46: =IF($B$5=1,G13,IF($B$5=2,G24,G35)) -> 175 | H46: =IF($B$5=1,H13,IF($B$5=2,H24,H35)) -> 160 | I46: =IF($B$5=1,I13,IF($B$5=2,I24,I35)) -> 130 | J46: =IF($B$5=1,J13,IF($B$5=2,J24,J35)) -> 100 | K46: =IF($B$5=1,K13,IF($B$5=2,K24,K35)) -> 70 | L46: =IF($B$5=1,L13,IF($B$5=2,L24,L35)) -> 45 | ... X46: =IF($B$5=1,X13,IF($B$5=2,X24,X35)) -> 0
A47: Total Starship Launches | E47: =IF($B$5=1,E14,IF($B$5=2,E25,E36)) -> 10 | F47: =IF($B$5=1,F14,IF($B$5=2,F25,F36)) -> 24 | G47: =IF($B$5=1,G14,IF($B$5=2,G25,G36)) -> 50 | H47: =IF($B$5=1,H14,IF($B$5=2,H25,H36)) -> 80 | I47: =IF($B$5=1,I14,IF($B$5=2,I25,I36)) -> 100 | J47: =IF($B$5=1,J14,IF($B$5=2,J25,J36)) -> 150 | K47: =IF($B$5=1,K14,IF($B$5=2,K25,K36)) -> 210 | L47: =IF($B$5=1,L14,IF($B$5=2,L25,L36)) -> 280 | ... X47: =IF($B$5=1,X14,IF($B$5=2,X25,X36)) -> 555
A48: Starship D&A / Launch ($M) | E48: =IF($B$5=1,E15,IF($B$5=2,E26,E37)) -> 2 | F48: =IF($B$5=1,F15,IF($B$5=2,F26,F37)) -> 1.8 | G48: =IF($B$5=1,G15,IF($B$5=2,G26,G37)) -> 1.6 | H48: =IF($B$5=1,H15,IF($B$5=2,H26,H37)) -> 1.4 | I48: =IF($B$5=1,I15,IF($B$5=2,I26,I37)) -> 1.2 | J48: =IF($B$5=1,J15,IF($B$5=2,J26,J37)) -> 1.1 | K48: =IF($B$5=1,K15,IF($B$5=2,K26,K37)) -> 1 | L48: =IF($B$5=1,L15,IF($B$5=2,L26,L37)) -> 0.9 | ... X48: =IF($B$5=1,X15,IF($B$5=2,X26,X37)) -> 0.6
A49: Terminal Growth Rate | B49: =IF($B$5=1,B16,IF($B$5=2,B27,B38)) -> 0.025
A50: WACC | B50: =IF($B$5=1,B17,IF($B$5=2,B28,B39)) -> 0.068984004
A51: Blended WACC (Sensitivity Center) | B51: =AVERAGE(E85:X85) -> 0.10092518
A53: SPACE SEGMENT – INCOME STATEMENT & FREE CASH FLOW ($M)
A54: Revenue | B54: =Actuals!B9 -> 3557 | C54: =Actuals!C9 -> 3796 | D54: =Actuals!D9 -> 4086 | E54: =D54*(1+E42) -> 4494.6 | F54: =E54*(1+F42) -> 5123.844 | G54: =F54*(1+G42) -> 6046.1359 | H54: =G54*(1+H42) -> 7376.2858 | I54: =H54*(1+I42) -> 9294.1201 | J54: =I54*(1+J42) -> 11338.827 | K54: =J54*(1+K42) -> 13379.815 | L54: =K54*(1+L42) -> 15386.788 | ... X54: =W54*(1+X42) -> 34482.478
A55: % YoY Growth | C55: =C54/B54-1 -> 0.067191453 | D55: =D54/C54-1 -> 0.076396207 | E55: =E54/D54-1 -> 0.1 | F55: =F54/E54-1 -> 0.14 | G55: =G54/F54-1 -> 0.18 | H55: =H54/G54-1 -> 0.22 | I55: =I54/H54-1 -> 0.26 | J55: =J54/I54-1 -> 0.22 | ... X55: =X54/W54-1 -> 0.03
A56: EBITDA | B56: =Actuals!B12 -> 997 | C56: =Actuals!C12 -> 1154 | D56: =Actuals!D12 -> 653 | E56: =E54*E43 -> 809.028 | F56: =F54*F43 -> 922.29192 | G56: =G54*G43 -> 1451.0726 | H56: =H54*H43 -> 2212.8857 | I56: =I54*I43 -> 3345.8832 | J56: =J54*J43 -> 4648.9189 | K56: =K54*K43 -> 6020.9169 | L56: =L54*L43 -> 7231.7902 | ... X56: =X54*X43 -> 19310.188
A57: EBITDA Margin % | B57: =B56/B54 -> 0.28029238 | C57: =C56/C54 -> 0.30400421 | D57: =D56/D54 -> 0.159814 | E57: =E56/E54 -> 0.18 | F57: =F56/F54 -> 0.18 | G57: =G56/G54 -> 0.24 | H57: =H56/H54 -> 0.3 | I57: =I56/I54 -> 0.36 | ... X57: =X56/X54 -> 0.56
A58: Depreciation & Amortization | B58: =Actuals!B15 -> 571 | C58: =Actuals!C15 -> 637 | D58: =Actuals!D15 -> 757 | E58: =E165 -> 817.25541 | F58: =F165 -> 875.15309 | G58: =G165 -> 939.42702 | H58: =H165 -> 996.60313 | I58: =I165 -> 1053.0273 | J58: =J165 -> 1105.2025 | K58: =K165 -> 1155.6098 | L58: =L165 -> 1196.8659 | ... X58: =X165 -> 1985.164
A59: EBIT (EBITDA − D&A) | B59: =B56-B58 -> 426 | C59: =C56-C58 -> 517 | D59: =D56-D58 -> -104 | E59: =E56-E58 -> -8.2274054 | F59: =F56-F58 -> 47.138832 | G59: =G56-G58 -> 511.6456 | H59: =H56-H58 -> 1216.2826 | I59: =I56-I58 -> 2292.856 | ... X59: =X56-X58 -> 17325.024
A60: EBIT Margin % | B60: =B59/B54 -> 0.11976385 | C60: =C59/C54 -> 0.136196 | D60: =D59/D54 -> -0.025452766 | E60: =E59/E54 -> -0.0018305089 | F60: =F59/F54 -> 0.009199896 | G60: =G59/G54 -> 0.084623568 | H60: =H59/H54 -> 0.16489093 | I60: =I59/I54 -> 0.24669963 | ... X60: =X59/X54 -> 0.50242978
A61: NOL Opening Balance ($M) | B61: 0 | C61: =B63 -> 0 | D61: =C63 -> 0 | E61: =D63 -> 104 | F61: =E63 -> 112.22741 | G61: =F63 -> 74.51634 | H61: =G63 -> 0 | I61: =H63 -> 0 | J61: =I63 -> 0 | ... X61: =W63 -> 0
A62: (–) NOL Utilization (IRC §172, 80% cap) | B62: =MIN(B61,MAX(B59,0)*0.8) -> 0 | C62: =MIN(C61,MAX(C59,0)*0.8) -> 0 | D62: =MIN(D61,MAX(D59,0)*0.8) -> 0 | E62: =MIN(E61,MAX(E59,0)*0.8) -> 0 | F62: =MIN(F61,MAX(F59,0)*0.8) -> 37.711065 | G62: =MIN(G61,MAX(G59,0)*0.8) -> 74.51634 | H62: =MIN(H61,MAX(H59,0)*0.8) -> 0 | I62: =MIN(I61,MAX(I59,0)*0.8) -> 0 | ... X62: =MIN(X61,MAX(X59,0)*0.8) -> 0
A63: NOL Closing Balance ($M) | B63: =B61-B62+MAX(-B59,0) -> 0 | C63: =C61-C62+MAX(-C59,0) -> 0 | D63: =D61-D62+MAX(-D59,0) -> 104 | E63: =E61-E62+MAX(-E59,0) -> 112.22741 | F63: =F61-F62+MAX(-F59,0) -> 74.51634 | G63: =G61-G62+MAX(-G59,0) -> 0 | H63: =H61-H62+MAX(-H59,0) -> 0 | I63: =I61-I62+MAX(-I59,0) -> 0 | ... X63: =X61-X62+MAX(-X59,0) -> 0
A64: (–) Tax on EBIT | B64: =(MAX(B59,0)-B62)*WACC!$B$9 -> 89.46 | C64: =(MAX(C59,0)-C62)*WACC!$B$9 -> 108.57 | D64: =(MAX(D59,0)-D62)*WACC!$B$9 -> 0 | E64: =(MAX(E59,0)-E62)*WACC!$B$9 -> 0 | F64: =(MAX(F59,0)-F62)*WACC!$B$9 -> 1.9798309 | G64: =(MAX(G59,0)-G62)*WACC!$B$9 -> 91.797144 | H64: =(MAX(H59,0)-H62)*WACC!$B$9 -> 255.41935 | I64: =(MAX(I59,0)-I62)*WACC!$B$9 -> 481.49976 | ... X64: =(MAX(X59,0)-X62)*WACC!$B$9 -> 3638.255
A65: NOPAT | B65: =B59-B64 -> 336.54 | C65: =C59-C64 -> 408.43 | D65: =D59-D64 -> -104 | E65: =E59-E64 -> -8.2274054 | F65: =F59-F64 -> 45.159001 | G65: =G59-G64 -> 419.84845 | H65: =H59-H64 -> 960.86326 | I65: =I59-I64 -> 1811.3562 | ... X65: =X59-X64 -> 13686.769
A66: (+) D&A | B66: =B58 -> 571 | C66: =C58 -> 637 | D66: =D58 -> 757 | E66: =E58 -> 817.25541 | F66: =F58 -> 875.15309 | G66: =G58 -> 939.42702 | H66: =H58 -> 996.60313 | I66: =I58 -> 1053.0273 | ... X66: =X58 -> 1985.164
A67: (–) Capital Expenditures | B67: =Actuals!B19 -> -1497 | C67: =Actuals!C19 -> -2032 | D67: =Actuals!D19 -> -3832 | E67: =-E54*E44 -> -3370.95 | F67: =-F54*F44 -> -3330.4986 | G67: =-G54*G44 -> -3325.3748 | H67: =-H54*H44 -> -3319.3286 | I67: =-I54*I44 -> -3345.8832 | J67: =-J54*J44 -> -3174.8714 | K67: =-K54*K44 -> -2943.5594 | L67: =-L54*L44 -> -2769.6218 | ... X67: =-X54*X44 -> -3103.423
A68: (–) Increase in Net Working Capital | B68: 0 | C68: 0 | D68: 0 | E68: =-(E54-D54)*E45 -> -20.43 | F68: =-(F54-E54)*F45 -> -31.4622 | G68: =-(G54-F54)*G45 -> -46.114596 | H68: =-(H54-G54)*H45 -> -53.205996 | I68: =-(I54-H54)*I45 -> -76.713373 | J68: =-(J54-I54)*J45 -> -81.788257 | K68: =-(K54-J54)*K45 -> -61.229663 | L68: =-(L54-K54)*L45 -> -60.209169 | ... X68: =-(X54-W54)*X45 -> -15.06516
A69: Unlevered Free Cash Flow | B69: =B65+B66+B67+B68 -> -589.46 | C69: =C65+C66+C67+C68 -> -986.57 | D69: =D65+D66+D67+D68 -> -3179 | E69: =E65+E66+E67+E68-E54*($B$71+($C$71-$B$71)*(COLUMN()-5)/19)*(1-WACC!$B$9) -> -2706.6277 | F69: =F65+F66+F67+F68-F54*($B$71+($C$71-$B$71)*(COLUMN()-5)/19)*(1-WACC!$B$9) -> -2579.0621 | G69: =G65+G66+G67+G68-G54*($B$71+($C$71-$B$71)*(COLUMN()-5)/19)*(1-WACC!$B$9) -> -2169.3339 | H69: =H65+H66+H67+H68-H54*($B$71+($C$71-$B$71)*(COLUMN()-5)/19)*(1-WACC!$B$9) -> -1600.6206 | I69: =I65+I66+I67+I68-I54*($B$71+($C$71-$B$71)*(COLUMN()-5)/19)*(1-WACC!$B$9) -> -784.28037 | J69: =J65+J66+J67+J68-J54*($B$71+($C$71-$B$71)*(COLUMN()-5)/19)*(1-WACC!$B$9) -> 381.70585 | K69: =K65+K66+K67+K68-K54*($B$71+($C$71-$B$71)*(COLUMN()-5)/19)*(1-WACC!$B$9) -> 1691.2197 | L69: =L65+L66+L67+L68-L54*($B$71+($C$71-$B$71)*(COLUMN()-5)/19)*(1-WACC!$B$9) -> 2798.7478 | ... X69: =X65+X66+X67+X68-X54*($B$71+($C$71-$B$71)*(COLUMN()-5)/19)*(1-WACC!$B$9) -> 12144.827
A70: FCF Margin % | B70: =B69/B54 -> -0.1657183 | C70: =C69/C54 -> -0.25989726 | D70: =D69/D54 -> -0.77802252 | E70: =E69/E54 -> -0.60219545 | F70: =F69/F54 -> -0.50334517 | G70: =G69/G54 -> -0.35879674 | H70: =H69/H54 -> -0.21699547 | I70: =I69/I54 -> -0.084384575 | ... X70: =X69/X54 -> 0.35220285
A71: SBC (% of Revenue) | B71: 0.035 | C71: 0.015
A73: DCF – DISCOUNT FACTORS & PRESENT VALUES (Mid-Year Convention)
A75: TIME-WEIGHTED BETA & WACC
A76: Tier 1 (NewSpace / Launch) Unlevered β | B76: ='Space Comps'!X21 -> 1.9230769 | C76: NewSpace / Launch | E76: =$B$76 -> 1.9230769 | F76: =$B$76 -> 1.9230769 | G76: =$B$76 -> 1.9230769 | H76: =$B$76 -> 1.9230769 | I76: =$B$76 -> 1.9230769 | J76: =$B$76 -> 1.9230769 | K76: =$B$76 -> 1.9230769 | L76: =$B$76 -> 1.9230769 | ... X76: =$B$76 -> 1.9230769
A77: Tier 2 (Big-5 Defense) Unlevered β | B77: ='Space Comps'!X35 -> 0.26644722 | C77: Big-5 Defense | E77: =$B$77 -> 0.26644722 | F77: =$B$77 -> 0.26644722 | G77: =$B$77 -> 0.26644722 | H77: =$B$77 -> 0.26644722 | I77: =$B$77 -> 0.26644722 | J77: =$B$77 -> 0.26644722 | K77: =$B$77 -> 0.26644722 | L77: =$B$77 -> 0.26644722 | ... X77: =$B$77 -> 0.26644722
A78: Tier 3 (N/A) | B78: =0 -> 0 | C78: – | E78: =$B$78 -> 0 | F78: =$B$78 -> 0 | G78: =$B$78 -> 0 | H78: =$B$78 -> 0 | I78: =$B$78 -> 0 | J78: =$B$78 -> 0 | K78: =$B$78 -> 0 | L78: =$B$78 -> 0 | ... X78: =$B$78 -> 0
A79: Tier 1 Weight | B79: =IF($B$5=1,0.7,IF($B$5=2,0.6,0.5)) -> 0.6 | C79: =IF($B$5=1,0.25,IF($B$5=2,0.15,0.1)) -> 0.15 | D79: B = Yr 1, C = Yr 20 | E79: =$B79+($C79-$B79)*(COLUMN()-5)/19 -> 0.6 | F79: =$B79+($C79-$B79)*(COLUMN()-5)/19 -> 0.57631579 | G79: =$B79+($C79-$B79)*(COLUMN()-5)/19 -> 0.55263158 | H79: =$B79+($C79-$B79)*(COLUMN()-5)/19 -> 0.52894737 | I79: =$B79+($C79-$B79)*(COLUMN()-5)/19 -> 0.50526316 | J79: =$B79+($C79-$B79)*(COLUMN()-5)/19 -> 0.48157895 | K79: =$B79+($C79-$B79)*(COLUMN()-5)/19 -> 0.45789474 | L79: =$B79+($C79-$B79)*(COLUMN()-5)/19 -> 0.43421053 | ... X79: =$B79+($C79-$B79)*(COLUMN()-5)/19 -> 0.15
A80: Tier 2 Weight | B80: =IF($B$5=1,0.3,IF($B$5=2,0.4,0.5)) -> 0.4 | C80: =IF($B$5=1,0.75,IF($B$5=2,0.85,0.9)) -> 0.85 | D80: (see E→X for glide) | E80: =$B80+($C80-$B80)*(COLUMN()-5)/19 -> 0.4 | F80: =$B80+($C80-$B80)*(COLUMN()-5)/19 -> 0.42368421 | G80: =$B80+($C80-$B80)*(COLUMN()-5)/19 -> 0.44736842 | H80: =$B80+($C80-$B80)*(COLUMN()-5)/19 -> 0.47105263 | I80: =$B80+($C80-$B80)*(COLUMN()-5)/19 -> 0.49473684 | J80: =$B80+($C80-$B80)*(COLUMN()-5)/19 -> 0.51842105 | K80: =$B80+($C80-$B80)*(COLUMN()-5)/19 -> 0.54210526 | L80: =$B80+($C80-$B80)*(COLUMN()-5)/19 -> 0.56578947 | ... X80: =$B80+($C80-$B80)*(COLUMN()-5)/19 -> 0.85
A81: Tier 3 Weight (= 1 – T1 – T2) | B81: =1-B79-B80 -> 0 | C81: =1-C79-C80 -> 0 | E81: =1-E79-E80 -> 0 | F81: =1-F79-F80 -> 0 | G81: =1-G79-G80 -> 0 | H81: =1-H79-H80 -> 0 | I81: =1-I79-I80 -> 0 | J81: =1-J79-J80 -> 0 | K81: =1-K79-K80 -> 0 | L81: =1-L79-L80 -> 0 | ... X81: =1-X79-X80 -> 0
A82: Blended Unlevered β | E82: =E76*E79+E77*E80+E78*E81 -> 1.260425 | F82: =F76*F79+F77*F80+F78*F81 -> 1.2211891 | G82: =G76*G79+G77*G80+G78*G81 -> 1.1819531 | H82: =H76*H79+H77*H80+H78*H81 -> 1.1427171 | I82: =I76*I79+I77*I80+I78*I81 -> 1.1034812 | J82: =J76*J79+J77*J80+J78*J81 -> 1.0642452 | K82: =K76*K79+K77*K80+K78*K81 -> 1.0250092 | L82: =L76*L79+L77*L80+L78*L81 -> 0.98577327 | ... X82: =X76*X79+X77*X80+X78*X81 -> 0.51494167
A83: Relevered β (Hamada) | E83: =E82*(1+(1-WACC!$B$9)*WACC!$C$22) -> 1.7085061 | F83: =F82*(1+(1-WACC!$B$9)*WACC!$C$22) -> 1.6553218 | G83: =G82*(1+(1-WACC!$B$9)*WACC!$C$22) -> 1.6021374 | H83: =H82*(1+(1-WACC!$B$9)*WACC!$C$22) -> 1.5489531 | I83: =I82*(1+(1-WACC!$B$9)*WACC!$C$22) -> 1.4957687 | J83: =J82*(1+(1-WACC!$B$9)*WACC!$C$22) -> 1.4425844 | K83: =K82*(1+(1-WACC!$B$9)*WACC!$C$22) -> 1.3894 | L83: =L82*(1+(1-WACC!$B$9)*WACC!$C$22) -> 1.3362157 | ... X83: =X82*(1+(1-WACC!$B$9)*WACC!$C$22) -> 0.69800344
A84: Cost of Equity (Ke) | E84: =WACC!$B$7+E83*WACC!$B$8+WACC!$B$10 -> 0.14746784 | F84: =WACC!$B$7+F83*WACC!$B$8+WACC!$B$10 -> 0.1445427 | G84: =WACC!$B$7+G83*WACC!$B$8+WACC!$B$10 -> 0.14161756 | H84: =WACC!$B$7+H83*WACC!$B$8+WACC!$B$10 -> 0.13869242 | I84: =WACC!$B$7+I83*WACC!$B$8+WACC!$B$10 -> 0.13576728 | J84: =WACC!$B$7+J83*WACC!$B$8+WACC!$B$10 -> 0.13284214 | K84: =WACC!$B$7+K83*WACC!$B$8+WACC!$B$10 -> 0.129917 | L84: =WACC!$B$7+L83*WACC!$B$8+WACC!$B$10 -> 0.12699186 | ... X84: =WACC!$B$7+X83*WACC!$B$8+WACC!$B$10 -> 0.091890189
A85: Time-Varying WACC | B85: =E85 -> 0.12008989 | C85: → | D85: =X85 -> 0.081760475 | E85: =E84*WACC!$C$35+WACC!$C$30*WACC!$C$36 -> 0.12008989 | F85: =F84*WACC!$C$35+WACC!$C$30*WACC!$C$36 -> 0.11807255 | G85: =G84*WACC!$C$35+WACC!$C$30*WACC!$C$36 -> 0.11605521 | H85: =H84*WACC!$C$35+WACC!$C$30*WACC!$C$36 -> 0.11403788 | I85: =I84*WACC!$C$35+WACC!$C$30*WACC!$C$36 -> 0.11202054 | J85: =J84*WACC!$C$35+WACC!$C$30*WACC!$C$36 -> 0.1100032 | K85: =K84*WACC!$C$35+WACC!$C$30*WACC!$C$36 -> 0.10798586 | L85: =L84*WACC!$C$35+WACC!$C$30*WACC!$C$36 -> 0.10596853 | ... X85: =X84*WACC!$C$35+WACC!$C$30*WACC!$C$36 -> 0.081760475
A87: Discount Period (mid-year) | E87: 0.5 | F87: 1.5 | G87: 2.5 | H87: 3.5 | I87: 4.5 | J87: 5.5 | K87: 6.5 | L87: 7.5 | M87: 8.5 | N87: 9.5 | O87: 10.5 | P87: 11.5 | Q87: 12.5 | R87: 13.5 | S87: 14.5 | T87: 15.5 | U87: 16.5 | V87: 17.5 | W87: 18.5 | X87: 19.5
A88: Discount Factor | E88: =1/(1+E85)^0.5 -> 0.94487327 | F88: =E88/((1+E85)^0.5*(1+F85)^0.5) -> 0.84432983 | G88: =F88/((1+F85)^0.5*(1+G85)^0.5) -> 0.7558477 | H88: =G88/((1+G85)^0.5*(1+H85)^0.5) -> 0.6778623 | I88: =H88/((1+H85)^0.5*(1+I85)^0.5) -> 0.60902497 | J88: =I88/((1+I85)^0.5*(1+J85)^0.5) -> 0.54817166 | K88: =J88/((1+J85)^0.5*(1+K85)^0.5) -> 0.49429629 | L88: =K88/((1+K85)^0.5*(1+L85)^0.5) -> 0.44652817 | M88: =L88/((1+L85)^0.5*(1+M85)^0.5) -> 0.40411274 | ... X88: =W88/((1+W85)^0.5*(1+X85)^0.5) -> 0.15219289
A89: Unlevered FCF ($M) | E89: =E69 -> -2706.6277 | F89: =F69 -> -2579.0621 | G89: =G69 -> -2169.3339 | H89: =H69 -> -1600.6206 | I89: =I69 -> -784.28037 | J89: =J69 -> 381.70585 | K89: =K69 -> 1691.2197 | L89: =L69 -> 2798.7478 | ... X89: =X69 -> 12144.827
A90: PV of FCF ($M) | E90: =E89*E88 -> -2557.4201 | F90: =F89*F88 -> -2177.5791 | G90: =G89*G88 -> -1639.686 | H90: =H89*H88 -> -1085.0004 | I90: =I89*I88 -> -477.64633 | J90: =J89*J88 -> 209.24033 | K90: =K89*K88 -> 835.96363 | L90: =L89*L88 -> 1249.7197 | ... X90: =X89*X88 -> 1848.3563
A92: TERMINAL VALUE
A93: Gordon Growth Model
A94: Terminal FCF ($M) | B94: =X69 -> 12144.827
A95: Terminal FCF × (1+g) | B95: =X69*(1+$B$49) -> 12448.448
A96: Terminal Value (Gordon Growth) | B96: =B95/($X$85-$B$49) -> 219315.43
A97: PV of Terminal Value (Gordon Growth) | B97: =B96*$X$88/(1+$X$85)^0.5 -> 32092.088
A98: GG-Implied Exit EV/EBITDA | B98: =B96/B102 -> 11.357498
A100: EV/EBITDA Exit Multiple Method
A101: Exit EV/EBITDA Multiple | B101: =IF(N('Space Comps'!K35)>0,'Space Comps'!K35,18) -> 15.138889 | D101: =IF(N('Space Comps'!K35)>0,"✓ LIVE – "&TEXT('Space Comps'!K35,"0.0x")&" from Space Comps mature tier","⚠ FALLBACK – using 18x default") -> ✓ LIVE – 15.1x from Space Comps mature tier
A102: Terminal Year EBITDA ($M) | B102: =X56 -> 19310.188
A103: Terminal Value (Exit Multiple) | B103: =B101*B102 -> 292334.79
A104: PV of Terminal Value (Exit Multiple) | B104: =B103*$X$88/(1+$X$85)^0.5 -> 42776.899
A106: SPACE SEGMENT VALUATION SUMMARY
B108: Gordon Growth | C108: Exit Multiple
A109: Sum of PV of FCFs ($M) | B109: =SUM(E90:X90) -> 17125.189 | C109: =SUM(E90:X90) -> 17125.189
A110: PV of Terminal Value ($M) | B110: =B97 -> 32092.088 | C110: =B104 -> 42776.899
A111: Enterprise Value ($M) | B111: =B109+B110 -> 49217.277 | C111: =C109+C110 -> 59902.088
A113: TV % of Enterprise Value | B113: =B110/B111 -> 0.65204924 | C113: =C110/C111 -> 0.71411365 | D113: header
A115: SENSITIVITY ANALYSIS – SPACE SEGMENT EV ($M)
A117: Table 1: EV ($M) – WACC vs. Terminal Growth Rate (Gordon Growth)
...

Sheet AI DCF
A1: SpaceX – AI Segment DCF (X / xAI / Grok)
A2: S-1 Filed May 20, 2026 | 20-Year Explicit Forecast FY2026E–FY2045E | $ in Millions
A3: ⚠ AI segment includes X (social/advertising), xAI (Grok/models), and compute infrastructure. Op losses reflect heavy investment phase; TV captures mature-state value.
A5: SCENARIO SELECTOR | B5: =Dashboard!B33 -> 2 | C5: =IF(B5=1,"◀ BEAR",IF(B5=2,"◀ BASE","◀ BULL")) -> ◀ BASE | D5: (1 = Bear | 2 = Base | 3 = Bull)
B6: FY2023A | C6: FY2024A | D6: FY2025A | E6: FY2026E | F6: FY2027E | G6: FY2028E | H6: FY2029E | I6: FY2030E | J6: FY2031E | K6: FY2032E | L6: FY2033E | M6: FY2034E | N6: FY2035E | O6: FY2036E | P6: FY2037E | Q6: FY2038E | R6: FY2039E | S6: FY2040E | T6: FY2041E | U6: FY2042E | V6: FY2043E | W6: FY2044E | X6: FY2045E
A8: BEAR CASE ASSUMPTIONS
A9: Revenue Growth % (YoY) | E9: 0.15 | F9: 0.2 | G9: 0.25 | H9: 0.28 | I9: 0.3 | J9: 0.28 | K9: 0.25 | L9: 0.22 | M9: 0.18 | N9: 0.15 | O9: 0.14 | P9: 0.13 | Q9: 0.12 | R9: 0.1 | S9: 0.09 | T9: 0.08 | U9: 0.07 | V9: 0.06 | W9: 0.05 | X9: 0.04
A10: EBITDA Margin % | E10: -0.3 | F10: -0.15 | G10: 0 | H10: 0.1 | I10: 0.18 | J10: 0.23 | K10: 0.27 | L10: 0.3 | M10: 0.32 | N10: 0.34 | O10: 0.36 | P10: 0.38 | Q10: 0.39 | R10: 0.4 | S10: 0.41 | T10: 0.42 | U10: 0.42 | V10: 0.43 | W10: 0.43 | X10: 0.44
A11: D&A % of Revenue | E11: 1.15 | F11: 1 | G11: 0.85 | H11: 0.72 | I11: 0.62 | J11: 0.54 | K11: 0.47 | L11: 0.42 | M11: 0.37 | N11: 0.33 | O11: 0.3 | P11: 0.28 | Q11: 0.26 | R11: 0.24 | S11: 0.23 | T11: 0.22 | U11: 0.21 | V11: 0.2 | W11: 0.19 | X11: 0.19
A12: Capex % of Revenue | E12: 3.6 | F12: 2.8 | G12: 2.1 | H12: 1.6 | I12: 1.2 | J12: 0.95 | K12: 0.78 | L12: 0.65 | M12: 0.55 | N12: 0.48 | O12: 0.44 | P12: 0.4 | Q12: 0.36 | R12: 0.33 | S12: 0.3 | T12: 0.27 | U12: 0.24 | V12: 0.22 | W12: 0.2 | X12: 0.18
A13: ΔNW Cap % of ΔRevenue | E13: 0.08 | F13: 0.07 | G13: 0.06 | H13: 0.06 | I13: 0.05 | J13: 0.05 | K13: 0.04 | L13: 0.04 | M13: 0.03 | N13: 0.03 | O13: 0.03 | P13: 0.03 | Q13: 0.025 | R13: 0.025 | S13: 0.025 | T13: 0.02 | U13: 0.02 | V13: 0.02 | W13: 0.02 | X13: 0.02
A14: Terminal Growth Rate | B14: =WACC!D44 -> 0.025
A15: WACC | B15: =WACC!B44 -> 0.10385358
A17: BASE CASE ASSUMPTIONS
A18: Revenue Growth % (YoY) | E18: 0.28 | F18: 0.38 | G18: 0.45 | H18: 0.48 | I18: 0.45 | J18: 0.38 | K18: 0.32 | L18: 0.27 | M18: 0.22 | N18: 0.18 | O18: 0.16 | P18: 0.15 | Q18: 0.13 | R18: 0.12 | S18: 0.1 | T18: 0.09 | U18: 0.08 | V18: 0.07 | W18: 0.06 | X18: 0.05
A19: EBITDA Margin % | E19: -0.15 | F19: 0.02 | G19: 0.12 | H19: 0.22 | I19: 0.3 | J19: 0.36 | K19: 0.4 | L19: 0.43 | M19: 0.45 | N19: 0.46 | O19: 0.48 | P19: 0.5 | Q19: 0.51 | R19: 0.52 | S19: 0.53 | T19: 0.54 | U19: 0.55 | V19: 0.56 | W19: 0.57 | X19: 0.58
A20: D&A % of Revenue | E20: 1.05 | F20: 0.9 | G20: 0.75 | H20: 0.62 | I20: 0.52 | J20: 0.44 | K20: 0.38 | L20: 0.33 | M20: 0.29 | N20: 0.26 | O20: 0.24 | P20: 0.22 | Q20: 0.2 | R20: 0.19 | S20: 0.18 | T20: 0.17 | U20: 0.16 | V20: 0.16 | W20: 0.15 | X20: 0.15
A21: Capex % of Revenue | E21: 3.2 | F21: 2.4 | G21: 1.8 | H21: 1.35 | I21: 1 | J21: 0.8 | K21: 0.65 | L21: 0.54 | M21: 0.46 | N21: 0.4 | O21: 0.36 | P21: 0.33 | Q21: 0.3 | R21: 0.27 | S21: 0.25 | T21: 0.22 | U21: 0.2 | V21: 0.18 | W21: 0.16 | X21: 0.15
A22: ΔNW Cap % of ΔRevenue | E22: 0.06 | F22: 0.06 | G22: 0.05 | H22: 0.05 | I22: 0.04 | J22: 0.04 | K22: 0.03 | L22: 0.03 | M22: 0.03 | N22: 0.02 | O22: 0.02 | P22: 0.02 | Q22: 0.02 | R22: 0.018 | S22: 0.018 | T22: 0.015 | U22: 0.015 | V22: 0.015 | W22: 0.015 | X22: 0.015
A23: Terminal Growth Rate | B23: =WACC!C44 -> 0.035
A24: WACC | B24: =WACC!B44 -> 0.10385358
A26: BULL CASE ASSUMPTIONS
A27: Revenue Growth % (YoY) | E27: 0.45 | F27: 0.6 | G27: 0.7 | H27: 0.7 | I27: 0.6 | J27: 0.5 | K27: 0.42 | L27: 0.35 | M27: 0.28 | N27: 0.22 | O27: 0.2 | P27: 0.18 | Q27: 0.16 | R27: 0.14 | S27: 0.12 | T27: 0.11 | U27: 0.1 | V27: 0.09 | W27: 0.07 | X27: 0.06
A28: EBITDA Margin % | E28: -0.1 | F28: -0.05 | G28: 0.05 | H28: 0.12 | I28: 0.2 | J28: 0.28 | K28: 0.35 | L28: 0.42 | M28: 0.48 | N28: 0.55 | O28: 0.57 | P28: 0.59 | Q28: 0.6 | R28: 0.61 | S28: 0.62 | T28: 0.63 | U28: 0.64 | V28: 0.65 | W28: 0.65 | X28: 0.66
A29: D&A % of Revenue | E29: 0.95 | F29: 0.78 | G29: 0.63 | H29: 0.5 | I29: 0.4 | J29: 0.33 | K29: 0.28 | L29: 0.24 | M29: 0.21 | N29: 0.19 | O29: 0.17 | P29: 0.16 | Q29: 0.15 | R29: 0.14 | S29: 0.13 | T29: 0.12 | U29: 0.12 | V29: 0.11 | W29: 0.11 | X29: 0.1
A30: Capex % of Revenue | E30: 2.9 | F30: 2.1 | G30: 1.55 | H30: 1.15 | I30: 0.85 | J30: 0.68 | K30: 0.55 | L30: 0.46 | M30: 0.39 | N30: 0.34 | O30: 0.3 | P30: 0.27 | Q30: 0.25 | R30: 0.22 | S30: 0.2 | T30: 0.18 | U30: 0.16 | V30: 0.15 | W30: 0.14 | X30: 0.13
A31: ΔNW Cap % of ΔRevenue | E31: 0.05 | F31: 0.05 | G31: 0.04 | H31: 0.04 | I31: 0.03 | J31: 0.03 | K31: 0.03 | L31: 0.02 | M31: 0.02 | N31: 0.02 | O31: 0.02 | P31: 0.018 | Q31: 0.018 | R31: 0.015 | S31: 0.015 | T31: 0.015 | U31: 0.012 | V31: 0.012 | W31: 0.012 | X31: 0.012
A32: Terminal Growth Rate | B32: =WACC!E44 -> 0.04
A33: WACC | B33: =WACC!B44 -> 0.10385358
A35: SELECTED CASE ASSUMPTIONS
A36: Revenue Growth % (YoY) | E36: =IF($B$5=1,E9,IF($B$5=2,E18,E27)) -> 0.28 | F36: =IF($B$5=1,F9,IF($B$5=2,F18,F27)) -> 0.38 | G36: =IF($B$5=1,G9,IF($B$5=2,G18,G27)) -> 0.45 | H36: =IF($B$5=1,H9,IF($B$5=2,H18,H27)) -> 0.48 | I36: =IF($B$5=1,I9,IF($B$5=2,I18,I27)) -> 0.45 | J36: =IF($B$5=1,J9,IF($B$5=2,J18,J27)) -> 0.38 | K36: =IF($B$5=1,K9,IF($B$5=2,K18,K27)) -> 0.32 | L36: =IF($B$5=1,L9,IF($B$5=2,L18,L27)) -> 0.27 | ... X36: =IF($B$5=1,X9,IF($B$5=2,X18,X27)) -> 0.05
A37: EBITDA Margin % | E37: =IF($B$5=1,E10,IF($B$5=2,E19,E28)) -> -0.15 | F37: =IF($B$5=1,F10,IF($B$5=2,F19,F28)) -> 0.02 | G37: =IF($B$5=1,G10,IF($B$5=2,G19,G28)) -> 0.12 | H37: =IF($B$5=1,H10,IF($B$5=2,H19,H28)) -> 0.22 | I37: =IF($B$5=1,I10,IF($B$5=2,I19,I28)) -> 0.3 | J37: =IF($B$5=1,J10,IF($B$5=2,J19,J28)) -> 0.36 | K37: =IF($B$5=1,K10,IF($B$5=2,K19,K28)) -> 0.4 | L37: =IF($B$5=1,L10,IF($B$5=2,L19,L28)) -> 0.43 | ... X37: =IF($B$5=1,X10,IF($B$5=2,X19,X28)) -> 0.58
A38: D&A % of Revenue | E38: =IF($B$5=1,E11,IF($B$5=2,E20,E29)) -> 1.05 | F38: =IF($B$5=1,F11,IF($B$5=2,F20,F29)) -> 0.9 | G38: =IF($B$5=1,G11,IF($B$5=2,G20,G29)) -> 0.75 | H38: =IF($B$5=1,H11,IF($B$5=2,H20,H29)) -> 0.62 | I38: =IF($B$5=1,I11,IF($B$5=2,I20,I29)) -> 0.52 | J38: =IF($B$5=1,J11,IF($B$5=2,J20,J29)) -> 0.44 | K38: =IF($B$5=1,K11,IF($B$5=2,K20,K29)) -> 0.38 | L38: =IF($B$5=1,L11,IF($B$5=2,L20,L29)) -> 0.33 | ... X38: =IF($B$5=1,X11,IF($B$5=2,X20,X29)) -> 0.15
A39: Capex % of Revenue | E39: =IF($B$5=1,E12,IF($B$5=2,E21,E30)) -> 3.2 | F39: =IF($B$5=1,F12,IF($B$5=2,F21,F30)) -> 2.4 | G39: =IF($B$5=1,G12,IF($B$5=2,G21,G30)) -> 1.8 | H39: =IF($B$5=1,H12,IF($B$5=2,H21,H30)) -> 1.35 | I39: =IF($B$5=1,I12,IF($B$5=2,I21,I30)) -> 1 | J39: =IF($B$5=1,J12,IF($B$5=2,J21,J30)) -> 0.8 | K39: =IF($B$5=1,K12,IF($B$5=2,K21,K30)) -> 0.65 | L39: =IF($B$5=1,L12,IF($B$5=2,L21,L30)) -> 0.54 | ... X39: =IF($B$5=1,X12,IF($B$5=2,X21,X30)) -> 0.15
A40: ΔNW Cap % of ΔRevenue | E40: =IF($B$5=1,E13,IF($B$5=2,E22,E31)) -> 0.06 | F40: =IF($B$5=1,F13,IF($B$5=2,F22,F31)) -> 0.06 | G40: =IF($B$5=1,G13,IF($B$5=2,G22,G31)) -> 0.05 | H40: =IF($B$5=1,H13,IF($B$5=2,H22,H31)) -> 0.05 | I40: =IF($B$5=1,I13,IF($B$5=2,I22,I31)) -> 0.04 | J40: =IF($B$5=1,J13,IF($B$5=2,J22,J31)) -> 0.04 | K40: =IF($B$5=1,K13,IF($B$5=2,K22,K31)) -> 0.03 | L40: =IF($B$5=1,L13,IF($B$5=2,L22,L31)) -> 0.03 | ... X40: =IF($B$5=1,X13,IF($B$5=2,X22,X31)) -> 0.015
A41: Terminal Growth Rate | B41: =IF($B$5=1,B14,IF($B$5=2,B23,B32)) -> 0.035
A42: WACC | B42: =IF($B$5=1,B15,IF($B$5=2,B24,B33)) -> 0.10385358
A43: Blended WACC (Sensitivity Center) | B43: =AVERAGE(E77:X77) -> 0.13727693
A45: AI SEGMENT – INCOME STATEMENT & FREE CASH FLOW ($M)
A46: Revenue | B46: =Actuals!B10 -> 2961 | C46: =Actuals!C10 -> 2620 | D46: =Actuals!D10 -> 3201 | E46: =D46*(1+E36) -> 4097.28 | F46: =E46*(1+F36) -> 5654.2464 | G46: =F46*(1+G36) -> 8198.6573 | H46: =G46*(1+H36) -> 12134.013 | I46: =H46*(1+I36) -> 17594.319 | J46: =I46*(1+J36) -> 24280.16 | K46: =J46*(1+K36) -> 32049.811 | L46: =K46*(1+L36) -> 40703.259 | ... X46: =W46*(1+X36) -> 152561.59
A47: % YoY Growth | C47: =C46/B46-1 -> -0.1151638 | D47: =D46/C46-1 -> 0.22175573 | E47: =E46/D46-1 -> 0.28 | F47: =F46/E46-1 -> 0.38 | G47: =G46/F46-1 -> 0.45 | H47: =H46/G46-1 -> 0.48 | I47: =I46/H46-1 -> 0.45 | J47: =J46/I46-1 -> 0.38 | ... X47: =X46/W46-1 -> 0.05
A48: EBITDA | B48: =Actuals!B13 -> 1222 | C48: =Actuals!C13 -> 347 | D48: =Actuals!D13 -> -1237 | E48: =E46*E37 -> -614.592 | F48: =F46*F37 -> 113.08493 | G48: =G46*G37 -> 983.83887 | H48: =H46*H37 -> 2669.4828 | I48: =I46*I37 -> 5278.2956 | J48: =J46*J37 -> 8740.8574 | K48: =K46*K37 -> 12819.924 | L48: =L46*L37 -> 17502.402 | ... X48: =X46*X37 -> 88485.722
A49: EBITDA Margin % | B49: =B48/B46 -> 0.41269841 | C49: =C48/C46 -> 0.13244275 | D49: =D48/D46 -> -0.38644174 | E49: =E48/E46 -> -0.15 | F49: =F48/F46 -> 0.02 | G49: =G48/G46 -> 0.12 | H49: =H48/H46 -> 0.22 | I49: =I48/I46 -> 0.3 | ... X49: =X48/X46 -> 0.58
A50: Depreciation & Amortization | B50: =Actuals!B16 -> 1180 | C50: =Actuals!C16 -> 1679 | D50: =Actuals!D16 -> 3568 | E50: =E46*E38 -> 4302.144 | F50: =F46*F38 -> 5088.8218 | G50: =G46*G38 -> 6148.993 | H50: =H46*H38 -> 7523.0879 | I50: =I46*I38 -> 9149.0456 | J50: =J46*J38 -> 10683.27 | K50: =K46*K38 -> 12178.928 | L50: =L46*L38 -> 13432.076 | ... X50: =X46*X38 -> 22884.238
A51: EBIT (EBITDA − D&A) | B51: =B48-B50 -> 42 | C51: =C48-C50 -> -1332 | D51: =D48-D50 -> -4805 | E51: =E48-E50 -> -4916.736 | F51: =F48-F50 -> -4975.7368 | G51: =G48-G50 -> -5165.1541 | H51: =H48-H50 -> -4853.6051 | I51: =I48-I50 -> -3870.7501 | ... X51: =X48-X50 -> 65601.483
A52: EBIT Margin % | B52: =B51/B46 -> 0.014184397 | C52: =C51/C46 -> -0.50839695 | D52: =D51/D46 -> -1.5010934 | E52: =E51/E46 -> -1.2 | F52: =F51/F46 -> -0.88 | G52: =G51/G46 -> -0.63 | H52: =H51/H46 -> -0.4 | I52: =I51/I46 -> -0.22 | ... X52: =X51/X46 -> 0.43
A53: NOL Opening Balance ($M) | B53: 0 | C53: =B55 -> 0 | D53: =C55 -> 1332 | E53: =D55 -> 6137 | F53: =E55 -> 11053.736 | G53: =F55 -> 16029.473 | H53: =G55 -> 21194.627 | I53: =H55 -> 26048.232 | J53: =I55 -> 29918.982 | ... X53: =W55 -> 0
A54: (–) NOL Utilization (IRC §172, 80% cap) | B54: =MIN(B53,MAX(B51,0)*0.8) -> 0 | C54: =MIN(C53,MAX(C51,0)*0.8) -> 0 | D54: =MIN(D53,MAX(D51,0)*0.8) -> 0 | E54: =MIN(E53,MAX(E51,0)*0.8) -> 0 | F54: =MIN(F53,MAX(F51,0)*0.8) -> 0 | G54: =MIN(G53,MAX(G51,0)*0.8) -> 0 | H54: =MIN(H53,MAX(H51,0)*0.8) -> 0 | I54: =MIN(I53,MAX(I51,0)*0.8) -> 0 | ... X54: =MIN(X53,MAX(X51,0)*0.8) -> 0
A55: NOL Closing Balance ($M) | B55: =B53-B54+MAX(-B51,0) -> 0 | C55: =C53-C54+MAX(-C51,0) -> 1332 | D55: =D53-D54+MAX(-D51,0) -> 6137 | E55: =E53-E54+MAX(-E51,0) -> 11053.736 | F55: =F53-F54+MAX(-F51,0) -> 16029.473 | G55: =G53-G54+MAX(-G51,0) -> 21194.627 | H55: =H53-H54+MAX(-H51,0) -> 26048.232 | I55: =I53-I54+MAX(-I51,0) -> 29918.982 | ... X55: =X53-X54+MAX(-X51,0) -> 0
A56: (–) Tax on EBIT | B56: =(MAX(B51,0)-B54)*WACC!$B$9 -> 8.82 | C56: =(MAX(C51,0)-C54)*WACC!$B$9 -> 0 | D56: =(MAX(D51,0)-D54)*WACC!$B$9 -> 0 | E56: =(MAX(E51,0)-E54)*WACC!$B$9 -> 0 | F56: =(MAX(F51,0)-F54)*WACC!$B$9 -> 0 | G56: =(MAX(G51,0)-G54)*WACC!$B$9 -> 0 | H56: =(MAX(H51,0)-H54)*WACC!$B$9 -> 0 | I56: =(MAX(I51,0)-I54)*WACC!$B$9 -> 0 | ... X56: =(MAX(X51,0)-X54)*WACC!$B$9 -> 13776.311
A57: NOPAT | B57: =B51-B56 -> 33.18 | C57: =C51-C56 -> -1332 | D57: =D51-D56 -> -4805 | E57: =E51-E56 -> -4916.736 | F57: =F51-F56 -> -4975.7368 | G57: =G51-G56 -> -5165.1541 | H57: =H51-H56 -> -4853.6051 | I57: =I51-I56 -> -3870.7501 | ... X57: =X51-X56 -> 51825.172
A58: (+) D&A | B58: =B50 -> 1180 | C58: =C50 -> 1679 | D58: =D50 -> 3568 | E58: =E50 -> 4302.144 | F58: =F50 -> 5088.8218 | G58: =G50 -> 6148.993 | H58: =H50 -> 7523.0879 | I58: =I50 -> 9149.0456 | ... X58: =X50 -> 22884.238
A59: (–) Capital Expenditures | B59: =Actuals!B20 -> -463 | C59: =Actuals!C20 -> -5633 | D59: =Actuals!D20 -> -12727 | E59: =-E46*E39 -> -13111.296 | F59: =-F46*F39 -> -13570.191 | G59: =-G46*G39 -> -14757.583 | H59: =-H46*H39 -> -16380.917 | I59: =-I46*I39 -> -17594.319 | J59: =-J46*J39 -> -19424.128 | K59: =-K46*K39 -> -20832.377 | L59: =-L46*L39 -> -21979.76 | ... X59: =-X46*X39 -> -22884.238
A60: (–) Increase in Net Working Capital | B60: 0 | C60: 0 | D60: 0 | E60: =-(E46-D46)*E40 -> -53.7768 | F60: =-(F46-E46)*F40 -> -93.417984 | G60: =-(G46-F46)*G40 -> -127.22054 | H60: =-(H46-G46)*H40 -> -196.76777 | I60: =-(I46-H46)*I40 -> -218.41223 | J60: =-(J46-I46)*J40 -> -267.43364 | K60: =-(K46-J46)*K40 -> -233.08953 | L60: =-(L46-K46)*L40 -> -259.60347 | ... X60: =-(X46-W46)*X40 -> -108.97256
A61: Unlevered Free Cash Flow | B61: =B57+B58+B59+B60 -> 750.18 | C61: =C57+C58+C59+C60 -> -5286 | D61: =D57+D58+D59+D60 -> -13964 | E61: =E57+E58+E59+E60-E46*($B$63+($C$63-$B$63)*(COLUMN()-5)/19)*(1-WACC!$B$9) -> -14038.613 | F61: =F57+F58+F59+F60-F46*($B$63+($C$63-$B$63)*(COLUMN()-5)/19)*(1-WACC!$B$9) -> -13893.767 | G61: =G57+G58+G59+G60-G46*($B$63+($C$63-$B$63)*(COLUMN()-5)/19)*(1-WACC!$B$9) -> -14378.213 | H61: =H57+H58+H59+H60-H46*($B$63+($C$63-$B$63)*(COLUMN()-5)/19)*(1-WACC!$B$9) -> -14584.258 | I61: =I57+I58+I59+I60-I46*($B$63+($C$63-$B$63)*(COLUMN()-5)/19)*(1-WACC!$B$9) -> -13470.823 | J61: =J57+J58+J59+J60-J46*($B$63+($C$63-$B$63)*(COLUMN()-5)/19)*(1-WACC!$B$9) -> -12182.347 | K61: =K57+K58+K59+K60-K46*($B$63+($C$63-$B$63)*(COLUMN()-5)/19)*(1-WACC!$B$9) -> -9818.277 | L61: =L57+L58+L59+L60-L46*($B$63+($C$63-$B$63)*(COLUMN()-5)/19)*(1-WACC!$B$9) -> -6769.5543 | ... X61: =X57+X58+X59+X60-X46*($B$63+($C$63-$B$63)*(COLUMN()-5)/19)*(1-WACC!$B$9) -> 49305.726
A62: FCF Margin % | B62: =B61/B46 -> 0.2533536 | C62: =C61/C46 -> -2.0175573 | D62: =D61/D46 -> -4.3623868 | E62: =E61/E46 -> -3.426325 | F62: =F61/F46 -> -2.457227 | G62: =G61/G46 -> -1.7537278 | H62: =H61/H46 -> -1.201932 | I62: =I61/I46 -> -0.76563485 | ... X62: =X61/X46 -> 0.32318571
A63: SBC (% of Revenue) | B63: 0.08 | C63: 0.02
A65: DCF – DISCOUNT FACTORS & PRESENT VALUES (Mid-Year Convention)
A67: TIME-WEIGHTED BETA & WACC
A68: Tier 1 (GPU Neoclouds) Unlevered β | B68: ='AI Comps'!X15 -> 2.4896937 | C68: GPU Neoclouds | E68: =$B$68 -> 2.4896937 | F68: =$B$68 -> 2.4896937 | G68: =$B$68 -> 2.4896937 | H68: =$B$68 -> 2.4896937 | I68: =$B$68 -> 2.4896937 | J68: =$B$68 -> 2.4896937 | K68: =$B$68 -> 2.4896937 | L68: =$B$68 -> 2.4896937 | ... X68: =$B$68 -> 2.4896937
A69: Tier 2 (Infra Hosting) Unlevered β | B69: ='AI Comps'!X29 -> 3.1307916 | C69: Infra Hosting (wt = 0) | E69: =$B$69 -> 3.1307916 | F69: =$B$69 -> 3.1307916 | G69: =$B$69 -> 3.1307916 | H69: =$B$69 -> 3.1307916 | I69: =$B$69 -> 3.1307916 | J69: =$B$69 -> 3.1307916 | K69: =$B$69 -> 3.1307916 | L69: =$B$69 -> 3.1307916 | ... X69: =$B$69 -> 3.1307916
A70: Tier 3 (Social Media) Unlevered β | B70: ='AI Comps'!X43 -> 0.90384475 | C70: Social Media | E70: =$B$70 -> 0.90384475 | F70: =$B$70 -> 0.90384475 | G70: =$B$70 -> 0.90384475 | H70: =$B$70 -> 0.90384475 | I70: =$B$70 -> 0.90384475 | J70: =$B$70 -> 0.90384475 | K70: =$B$70 -> 0.90384475 | L70: =$B$70 -> 0.90384475 | ... X70: =$B$70 -> 0.90384475
A71: Tier 1 Weight | B71: =IF($B$5=1,0.7,IF($B$5=2,0.6,0.5)) -> 0.6 | C71: =IF($B$5=1,0.3,IF($B$5=2,0.2,0.15)) -> 0.2 | D71: B = Yr 1, C = Yr 20 | E71: =$B71+($C71-$B71)*(COLUMN()-5)/19 -> 0.6 | F71: =$B71+($C71-$B71)*(COLUMN()-5)/19 -> 0.57894737 | G71: =$B71+($C71-$B71)*(COLUMN()-5)/19 -> 0.55789474 | H71: =$B71+($C71-$B71)*(COLUMN()-5)/19 -> 0.53684211 | I71: =$B71+($C71-$B71)*(COLUMN()-5)/19 -> 0.51578947 | J71: =$B71+($C71-$B71)*(COLUMN()-5)/19 -> 0.49473684 | K71: =$B71+($C71-$B71)*(COLUMN()-5)/19 -> 0.47368421 | L71: =$B71+($C71-$B71)*(COLUMN()-5)/19 -> 0.45263158 | ... X71: =$B71+($C71-$B71)*(COLUMN()-5)/19 -> 0.2
A72: Tier 2 Weight | B72: =IF($B$5=1,0,IF($B$5=2,0,0)) -> 0 | C72: =IF($B$5=1,0,IF($B$5=2,0,0)) -> 0 | D72: (see E→X for glide) | E72: =$B72+($C72-$B72)*(COLUMN()-5)/19 -> 0 | F72: =$B72+($C72-$B72)*(COLUMN()-5)/19 -> 0 | G72: =$B72+($C72-$B72)*(COLUMN()-5)/19 -> 0 | H72: =$B72+($C72-$B72)*(COLUMN()-5)/19 -> 0 | I72: =$B72+($C72-$B72)*(COLUMN()-5)/19 -> 0 | J72: =$B72+($C72-$B72)*(COLUMN()-5)/19 -> 0 | K72: =$B72+($C72-$B72)*(COLUMN()-5)/19 -> 0 | L72: =$B72+($C72-$B72)*(COLUMN()-5)/19 -> 0 | ... X72: =$B72+($C72-$B72)*(COLUMN()-5)/19 -> 0
A73: Tier 3 Weight (= 1 – T1 – T2) | B73: =1-B71-B72 -> 0.4 | C73: =1-C71-C72 -> 0.8 | E73: =1-E71-E72 -> 0.4 | F73: =1-F71-F72 -> 0.42105263 | G73: =1-G71-G72 -> 0.44210526 | H73: =1-H71-H72 -> 0.46315789 | I73: =1-I71-I72 -> 0.48421053 | J73: =1-J71-J72 -> 0.50526316 | K73: =1-K71-K72 -> 0.52631579 | L73: =1-L71-L72 -> 0.54736842 | ... X73: =1-X71-X72 -> 0.8
A74: Blended Unlevered β | E74: =E68*E71+E69*E72+E70*E73 -> 1.8553541 | F74: =F68*F71+F69*F72+F70*F73 -> 1.8219678 | G74: =G68*G71+G69*G72+G70*G73 -> 1.7885815 | H74: =H68*H71+H69*H72+H70*H73 -> 1.7551952 | I74: =I68*I71+I69*I72+I70*I73 -> 1.7218089 | J74: =J68*J71+J69*J72+J70*J73 -> 1.6884226 | K74: =K68*K71+K69*K72+K70*K73 -> 1.6550363 | L74: =L68*L71+L69*L72+L70*L73 -> 1.62165 | ... X74: =X68*X71+X69*X72+X70*X73 -> 1.2210145
A75: Relevered β (Hamada) | E75: =E74*(1+(1-WACC!$B$9)*WACC!$D$22) -> 2.2217865 | F75: =F74*(1+(1-WACC!$B$9)*WACC!$D$22) -> 2.1818064 | G75: =G74*(1+(1-WACC!$B$9)*WACC!$D$22) -> 2.1418264 | H75: =H74*(1+(1-WACC!$B$9)*WACC!$D$22) -> 2.1018463 | I75: =I74*(1+(1-WACC!$B$9)*WACC!$D$22) -> 2.0618662 | J75: =J74*(1+(1-WACC!$B$9)*WACC!$D$22) -> 2.0218861 | K75: =K74*(1+(1-WACC!$B$9)*WACC!$D$22) -> 1.981906 | L75: =L74*(1+(1-WACC!$B$9)*WACC!$D$22) -> 1.9419259 | ... X75: =X74*(1+(1-WACC!$B$9)*WACC!$D$22) -> 1.4621649
A76: Cost of Equity (Ke) | E76: =WACC!$B$7+E75*WACC!$B$8+WACC!$B$10 -> 0.17569826 | F76: =WACC!$B$7+F75*WACC!$B$8+WACC!$B$10 -> 0.17349935 | G76: =WACC!$B$7+G75*WACC!$B$8+WACC!$B$10 -> 0.17130045 | H76: =WACC!$B$7+H75*WACC!$B$8+WACC!$B$10 -> 0.16910155 | I76: =WACC!$B$7+I75*WACC!$B$8+WACC!$B$10 -> 0.16690264 | J76: =WACC!$B$7+J75*WACC!$B$8+WACC!$B$10 -> 0.16470374 | K76: =WACC!$B$7+K75*WACC!$B$8+WACC!$B$10 -> 0.16250483 | L76: =WACC!$B$7+L75*WACC!$B$8+WACC!$B$10 -> 0.16030593 | ... X76: =WACC!$B$7+X75*WACC!$B$8+WACC!$B$10 -> 0.13391907
A77: Time-Varying WACC | B77: =E77 -> 0.15398861 | C77: → | D77: =X77 -> 0.12056526 | E77: =E76*WACC!$D$35+WACC!$D$30*WACC!$D$36 -> 0.15398861 | F77: =F76*WACC!$D$35+WACC!$D$30*WACC!$D$36 -> 0.15222948 | G77: =G76*WACC!$D$35+WACC!$D$30*WACC!$D$36 -> 0.15047036 | H77: =H76*WACC!$D$35+WACC!$D$30*WACC!$D$36 -> 0.14871124 | I77: =I76*WACC!$D$35+WACC!$D$30*WACC!$D$36 -> 0.14695211 | J77: =J76*WACC!$D$35+WACC!$D$30*WACC!$D$36 -> 0.14519299 | K77: =K76*WACC!$D$35+WACC!$D$30*WACC!$D$36 -> 0.14343386 | L77: =L76*WACC!$D$35+WACC!$D$30*WACC!$D$36 -> 0.14167474 | ... X77: =X76*WACC!$D$35+WACC!$D$30*WACC!$D$36 -> 0.12056526
A79: Discount Period (mid-year) | E79: 0.5 | F79: 1.5 | G79: 2.5 | H79: 3.5 | I79: 4.5 | J79: 5.5 | K79: 6.5 | L79: 7.5 | M79: 8.5 | N79: 9.5 | O79: 10.5 | P79: 11.5 | Q79: 12.5 | R79: 13.5 | S79: 14.5 | T79: 15.5 | U79: 16.5 | V79: 17.5 | W79: 18.5 | X79: 19.5
A80: Discount Factor | E80: =1/(1+E77)^0.5 -> 0.93089187 | F80: =E80/((1+E77)^0.5*(1+F77)^0.5) -> 0.80728891 | G80: =F80/((1+F77)^0.5*(1+G77)^0.5) -> 0.7011675 | H80: =G80/((1+G77)^0.5*(1+H77)^0.5) -> 0.60992808 | I80: =H80/((1+H77)^0.5*(1+I77)^0.5) -> 0.5313743 | J80: =I80/((1+I77)^0.5*(1+J77)^0.5) -> 0.46364819 | K80: =J80/((1+J77)^0.5*(1+K77)^0.5) -> 0.40517599 | L80: =K80/((1+K77)^0.5*(1+L77)^0.5) -> 0.35462306 | M80: =L80/((1+L77)^0.5*(1+M77)^0.5) -> 0.31085613 | ... X80: =W80/((1+W77)^0.5*(1+X77)^0.5) -> 0.080861071
A81: Unlevered FCF ($M) | E81: =E61 -> -14038.613 | F81: =F61 -> -13893.767 | G81: =G61 -> -14378.213 | H81: =H61 -> -14584.258 | I81: =I61 -> -13470.823 | J81: =J61 -> -12182.347 | K81: =K61 -> -9818.277 | L81: =L61 -> -6769.5543 | ... X81: =X61 -> 49305.726
A82: PV of FCF ($M) | E82: =E81*E80 -> -13068.431 | F82: =F81*F80 -> -11216.284 | G82: =G81*G80 -> -10081.536 | H82: =H81*H80 -> -8895.3486 | I82: =I81*I80 -> -7158.0494 | J82: =J81*J80 -> -5648.323 | K82: =K81*K80 -> -3978.1301 | L82: =L81*L80 -> -2400.6401 | ... X82: =X81*X80 -> 3986.9138
A84: TERMINAL VALUE
A85: Gordon Growth Model
A86: Terminal FCF ($M) | B86: =X61 -> 49305.726
A87: Terminal FCF × (1+g) | B87: =X61*(1+$B$41) -> 51031.426
A88: Terminal Value (Gordon Growth) | B88: =B87/($X$77-$B$41) -> 596403.6
A89: PV of Terminal Value (Gordon Growth) | B89: =B88*$X$80/(1+$X$77)^0.5 -> 45557.635
A90: GG-Implied Exit EV/Revenue | B90: =B88/B94 -> 3.9092645
A92: EV/Revenue Exit Multiple Method (preferred for pre-profit businesses)
A93: Exit EV/Revenue Multiple (= Tier 3 Social Media comp median, fallback 6.0x) | B93: =IF(N('AI Comps'!J43)>0,'AI Comps'!J43,6) -> 3.2301136 | D93: =IF(N('AI Comps'!J43)>0,"✓ LIVE – "&TEXT('AI Comps'!J43,"0.0x")&" from AI Comps Tier 3 (Social Media)","⚠ FALLBACK – using 6.0x default") -> ✓ LIVE – 3.2x from AI Comps Tier 3 (Social Media)
A94: Terminal Year Revenue ($M) | B94: =X46 -> 152561.59
A95: Terminal Value (Exit EV/Rev) | B95: =B93*B94 -> 492791.27
A96: PV of Terminal Value (Exit EV/Rev) | B96: =B95*$X$80/(1+$X$77)^0.5 -> 37642.973
A98: AI SEGMENT VALUATION SUMMARY
B100: EV/Revenue (Primary) | C100: Gordon (Cross-Check)
A101: Sum of PV of FCFs ($M) | B101: =SUM(E82:X82) -> -35350.807 | C101: =SUM(E82:X82) -> -35350.807
A102: PV of Terminal Value ($M) | B102: =B96 -> 37642.973 | C102: =B89 -> 45557.635
A103: Enterprise Value ($M) | B103: =B101+B102 -> 2292.1662 | C103: =C101+C102 -> 10206.828
A105: TV % of Enterprise Value | B105: =B102/B103 -> 16.422445 | C105: =C102/C103 -> 4.463447
A107: SENSITIVITY ANALYSIS – AI SEGMENT EV ($M)
A109: Table 1: EV ($M) – WACC vs. Terminal Growth Rate (Gordon Growth)
B110: WACC ↓ \ Tg → | C110: =$B$41-0.0075 -> 0.0275 | D110: =$B$41-0.005 -> 0.03 | E110: =$B$41-0.0025 -> 0.0325 | F110: =$B$41 -> 0.035 | G110: =$B$41+0.0025 -> 0.0375 | H110: =$B$41+0.005 -> 0.04 | I110: =$B$41+0.0075 -> 0.0425
B111: =$B$43-0.0075 -> 0.12977693 | C111: =SUMPRODUCT($E$61:$X$61,1/(1+$B111)^$E$79:$X$79)+($X$61*(1+C$110)/($B111-C$110))/(1+$B111)^20 -> 8588.0303 | D111: =SUMPRODUCT($E$61:$X$61,1/(1+$B111)^$E$79:$X$79)+($X$61*(1+D$110)/($B111-D$110))/(1+$B111)^20 -> 9776.9928 | E111: =SUMPRODUCT($E$61:$X$61,1/(1+$B111)^$E$79:$X$79)+($X$61*(1+E$110)/($B111-E$110))/(1+$B111)^20 -> 11027.068 | F111: =SUMPRODUCT($E$61:$X$61,1/(1+$B111)^$E$79:$X$79)+($X$61*(1+F$110)/($B111-F$110))/(1+$B111)^20 -> 12343.091 | G111: =SUMPRODUCT($E$61:$X$61,1/(1+$B111)^$E$79:$X$79)+($X$61*(1+G$110)/($B111-G$110))/(1+$B111)^20 -> 13730.422 | H111: =SUMPRODUCT($E$61:$X$61,1/(1+$B111)^$E$79:$X$79)+($X$61*(1+H$110)/($B111-H$110))/(1+$B111)^20 -> 15195.019 | I111: =SUMPRODUCT($E$61:$X$61,1/(1+$B111)^$E$79:$X$79)+($X$61*(1+I$110)/($B111-I$110))/(1+$B111)^20 -> 16743.521
B112: =$B$43-0.005 -> 0.13227693 | C112: =SUMPRODUCT($E$61:$X$61,1/(1+$B112)^$E$79:$X$79)+($X$61*(1+C$110)/($B112-C$110))/(1+$B112)^20 -> 5067.6109 | D112: =SUMPRODUCT($E$61:$X$61,1/(1+$B112)^$E$79:$X$79)+($X$61*(1+D$110)/($B112-D$110))/(1+$B112)^20 -> 6153.27 | E112: =SUMPRODUCT($E$61:$X$61,1/(1+$B112)^$E$79:$X$79)+($X$61*(1+E$110)/($B112-E$110))/(1+$B112)^20 -> 7293.3334 | F112: =SUMPRODUCT($E$61:$X$61,1/(1+$B112)^$E$79:$X$79)+($X$61*(1+F$110)/($B112-F$110))/(1+$B112)^20 -> 8491.9957 | G112: =SUMPRODUCT($E$61:$X$61,1/(1+$B112)^$E$79:$X$79)+($X$61*(1+G$110)/($B112-G$110))/(1+$B112)^20 -> 9753.8939 | H112: =SUMPRODUCT($E$61:$X$61,1/(1+$B112)^$E$79:$X$79)+($X$61*(1+H$110)/($B112-H$110))/(1+$B112)^20 -> 11084.168 | I112: =SUMPRODUCT($E$61:$X$61,1/(1+$B112)^$E$79:$X$79)+($X$61*(1+I$110)/($B112-I$110))/(1+$B112)^20 -> 12488.529
B113: =$B$43-0.0025 -> 0.13477693 | C113: =SUMPRODUCT($E$61:$X$61,1/(1+$B113)^$E$79:$X$79)+($X$61*(1+C$110)/($B113-C$110))/(1+$B113)^20 -> 1797.8255 | D113: =SUMPRODUCT($E$61:$X$61,1/(1+$B113)^$E$79:$X$79)+($X$61*(1+D$110)/($B113-D$110))/(1+$B113)^20 -> 2790.4063 | E113: =SUMPRODUCT($E$61:$X$61,1/(1+$B113)^$E$79:$X$79)+($X$61*(1+E$110)/($B113-E$110))/(1+$B113)^20 -> 3831.5113 | F113: =SUMPRODUCT($E$61:$X$61,1/(1+$B113)^$E$79:$X$79)+($X$61*(1+F$110)/($B113-F$110))/(1+$B113)^20 -> 4924.7879 | G113: =SUMPRODUCT($E$61:$X$61,1/(1+$B113)^$E$79:$X$79)+($X$61*(1+G$110)/($B113-G$110))/(1+$B113)^20 -> 6074.2586 | H113: =SUMPRODUCT($E$61:$X$61,1/(1+$B113)^$E$79:$X$79)+($X$61*(1+H$110)/($B113-H$110))/(1+$B113)^20 -> 7284.3701 | I113: =SUMPRODUCT($E$61:$X$61,1/(1+$B113)^$E$79:$X$79)+($X$61*(1+I$110)/($B113-I$110))/(1+$B113)^20 -> 8560.0511
B114: =$B$43 -> 0.13727693 | C114: =SUMPRODUCT($E$61:$X$61,1/(1+$B114)^$E$79:$X$79)+($X$61*(1+C$110)/($B114-C$110))/(1+$B114)^20 -> -1241.2914 | D114: =SUMPRODUCT($E$61:$X$61,1/(1+$B114)^$E$79:$X$79)+($X$61*(1+D$110)/($B114-D$110))/(1+$B114)^20 -> -332.71479 | E114: =SUMPRODUCT($E$61:$X$61,1/(1+$B114)^$E$79:$X$79)+($X$61*(1+E$110)/($B114-E$110))/(1+$B114)^20 -> 619.21951 | F114: =SUMPRODUCT($E$61:$X$61,1/(1+$B114)^$E$79:$X$79)+($X$61*(1+F$110)/($B114-F$110))/(1+$B114)^20 -> 1617.6909 | G114: =SUMPRODUCT($E$61:$X$61,1/(1+$B114)^$E$79:$X$79)+($X$61*(1+G$110)/($B114-G$110))/(1+$B114)^20 -> 2666.1975 | H114: =SUMPRODUCT($E$61:$X$61,1/(1+$B114)^$E$79:$X$79)+($X$61*(1+H$110)/($B114-H$110))/(1+$B114)^20 -> 3768.5969 | I114: =SUMPRODUCT($E$61:$X$61,1/(1+$B114)^$E$79:$X$79)+($X$61*(1+I$110)/($B114-I$110))/(1+$B114)^20 -> 4929.154
B115: =$B$43+0.0025 -> 0.13977693 | C115: =SUMPRODUCT($E$61:$X$61,1/(1+$B115)^$E$79:$X$79)+($X$61*(1+C$110)/($B115-C$110))/(1+$B115)^20 -> -4067.82 | D115: =SUMPRODUCT($E$61:$X$61,1/(1+$B115)^$E$79:$X$79)+($X$61*(1+D$110)/($B115-D$110))/(1+$B115)^20 -> -3235.178 | E115: =SUMPRODUCT($E$61:$X$61,1/(1+$B115)^$E$79:$X$79)+($X$61*(1+E$110)/($B115-E$110))/(1+$B115)^20 -> -2363.7278 | F115: =SUMPRODUCT($E$61:$X$61,1/(1+$B115)^$E$79:$X$79)+($X$61*(1+F$110)/($B115-F$110))/(1+$B115)^20 -> -1450.6917 | G115: =SUMPRODUCT($E$61:$X$61,1/(1+$B115)^$E$79:$X$79)+($X$61*(1+G$110)/($B115-G$110))/(1+$B115)^20 -> -493.02014 | H115: =SUMPRODUCT($E$61:$X$61,1/(1+$B115)^$E$79:$X$79)+($X$61*(1+H$110)/($B115-H$110))/(1+$B115)^20 -> 512.64209 | I115: =SUMPRODUCT($E$61:$X$61,1/(1+$B115)^$E$79:$X$79)+($X$61*(1+I$110)/($B115-I$110))/(1+$B115)^20 -> 1569.995
B116: =$B$43+0.005 -> 0.14227693 | C116: =SUMPRODUCT($E$61:$X$61,1/(1+$B116)^$E$79:$X$79)+($X$61*(1+C$110)/($B116-C$110))/(1+$B116)^20 -> -6698.165 | D116: =SUMPRODUCT($E$61:$X$61,1/(1+$B116)^$E$79:$X$79)+($X$61*(1+D$110)/($B116-D$110))/(1+$B116)^20 -> -5934.2668 | E116: =SUMPRODUCT($E$61:$X$61,1/(1+$B116)^$E$79:$X$79)+($X$61*(1+E$110)/($B116-E$110))/(1+$B116)^20 -> -5135.5754 | F116: =SUMPRODUCT($E$61:$X$61,1/(1+$B116)^$E$79:$X$79)+($X$61*(1+F$110)/($B116-F$110))/(1+$B116)^20 -> -4299.6582 | G116: =SUMPRODUCT($E$61:$X$61,1/(1+$B116)^$E$79:$X$79)+($X$61*(1+G$110)/($B116-G$110))/(1+$B116)^20 -> -3423.8508 | H116: =SUMPRODUCT($E$61:$X$61,1/(1+$B116)^$E$79:$X$79)+($X$61*(1+H$110)/($B116-H$110))/(1+$B116)^20 -> -2505.2279 | I116: =SUMPRODUCT($E$61:$X$61,1/(1+$B116)^$E$79:$X$79)+($X$61*(1+I$110)/($B116-I$110))/(1+$B116)^20 -> -1540.5711
...

Sheet WACC
A1: SpaceX – Weighted Average Cost of Capital
A2: May 2026 | Sum-of-the-Parts Segment WACCs | $M
A4: MACRO INPUTS
A6: Item | B6: Value | G6: Note
A7: Risk-Free Rate (10Y US Treasury) | B7: 0.0435 | G7: US Treasury, Jun 2026
A8: Equity Risk Premium | B8: 0.055 | G8: Damodaran Jan 2026 (US ERP)
A9: Tax Rate | B9: 0.21 | G9: US statutory; SpaceX has large NOL carryforwards
A10: Specific Risk Premium (Size / Illiquidity) | B10: 0.01 | G10: Pre-IPO illiquidity + size/execution risk; 2–3% typical for late-stage private
A12: UNLEVERED BETA BY SEGMENT (Comp-Driven – mature-stage tier median)
A14: Segment | B14: Selected Unlevered β | G14: Rationale
A15: Connectivity (Starlink) | B15: =IF(N('Conn Comps'!X54)>0,'Conn Comps'!X54,0.85) -> 0.20833333 | G15: Mature Wireless comp median unlevered β (fallback 0.85)
A16: Space (Launch) | B16: =IF(N('Space Comps'!X35)>0,'Space Comps'!X35,1.1) -> 0.26644722 | G16: Big-5 Defense comp median unlevered β (fallback 1.10)
A17: AI (X + xAI) | B17: =IF(N('AI Comps'!X43)>0,'AI Comps'!X43,1.35) -> 0.90384475 | G17: Social Media comp median unlevered β (fallback 1.35); excludes high-β neoclouds
A19: COST OF EQUITY BY SEGMENT
B21: Connectivity | C21: Space | D21: AI | G21: Formula
A22: Target D/E (post-IPO est.) | B22: 0.3 | C22: 0.45 | D22: 0.25 | G22: Based on Dec 2025 debt / est. post-IPO market cap by seg
A23: Relevered β | B23: =B15*(1+(1-$B$9)*B22) -> 0.25770833 | C23: =B16*(1+(1-$B$9)*C22) -> 0.3611692 | D23: =B17*(1+(1-$B$9)*D22) -> 1.0823541 | G23: βL = βU × (1 + (1-t) × D/E)
A24: Cost of Equity (CAPM) | B24: =$B$7+B23*$B$8+$B$10 -> 0.067673958 | C24: =$B$7+C23*$B$8+$B$10 -> 0.073364306 | D24: =$B$7+D23*$B$8+$B$10 -> 0.11302947 | G24: Ke = Rf + βL × ERP + SRP
A26: COST OF DEBT
B28: Connectivity | C28: Space | D28: AI | G28: Note
A29: Pre-Tax Cost of Debt | B29: 0.065 | C29: 0.075 | D29: 0.085 | G29: Based on SpaceX credit facility + X debt yields, Jun 2026
A30: After-Tax Cost of Debt | B30: =B29*(1-$B$9) -> 0.05135 | C30: =C29*(1-$B$9) -> 0.05925 | D30: =D29*(1-$B$9) -> 0.06715 | G30: Kd × (1-t)
A32: WACC CALCULATION
B34: Connectivity | C34: Space | D34: AI
A35: Equity Weight | B35: =1/(1+B22) -> 0.76923077 | C35: =1/(1+C22) -> 0.68965517 | D35: =1/(1+D22) -> 0.8 | G35: E/(E+D) = 1/(1+D/E)
A36: Debt Weight | B36: =B22/(1+B22) -> 0.23076923 | C36: =C22/(1+C22) -> 0.31034483 | D36: =D22/(1+D22) -> 0.2 | G36: D/(E+D) = (D/E)/(1+D/E)
A37: WACC | B37: =B24*B35+B30*B36 -> 0.063906891 | C37: =C24*C35+C30*C36 -> 0.068984004 | D37: =D24*D35+D30*D36 -> 0.10385358 | G37: WACC = Ke×We + Kd×Wd
A39: WACC SUMMARY (referenced by DCF sheets)
A41: Segment | B41: WACC | C41: Tg (Base) | D41: Tg (Bear) | E41: Tg (Bull)
A42: Connectivity | B42: =B37 -> 0.063906891 | C42: 0.03 | D42: 0.025 | E42: 0.035
A43: Space | B43: =C37 -> 0.068984004 | C43: 0.025 | D43: 0.02 | E43: 0.03
A44: AI | B44: =D37 -> 0.10385358 | C44: 0.035 | D44: 0.025 | E44: 0.04
A46: TIME-WEIGHTED WACC (per-year, used in primary DCF valuation)
A48: Segment | B48: Year 1 WACC | C48: Year 20 WACC | D48: Static WACC | E48: Yr 1 Δ | G48: Note
A49: Connectivity | B49: ='Conn DCF'!E77 -> 0.076352699 | C49: ='Conn DCF'!X77 -> 0.068413495 | D49: =B42 -> 0.063906891 | E49: =B49-D49 -> 0.012445808 | G49: Time-weighted beta glides from Tier 1 (satellite) → Tier 3 (mature wireless) over 20 years
A50: Space | B50: ='Space DCF'!E85 -> 0.12008989 | C50: ='Space DCF'!X85 -> 0.081760475 | D50: =B43 -> 0.068984004 | E50: =B50-D50 -> 0.051105884 | G50: Glides from Tier 1 (NewSpace) → Tier 2 (Big-5 Defense) over 20 years
A51: AI | B51: ='AI DCF'!E77 -> 0.15398861 | C51: ='AI DCF'!X77 -> 0.12056526 | D51: =B44 -> 0.10385358 | E51: =B51-D51 -> 0.050135028 | G51: Glides from Tier 1 (GPU Neoclouds) → Tier 3 (Social Media); Tier 2 (Infra Hosting) excluded (β=3.1 unreliable)

Sheet Conn Comps
A1: CONNECTIVITY – COMPARABLE COMPANY ANALYSIS
A2: Comparable Public Companies by Maturity & Industry | Satellite Broadband + Telecom Infrastructure | $ in Millions
A3: Current-stage anchor = Satellite / LEO Broadband • Mature-stage anchor = Telecom Infrastructure. Input cells (blue) to be populated from terminal (CapIQ/Bloomberg).
A5: Name | B5: Ticker | C5: Mkt Cap | D5: Enterprise | E5: LTM | F5: Gross | G5: EBITDA | H5: Capex % | I5: 3-Yr Ann. | J5: TEV / | K5: TEV / | M5: # Subs | N5: ARPU | P5: Levered | Q5: Debt | R5: % Debt | S5: Preferred | T5: % Pref | U5: Equity | V5: % Equity | W5: Tax | X5: Unlevered
C6: ($M) | D6: Value ($M) | E6: Revenue ($M) | F6: Margin | G6: Margin | H6: Revenue | I6: Rev Growth | J6: Revenue | K6: EBITDA | M6: (M) | N6: ($) | P6: Beta | Q6: ($M) | S6: Stock ($M) | U6: Value ($M) | W6: Rate | X6: Beta
A8: TIER 1 – PUBLIC SATELLITE OPERATORS (current-stage anchor)
A9: Iridium Communications | B9: NasdaqGS:IRDM | C9: 3200 | D9: 4600 | E9: 830 | F9: 0.7195 | G9: 0.62 | H9: 0.045 | I9: 0.05 | J9: =IFERROR(IF(D9=0,"NM",D9/E9),"NM") -> 5.5421687 | K9: =IF(OR(G9<=0,E9=0,D9=0),"NM",IF(D9/(E9*G9)>100,"NM",D9/(E9*G9))) -> 8.9389817 | M9: 2.555 | N9: 27 | P9: 0.6 | Q9: 1810 | R9: =IFERROR(Q9/(Q9+S9+U9),"") -> 0.25138889 | S9: 0 | T9: =IFERROR(S9/($Q9+$S9+$U9),"") -> 0 | U9: 5390 | V9: =IFERROR(U9/(Q9+S9+U9),"") -> 0.74861111 | W9: 0.21 | X9: =IFERROR(P9/(1+(Q9/U9)*(1-W9)+S9/U9),"") -> 0.4742005
A10: EchoStar Corporation | B10: NasdaqGS:SATS | C10: 36100 | D10: 61430 | E10: 14800 | F10: 0.37 | G10: 0.37 | H10: 0.115 | I10: 0.11 | J10: =IFERROR(IF(D10=0,"NM",D10/E10),"NM") -> 4.1506757 | K10: =IF(OR(G10<=0,E10=0,D10=0),"NM",IF(D10/(E10*G10)>100,"NM",D10/(E10*G10))) -> 11.218042 | M10: 29.2 | N10: 40 | P10: 0.96 | Q10: 29240 | R10: =IFERROR(Q10/(Q10+S10+U10),"") -> 0.47130883 | S10: 0 | T10: =IFERROR(S10/($Q10+$S10+$U10),"") -> 0 | U10: 32800 | V10: =IFERROR(U10/(Q10+S10+U10),"") -> 0.52869117 | W10: 0.21 | X10: =IFERROR(P10/(1+(Q10/U10)*(1-W10)+S10/U10),"") -> 0.56329562
A11: Globalstar, Inc. | B11: NasdaqGS:GSAT | C11: 3000 | D11: 3500 | E11: 250 | F11: 0.6381 | G11: 0.4 | H11: 0.8 | I11: 0.1 | J11: =IFERROR(IF(D11=0,"NM",D11/E11),"NM") -> 14 | K11: =IF(OR(G11<=0,E11=0,D11=0),"NM",IF(D11/(E11*G11)>100,"NM",D11/(E11*G11))) -> 35 | M11: NM | N11: NM | P11: 2.6 | Q11: 546 | R11: =IFERROR(Q11/(Q11+S11+U11),"") -> 0.044953071 | S11: 0 | T11: =IFERROR(S11/($Q11+$S11+$U11),"") -> 0 | U11: 11600 | V11: =IFERROR(U11/(Q11+S11+U11),"") -> 0.95504693 | W11: 0.21 | X11: =IFERROR(P11/(1+(Q11/U11)*(1-W11)+S11/U11),"") -> 2.5067864
A12: AST SpaceMobile, Inc. | B12: NasdaqGS:ASTS | C12: 15600 | D12: 15100 | E12: 71 | F12: 0.4482 | G12: -2 | H12: 5 | I12: 0.15 | J12: =IFERROR(IF(D12=0,"NM",D12/E12),"NM") -> 212.67606 | K12: =IF(OR(G12<=0,E12=0,D12=0),"NM",IF(D12/(E12*G12)>100,"NM",D12/(E12*G12))) -> NM | M12: NM | N12: NM | P12: 2.6 | Q12: 2990 | R12: =IFERROR(Q12/(Q12+S12+U12),"") -> 0.096607431 | S12: 0 | T12: =IFERROR(S12/($Q12+$S12+$U12),"") -> 0 | U12: 27960 | V12: =IFERROR(U12/(Q12+S12+U12),"") -> 0.90339257 | W12: 0.21 | X12: =IFERROR(P12/(1+(Q12/U12)*(1-W12)+S12/U12),"") -> 2.3974593
A13: Viasat, Inc. | B13: NasdaqGS:VSAT | C13: 6640 | D13: 12000 | E13: 4500 | F13: 0.332 | G13: 0.3 | H13: 0.199 | I13: 0.08 | J13: =IFERROR(IF(D13=0,"NM",D13/E13),"NM") -> 2.6666667 | K13: =IF(OR(G13<=0,E13=0,D13=0),"NM",IF(D13/(E13*G13)>100,"NM",D13/(E13*G13))) -> 8.8888889 | M13: NM | N13: NM | P13: 1.37 | Q13: 7080 | R13: =IFERROR(Q13/(Q13+S13+U13),"") -> 0.43839009 | S13: 0 | T13: =IFERROR(S13/($Q13+$S13+$U13),"") -> 0 | U13: 9070 | V13: =IFERROR(U13/(Q13+S13+U13),"") -> 0.56160991 | W13: 0.21 | X13: =IFERROR(P13/(1+(Q13/U13)*(1-W13)+S13/U13),"") -> 0.84742075
A14: SES S.A. | B14: ENXTPA:SESG | C14: 6300 | D14: 12560 | E14: 2850 | F14: 0.6 | G14: 0.43 | H14: 0.5 | I14: 0.05 | J14: =IFERROR(IF(D14=0,"NM",D14/E14),"NM") -> 4.4070175 | K14: =IF(OR(G14<=0,E14=0,D14=0),"NM",IF(D14/(E14*G14)>100,"NM",D14/(E14*G14))) -> 10.248878 | M14: NM | N14: NM | P14: 0.51 | Q14: 3400 | R14: =IFERROR(Q14/(Q14+S14+U14),"") -> 0.57627119 | S14: 0 | T14: =IFERROR(S14/($Q14+$S14+$U14),"") -> 0 | U14: 2500 | V14: =IFERROR(U14/(Q14+S14+U14),"") -> 0.42372881 | W14: 0.21 | X14: =IFERROR(P14/(1+(Q14/U14)*(1-W14)+S14/U14),"") -> 0.24585422
A15: Eutelsat Communications | B15: ENXTPA:ETL | C15: 3840 | D15: 4810 | E15: 1230 | F15: 0.5 | G15: 0.3 | H15: 0.45 | I15: 0.08 | J15: =IFERROR(IF(D15=0,"NM",D15/E15),"NM") -> 3.9105691 | K15: =IF(OR(G15<=0,E15=0,D15=0),"NM",IF(D15/(E15*G15)>100,"NM",D15/(E15*G15))) -> 13.03523 | M15: NM | N15: NM | P15: 0.9 | Q15: 7300 | R15: =IFERROR(Q15/(Q15+S15+U15),"") -> 0.72277228 | S15: 0 | T15: =IFERROR(S15/($Q15+$S15+$U15),"") -> 0 | U15: 2800 | V15: =IFERROR(U15/(Q15+S15+U15),"") -> 0.27722772 | W15: 0.25 | X15: =IFERROR(P15/(1+(Q15/U15)*(1-W15)+S15/U15),"") -> 0.30453172
A16: Telesat Corporation | B16: NasdaqGS:TSAT | C16: 2460 | D16: 5500 | E16: 279 | F16: 0.65 | G16: 0.65 | H16: 0.35 | I16: 0.05 | J16: =IFERROR(IF(D16=0,"NM",D16/E16),"NM") -> 19.713262 | K16: =IF(OR(G16<=0,E16=0,D16=0),"NM",IF(D16/(E16*G16)>100,"NM",D16/(E16*G16))) -> 30.328095 | M16: NM | N16: NM | P16: 2 | Q16: 4200 | R16: =IFERROR(Q16/(Q16+S16+U16),"") -> 0.87318087 | S16: 0 | T16: =IFERROR(S16/($Q16+$S16+$U16),"") -> 0 | U16: 610 | V16: =IFERROR(U16/(Q16+S16+U16),"") -> 0.12681913 | W16: 0.265 | X16: =IFERROR(P16/(1+(Q16/U16)*(1-W16)+S16/U16),"") -> 0.3299973
A18: Min: | C18: =IFERROR(MIN(C9:C16),"") -> 2460 | D18: =IFERROR(MIN(D9:D16),"") -> 3500 | E18: =IFERROR(MIN(E9:E16),"") -> 71 | F18: =IFERROR(MIN(F9:F16),"") -> 0.332 | G18: =IFERROR(MIN(G9:G16),"") -> -2 | H18: =IFERROR(MIN(H9:H16),"") -> 0.045 | I18: =IFERROR(MIN(I9:I16),"") -> 0.05 | J18: =IFERROR(_xlfn.AGGREGATE(5,6,J9:J16),"") -> 2.6666667 | K18: =IFERROR(MIN(K9:K16),"") -> 8.8888889 | M18: =IFERROR(IF(COUNTA(M9:M16)=0,"",MIN(M9:M16)),"") -> 2.555 | N18: =IFERROR(IF(COUNTA(N9:N16)=0,"",MIN(N9:N16)),"") -> 27 | P18: =IFERROR(MIN(P9:P16),"") -> 0.51 | Q18: =IFERROR(MIN(Q9:Q16),"") -> 546 | R18: =IFERROR(MIN(R9:R16),"") -> 0.044953071 | S18: =IFERROR(MIN(S9:S16),"") -> 0 | T18: =IFERROR(MIN(T9:T16),"") -> 0 | U18: =IFERROR(MIN(U9:U16),"") -> 610 | V18: =IFERROR(MIN(V9:V16),"") -> 0.12681913 | W18: =IFERROR(MIN(W9:W16),"") -> 0.21 | X18: =IFERROR(MIN(X9:X16),"") -> 0.24585422
A19: 25th Pctl: | C19: =IFERROR(QUARTILE(C9:C16,1),"") -> 3150 | D19: =IFERROR(QUARTILE(D9:D16,1),"") -> 4757.5 | E19: =IFERROR(QUARTILE(E9:E16,1),"") -> 271.75 | F19: =IFERROR(QUARTILE(F9:F16,1),"") -> 0.42865 | G19: =IFERROR(QUARTILE(G9:G16,1),"") -> 0.3 | H19: =IFERROR(QUARTILE(H9:H16,1),"") -> 0.178 | I19: =IFERROR(QUARTILE(I9:I16,1),"") -> 0.05 | J19: =IFERROR(QUARTILE(J9:J16,1),"") -> 4.090649 | K19: =QUARTILE((K9,K10,K11,K13,K14,K15,K16),1) -> 9.5939299 | M19: =IFERROR(QUARTILE(M9:M16,1),"") -> 9.21625 | N19: =IFERROR(QUARTILE(N9:N16,1),"") -> 30.25 | P19: =IFERROR(QUARTILE(P9:P16,1),"") -> 0.825 | Q19: =IFERROR(QUARTILE(Q9:Q16,1),"") -> 2695 | R19: =IFERROR(QUARTILE(R9:R16,1),"") -> 0.21269352 | S19: =IFERROR(QUARTILE(S9:S16,1),"") -> 0 | T19: =IFERROR(QUARTILE(T9:T16,1),"") -> 0 | U19: =IFERROR(QUARTILE(U9:U16,1),"") -> 2725 | V19: =IFERROR(QUARTILE(V9:V16,1),"") -> 0.38710354 | W19: =IFERROR(QUARTILE(W9:W16,1),"") -> 0.21 | X19: =IFERROR(QUARTILE(X9:X16,1),"") -> 0.3236309
A20: Median: | C20: =IFERROR(MEDIAN(C9:C16),"") -> 5070 | D20: =IFERROR(MEDIAN(D9:D16),"") -> 8750 | E20: =IFERROR(MEDIAN(E9:E16),"") -> 1030 | F20: =IFERROR(MEDIAN(F9:F16),"") -> 0.55 | G20: =IFERROR(MEDIAN(G9:G16),"") -> 0.385 | H20: =IFERROR(MEDIAN(H9:H16),"") -> 0.4 | I20: =IFERROR(MEDIAN(I9:I16),"") -> 0.08 | J20: =IFERROR(QUARTILE(J9:J16,2),"") -> 4.9745931 | K20: =QUARTILE((K9,K10,K11,K13,K14,K15,K16),2) -> 11.218042 | M20: =IFERROR(MEDIAN(M9:M16),"") -> 15.8775 | N20: =IFERROR(MEDIAN(N9:N16),"") -> 33.5 | P20: =IFERROR(MEDIAN(P9:P16),"") -> 1.165 | Q20: =IFERROR(MEDIAN(Q9:Q16),"") -> 3800 | R20: =IFERROR(MEDIAN(R9:R16),"") -> 0.45484946 | S20: =IFERROR(MEDIAN(S9:S16),"") -> 0 | T20: =IFERROR(MEDIAN(T9:T16),"") -> 0 | U20: =IFERROR(MEDIAN(U9:U16),"") -> 7230 | V20: =IFERROR(MEDIAN(V9:V16),"") -> 0.54515054 | W20: =IFERROR(MEDIAN(W9:W16),"") -> 0.21 | X20: =IFERROR(MEDIAN(X9:X16),"") -> 0.51874806
A21: Mean: | C21: =IFERROR(AVERAGE(C9:C16),"") -> 9642.5 | D21: =IFERROR(AVERAGE(D9:D16),"") -> 14937.5 | E21: =IFERROR(AVERAGE(E9:E16),"") -> 3101.25 | F21: =IFERROR(AVERAGE(F9:F16),"") -> 0.532225 | G21: =IFERROR(AVERAGE(G9:G16),"") -> 0.13375 | H21: =IFERROR(AVERAGE(H9:H16),"") -> 0.932375 | I21: =IFERROR(AVERAGE(I9:I16),"") -> 0.08375 | J21: =IFERROR(_xlfn.AGGREGATE(1,6,J9:J16),"") -> 33.383302 | K21: =IFERROR(AVERAGE(K9:K16),"") -> 16.808302 | M21: =IFERROR(AVERAGE(M9:M16),"") -> 15.8775 | N21: =IFERROR(AVERAGE(N9:N16),"") -> 33.5 | P21: =IFERROR(AVERAGE(P9:P16),"") -> 1.4425 | Q21: =IFERROR(AVERAGE(Q9:Q16),"") -> 7070.75 | R21: =IFERROR(AVERAGE(R9:R16),"") -> 0.43435908 | S21: =IFERROR(AVERAGE(S9:S16),"") -> 0 | T21: =IFERROR(AVERAGE(T9:T16),"") -> 0 | U21: =IFERROR(AVERAGE(U9:U16),"") -> 11591.25 | V21: =IFERROR(AVERAGE(V9:V16),"") -> 0.56564092 | W21: =IFERROR(AVERAGE(W9:W16),"") -> 0.221875 | X21: =IFERROR(AVERAGE(X9:X16),"") -> 0.95869323
A22: 75th Pctl: | C22: =IFERROR(QUARTILE(C9:C16,3),"") -> 8880 | D22: =IFERROR(QUARTILE(D9:D16,3),"") -> 13195 | E22: =IFERROR(QUARTILE(E9:E16,3),"") -> 3262.5 | F22: =IFERROR(QUARTILE(F9:F16,3),"") -> 0.641075 | G22: =IFERROR(QUARTILE(G9:G16,3),"") -> 0.4775 | H22: =IFERROR(QUARTILE(H9:H16,3),"") -> 0.575 | I22: =IFERROR(QUARTILE(I9:I16,3),"") -> 0.1025 | J22: =IFERROR(QUARTILE(J9:J16,3),"") -> 15.428315 | K22: =QUARTILE((K9,K10,K11,K13,K14,K15,K16),3) -> 21.681663 | M22: =IFERROR(QUARTILE(M9:M16,3),"") -> 22.53875 | N22: =IFERROR(QUARTILE(N9:N16,3),"") -> 36.75 | P22: =IFERROR(QUARTILE(P9:P16,3),"") -> 2.15 | Q22: =IFERROR(QUARTILE(Q9:Q16,3),"") -> 7135 | R22: =IFERROR(QUARTILE(R9:R16,3),"") -> 0.61289646 | S22: =IFERROR(QUARTILE(S9:S16,3),"") -> 0 | T22: =IFERROR(QUARTILE(T9:T16,3),"") -> 0 | U22: =IFERROR(QUARTILE(U9:U16,3),"") -> 15690 | V22: =IFERROR(QUARTILE(V9:V16,3),"") -> 0.78730648 | W22: =IFERROR(QUARTILE(W9:W16,3),"") -> 0.22 | X22: =IFERROR(QUARTILE(X9:X16,3),"") -> 1.2349304
A23: Max: | C23: =IFERROR(MAX(C9:C16),"") -> 36100 | D23: =IFERROR(MAX(D9:D16),"") -> 61430 | E23: =IFERROR(MAX(E9:E16),"") -> 14800 | F23: =IFERROR(MAX(F9:F16),"") -> 0.7195 | G23: =IFERROR(MAX(G9:G16),"") -> 0.65 | H23: =IFERROR(MAX(H9:H16),"") -> 5 | I23: =IFERROR(MAX(I9:I16),"") -> 0.15 | J23: =IFERROR(_xlfn.AGGREGATE(4,6,J9:J16),"") -> 212.67606 | K23: =IFERROR(MAX(K9:K16),"") -> 35 | M23: =IFERROR(IF(COUNTA(M9:M16)=0,"",MAX(M9:M16)),"") -> 29.2 | N23: =IFERROR(IF(COUNTA(N9:N16)=0,"",MAX(N9:N16)),"") -> 40 | P23: =IFERROR(MAX(P9:P16),"") -> 2.6 | Q23: =IFERROR(MAX(Q9:Q16),"") -> 29240 | R23: =IFERROR(MAX(R9:R16),"") -> 0.87318087 | S23: =IFERROR(MAX(S9:S16),"") -> 0 | T23: =IFERROR(MAX(T9:T16),"") -> 0 | U23: =IFERROR(MAX(U9:U16),"") -> 32800 | V23: =IFERROR(MAX(V9:V16),"") -> 0.95504693 | W23: =IFERROR(MAX(W9:W16),"") -> 0.265 | X23: =IFERROR(MAX(X9:X16),"") -> 2.5067864
A25: TIER 2 – EMERGING-MARKETS TELECOM / WIRELESS (>10% Projected Organic Revenue Growth)
A26: Bharti Airtel Limited | B26: BSE:532454 | C26: 116130 | D26: 137956 | E26: 23300 | F26: 0.5 | G26: 0.38 | H26: 0.22 | I26: 0.22 | J26: =IF(OR(D26="",D26=0,E26="",E26=0),"NM",D26/E26) -> 5.9208584 | K26: =IF(OR(G26<=0,E26=0,D26=0),"NM",IF(D26/(E26*G26)>100,"NM",D26/(E26*G26))) -> 15.581206 | M26: 478 | N26: 3 | P26: 0.5 | Q26: 14000 | R26: =IFERROR(Q26/(Q26+S26+U26),"") -> 0.11070694 | S26: 0 | T26: =IFERROR(S26/(Q26+S26+U26),"") -> 0 | U26: 112460 | V26: =IFERROR(U26/(Q26+S26+U26),"") -> 0.88929306 | W26: 0.25 | X26: =IFERROR(P26/(1+(Q26/U26)*(1-W26)+S26/U26),"") -> 0.45730319
A27: MTN Group Limited | B27: JSE:MTN | C27: 21828 | D27: 24074 | E27: 10010 | F27: 0.45 | G27: 0.44 | H27: 0.19 | I27: 0.08 | J27: =IF(OR(D27="",D27=0,E27="",E27=0),"NM",D27/E27) -> 2.404995 | K27: =IF(OR(G27<=0,E27=0,D27=0),"NM",IF(D27/(E27*G27)>100,"NM",D27/(E27*G27))) -> 5.4658977 | M27: 307 | N27: 3.5 | P27: 0.97 | Q27: 8100 | R27: =IFERROR(Q27/(Q27+S27+U27),"") -> 0.29454545 | S27: 0 | T27: =IFERROR(S27/(Q27+S27+U27),"") -> 0 | U27: 19400 | V27: =IFERROR(U27/(Q27+S27+U27),"") -> 0.70545455 | W27: 0.28 | X27: =IFERROR(P27/(1+(Q27/U27)*(1-W27)+S27/U27),"") -> 0.74579899
A28: Vodacom Group Limited | B28: JSE:VOD | C28: 17080 | D28: 20380 | E28: 8860 | F28: 0.55 | G28: 0.4 | H28: 0.18 | I28: 0.12 | J28: =IF(OR(D28="",D28=0,E28="",E28=0),"NM",D28/E28) -> 2.3002257 | K28: =IF(OR(G28<=0,E28=0,D28=0),"NM",IF(D28/(E28*G28)>100,"NM",D28/(E28*G28))) -> 5.7505643 | M28: 83 | N28: 7 | P28: 0.42 | Q28: 4400 | R28: =IFERROR(Q28/(Q28+S28+U28),"") -> 0.19634092 | S28: 0 | T28: =IFERROR(S28/(Q28+S28+U28),"") -> 0 | U28: 18010 | V28: =IFERROR(U28/(Q28+S28+U28),"") -> 0.80365908 | W28: 0.28 | X28: =IFERROR(P28/(1+(Q28/U28)*(1-W28)+S28/U28),"") -> 0.35717254
A29: Vodafone Idea Limited | B29: NSEI:IDEA | C29: 15293 | D29: 36374 | E29: 4000 | F29: 0.3 | G29: 0.27 | H29: 0.25 | I29: 0.05 | J29: =IF(OR(D29="",D29=0,E29="",E29=0),"NM",D29/E29) -> 9.0935 | K29: =IF(OR(G29<=0,E29=0,D29=0),"NM",IF(D29/(E29*G29)>100,"NM",D29/(E29*G29))) -> 33.67963 | M29: 198 | N29: 2 | P29: 1.1 | Q29: 23000 | R29: =IFERROR(Q29/(Q29+S29+U29),"") -> 0.71875 | S29: 0 | T29: =IFERROR(S29/(Q29+S29+U29),"") -> 0 | U29: 9000 | V29: =IFERROR(U29/(Q29+S29+U29),"") -> 0.28125 | W29: 0.25 | X29: =IFERROR(P29/(1+(Q29/U29)*(1-W29)+S29/U29),"") -> 0.37714286
A30: VEON Ltd. | B30: NasdaqGS:VEON | C30: 3630 | D30: 5130 | E30: 4400 | F30: 0.88 | G30: 0.43 | H30: 0.2 | I30: 0.14 | J30: =IF(OR(D30="",D30=0,E30="",E30=0),"NM",D30/E30) -> 1.1659091 | K30: =IF(OR(G30<=0,E30=0,D30=0),"NM",IF(D30/(E30*G30)>100,"NM",D30/(E30*G30))) -> 2.7114165 | M30: 150.5 | N30: 2.3 | P30: 1.61 | Q30: 5150 | R30: =IFERROR(Q30/(Q30+S30+U30),"") -> 0.56593407 | S30: 0 | T30: =IFERROR(S30/(Q30+S30+U30),"") -> 0 | U30: 3950 | V30: =IFERROR(U30/(Q30+S30+U30),"") -> 0.43406593 | W30: 0.2 | X30: =IFERROR(P30/(1+(Q30/U30)*(1-W30)+S30/U30),"") -> 0.78804213
A31: Mobile Telecom Co. (Zain) | B31: KWSE:ZAIN | C31: 7612 | D31: 9717 | E31: 5500 | F31: 0.55 | G31: 0.34 | H31: 0.16 | I31: 0.08 | J31: =IF(OR(D31="",D31=0,E31="",E31=0),"NM",D31/E31) -> 1.7667273 | K31: =IF(OR(G31<=0,E31=0,D31=0),"NM",IF(D31/(E31*G31)>100,"NM",D31/(E31*G31))) -> 5.1962567 | M31: 51.2 | N31: 12 | P31: 0.65 | Q31: 3500 | R31: =IFERROR(Q31/(Q31+S31+U31),"") -> 0.24475524 | S31: 0 | T31: =IFERROR(S31/(Q31+S31+U31),"") -> 0 | U31: 10800 | V31: =IFERROR(U31/(Q31+S31+U31),"") -> 0.75524476 | W31: 0.15 | X31: =IFERROR(P31/(1+(Q31/U31)*(1-W31)+S31/U31),"") -> 0.50961887
A32: Safaricom PLC | B32: NASE:SCOM | C32: 9815 | D32: 11440 | E32: 3080 | F32: 0.6 | G32: 0.44 | H32: 0.21 | I32: 0.11 | J32: =IF(OR(D32="",D32=0,E32="",E32=0),"NM",D32/E32) -> 3.7142857 | K32: =IF(OR(G32<=0,E32=0,D32=0),"NM",IF(D32/(E32*G32)>100,"NM",D32/(E32*G32))) -> 8.4415584 | M32: 46 | N32: 3 | P32: 0.5 | Q32: 1200 | R32: =IFERROR(Q32/(Q32+S32+U32),"") -> 0.11650485 | S32: 0 | T32: =IFERROR(S32/(Q32+S32+U32),"") -> 0 | U32: 9100 | V32: =IFERROR(U32/(Q32+S32+U32),"") -> 0.88349515 | W32: 0.3 | X32: =IFERROR(P32/(1+(Q32/U32)*(1-W32)+S32/U32),"") -> 0.45774648
A33: PT XLSMART Telecom | B33: IDX:EXCL | C33: 3255 | D33: 4037 | E33: 1500 | F33: 0.52 | G33: 0.3 | H33: 0.22 | I33: 0.1 | J33: =IF(OR(D33="",D33=0,E33="",E33=0),"NM",D33/E33) -> 2.6913333 | K33: =IF(OR(G33<=0,E33=0,D33=0),"NM",IF(D33/(E33*G33)>100,"NM",D33/(E33*G33))) -> 8.9711111 | M33: 94.5 | N33: 1.5 | P33: 1 | Q33: 1800 | R33: =IFERROR(Q33/(Q33+S33+U33),"") -> 0.36 | S33: 0 | T33: =IFERROR(S33/(Q33+S33+U33),"") -> 0 | U33: 3200 | V33: =IFERROR(U33/(Q33+S33+U33),"") -> 0.64 | W33: 0.22 | X33: =IFERROR(P33/(1+(Q33/U33)*(1-W33)+S33/U33),"") -> 0.69504778
A35: Min: | C35: =IFERROR(IF(COUNTA(C26:C33)=0,"",MIN(C26:C33)),"") -> 3255 | D35: =IFERROR(IF(COUNTA(D26:D33)=0,"",MIN(D26:D33)),"") -> 4037 | E35: =IFERROR(MIN(E26:E33),"") -> 1500 | F35: =MIN(F26:F33) -> 0.3 | G35: =IFERROR(MIN(G26:G33),"") -> 0.27 | H35: =IFERROR(MIN(H26:H33),"") -> 0.16 | I35: =IFERROR(IF(COUNTA(I26:I33)=0,"",MIN(I26:I33)),"") -> 0.05 | J35: =IFERROR(IF(COUNTA(D26:D33)=0,"",_xlfn.AGGREGATE(5,6,J26:J33)),"") -> 1.1659091 | K35: =IFERROR(IF(COUNTA(G26:G33)=0,"",_xlfn.AGGREGATE(5,6,K26:K33)),"") -> 2.7114165 | M35: =IFERROR(IF(COUNTA(M26:M33)=0,"",MIN(M26:M33)),"") -> 46 | N35: =IFERROR(IF(COUNTA(N26:N33)=0,"",MIN(N26:N33)),"") -> 1.5 | P35: =IFERROR(MIN(P26:P33),"") -> 0.42 | Q35: =MIN(Q26:Q33) -> 1200 | R35: =IFERROR(MIN(R26:R33),"") -> 0.11070694 | S35: =MIN(S26:S33) -> 0 | T35: =IFERROR(MIN(T26:T33),"") -> 0 | U35: =MIN(U26:U33) -> 3200 | V35: =IFERROR(MIN(V26:V33),"") -> 0.28125 | W35: =IFERROR(MIN(W26:W33),"") -> 0.15 | X35: =IFERROR(MIN(X26:X33),"") -> 0.35717254
A36: 25th Pctl: | C36: =IFERROR(IF(COUNTA(C26:C33)=0,"",QUARTILE(C26:C33,1)),"") -> 6616.5 | D36: =IFERROR(IF(COUNTA(D26:D33)=0,"",QUARTILE(D26:D33,1)),"") -> 8570.25 | E36: =IFERROR(QUARTILE(E26:E33,1),"") -> 3770 | F36: =PERCENTILE(F26:F33,0.25) -> 0.4875 | G36: =IFERROR(QUARTILE(G26:G33,1),"") -> 0.33 | H36: =IFERROR(QUARTILE(H26:H33,1),"") -> 0.1875 | I36: =IFERROR(IF(COUNTA(I26:I33)=0,"",QUARTILE(I26:I33,1)),"") -> 0.08 | J36: =QUARTILE(J26:J33,1) -> 2.1668511 | K36: =QUARTILE(K26:K33,1) -> 5.3984875 | M36: =QUARTILE(M26:M33,1) -> 75.05 | N36: =QUARTILE(N26:N33,1) -> 2.225 | P36: =IFERROR(QUARTILE(P26:P33,1),"") -> 0.5 | Q36: =PERCENTILE(Q26:Q33,0.25) -> 3075 | R36: =IFERROR(QUARTILE(R26:R33,1),"") -> 0.1763819 | S36: =PERCENTILE(S26:S33,0.25) -> 0 | T36: =IFERROR(QUARTILE(T26:T33,1),"") -> 0 | U36: =PERCENTILE(U26:U33,0.25) -> 7737.5 | V36: =IFERROR(QUARTILE(V26:V33,1),"") -> 0.58851648 | W36: =IFERROR(QUARTILE(W26:W33,1),"") -> 0.215 | X36: =IFERROR(QUARTILE(X26:X33,1),"") -> 0.43726311
A37: Median: | C37: =IFERROR(IF(COUNTA(C26:C33)=0,"",MEDIAN(C26:C33)),"") -> 12554 | D37: =IFERROR(IF(COUNTA(D26:D33)=0,"",MEDIAN(D26:D33)),"") -> 15910 | E37: =IFERROR(MEDIAN(E26:E33),"") -> 4950 | F37: =MEDIAN(F26:F33) -> 0.535 | G37: =IFERROR(MEDIAN(G26:G33),"") -> 0.39 | H37: =IFERROR(MEDIAN(H26:H33),"") -> 0.205 | I37: =IFERROR(IF(COUNTA(I26:I33)=0,"",MEDIAN(I26:I33)),"") -> 0.105 | J37: =QUARTILE(J26:J33,2) -> 2.5481642 | K37: =QUARTILE(K26:K33,2) -> 7.0960614 | M37: =QUARTILE(M26:M33,2) -> 122.5 | N37: =QUARTILE(N26:N33,2) -> 3 | P37: =IFERROR(MEDIAN(P26:P33),"") -> 0.81 | Q37: =MEDIAN(Q26:Q33) -> 4775 | R37: =IFERROR(MEDIAN(R26:R33),"") -> 0.26965035 | S37: =MEDIAN(S26:S33) -> 0 | T37: =IFERROR(MEDIAN(T26:T33),"") -> 0 | U37: =MEDIAN(U26:U33) -> 9950 | V37: =IFERROR(MEDIAN(V26:V33),"") -> 0.73034965 | W37: =IFERROR(MEDIAN(W26:W33),"") -> 0.25 | X37: =IFERROR(MEDIAN(X26:X33),"") -> 0.48368268
A38: Mean: | C38: =IFERROR(IF(COUNTA(C26:C33)=0,"",AVERAGE(C26:C33)),"") -> 24330.375 | D38: =IFERROR(IF(COUNTA(D26:D33)=0,"",AVERAGE(D26:D33)),"") -> 31138.5 | E38: =IFERROR(AVERAGE(E26:E33),"") -> 7581.25 | F38: =AVERAGE(F26:F33) -> 0.54375 | G38: =IFERROR(AVERAGE(G26:G33),"") -> 0.375 | H38: =IFERROR(AVERAGE(H26:H33),"") -> 0.20375 | I38: =IFERROR(IF(COUNTA(I26:I33)=0,"",AVERAGE(I26:I33)),"") -> 0.1125 | J38: =IFERROR(IF(COUNTA(D26:D33)=0,"",_xlfn.AGGREGATE(1,6,J26:J33)),"") -> 3.6322293 | K38: =IFERROR(IF(COUNTA(G26:G33)=0,"",_xlfn.AGGREGATE(1,6,K26:K33)),"") -> 10.724705 | M38: =IFERROR(IF(COUNTA(I26:I33)=0,"",_xlfn.AGGREGATE(1,6,M26:M33)),"") -> 176.025 | N38: =IFERROR(IF(COUNTA(J26:J33)=0,"",_xlfn.AGGREGATE(1,6,N26:N33)),"") -> 4.2875 | P38: =IFERROR(AVERAGE(P26:P33),"") -> 0.84375 | Q38: =AVERAGE(Q26:Q33) -> 7643.75 | R38: =IFERROR(AVERAGE(R26:R33),"") -> 0.32594219 | S38: =AVERAGE(S26:S33) -> 0 | T38: =IFERROR(AVERAGE(T26:T33),"") -> 0 | U38: =AVERAGE(U26:U33) -> 23240 | V38: =IFERROR(AVERAGE(V26:V33),"") -> 0.67405781 | W38: =IFERROR(AVERAGE(W26:W33),"") -> 0.24125 | X38: =IFERROR(AVERAGE(X26:X33),"") -> 0.5484841
A39: 75th Pctl: | C39: =IFERROR(IF(COUNTA(C26:C33)=0,"",QUARTILE(C26:C33,3)),"") -> 18267 | D39: =IFERROR(IF(COUNTA(D26:D33)=0,"",QUARTILE(D26:D33,3)),"") -> 27149 | E39: =IFERROR(QUARTILE(E26:E33,3),"") -> 9147.5 | F39: =PERCENTILE(F26:F33,0.75) -> 0.5625 | G39: =IFERROR(QUARTILE(G26:G33,3),"") -> 0.4325 | H39: =IFERROR(QUARTILE(H26:H33,3),"") -> 0.22 | I39: =IFERROR(IF(COUNTA(I26:I33)=0,"",QUARTILE(I26:I33,3)),"") -> 0.125 | J39: =QUARTILE(J26:J33,3) -> 4.2659289 | K39: =QUARTILE(K26:K33,3) -> 10.623635 | M39: =QUARTILE(M26:M33,3) -> 225.25 | N39: =QUARTILE(N26:N33,3) -> 4.375 | P39: =IFERROR(QUARTILE(P26:P33,3),"") -> 1.025 | Q39: =PERCENTILE(Q26:Q33,0.75) -> 9575 | R39: =IFERROR(QUARTILE(R26:R33,3),"") -> 0.41148352 | S39: =PERCENTILE(S26:S33,0.75) -> 0 | T39: =IFERROR(QUARTILE(T26:T33,3),"") -> 0 | U39: =PERCENTILE(U26:U33,0.75) -> 18357.5 | V39: =IFERROR(QUARTILE(V26:V33,3),"") -> 0.8236181 | W39: =IFERROR(QUARTILE(W26:W33,3),"") -> 0.28 | X39: =IFERROR(QUARTILE(X26:X33,3),"") -> 0.70773558
A40: Max: | C40: =IFERROR(IF(COUNTA(C26:C33)=0,"",MAX(C26:C33)),"") -> 116130 | D40: =IFERROR(IF(COUNTA(D26:D33)=0,"",MAX(D26:D33)),"") -> 137956 | E40: =IFERROR(MAX(E26:E33),"") -> 23300 | F40: =MAX(F26:F33) -> 0.88 | G40: =IFERROR(MAX(G26:G33),"") -> 0.44 | H40: =IFERROR(MAX(H26:H33),"") -> 0.25 | I40: =IFERROR(IF(COUNTA(I26:I33)=0,"",MAX(I26:I33)),"") -> 0.22 | J40: =IFERROR(IF(COUNTA(D26:D33)=0,"",_xlfn.AGGREGATE(4,6,J26:J33)),"") -> 9.0935 | K40: =IFERROR(IF(COUNTA(G26:G33)=0,"",_xlfn.AGGREGATE(4,6,K26:K33)),"") -> 33.67963 | M40: =IFERROR(IF(COUNTA(M26:M33)=0,"",MAX(M26:M33)),"") -> 478 | N40: =IFERROR(IF(COUNTA(N26:N33)=0,"",MAX(N26:N33)),"") -> 12 | P40: =IFERROR(MAX(P26:P33),"") -> 1.61 | Q40: =MAX(Q26:Q33) -> 23000 | R40: =IFERROR(MAX(R26:R33),"") -> 0.71875 | S40: =MAX(S26:S33) -> 0 | T40: =IFERROR(MAX(T26:T33),"") -> 0 | U40: =MAX(U26:U33) -> 112460 | V40: =IFERROR(MAX(V26:V33),"") -> 0.88929306 | W40: =IFERROR(MAX(W26:W33),"") -> 0.3 | X40: =IFERROR(MAX(X26:X33),"") -> 0.78804213
A42: TIER 3 – LARGE, MATURE WIRELESS (>$10B Revenue – Mature-Stage Anchor)
A43: América Móvil | B43: BMV:AMX B | C43: 76000 | D43: 121230 | E43: 45430 | F43: 0.434 | G43: 0.3973 | H43: 0.155 | I43: 0.07 | J43: =IF(OR(D43="",D43=0,E43="",E43=0),"NM",D43/E43) -> 2.668501 | K43: =IF(OR(G43<=0,E43=0,D43=0),"NM",IF(D43/(E43*G43)>100,"NM",D43/(E43*G43))) -> 6.7165895 | M43: 329 | N43: 11 | P43: 0.28 | Q43: 119500 | R43: =IFERROR(Q43/(Q43+S43+U43),"") -> 0.82698962 | S43: 0 | T43: =IFERROR(S43/(Q43+S43+U43),"") -> 0 | U43: 25000 | V43: =IFERROR(U43/(Q43+S43+U43),"") -> 0.17301038 | W43: 0.28 | X43: =IFERROR(P43/(1+(Q43/U43)*(1-W43)+S43/U43),"") -> 0.063040346
A44: China Mobile Limited | B44: SEHK:941 | C44: 224000 | D44: 186000 | E44: 144000 | F44: 0.284 | G44: 0.35 | H44: 0.16 | I44: 0.03 | J44: =IF(OR(D44="",D44=0,E44="",E44=0),"NM",D44/E44) -> 1.2916667 | K44: =IF(OR(G44<=0,E44=0,D44=0),"NM",IF(D44/(E44*G44)>100,"NM",D44/(E44*G44))) -> 3.6904762 | M44: 1009 | N44: 6.7 | P44: 0.23 | Q44: 0 | R44: =IFERROR(Q44/(Q44+S44+U44),"") -> 0 | S44: 0 | T44: =IFERROR(S44/(Q44+S44+U44),"") -> 0 | U44: 82000 | V44: =IFERROR(U44/(Q44+S44+U44),"") -> 1 | W44: 0.3 | X44: =IFERROR(P44/(1+(Q44/U44)*(1-W44)+S44/U44),"") -> 0.23
A45: T-Mobile US, Inc. | B45: NasdaqGS:TMUS | C45: 202950 | D45: 321560 | E45: 90530 | F45: 0.638 | G45: 0.38 | H45: 0.13 | I45: 0.1 | J45: =IF(OR(D45="",D45=0,E45="",E45=0),"NM",D45/E45) -> 3.5519717 | K45: =IF(OR(G45<=0,E45=0,D45=0),"NM",IF(D45/(E45*G45)>100,"NM",D45/(E45*G45))) -> 9.347294 | M45: 142.4 | N45: 48 | P45: 0.32 | Q45: 86000 | R45: =IFERROR(Q45/(Q45+S45+U45),"") -> 0.29122926 | S45: 0 | T45: =IFERROR(S45/(Q45+S45+U45),"") -> 0 | U45: 209300 | V45: =IFERROR(U45/(Q45+S45+U45),"") -> 0.70877074 | W45: 0.21 | X45: =IFERROR(P45/(1+(Q45/U45)*(1-W45)+S45/U45),"") -> 0.2415813
A46: China Unicom | B46: SHSE:600050 | C46: 80000 | D46: 110000 | E46: 43000 | F46: 0.55 | G46: 0.285 | H46: 0.22 | I46: 0.02 | J46: =IF(OR(D46="",D46=0,E46="",E46=0),"NM",D46/E46) -> 2.5581395 | K46: =IF(OR(G46<=0,E46=0,D46=0),"NM",IF(D46/(E46*G46)>100,"NM",D46/(E46*G46))) -> 8.9759282 | M46: 335 | N46: 5.5 | P46: 0.5 | Q46: 97310 | R46: =IFERROR(Q46/(Q46+S46+U46),"") -> 0.80950004 | S46: 0 | T46: =IFERROR(S46/(Q46+S46+U46),"") -> 0 | U46: 22900 | V46: =IFERROR(U46/(Q46+S46+U46),"") -> 0.19049996 | W46: 0.25 | X46: =IFERROR(P46/(1+(Q46/U46)*(1-W46)+S46/U46),"") -> 0.11941699
A47: Charter Communications | B47: NasdaqGS:CHTR | C47: 27710 | D47: 124500 | E47: 54636 | F47: 0.553 | G47: 0.4 | H47: 0.18 | I47: -0.01 | J47: =IF(OR(D47="",D47=0,E47="",E47=0),"NM",D47/E47) -> 2.2787173 | K47: =IF(OR(G47<=0,E47=0,D47=0),"NM",IF(D47/(E47*G47)>100,"NM",D47/(E47*G47))) -> 5.6967933 | M47: 32 | N47: 114 | P47: 1.05 | Q47: 97310 | R47: =IFERROR(Q47/(Q47+S47+U47),"") -> 0.80950004 | S47: 0 | T47: =IFERROR(S47/(Q47+S47+U47),"") -> 0 | U47: 22900 | V47: =IFERROR(U47/(Q47+S47+U47),"") -> 0.19049996 | W47: 0.21 | X47: =IFERROR(P47/(1+(Q47/U47)*(1-W47)+S47/U47),"") -> 0.24099247
A48: SoftBank Corp. | B48: TSE:9434 | C48: 28000 | D48: 63000 | E48: 49000 | F48: 0.44 | G48: 0.32 | H48: 0.15 | I48: 0.05 | J48: =IF(OR(D48="",D48=0,E48="",E48=0),"NM",D48/E48) -> 1.2857143 | K48: =IF(OR(G48<=0,E48=0,D48=0),"NM",IF(D48/(E48*G48)>100,"NM",D48/(E48*G48))) -> 4.0178571 | M48: 44 | N48: 41 | P48: 0.35 | Q48: 35000 | R48: =IFERROR(Q48/(Q48+S48+U48),"") -> 0.55555556 | S48: 0 | T48: =IFERROR(S48/(Q48+S48+U48),"") -> 0 | U48: 28000 | V48: =IFERROR(U48/(Q48+S48+U48),"") -> 0.44444444 | W48: 0.3 | X48: =IFERROR(P48/(1+(Q48/U48)*(1-W48)+S48/U48),"") -> 0.18666667
A49: Vodafone Group plc | B49: LSE:VOD | C49: 34460 | D49: 98000 | E49: 45500 | F49: 0.33 | G49: 0.35 | H49: 0.12 | I49: 0.03 | J49: =IF(OR(D49="",D49=0,E49="",E49=0),"NM",D49/E49) -> 2.1538462 | K49: =IF(OR(G49<=0,E49=0,D49=0),"NM",IF(D49/(E49*G49)>100,"NM",D49/(E49*G49))) -> 6.1538462 | M49: 270 | N49: 5 | P49: 0.34 | Q49: 63250 | R49: =IFERROR(Q49/(Q49+S49+U49),"") -> 0.64732371 | S49: 0 | T49: =IFERROR(S49/(Q49+S49+U49),"") -> 0 | U49: 34460 | V49: =IFERROR(U49/(Q49+S49+U49),"") -> 0.35267629 | W49: 0.19 | X49: =IFERROR(P49/(1+(Q49/U49)*(1-W49)+S49/U49),"") -> 0.13672608
A50: KDDI Corporation | B50: TSE:9433 | C50: 56000 | D50: 74000 | E50: 42000 | F50: 0.45 | G50: 0.33 | H50: 0.18 | I50: 0.04 | J50: =IF(OR(D50="",D50=0,E50="",E50=0),"NM",D50/E50) -> 1.7619048 | K50: =IF(OR(G50<=0,E50=0,D50=0),"NM",IF(D50/(E50*G50)>100,"NM",D50/(E50*G50))) -> 5.3391053 | M50: 55 | N50: 54 | P50: 0.4 | Q50: 18000 | R50: =IFERROR(Q50/(Q50+S50+U50),"") -> 0.24324324 | S50: 0 | T50: =IFERROR(S50/(Q50+S50+U50),"") -> 0 | U50: 56000 | V50: =IFERROR(U50/(Q50+S50+U50),"") -> 0.75675676 | W50: 0.3 | X50: =IFERROR(P50/(1+(Q50/U50)*(1-W50)+S50/U50),"") -> 0.32653061
A52: Min: | C52: =IFERROR(MIN(C43:C50),"") -> 27710 | D52: =IFERROR(MIN(D43:D50),"") -> 63000 | E52: =IFERROR(MIN(E43:E50),"") -> 42000 | F52: =MIN(F43:F50) -> 0.284 | G52: =IFERROR(MIN(G43:G50),"") -> 0.285 | H52: =IFERROR(MIN(H43:H50),"") -> 0.12 | I52: =IFERROR(MIN(I43:I50),"") -> -0.01 | J52: =IFERROR(_xlfn.AGGREGATE(5,5,J43:J50),"NM") -> 1.2857143 | K52: =IFERROR(MIN(K43:K50),"") -> 3.6904762 | M52: =IFERROR(IF(COUNTA(M43:M50)=0,"",MIN(M43:M50)),"") -> 32 | N52: =IFERROR(IF(COUNTA(N43:N50)=0,"",MIN(N43:N50)),"") -> 5 | P52: =IFERROR(MIN(P43:P50),"") -> 0.23 | Q52: =MIN(Q43:Q50) -> 0 | R52: =IFERROR(MIN(R43:R50),"") -> 0 | S52: =MIN(S43:S50) -> 0 | T52: =IFERROR(MIN(T43:T50),"") -> 0 | U52: =MIN(U43:U50) -> 22900 | V52: =IFERROR(MIN(V43:V50),"") -> 0.17301038 | W52: =IFERROR(MIN(W43:W50),"") -> 0.19 | X52: =IFERROR(MIN(X43:X50),"") -> 0.063040346
A53: 25th Pctl: | C53: =IFERROR(QUARTILE(C43:C50,1),"") -> 32845 | D53: =IFERROR(QUARTILE(D43:D50,1),"") -> 92000 | E53: =IFERROR(QUARTILE(E43:E50,1),"") -> 44822.5 | F53: =PERCENTILE(F43:F50,0.25) -> 0.408 | G53: =IFERROR(QUARTILE(G43:G50,1),"") -> 0.3275 | H53: =IFERROR(QUARTILE(H43:H50,1),"") -> 0.145 | I53: =IFERROR(QUARTILE(I43:I50,1),"") -> 0.0275 | J53: =IFERROR(PERCENTILE(J43:J50,0.25),"NM") -> 1.6443452 | K53: =IFERROR(QUARTILE(K43:K50,1),"") -> 5.0087933 | M53: =IFERROR(QUARTILE(M43:M50,1),"") -> 52.25 | N53: =IFERROR(QUARTILE(N43:N50,1),"") -> 6.4 | P53: =IFERROR(QUARTILE(P43:P50,1),"") -> 0.31 | Q53: =PERCENTILE(Q43:Q50,0.25) -> 30750 | R53: =IFERROR(QUARTILE(R43:R50,1),"") -> 0.27923275 | S53: =PERCENTILE(S43:S50,0.25) -> 0 | T53: =IFERROR(QUARTILE(T43:T50,1),"") -> 0 | U53: =PERCENTILE(U43:U50,0.25) -> 24475 | V53: =IFERROR(QUARTILE(V43:V50,1),"") -> 0.19049996 | W53: =IFERROR(QUARTILE(W43:W50,1),"") -> 0.21 | X53: =IFERROR(QUARTILE(X43:X50,1),"") -> 0.13239881
A54: Median: | C54: =IFERROR(MEDIAN(C43:C50),"") -> 66000 | D54: =IFERROR(MEDIAN(D43:D50),"") -> 115615 | E54: =IFERROR(MEDIAN(E43:E50),"") -> 47250 | F54: =MEDIAN(F43:F50) -> 0.445 | G54: =IFERROR(MEDIAN(G43:G50),"") -> 0.35 | H54: =IFERROR(MEDIAN(H43:H50),"") -> 0.1575 | I54: =IFERROR(MEDIAN(I43:I50),"") -> 0.035 | J54: =IFERROR(PERCENTILE(J43:J50,0.5),"NM") -> 2.2162817 | K54: =IFERROR(MEDIAN(K43:K50),"") -> 5.9253197 | M54: =IFERROR(MEDIAN(M43:M50),"") -> 206.2 | N54: =IFERROR(MEDIAN(N43:N50),"") -> 26 | P54: =IFERROR(MEDIAN(P43:P50),"") -> 0.345 | Q54: =MEDIAN(Q43:Q50) -> 74625 | R54: =IFERROR(MEDIAN(R43:R50),"") -> 0.60143963 | S54: =MEDIAN(S43:S50) -> 0 | T54: =IFERROR(MEDIAN(T43:T50),"") -> 0 | U54: =MEDIAN(U43:U50) -> 31230 | V54: =IFERROR(MEDIAN(V43:V50),"") -> 0.39856037 | W54: =IFERROR(MEDIAN(W43:W50),"") -> 0.265 | X54: =IFERROR(MEDIAN(X43:X50),"") -> 0.20833333
A55: Mean: | C55: =IFERROR(AVERAGE(C43:C50),"") -> 91140 | D55: =IFERROR(AVERAGE(D43:D50),"") -> 137286.25 | E55: =IFERROR(AVERAGE(E43:E50),"") -> 64262 | F55: =AVERAGE(F43:F50) -> 0.459875 | G55: =IFERROR(AVERAGE(G43:G50),"") -> 0.3515375 | H55: =IFERROR(AVERAGE(H43:H50),"") -> 0.161875 | I55: =IFERROR(AVERAGE(I43:I50),"") -> 0.04125 | J55: =IFERROR(_xlfn.AGGREGATE(1,5,J43:J50),"NM") -> 2.1938077 | K55: =IFERROR(AVERAGE(K43:K50),"") -> 6.2422362 | M55: =IFERROR(AVERAGE(M43:M50),"") -> 277.05 | N55: =IFERROR(AVERAGE(N43:N50),"") -> 35.65 | P55: =IFERROR(AVERAGE(P43:P50),"") -> 0.43375 | Q55: =AVERAGE(Q43:Q50) -> 64546.25 | R55: =IFERROR(AVERAGE(R43:R50),"") -> 0.52291768 | S55: =AVERAGE(S43:S50) -> 0 | T55: =IFERROR(AVERAGE(T43:T50),"") -> 0 | U55: =AVERAGE(U43:U50) -> 60070 | V55: =IFERROR(AVERAGE(V43:V50),"") -> 0.47708232 | W55: =IFERROR(AVERAGE(W43:W50),"") -> 0.255 | X55: =IFERROR(AVERAGE(X43:X50),"") -> 0.19311931
A56: 75th Pctl: | C56: =IFERROR(QUARTILE(C43:C50,3),"") -> 110737.5 | D56: =IFERROR(QUARTILE(D43:D50,3),"") -> 139875 | E56: =IFERROR(QUARTILE(E43:E50,3),"") -> 63609.5 | F56: =PERCENTILE(F43:F50,0.75) -> 0.55075 | G56: =IFERROR(QUARTILE(G43:G50,3),"") -> 0.384325 | H56: =IFERROR(QUARTILE(H43:H50,3),"") -> 0.18 | I56: =IFERROR(QUARTILE(I43:I50,3),"") -> 0.055 | J56: =IFERROR(PERCENTILE(J43:J50,0.75),"NM") -> 2.5857299 | K56: =IFERROR(QUARTILE(K43:K50,3),"") -> 7.2814241 | M56: =IFERROR(QUARTILE(M43:M50,3),"") -> 330.5 | N56: =IFERROR(QUARTILE(N43:N50,3),"") -> 49.5 | P56: =IFERROR(QUARTILE(P43:P50,3),"") -> 0.425 | Q56: =PERCENTILE(Q43:Q50,0.75) -> 97310 | R56: =IFERROR(QUARTILE(R43:R50,3),"") -> 0.80950004 | S56: =PERCENTILE(S43:S50,0.75) -> 0 | T56: =IFERROR(QUARTILE(T43:T50,3),"") -> 0 | U56: =PERCENTILE(U43:U50,0.75) -> 62500 | V56: =IFERROR(QUARTILE(V43:V50,3),"") -> 0.72076725 | W56: =IFERROR(QUARTILE(W43:W50,3),"") -> 0.3 | X56: =IFERROR(QUARTILE(X43:X50,3),"") -> 0.24113968
A57: Max: | C57: =IFERROR(MAX(C43:C50),"") -> 224000 | D57: =IFERROR(MAX(D43:D50),"") -> 321560 | E57: =IFERROR(MAX(E43:E50),"") -> 144000 | F57: =MAX(F43:F50) -> 0.638 | G57: =IFERROR(MAX(G43:G50),"") -> 0.4 | H57: =IFERROR(MAX(H43:H50),"") -> 0.22 | I57: =IFERROR(MAX(I43:I50),"") -> 0.1 | J57: =IFERROR(_xlfn.AGGREGATE(4,5,J43:J50),"NM") -> 3.5519717 | K57: =IFERROR(MAX(K43:K50),"") -> 9.347294 | M57: =IFERROR(IF(COUNTA(M43:M50)=0,"",MAX(M43:M50)),"") -> 1009 | N57: =IFERROR(IF(COUNTA(N43:N50)=0,"",MAX(N43:N50)),"") -> 114 | P57: =IFERROR(MAX(P43:P50),"") -> 1.05 | Q57: =MAX(Q43:Q50) -> 119500 | R57: =IFERROR(MAX(R43:R50),"") -> 0.82698962 | S57: =MAX(S43:S50) -> 0 | T57: =IFERROR(MAX(T43:T50),"") -> 0 | U57: =MAX(U43:U50) -> 209300 | V57: =IFERROR(MAX(V43:V50),"") -> 1 | W57: =IFERROR(MAX(W43:W50),"") -> 0.3 | X57: =IFERROR(MAX(X43:X50),"") -> 0.32653061

Sheet Space Comps
A1: SPACE – COMPARABLE COMPANY ANALYSIS
A2: Comparable Public Companies by Maturity & Industry | Launch Services + Defense / Aerospace | $ in Millions
A3: Current-stage anchor = Launch Services / NewSpace • Mature-stage anchor = Big-5 Defense Primes. Input cells (blue) to be populated from terminal (CapIQ/Bloomberg).
A5: Name | B5: Ticker | C5: Mkt Cap | D5: Enterprise | E5: LTM | F5: Gross | G5: EBITDA | H5: Capex % | I5: 3-Yr Ann. | J5: TEV / | K5: TEV / | M5: Backlog | N5: Backlog / | P5: Levered | Q5: Debt | R5: % Debt | S5: Preferred | T5: % Pref | U5: Equity | V5: % Equity | W5: Tax | X5: Unlevered
C6: ($M) | D6: Value ($M) | E6: Revenue ($M) | F6: Margin | G6: Margin | H6: Revenue | I6: Rev Growth | J6: Revenue | K6: EBITDA | M6: ($M) | N6: Rev (x) | P6: Beta | Q6: ($M) | S6: Stock ($M) | U6: Value ($M) | W6: Rate | X6: Beta
A8: TIER 1 – SMALLER-SCALE ROCKET / SPACE TECH (Current-Stage Anchor)
A9: Rocket Lab Corporation | B9: NasdaqGS:RKLB | C9: 74950 | D9: 73700 | E9: 602 | F9: 0.317 | G9: -0.15 | H9: 0.256 | I9: 0.38 | J9: =IFERROR(D9/E9,"NM") -> 122.42525 | K9: =IF(OR(G9<=0,E9=0,D9=0),"NM",IF(D9/(E9*G9)>100,"NM",D9/(E9*G9))) -> NM | M9: 2200 | N9: =IFERROR(M9/E9,"NM") -> 3.654485 | P9: 2.31 | Q9: 139 | R9: =IFERROR(Q9/(Q9+S9+U9),"") -> 0.0021766705 | S9: 0 | T9: =IFERROR(S9/(Q9+S9+U9),"") -> 0 | U9: 63720 | V9: =IFERROR(U9/(Q9+S9+U9),"") -> 0.99782333 | W9: 0.21 | X9: =IFERROR(P9/(1+(Q9/U9)*(1-W9)+S9/U9),"") -> 2.306026
A10: AeroVironment, Inc. | B10: NasdaqGS:AVAV | C10: 9410 | D10: 9650 | E10: 821 | F10: 0.25 | G10: 0.1 | H10: 0.034 | I10: 0.3 | J10: =IFERROR(D10/E10,"NM") -> 11.753959 | K10: =IF(OR(G10<=0,E10=0,D10=0),"NM",IF(D10/(E10*G10)>100,"NM",D10/(E10*G10))) -> NM | M10: 1100 | N10: =IFERROR(M10/E10,"NM") -> 1.3398295 | P10: 1.4 | Q10: 826 | R10: =IFERROR(Q10/(Q10+S10+U10),"") -> 0.080695584 | S10: 0 | T10: =IFERROR(S10/(Q10+S10+U10),"") -> 0 | U10: 9410 | V10: =IFERROR(U10/(Q10+S10+U10),"") -> 0.91930442 | W10: 0.21 | X10: =IFERROR(P10/(1+(Q10/U10)*(1-W10)+S10/U10),"") -> 1.3092122
A11: Kratos Defense & Security | B11: NasdaqGS:KTOS | C11: 10970 | D11: 10860 | E11: 1350 | F11: 0.28 | G11: 0.08 | H11: 0.04 | I11: 0.19 | J11: =IFERROR(D11/E11,"NM") -> 8.0444444 | K11: =IF(OR(G11<=0,E11=0,D11=0),"NM",IF(D11/(E11*G11)>100,"NM",D11/(E11*G11))) -> NM | M11: 2000 | N11: =IFERROR(M11/E11,"NM") -> 1.4814815 | P11: 1.15 | Q11: 280 | R11: =IFERROR(Q11/(Q11+S11+U11),"") -> 0.024888889 | S11: 0 | T11: =IFERROR(S11/(Q11+S11+U11),"") -> 0 | U11: 10970 | V11: =IFERROR(U11/(Q11+S11+U11),"") -> 0.97511111 | W11: 0.21 | X11: =IFERROR(P11/(1+(Q11/U11)*(1-W11)+S11/U11),"") -> 1.1272696
A12: Redwire Corporation | B12: NYSE:RDW | C12: 4000 | D12: 4080 | E12: 469 | F12: 0.092 | G12: -0.1 | H12: 0.062 | I12: 0.41 | J12: =IFERROR(D12/E12,"NM") -> 8.6993603 | K12: =IF(OR(G12<=0,E12=0,D12=0),"NM",IF(D12/(E12*G12)>100,"NM",D12/(E12*G12))) -> NM | M12: 498 | N12: =IFERROR(M12/E12,"NM") -> 1.0618337 | P12: 2.5 | Q12: 80 | R12: =IFERROR(Q12/(Q12+S12+U12),"") -> 0.019607843 | S12: 0 | T12: =IFERROR(S12/(Q12+S12+U12),"") -> 0 | U12: 4000 | V12: =IFERROR(U12/(Q12+S12+U12),"") -> 0.98039216 | W12: 0.21 | X12: =IFERROR(P12/(1+(Q12/U12)*(1-W12)+S12/U12),"") -> 2.4611144
A13: MDA Space Ltd. | B13: TSX:MDA | C13: 5390 | D13: 5230 | E13: 1250 | F13: 0.287 | G13: 0.18 | H13: 0.163 | I13: 0.3 | J13: =IFERROR(D13/E13,"NM") -> 4.184 | K13: =IF(OR(G13<=0,E13=0,D13=0),"NM",IF(D13/(E13*G13)>100,"NM",D13/(E13*G13))) -> 23.244444 | M13: 1500 | N13: =IFERROR(M13/E13,"NM") -> 1.2 | P13: 0.12 | Q13: 273 | R13: =IFERROR(Q13/(Q13+S13+U13),"") -> 0.048207664 | S13: 0 | T13: =IFERROR(S13/(Q13+S13+U13),"") -> 0 | U13: 5390 | V13: =IFERROR(U13/(Q13+S13+U13),"") -> 0.95179234 | W13: 0.265 | X13: =IFERROR(P13/(1+(Q13/U13)*(1-W13)+S13/U13),"") -> 0.11569306
A14: York Space Systems | B14: NYSE:YSS | C14: 3950 | D14: 4150 | E14: 420 | F14: 0.19 | G14: -0.1 | H14: 0.05 | I14: 0.48 | J14: =IFERROR(D14/E14,"NM") -> 9.8809524 | K14: =IF(OR(G14<=0,E14=0,D14=0),"NM",IF(D14/(E14*G14)>100,"NM",D14/(E14*G14))) -> NM | M14: 450 | N14: =IFERROR(M14/E14,"NM") -> 1.0714286 | P14: 2 | Q14: 200 | R14: =IFERROR(Q14/(Q14+S14+U14),"") -> 0.048192771 | S14: 0 | T14: =IFERROR(S14/(Q14+S14+U14),"") -> 0 | U14: 3950 | V14: =IFERROR(U14/(Q14+S14+U14),"") -> 0.95180723 | W14: 0.21 | X14: =IFERROR(P14/(1+(Q14/U14)*(1-W14)+S14/U14),"") -> 1.9230769
A15: Intuitive Machines | B15: NasdaqGM:LUNR | C15: 2500 | D15: 2300 | E15: 230 | F15: 0.18 | G15: -0.2 | H15: 0.5 | I15: 0.5 | J15: =IFERROR(D15/E15,"NM") -> 10 | K15: =IF(OR(G15<=0,E15=0,D15=0),"NM",IF(D15/(E15*G15)>100,"NM",D15/(E15*G15))) -> NM | M15: 1100 | N15: =IFERROR(M15/E15,"NM") -> 4.7826087 | P15: 1.47 | Q15: 336 | R15: =IFERROR(Q15/(Q15+S15+U15),"") -> 0.061617458 | S15: 7 | T15: =IFERROR(S15/(Q15+S15+U15),"") -> 0.001283697 | U15: 5110 | V15: =IFERROR(U15/(Q15+S15+U15),"") -> 0.93709884 | W15: 0.21 | X15: =IFERROR(P15/(1+(Q15/U15)*(1-W15)+S15/U15),"") -> 1.3955938
A16: Firefly Aerospace Inc. | B16: NasdaqGM:FLY | C16: 6000 | D16: 5500 | E16: 185 | F16: 0.248 | G16: -0.3 | H16: 0.25 | I16: 0.55 | J16: =IFERROR(D16/E16,"NM") -> 29.72973 | K16: =IF(OR(G16<=0,E16=0,D16=0),"NM",IF(D16/(E16*G16)>100,"NM",D16/(E16*G16))) -> NM | M16: 1300 | N16: =IFERROR(M16/E16,"NM") -> 7.027027 | P16: 3 | Q16: 53 | R16: =IFERROR(Q16/(Q16+S16+U16),"") -> 0.0087559888 | S16: 0 | T16: =IFERROR(S16/(Q16+S16+U16),"") -> 0 | U16: 6000 | V16: =IFERROR(U16/(Q16+S16+U16),"") -> 0.99124401 | W16: 0.21 | X16: =IFERROR(P16/(1+(Q16/U16)*(1-W16)+S16/U16),"") -> 2.9792101
A17: Voyager Technologies | B17: NYSE:VOYG | C17: 2800 | D17: 2850 | E17: 166 | F17: 0.179 | G17: -0.25 | H17: 0.366 | I17: 0.4 | J17: =IFERROR(D17/E17,"NM") -> 17.168675 | K17: =IF(OR(G17<=0,E17=0,D17=0),"NM",IF(D17/(E17*G17)>100,"NM",D17/(E17*G17))) -> NM | M17: 275 | N17: =IFERROR(M17/E17,"NM") -> 1.6566265 | P17: 2.5 | Q17: 50 | R17: =IFERROR(Q17/(Q17+S17+U17),"") -> 0.01754386 | S17: 0 | T17: =IFERROR(S17/(Q17+S17+U17),"") -> 0 | U17: 2800 | V17: =IFERROR(U17/(Q17+S17+U17),"") -> 0.98245614 | W17: 0.21 | X17: =IFERROR(P17/(1+(Q17/U17)*(1-W17)+S17/U17),"") -> 2.4652228
A19: Min: | C19: =IFERROR(MIN(C9:C17),"") -> 2500 | D19: =IFERROR(MIN(D9:D17),"") -> 2300 | E19: =IFERROR(MIN(E9:E17),"") -> 166 | F19: =IFERROR(MIN(F9:F17),"") -> 0.092 | G19: =IFERROR(MIN(G9:G17),"") -> -0.3 | H19: =IFERROR(MIN(H9:H17),"") -> 0.034 | I19: =IFERROR(MIN(I9:I17),"") -> 0.19 | J19: =IFERROR(MIN(J9:J17),"") -> 4.184 | K19: =IFERROR(_xlfn.AGGREGATE(15,6,K9:K17,1),"NM") -> 23.244444 | M19: =IFERROR(MIN(M9:M17),"") -> 275 | N19: =IFERROR(MIN(N9:N17),"") -> 1.0618337 | P19: =IFERROR(MIN(P9:P17),"") -> 0.12 | Q19: =IFERROR(MIN(Q9:Q17),"") -> 50 | R19: =IFERROR(MIN(R9:R17),"") -> 0.0021766705 | S19: =IFERROR(MIN(S9:S17),"") -> 0 | T19: =IFERROR(MIN(T9:T17),"") -> 0 | U19: =IFERROR(MIN(U9:U17),"") -> 2800 | V19: =IFERROR(MIN(V9:V17),"") -> 0.91930442 | W19: =IFERROR(MIN(W9:W17),"") -> 0.21 | X19: =IFERROR(MIN(X9:X17),"") -> 0.11569306
A20: 25th Pctl: | C20: =IFERROR(QUARTILE(C9:C17,1),"") -> 3950 | D20: =IFERROR(QUARTILE(D9:D17,1),"") -> 4080 | E20: =IFERROR(QUARTILE(E9:E17,1),"") -> 230 | F20: =IFERROR(QUARTILE(F9:F17,1),"") -> 0.18 | G20: =IFERROR(QUARTILE(G9:G17,1),"") -> -0.2 | H20: =IFERROR(QUARTILE(H9:H17,1),"") -> 0.05 | I20: =IFERROR(QUARTILE(I9:I17,1),"") -> 0.3 | J20: =IFERROR(QUARTILE(J9:J17,1),"") -> 8.6993603 | K20: =IFERROR(_xlfn.AGGREGATE(16,6,K9:K17,0.25),"NM") -> 23.244444 | M20: =IFERROR(QUARTILE(M9:M17,1),"") -> 498 | N20: =IFERROR(QUARTILE(N9:N17,1),"") -> 1.2 | P20: =IFERROR(QUARTILE(P9:P17,1),"") -> 1.4 | Q20: =IFERROR(QUARTILE(Q9:Q17,1),"") -> 80 | R20: =IFERROR(QUARTILE(R9:R17,1),"") -> 0.01754386 | S20: =IFERROR(QUARTILE(S9:S17,1),"") -> 0 | T20: =IFERROR(QUARTILE(T9:T17,1),"") -> 0 | U20: =IFERROR(QUARTILE(U9:U17,1),"") -> 4000 | V20: =IFERROR(QUARTILE(V9:V17,1),"") -> 0.95179234 | W20: =IFERROR(QUARTILE(W9:W17,1),"") -> 0.21 | X20: =IFERROR(QUARTILE(X9:X17,1),"") -> 1.3092122
A21: Median: | C21: =IFERROR(MEDIAN(C9:C17),"") -> 5390 | D21: =IFERROR(MEDIAN(D9:D17),"") -> 5230 | E21: =IFERROR(MEDIAN(E9:E17),"") -> 469 | F21: =IFERROR(MEDIAN(F9:F17),"") -> 0.248 | G21: =IFERROR(MEDIAN(G9:G17),"") -> -0.1 | H21: =IFERROR(MEDIAN(H9:H17),"") -> 0.163 | I21: =IFERROR(MEDIAN(I9:I17),"") -> 0.4 | J21: =IFERROR(MEDIAN(J9:J17),"") -> 10 | K21: =IFERROR(_xlfn.AGGREGATE(16,6,K9:K17,0.5),"NM") -> 23.244444 | M21: =IFERROR(MEDIAN(M9:M17),"") -> 1100 | N21: =IFERROR(MEDIAN(N9:N17),"") -> 1.4814815 | P21: =IFERROR(MEDIAN(P9:P17),"") -> 2 | Q21: =IFERROR(MEDIAN(Q9:Q17),"") -> 200 | R21: =IFERROR(MEDIAN(R9:R17),"") -> 0.024888889 | S21: =IFERROR(MEDIAN(S9:S17),"") -> 0 | T21: =IFERROR(MEDIAN(T9:T17),"") -> 0 | U21: =IFERROR(MEDIAN(U9:U17),"") -> 5390 | V21: =IFERROR(MEDIAN(V9:V17),"") -> 0.97511111 | W21: =IFERROR(MEDIAN(W9:W17),"") -> 0.21 | X21: =IFERROR(MEDIAN(X9:X17),"") -> 1.9230769
A22: Mean: | C22: =IFERROR(AVERAGE(C9:C17),"") -> 13330 | D22: =IFERROR(AVERAGE(D9:D17),"") -> 13146.667 | E22: =IFERROR(AVERAGE(E9:E17),"") -> 610.33333 | F22: =IFERROR(AVERAGE(F9:F17),"") -> 0.22477778 | G22: =IFERROR(AVERAGE(G9:G17),"") -> -0.082222222 | H22: =IFERROR(AVERAGE(H9:H17),"") -> 0.19122222 | I22: =IFERROR(AVERAGE(I9:I17),"") -> 0.39 | J22: =IFERROR(AVERAGE(J9:J17),"") -> 24.654041 | K22: =IFERROR(_xlfn.AGGREGATE(1,6,K9:K17),"NM") -> 23.244444 | M22: =IFERROR(AVERAGE(M9:M17),"") -> 1158.1111 | N22: =IFERROR(AVERAGE(N9:N17),"") -> 2.5861467 | P22: =IFERROR(AVERAGE(P9:P17),"") -> 1.8277778 | Q22: =IFERROR(AVERAGE(Q9:Q17),"") -> 248.55556 | R22: =IFERROR(AVERAGE(R9:R17),"") -> 0.034631859 | S22: =IFERROR(AVERAGE(S9:S17),"") -> 0.77777778 | T22: =IFERROR(AVERAGE(T9:T17),"") -> 0.00014263301 | U22: =IFERROR(AVERAGE(U9:U17),"") -> 12372.222 | V22: =IFERROR(AVERAGE(V9:V17),"") -> 0.96522551 | W22: =IFERROR(AVERAGE(W9:W17),"") -> 0.21611111 | X22: =IFERROR(AVERAGE(X9:X17),"") -> 1.7869354
A23: 75th Pctl: | C23: =IFERROR(QUARTILE(C9:C17,3),"") -> 9410 | D23: =IFERROR(QUARTILE(D9:D17,3),"") -> 9650 | E23: =IFERROR(QUARTILE(E9:E17,3),"") -> 821 | F23: =IFERROR(QUARTILE(F9:F17,3),"") -> 0.28 | G23: =IFERROR(QUARTILE(G9:G17,3),"") -> 0.08 | H23: =IFERROR(QUARTILE(H9:H17,3),"") -> 0.256 | I23: =IFERROR(QUARTILE(I9:I17,3),"") -> 0.48 | J23: =IFERROR(QUARTILE(J9:J17,3),"") -> 17.168675 | K23: =IFERROR(_xlfn.AGGREGATE(16,6,K9:K17,0.75),"NM") -> 23.244444 | M23: =IFERROR(QUARTILE(M9:M17,3),"") -> 1500 | N23: =IFERROR(QUARTILE(N9:N17,3),"") -> 3.654485 | P23: =IFERROR(QUARTILE(P9:P17,3),"") -> 2.5 | Q23: =IFERROR(QUARTILE(Q9:Q17,3),"") -> 280 | R23: =IFERROR(QUARTILE(R9:R17,3),"") -> 0.048207664 | S23: =IFERROR(QUARTILE(S9:S17,3),"") -> 0 | T23: =IFERROR(QUARTILE(T9:T17,3),"") -> 0 | U23: =IFERROR(QUARTILE(U9:U17,3),"") -> 9410 | V23: =IFERROR(QUARTILE(V9:V17,3),"") -> 0.98245614 | W23: =IFERROR(QUARTILE(W9:W17,3),"") -> 0.21 | X23: =IFERROR(QUARTILE(X9:X17,3),"") -> 2.4611144
A24: Max: | C24: =IFERROR(MAX(C9:C17),"") -> 74950 | D24: =IFERROR(MAX(D9:D17),"") -> 73700 | E24: =IFERROR(MAX(E9:E17),"") -> 1350 | F24: =IFERROR(MAX(F9:F17),"") -> 0.317 | G24: =IFERROR(MAX(G9:G17),"") -> 0.18 | H24: =IFERROR(MAX(H9:H17),"") -> 0.5 | I24: =IFERROR(MAX(I9:I17),"") -> 0.55 | J24: =IFERROR(MAX(J9:J17),"") -> 122.42525 | K24: =IFERROR(_xlfn.AGGREGATE(14,6,K9:K17,1),"NM") -> 23.244444 | M24: =IFERROR(MAX(M9:M17),"") -> 2200 | N24: =IFERROR(MAX(N9:N17),"") -> 7.027027 | P24: =IFERROR(MAX(P9:P17),"") -> 3 | Q24: =IFERROR(MAX(Q9:Q17),"") -> 826 | R24: =IFERROR(MAX(R9:R17),"") -> 0.080695584 | S24: =IFERROR(MAX(S9:S17),"") -> 7 | T24: =IFERROR(MAX(T9:T17),"") -> 0.001283697 | U24: =IFERROR(MAX(U9:U17),"") -> 63720 | V24: =IFERROR(MAX(V9:V17),"") -> 0.99782333 | W24: =IFERROR(MAX(W9:W17),"") -> 0.265 | X24: =IFERROR(MAX(X9:X17),"") -> 2.9792101
A26: TIER 2 – "BIG 5" U.S. DEFENSE CONTRACTORS (Mature-Stage Anchor)
A27: The Boeing Company | B27: NYSE:BA | C27: 170000 | D27: 196150 | E27: 92184 | F27: 0.048 | G27: 0.045 | H27: 0.017 | I27: 0.11 | J27: =IFERROR(D27/E27,"NM") -> 2.1278096 | K27: =IF(OR(G27<=0,E27=0,D27=0),"NM",IF(D27/(E27*G27)>100,"NM",D27/(E27*G27))) -> 47.284658 | M27: 516000 | N27: =IFERROR(M27/E27,"NM") -> 5.5975007 | P27: 1.21 | Q27: 44354 | R27: =IFERROR(Q27/(Q27+S27+U27),"") -> 0.20113004 | S27: 5750 | T27: =IFERROR(S27/(Q27+S27+U27),"") -> 0.026074259 | U27: 170420 | V27: =IFERROR(U27/(Q27+S27+U27),"") -> 0.7727957 | W27: 0.21 | X27: =IFERROR(P27/(1+(Q27/U27)*(1-W27)+S27/U27),"") -> 0.97631993
A28: RTX Corporation | B28: NYSE:RTX | C28: 238380 | D28: 247000 | E28: 90373 | F28: 0.202 | G28: 0.145 | H28: 0.029 | I28: 0.1 | J28: =IFERROR(D28/E28,"NM") -> 2.7331172 | K28: =IF(OR(G28<=0,E28=0,D28=0),"NM",IF(D28/(E28*G28)>100,"NM",D28/(E28*G28))) -> 18.849084 | M28: 217000 | N28: =IFERROR(M28/E28,"NM") -> 2.4011596 | P28: 0.3 | Q28: 38940 | R28: =IFERROR(Q28/(Q28+S28+U28),"") -> 0.13748544 | S28: 0 | T28: =IFERROR(S28/(Q28+S28+U28),"") -> 0 | U28: 244290 | V28: =IFERROR(U28/(Q28+S28+U28),"") -> 0.86251456 | W28: 0.21 | X28: =IFERROR(P28/(1+(Q28/U28)*(1-W28)+S28/U28),"") -> 0.26644722
A29: Lockheed Martin | B29: NYSE:LMT | C29: 121000 | D29: 141700 | E29: 72000 | F29: 0.11 | G29: 0.13 | H29: 0.016 | I29: 0.04 | J29: =IFERROR(D29/E29,"NM") -> 1.9680556 | K29: =IF(OR(G29<=0,E29=0,D29=0),"NM",IF(D29/(E29*G29)>100,"NM",D29/(E29*G29))) -> 15.138889 | M29: 160000 | N29: =IFERROR(M29/E29,"NM") -> 2.2222222 | P29: 0.2 | Q29: 20530 | R29: =IFERROR(Q29/(Q29+S29+U29),"") -> 0.14530398 | S29: 0 | T29: =IFERROR(S29/(Q29+S29+U29),"") -> 0 | U29: 120760 | V29: =IFERROR(U29/(Q29+S29+U29),"") -> 0.85469602 | W29: 0.21 | X29: =IFERROR(P29/(1+(Q29/U29)*(1-W29)+S29/U29),"") -> 0.17631938
A30: General Dynamics | B30: NYSE:GD | C30: 92350 | D30: 99000 | E30: 53810 | F30: 0.152 | G30: 0.13 | H30: 0.013 | I30: 0.1 | J30: =IFERROR(D30/E30,"NM") -> 1.8398067 | K30: =IF(OR(G30<=0,E30=0,D30=0),"NM",IF(D30/(E30*G30)>100,"NM",D30/(E30*G30))) -> 14.152359 | M30: 100000 | N30: =IFERROR(M30/E30,"NM") -> 1.8583906 | P30: 0.5 | Q30: 12800 | R30: =IFERROR(Q30/(Q30+S30+U30),"") -> 0.12019908 | S30: 0 | T30: =IFERROR(S30/(Q30+S30+U30),"") -> 0 | U30: 93690 | V30: =IFERROR(U30/(Q30+S30+U30),"") -> 0.87980092 | W30: 0.21 | X30: =IFERROR(P30/(1+(Q30/U30)*(1-W30)+S30/U30),"") -> 0.45129188
A31: Northrop Grumman | B31: NYSE:NOC | C31: 79800 | D31: 94000 | E31: 42000 | F31: 0.2 | G31: 0.16 | H31: 0.016 | I31: 0.03 | J31: =IFERROR(D31/E31,"NM") -> 2.2380952 | K31: =IF(OR(G31<=0,E31=0,D31=0),"NM",IF(D31/(E31*G31)>100,"NM",D31/(E31*G31))) -> 13.988095 | M31: 90000 | N31: =IFERROR(M31/E31,"NM") -> 2.1428571 | P31: 0.05 | Q31: 14600 | R31: =IFERROR(Q31/(Q31+S31+U31),"") -> 0.15883377 | S31: 0 | T31: =IFERROR(S31/(Q31+S31+U31),"") -> 0 | U31: 77320 | V31: =IFERROR(U31/(Q31+S31+U31),"") -> 0.84116623 | W31: 0.21 | X31: =IFERROR(P31/(1+(Q31/U31)*(1-W31)+S31/U31),"") -> 0.043509578
A33: Min: | C33: =IFERROR(MIN(C27:C31),"") -> 79800 | D33: =IFERROR(MIN(D27:D31),"") -> 94000 | E33: =IFERROR(MIN(E27:E31),"") -> 42000 | F33: =IFERROR(MIN(F27:F31),"") -> 0.048 | G33: =IFERROR(MIN(G27:G31),"") -> 0.045 | H33: =IFERROR(MIN(H27:H31),"") -> 0.013 | I33: =IFERROR(MIN(I27:I31),"") -> 0.03 | J33: =IFERROR(MIN(J27:J31),"") -> 1.8398067 | K33: =IFERROR(MIN(K27:K31),"") -> 13.988095 | M33: =IFERROR(MIN(M27:M31),"") -> 90000 | N33: =IFERROR(MIN(N27:N31),"") -> 1.8583906 | P33: =IFERROR(MIN(P27:P31),"") -> 0.05 | Q33: =IFERROR(MIN(Q27:Q31),"") -> 12800 | R33: =IFERROR(MIN(R27:R31),"") -> 0.12019908 | S33: =IFERROR(MIN(S27:S31),"") -> 0 | T33: =IFERROR(MIN(T27:T31),"") -> 0 | U33: =IFERROR(MIN(U27:U31),"") -> 77320 | V33: =IFERROR(MIN(V27:V31),"") -> 0.7727957 | W33: =IFERROR(MIN(W27:W31),"") -> 0.21 | X33: =IFERROR(MIN(X27:X31),"") -> 0.043509578
A34: 25th Pctl: | C34: =IFERROR(QUARTILE(C27:C31,1),"") -> 92350 | D34: =IFERROR(QUARTILE(D27:D31,1),"") -> 99000 | E34: =IFERROR(QUARTILE(E27:E31,1),"") -> 53810 | F34: =IFERROR(QUARTILE(F27:F31,1),"") -> 0.11 | G34: =IFERROR(QUARTILE(G27:G31,1),"") -> 0.13 | H34: =IFERROR(QUARTILE(H27:H31,1),"") -> 0.016 | I34: =IFERROR(QUARTILE(I27:I31,1),"") -> 0.04 | J34: =IFERROR(QUARTILE(J27:J31,1),"") -> 1.9680556 | K34: =IFERROR(QUARTILE(K27:K31,1),"") -> 14.152359 | M34: =IFERROR(QUARTILE(M27:M31,1),"") -> 100000 | N34: =IFERROR(QUARTILE(N27:N31,1),"") -> 2.1428571 | P34: =IFERROR(QUARTILE(P27:P31,1),"") -> 0.2 | Q34: =IFERROR(QUARTILE(Q27:Q31,1),"") -> 14600 | R34: =IFERROR(QUARTILE(R27:R31,1),"") -> 0.13748544 | S34: =IFERROR(QUARTILE(S27:S31,1),"") -> 0 | T34: =IFERROR(QUARTILE(T27:T31,1),"") -> 0 | U34: =IFERROR(QUARTILE(U27:U31,1),"") -> 93690 | V34: =IFERROR(QUARTILE(V27:V31,1),"") -> 0.84116623 | W34: =IFERROR(QUARTILE(W27:W31,1),"") -> 0.21 | X34: =IFERROR(QUARTILE(X27:X31,1),"") -> 0.17631938
A35: Median: | C35: =IFERROR(MEDIAN(C27:C31),"") -> 121000 | D35: =IFERROR(MEDIAN(D27:D31),"") -> 141700 | E35: =IFERROR(MEDIAN(E27:E31),"") -> 72000 | F35: =IFERROR(MEDIAN(F27:F31),"") -> 0.152 | G35: =IFERROR(MEDIAN(G27:G31),"") -> 0.13 | H35: =IFERROR(MEDIAN(H27:H31),"") -> 0.016 | I35: =IFERROR(MEDIAN(I27:I31),"") -> 0.1 | J35: =IFERROR(MEDIAN(J27:J31),"") -> 2.1278096 | K35: =IFERROR(MEDIAN(K27:K31),"") -> 15.138889 | M35: =IFERROR(MEDIAN(M27:M31),"") -> 160000 | N35: =IFERROR(MEDIAN(N27:N31),"") -> 2.2222222 | P35: =IFERROR(MEDIAN(P27:P31),"") -> 0.3 | Q35: =IFERROR(MEDIAN(Q27:Q31),"") -> 20530 | R35: =IFERROR(MEDIAN(R27:R31),"") -> 0.14530398 | S35: =IFERROR(MEDIAN(S27:S31),"") -> 0 | T35: =IFERROR(MEDIAN(T27:T31),"") -> 0 | U35: =IFERROR(MEDIAN(U27:U31),"") -> 120760 | V35: =IFERROR(MEDIAN(V27:V31),"") -> 0.85469602 | W35: =IFERROR(MEDIAN(W27:W31),"") -> 0.21 | X35: =IFERROR(MEDIAN(X27:X31),"") -> 0.26644722
A36: Mean: | C36: =IFERROR(AVERAGE(C27:C31),"") -> 140306 | D36: =IFERROR(AVERAGE(D27:D31),"") -> 155570 | E36: =IFERROR(AVERAGE(E27:E31),"") -> 70073.4 | F36: =IFERROR(AVERAGE(F27:F31),"") -> 0.1424 | G36: =IFERROR(AVERAGE(G27:G31),"") -> 0.122 | H36: =IFERROR(AVERAGE(H27:H31),"") -> 0.0182 | I36: =IFERROR(AVERAGE(I27:I31),"") -> 0.076 | J36: =IFERROR(AVERAGE(J27:J31),"") -> 2.1813769 | K36: =IFERROR(AVERAGE(K27:K31),"") -> 21.882617 | M36: =IFERROR(AVERAGE(M27:M31),"") -> 216600 | N36: =IFERROR(AVERAGE(N27:N31),"") -> 2.8444261 | P36: =IFERROR(AVERAGE(P27:P31),"") -> 0.452 | Q36: =IFERROR(AVERAGE(Q27:Q31),"") -> 26244.8 | R36: =IFERROR(AVERAGE(R27:R31),"") -> 0.15259046 | S36: =IFERROR(AVERAGE(S27:S31),"") -> 1150 | T36: =IFERROR(AVERAGE(T27:T31),"") -> 0.0052148519 | U36: =IFERROR(AVERAGE(U27:U31),"") -> 141296 | V36: =IFERROR(AVERAGE(V27:V31),"") -> 0.84219469 | W36: =IFERROR(AVERAGE(W27:W31),"") -> 0.21 | X36: =IFERROR(AVERAGE(X27:X31),"") -> 0.3827776
A37: 75th Pctl: | C37: =IFERROR(QUARTILE(C27:C31,3),"") -> 170000 | D37: =IFERROR(QUARTILE(D27:D31,3),"") -> 196150 | E37: =IFERROR(QUARTILE(E27:E31,3),"") -> 90373 | F37: =IFERROR(QUARTILE(F27:F31,3),"") -> 0.2 | G37: =IFERROR(QUARTILE(G27:G31,3),"") -> 0.145 | H37: =IFERROR(QUARTILE(H27:H31,3),"") -> 0.017 | I37: =IFERROR(QUARTILE(I27:I31,3),"") -> 0.1 | J37: =IFERROR(QUARTILE(J27:J31,3),"") -> 2.2380952 | K37: =IFERROR(QUARTILE(K27:K31,3),"") -> 18.849084 | M37: =IFERROR(QUARTILE(M27:M31,3),"") -> 217000 | N37: =IFERROR(QUARTILE(N27:N31,3),"") -> 2.4011596 | P37: =IFERROR(QUARTILE(P27:P31,3),"") -> 0.5 | Q37: =IFERROR(QUARTILE(Q27:Q31,3),"") -> 38940 | R37: =IFERROR(QUARTILE(R27:R31,3),"") -> 0.15883377 | S37: =IFERROR(QUARTILE(S27:S31,3),"") -> 0 | T37: =IFERROR(QUARTILE(T27:T31,3),"") -> 0 | U37: =IFERROR(QUARTILE(U27:U31,3),"") -> 170420 | V37: =IFERROR(QUARTILE(V27:V31,3),"") -> 0.86251456 | W37: =IFERROR(QUARTILE(W27:W31,3),"") -> 0.21 | X37: =IFERROR(QUARTILE(X27:X31,3),"") -> 0.45129188
A38: Max: | C38: =IFERROR(MAX(C27:C31),"") -> 238380 | D38: =IFERROR(MAX(D27:D31),"") -> 247000 | E38: =IFERROR(MAX(E27:E31),"") -> 92184 | F38: =IFERROR(MAX(F27:F31),"") -> 0.202 | G38: =IFERROR(MAX(G27:G31),"") -> 0.16 | H38: =IFERROR(MAX(H27:H31),"") -> 0.029 | I38: =IFERROR(MAX(I27:I31),"") -> 0.11 | J38: =IFERROR(MAX(J27:J31),"") -> 2.7331172 | K38: =IFERROR(MAX(K27:K31),"") -> 47.284658 | M38: =IFERROR(MAX(M27:M31),"") -> 516000 | N38: =IFERROR(MAX(N27:N31),"") -> 5.5975007 | P38: =IFERROR(MAX(P27:P31),"") -> 1.21 | Q38: =IFERROR(MAX(Q27:Q31),"") -> 44354 | R38: =IFERROR(MAX(R27:R31),"") -> 0.20113004 | S38: =IFERROR(MAX(S27:S31),"") -> 5750 | T38: =IFERROR(MAX(T27:T31),"") -> 0.026074259 | U38: =IFERROR(MAX(U27:U31),"") -> 244290 | V38: =IFERROR(MAX(V27:V31),"") -> 0.87980092 | W38: =IFERROR(MAX(W27:W31),"") -> 0.21 | X38: =IFERROR(MAX(X27:X31),"") -> 0.97631993

Sheet AI Comps
A1: AI – COMPARABLE COMPANY ANALYSIS
A2: Comparable Public Companies by Maturity & Industry | Compute Infrastructure + Social Media | $ in Millions
A3: Current-stage anchor = GPU Neoclouds / Infra Hosting • Mature-stage anchor = Social Media. Input cells (blue) to be populated from terminal (CapIQ/Bloomberg).
A5: Name | B5: Ticker | C5: Mkt Cap | D5: Enterprise | E5: LTM | F5: Gross | G5: EBITDA | H5: CapEx / | I5: 3-Yr Ann. | J5: TEV / | K5: TEV / | M5: Power | N5: Rev / | P5: Levered | Q5: Debt | R5: % Debt | S5: Preferred | T5: % Pref | U5: Equity | V5: % Equity | W5: Tax | X5: Unlevered
C6: ($M) | D6: Value ($M) | E6: Revenue ($M) | F6: Margin | G6: Margin | H6: Revenue | I6: Rev Growth | J6: Revenue | K6: EBITDA | M6: (MW) | N6: MW ($M) | P6: Beta | Q6: ($M) | S6: Stock ($M) | U6: Value ($M) | W6: Rate | X6: Beta
A8: TIER 1 – GPU-FIRST NEOCLOUDS (Current-Stage Anchor)
A9: Cerebras Systems, Inc. | B9: NasdaqGS:CBRS | C9: 50000 | D9: 49150 | E9: 510 | F9: 0.39 | G9: -0.14 | H9: 0.75 | I9: 0.76 | J9: =IFERROR(D9/E9,"NM") -> 96.372549 | K9: =IF(OR(G9<=0,E9=0,D9=0),"NM",IF(D9/(E9*G9)>100,"NM",D9/(E9*G9))) -> NM | P9: 2.5 | Q9: 262 | R9: =IFERROR(Q9/(Q9+S9+U9),"") -> 0.0052126855 | S9: 0 | T9: =IFERROR(S9/(Q9+S9+U9),"") -> 0 | U9: 50000 | V9: =IFERROR(U9/(Q9+S9+U9),"") -> 0.99478731 | W9: 0.21 | X9: =IFERROR(P9/(1+(Q9/U9)*(1-W9)+(S9/U9)),"") -> 2.4896937
A10: CoreWeave, Inc. | B10: NasdaqGS:CRWV | C10: 55470 | D10: 88930 | E10: 6230 | F10: -0.29 | G10: -0.29 | H10: 5 | I10: 1.12 | J10: =IFERROR(D10/E10,"NM") -> 14.274478 | K10: =IF(OR(G10<=0,E10=0,D10=0),"NM",IF(D10/(E10*G10)>100,"NM",D10/(E10*G10))) -> NM | M10: 470 | N10: =IFERROR(E10/M10,"NM") -> 13.255319 | P10: 1.8 | Q10: 35150 | R10: =IFERROR(Q10/(Q10+S10+U10),"") -> 0.38788347 | S10: 0 | T10: =IFERROR(S10/(Q10+S10+U10),"") -> 0 | U10: 55470 | V10: =IFERROR(U10/(Q10+S10+U10),"") -> 0.61211653 | W10: 0.21 | X10: =IFERROR(P10/(1+(Q10/U10)*(1-W10)+S10/U10),"") -> 1.1995171
A11: Nebius Group N.V. | B11: NasdaqGS:NBIS | C11: 56000 | D11: 58040 | E11: 878 | F11: 0.45 | G11: 0.45 | H11: 2.5 | I11: 6.84 | J11: =IFERROR(D11/E11,"NM") -> 66.104784 | K11: =IF(OR(G11<=0,E11=0,D11=0),"NM",IF(D11/(E11*G11)>100,"NM",D11/(E11*G11))) -> NM | M11: 300 | N11: =IFERROR(E11/M11,"NM") -> 2.9266667 | P11: 2.8 | Q11: 7800 | R11: =IFERROR(Q11/(Q11+S11+U11),"") -> 0.12225705 | S11: 0 | T11: =IFERROR(S11/(Q11+S11+U11),"") -> 0 | U11: 56000 | V11: =IFERROR(U11/(Q11+S11+U11),"") -> 0.87774295 | W11: 0.25 | X11: =IFERROR(P11/(1+(Q11/U11)*(1-W11)+S11/U11),"") -> 2.5351657
A13: Min: | C13: =IFERROR(MIN(C9:C11),"") -> 50000 | D13: =IFERROR(MIN(D9:D11),"") -> 49150 | E13: =IFERROR(MIN(E9:E11),"") -> 510 | F13: =IFERROR(MIN(F9:F11),"") -> -0.29 | G13: =IFERROR(MIN(G9:G11),"") -> -0.29 | H13: =IFERROR(MIN(H9:H11),"") -> 0.75 | I13: =IFERROR(MIN(I9:I11),"") -> 0.76 | J13: =IFERROR(MIN(J9:J11),"") -> 14.274478 | K13: =IFERROR(_xlfn.AGGREGATE(15,6,K9:K11,1),"NM") -> NM | M13: =IFERROR(MIN(M9:M11),"") -> 300 | N13: =IFERROR(MIN(N9:N11),"") -> 2.9266667 | P13: =IFERROR(MIN(P9:P11),"") -> 1.8 | Q13: =IFERROR(MIN(Q9:Q11),"") -> 262 | R13: =IFERROR(MIN(R9:R11),"") -> 0.0052126855 | S13: =IFERROR(MIN(S9:S11),"") -> 0 | T13: =IFERROR(MIN(T9:T11),"") -> 0 | U13: =IFERROR(MIN(U9:U11),"") -> 50000 | V13: =IFERROR(MIN(V9:V11),"") -> 0.61211653 | W13: =IFERROR(MIN(W9:W11),"") -> 0.21 | X13: =IFERROR(MIN(X9:X11),"") -> 1.1995171
A14: 25th Pctl: | C14: =IFERROR(QUARTILE(C9:C11,1),"") -> 52735 | D14: =IFERROR(QUARTILE(D9:D11,1),"") -> 53595 | E14: =IFERROR(QUARTILE(E9:E11,1),"") -> 694 | F14: =IFERROR(QUARTILE(F9:F11,1),"") -> 0.05 | G14: =IFERROR(QUARTILE(G9:G11,1),"") -> -0.215 | H14: =IFERROR(QUARTILE(H9:H11,1),"") -> 1.625 | I14: =IFERROR(QUARTILE(I9:I11,1),"") -> 0.94 | J14: =IFERROR(QUARTILE(J9:J11,1),"") -> 40.189631 | K14: =IFERROR(_xlfn.AGGREGATE(16,6,K9:K11,0.25),"NM") -> NM | M14: =IFERROR(QUARTILE(M9:M11,1),"") -> 342.5 | N14: =IFERROR(QUARTILE(N9:N11,1),"") -> 5.5088298 | P14: =IFERROR(QUARTILE(P9:P11,1),"") -> 2.15 | Q14: =IFERROR(QUARTILE(Q9:Q11,1),"") -> 4031 | R14: =IFERROR(QUARTILE(R9:R11,1),"") -> 0.063734869 | S14: =IFERROR(QUARTILE(S9:S11,1),"") -> 0 | T14: =IFERROR(QUARTILE(T9:T11,1),"") -> 0 | U14: =IFERROR(QUARTILE(U9:U11,1),"") -> 52735 | V14: =IFERROR(QUARTILE(V9:V11,1),"") -> 0.74492974 | W14: =IFERROR(QUARTILE(W9:W11,1),"") -> 0.21 | X14: =IFERROR(QUARTILE(X9:X11,1),"") -> 1.8446054
A15: Median: | C15: =IFERROR(MEDIAN(C9:C11),"") -> 55470 | D15: =IFERROR(MEDIAN(D9:D11),"") -> 58040 | E15: =IFERROR(MEDIAN(E9:E11),"") -> 878 | F15: =IFERROR(MEDIAN(F9:F11),"") -> 0.39 | G15: =IFERROR(MEDIAN(G9:G11),"") -> -0.14 | H15: =IFERROR(MEDIAN(H9:H11),"") -> 2.5 | I15: =IFERROR(MEDIAN(I9:I11),"") -> 1.12 | J15: =IFERROR(MEDIAN(J9:J11),"") -> 66.104784 | K15: =IFERROR(_xlfn.AGGREGATE(16,6,K9:K11,0.5),"NM") -> NM | M15: =IFERROR(MEDIAN(M9:M11),"") -> 385 | N15: =IFERROR(MEDIAN(N9:N11),"") -> 8.0909929 | P15: =IFERROR(MEDIAN(P9:P11),"") -> 2.5 | Q15: =IFERROR(MEDIAN(Q9:Q11),"") -> 7800 | R15: =IFERROR(MEDIAN(R9:R11),"") -> 0.12225705 | S15: =IFERROR(MEDIAN(S9:S11),"") -> 0 | T15: =IFERROR(MEDIAN(T9:T11),"") -> 0 | U15: =IFERROR(MEDIAN(U9:U11),"") -> 55470 | V15: =IFERROR(MEDIAN(V9:V11),"") -> 0.87774295 | W15: =IFERROR(MEDIAN(W9:W11),"") -> 0.21 | X15: =IFERROR(MEDIAN(X9:X11),"") -> 2.4896937
A16: Mean: | C16: =IFERROR(AVERAGE(C9:C11),"") -> 53823.333 | D16: =IFERROR(AVERAGE(D9:D11),"") -> 65373.333 | E16: =IFERROR(AVERAGE(E9:E11),"") -> 2539.3333 | F16: =IFERROR(AVERAGE(F9:F11),"") -> 0.18333333 | G16: =IFERROR(AVERAGE(G9:G11),"") -> 0.0066666667 | H16: =IFERROR(AVERAGE(H9:H11),"") -> 2.75 | I16: =IFERROR(AVERAGE(I9:I11),"") -> 2.9066667 | J16: =IFERROR(AVERAGE(J9:J11),"") -> 58.91727 | K16: =IFERROR(_xlfn.AGGREGATE(1,6,K9:K11),"NM") -> NM | M16: =IFERROR(AVERAGE(M9:M11),"") -> 385 | N16: =IFERROR(AVERAGE(N9:N11),"") -> 8.0909929 | P16: =IFERROR(AVERAGE(P9:P11),"") -> 2.3666667 | Q16: =IFERROR(AVERAGE(Q9:Q11),"") -> 14404 | R16: =IFERROR(AVERAGE(R9:R11),"") -> 0.1717844 | S16: =IFERROR(AVERAGE(S9:S11),"") -> 0 | T16: =IFERROR(AVERAGE(T9:T11),"") -> 0 | U16: =IFERROR(AVERAGE(U9:U11),"") -> 53823.333 | V16: =IFERROR(AVERAGE(V9:V11),"") -> 0.8282156 | W16: =IFERROR(AVERAGE(W9:W11),"") -> 0.22333333 | X16: =IFERROR(AVERAGE(X9:X11),"") -> 2.0747921
A17: 75th Pctl: | C17: =IFERROR(QUARTILE(C9:C11,3),"") -> 55735 | D17: =IFERROR(QUARTILE(D9:D11,3),"") -> 73485 | E17: =IFERROR(QUARTILE(E9:E11,3),"") -> 3554 | F17: =IFERROR(QUARTILE(F9:F11,3),"") -> 0.42 | G17: =IFERROR(QUARTILE(G9:G11,3),"") -> 0.155 | H17: =IFERROR(QUARTILE(H9:H11,3),"") -> 3.75 | I17: =IFERROR(QUARTILE(I9:I11,3),"") -> 3.98 | J17: =IFERROR(QUARTILE(J9:J11,3),"") -> 81.238666 | K17: =IFERROR(_xlfn.AGGREGATE(16,6,K9:K11,0.75),"NM") -> NM | M17: =IFERROR(QUARTILE(M9:M11,3),"") -> 427.5 | N17: =IFERROR(QUARTILE(N9:N11,3),"") -> 10.673156 | P17: =IFERROR(QUARTILE(P9:P11,3),"") -> 2.65 | Q17: =IFERROR(QUARTILE(Q9:Q11,3),"") -> 21475 | R17: =IFERROR(QUARTILE(R9:R11,3),"") -> 0.25507026 | S17: =IFERROR(QUARTILE(S9:S11,3),"") -> 0 | T17: =IFERROR(QUARTILE(T9:T11,3),"") -> 0 | U17: =IFERROR(QUARTILE(U9:U11,3),"") -> 55735 | V17: =IFERROR(QUARTILE(V9:V11,3),"") -> 0.93626513 | W17: =IFERROR(QUARTILE(W9:W11,3),"") -> 0.23 | X17: =IFERROR(QUARTILE(X9:X11,3),"") -> 2.5124297
A18: Max: | C18: =IFERROR(MAX(C9:C11),"") -> 56000 | D18: =IFERROR(MAX(D9:D11),"") -> 88930 | E18: =IFERROR(MAX(E9:E11),"") -> 6230 | F18: =IFERROR(MAX(F9:F11),"") -> 0.45 | G18: =IFERROR(MAX(G9:G11),"") -> 0.45 | H18: =IFERROR(MAX(H9:H11),"") -> 5 | I18: =IFERROR(MAX(I9:I11),"") -> 6.84 | J18: =IFERROR(MAX(J9:J11),"") -> 96.372549 | K18: =IFERROR(_xlfn.AGGREGATE(14,6,K9:K11,1),"NM") -> NM | M18: =IFERROR(MAX(M9:M11),"") -> 470 | N18: =IFERROR(MAX(N9:N11),"") -> 13.255319 | P18: =IFERROR(MAX(P9:P11),"") -> 2.8 | Q18: =IFERROR(MAX(Q9:Q11),"") -> 35150 | R18: =IFERROR(MAX(R9:R11),"") -> 0.38788347 | S18: =IFERROR(MAX(S9:S11),"") -> 0 | T18: =IFERROR(MAX(T9:T11),"") -> 0 | U18: =IFERROR(MAX(U9:U11),"") -> 56000 | V18: =IFERROR(MAX(V9:V11),"") -> 0.99478731 | W18: =IFERROR(MAX(W9:W11),"") -> 0.25 | X18: =IFERROR(MAX(X9:X11),"") -> 2.5351657
A20: TIER 2 – INFRASTRUCTURE-FIRST HOSTING (No GPUs) | C20: Mkt | D20: Enterprise
A21: WhiteFiber, Inc. | B21: NasdaqCM:WYFI | C21: 898 | D21: 1070 | E21: 84 | F21: 0.45 | G21: -0.25 | H21: 2 | I21: 0.79 | J21: =IFERROR(D21/E21,"NM") -> 12.738095 | K21: =IF(OR(G21<=0,E21=0,D21=0),"NM",IF(D21/(E21*G21)>100,"NM",D21/(E21*G21))) -> NM | M21: 54 | N21: 1.2 | P21: 1.5 | Q21: 230 | R21: =IFERROR(Q21/(Q21+S21+U21),"") -> 0.20390071 | S21: 0 | T21: =IFERROR(S21/(Q21+S21+U21),"") -> 0 | U21: 898 | V21: =IFERROR(U21/(Q21+S21+U21),"") -> 0.79609929 | W21: 0.21 | X21: =IFERROR(P21/(1+(Q21/U21)*(1-W21)+S21/U21),"") -> 1.2475688
A22: IREN Limited | B22: NasdaqGS:IREN | C22: 16000 | D22: 17750 | E22: 757 | F22: 0.5 | G22: -0.33 | H22: 5 | I22: 1.07 | J22: =IFERROR(D22/E22,"NM") -> 23.44782 | K22: =IF(OR(G22<=0,E22=0,D22=0),"NM",IF(D22/(E22*G22)>100,"NM",D22/(E22*G22))) -> NM | M22: 480 | N22: 1.58 | P22: 4.18 | Q22: 3960 | R22: =IFERROR(Q22/(Q22+S22+U22),"") -> 0.19839679 | S22: 0 | T22: =IFERROR(S22/(Q22+S22+U22),"") -> 0 | U22: 16000 | V22: =IFERROR(U22/(Q22+S22+U22),"") -> 0.80160321 | W22: 0.21 | X22: =IFERROR(P22/(1+(Q22/U22)*(1-W22)+S22/U22),"") -> 3.4963719
A23: Applied Digital Corp. | B23: NasdaqGS:APLD | C23: 11320 | D23: 13235 | E23: 264 | F23: 0.5 | G23: -0.48 | H23: 4 | I23: 0.52 | J23: =IFERROR(D23/E23,"NM") -> 50.132576 | K23: =IF(OR(G23<=0,E23=0,D23=0),"NM",IF(D23/(E23*G23)>100,"NM",D23/(E23*G23))) -> NM | M23: 300 | N23: 0.88 | P23: 7.34 | Q23: 2610 | R23: =IFERROR(Q23/(Q23+S23+U23),"") -> 0.1873654 | S23: 0 | T23: =IFERROR(S23/(Q23+S23+U23),"") -> 0 | U23: 11320 | V23: =IFERROR(U23/(Q23+S23+U23),"") -> 0.8126346 | W23: 0.21 | X23: =IFERROR(P23/(1+(Q23/U23)*(1-W23)+S23/U23),"") -> 6.2090436
A24: TeraWulf Inc. | B24: NasdaqCM:WULF | C24: 11000 | D24: 14930 | E24: 168 | F24: 0.55 | G24: -3.93 | H24: 5 | I24: 0.73 | J24: =IFERROR(D24/E24,"NM") -> 88.869048 | K24: =IF(OR(G24<=0,E24=0,D24=0),"NM",IF(D24/(E24*G24)>100,"NM",D24/(E24*G24))) -> NM | M24: 480 | N24: 0.35 | P24: 4.3 | Q24: 5200 | R24: =IFERROR(Q24/(Q24+S24+U24),"") -> 0.32098765 | S24: 0 | T24: =IFERROR(S24/(Q24+S24+U24),"") -> 0 | U24: 11000 | V24: =IFERROR(U24/(Q24+S24+U24),"") -> 0.67901235 | W24: 0.21 | X24: =IFERROR(P24/(1+(Q24/U24)*(1-W24)+S24/U24),"") -> 3.1307916
A25: Cipher Mining Inc. | B25: NasdaqGS:CIFR | C25: 10620 | D25: 10440 | E25: 224 | F25: 0.637 | G25: -3.67 | H25: 3 | I25: 0.65 | J25: =IFERROR(D25/E25,"NM") -> 46.607143 | K25: =IF(OR(G25<=0,E25=0,D25=0),"NM",IF(D25/(E25*G25)>100,"NM",D25/(E25*G25))) -> NM | M25: 495 | N25: 0.45 | P25: 2.89 | Q25: 500 | R25: =IFERROR(Q25/(Q25+S25+U25),"") -> 0.044964029 | S25: 0 | T25: =IFERROR(S25/(Q25+S25+U25),"") -> 0 | U25: 10620 | V25: =IFERROR(U25/(Q25+S25+U25),"") -> 0.95503597 | W25: 0.21 | X25: =IFERROR(P25/(1+(Q25/U25)*(1-W25)+S25/U25),"") -> 2.786364
A27: Min: | C27: =IFERROR(MIN(C21:C25),"") -> 898 | D27: =IFERROR(MIN(D21:D25),"") -> 1070 | E27: =IFERROR(MIN(E21:E25),"") -> 84 | F27: =IFERROR(MIN(F21:F25),"") -> 0.45 | G27: =IFERROR(MIN(G21:G25),"") -> -3.93 | H27: =IFERROR(MIN(H21:H25),"") -> 2 | I27: =IFERROR(MIN(I21:I25),"") -> 0.52 | J27: =IFERROR(MIN(J21:J25),"") -> 12.738095 | K27: =IFERROR(_xlfn.AGGREGATE(15,6,K21:K25,1),"NM") -> NM | M27: =IFERROR(MIN(M21:M25),"") -> 54 | N27: =IFERROR(MIN(N21:N25),"") -> 0.35 | P27: =IFERROR(MIN(P21:P25),"") -> 1.5 | Q27: =IFERROR(MIN(Q21:Q25),"") -> 230 | R27: =IFERROR(MIN(R21:R25),"") -> 0.044964029 | S27: =IFERROR(MIN(S21:S25),"") -> 0 | T27: =IFERROR(MIN(T21:T25),"") -> 0 | U27: =IFERROR(MIN(U21:U25),"") -> 898 | V27: =IFERROR(MIN(V21:V25),"") -> 0.67901235 | W27: =IFERROR(MIN(W21:W25),"") -> 0.21 | X27: =IFERROR(MIN(X21:X25),"") -> 1.2475688
A28: 25th Pctl: | C28: =IFERROR(QUARTILE(C21:C25,1),"") -> 10620 | D28: =IFERROR(QUARTILE(D21:D25,1),"") -> 10440 | E28: =IFERROR(QUARTILE(E21:E25,1),"") -> 168 | F28: =IFERROR(QUARTILE(F21:F25,1),"") -> 0.5 | G28: =IFERROR(QUARTILE(G21:G25,1),"") -> -3.67 | H28: =IFERROR(QUARTILE(H21:H25,1),"") -> 3 | I28: =IFERROR(QUARTILE(I21:I25,1),"") -> 0.65 | J28: =IFERROR(QUARTILE(J21:J25,1),"") -> 23.44782 | K28: =IFERROR(_xlfn.AGGREGATE(16,6,K21:K25,0.25),"NM") -> NM | M28: =IFERROR(QUARTILE(M21:M25,1),"") -> 300 | N28: =IFERROR(QUARTILE(N21:N25,1),"") -> 0.45 | P28: =IFERROR(QUARTILE(P21:P25,1),"") -> 2.89 | Q28: =IFERROR(QUARTILE(Q21:Q25,1),"") -> 500 | R28: =IFERROR(QUARTILE(R21:R25,1),"") -> 0.1873654 | S28: =IFERROR(QUARTILE(S21:S25,1),"") -> 0 | T28: =IFERROR(QUARTILE(T21:T25,1),"") -> 0 | U28: =IFERROR(QUARTILE(U21:U25,1),"") -> 10620 | V28: =IFERROR(QUARTILE(V21:V25,1),"") -> 0.79609929 | W28: =IFERROR(QUARTILE(W21:W25,1),"") -> 0.21 | X28: =IFERROR(QUARTILE(X21:X25,1),"") -> 2.786364
A29: Median: | C29: =IFERROR(MEDIAN(C21:C25),"") -> 11000 | D29: =IFERROR(MEDIAN(D21:D25),"") -> 13235 | E29: =IFERROR(MEDIAN(E21:E25),"") -> 224 | F29: =IFERROR(MEDIAN(F21:F25),"") -> 0.5 | G29: =IFERROR(MEDIAN(G21:G25),"") -> -0.48 | H29: =IFERROR(MEDIAN(H21:H25),"") -> 4 | I29: =IFERROR(MEDIAN(I21:I25),"") -> 0.73 | J29: =IFERROR(MEDIAN(J21:J25),"") -> 46.607143 | K29: =IFERROR(_xlfn.AGGREGATE(16,6,K21:K25,0.5),"NM") -> NM | M29: =IFERROR(MEDIAN(M21:M25),"") -> 480 | N29: =IFERROR(MEDIAN(N21:N25),"") -> 0.88 | P29: =IFERROR(MEDIAN(P21:P25),"") -> 4.18 | Q29: =IFERROR(MEDIAN(Q21:Q25),"") -> 2610 | R29: =IFERROR(MEDIAN(R21:R25),"") -> 0.19839679 | S29: =IFERROR(MEDIAN(S21:S25),"") -> 0 | T29: =IFERROR(MEDIAN(T21:T25),"") -> 0 | U29: =IFERROR(MEDIAN(U21:U25),"") -> 11000 | V29: =IFERROR(MEDIAN(V21:V25),"") -> 0.80160321 | W29: =IFERROR(MEDIAN(W21:W25),"") -> 0.21 | X29: =IFERROR(MEDIAN(X21:X25),"") -> 3.1307916
A30: Mean: | C30: =IFERROR(AVERAGE(C21:C25),"") -> 9967.6 | D30: =IFERROR(AVERAGE(D21:D25),"") -> 11485 | E30: =IFERROR(AVERAGE(E21:E25),"") -> 299.4 | F30: =IFERROR(AVERAGE(F21:F25),"") -> 0.5274 | G30: =IFERROR(AVERAGE(G21:G25),"") -> -1.732 | H30: =IFERROR(AVERAGE(H21:H25),"") -> 3.8 | I30: =IFERROR(AVERAGE(I21:I25),"") -> 0.752 | J30: =IFERROR(AVERAGE(J21:J25),"") -> 44.358936 | K30: =IFERROR(_xlfn.AGGREGATE(1,6,K21:K25),"NM") -> NM | M30: =IFERROR(AVERAGE(M21:M25),"") -> 361.8 | N30: =IFERROR(AVERAGE(N21:N25),"") -> 0.892 | P30: =IFERROR(AVERAGE(P21:P25),"") -> 4.042 | Q30: =IFERROR(AVERAGE(Q21:Q25),"") -> 2500 | R30: =IFERROR(AVERAGE(R21:R25),"") -> 0.19112292 | S30: =IFERROR(AVERAGE(S21:S25),"") -> 0 | T30: =IFERROR(AVERAGE(T21:T25),"") -> 0 | U30: =IFERROR(AVERAGE(U21:U25),"") -> 9967.6 | V30: =IFERROR(AVERAGE(V21:V25),"") -> 0.80887708 | W30: =IFERROR(AVERAGE(W21:W25),"") -> 0.21 | X30: =IFERROR(AVERAGE(X21:X25),"") -> 3.374028
A31: 75th Pctl: | C31: =IFERROR(QUARTILE(C21:C25,3),"") -> 11320 | D31: =IFERROR(QUARTILE(D21:D25,3),"") -> 14930 | E31: =IFERROR(QUARTILE(E21:E25,3),"") -> 264 | F31: =IFERROR(QUARTILE(F21:F25,3),"") -> 0.55 | G31: =IFERROR(QUARTILE(G21:G25,3),"") -> -0.33 | H31: =IFERROR(QUARTILE(H21:H25,3),"") -> 5 | I31: =IFERROR(QUARTILE(I21:I25,3),"") -> 0.79 | J31: =IFERROR(QUARTILE(J21:J25,3),"") -> 50.132576 | K31: =IFERROR(_xlfn.AGGREGATE(16,6,K21:K25,0.75),"NM") -> NM | M31: =IFERROR(QUARTILE(M21:M25,3),"") -> 480 | N31: =IFERROR(QUARTILE(N21:N25,3),"") -> 1.2 | P31: =IFERROR(QUARTILE(P21:P25,3),"") -> 4.3 | Q31: =IFERROR(QUARTILE(Q21:Q25,3),"") -> 3960 | R31: =IFERROR(QUARTILE(R21:R25,3),"") -> 0.20390071 | S31: =IFERROR(QUARTILE(S21:S25,3),"") -> 0 | T31: =IFERROR(QUARTILE(T21:T25,3),"") -> 0 | U31: =IFERROR(QUARTILE(U21:U25,3),"") -> 11320 | V31: =IFERROR(QUARTILE(V21:V25,3),"") -> 0.8126346 | W31: =IFERROR(QUARTILE(W21:W25,3),"") -> 0.21 | X31: =IFERROR(QUARTILE(X21:X25,3),"") -> 3.4963719
A32: Max: | C32: =IFERROR(MAX(C21:C25),"") -> 16000 | D32: =IFERROR(MAX(D21:D25),"") -> 17750 | E32: =IFERROR(MAX(E21:E25),"") -> 757 | F32: =IFERROR(MAX(F21:F25),"") -> 0.637 | G32: =IFERROR(MAX(G21:G25),"") -> -0.25 | H32: =IFERROR(MAX(H21:H25),"") -> 5 | I32: =IFERROR(MAX(I21:I25),"") -> 1.07 | J32: =IFERROR(MAX(J21:J25),"") -> 88.869048 | K32: =IFERROR(_xlfn.AGGREGATE(14,6,K21:K25,1),"NM") -> NM | M32: =IFERROR(MAX(M21:M25),"") -> 495 | N32: =IFERROR(MAX(N21:N25),"") -> 1.58 | P32: =IFERROR(MAX(P21:P25),"") -> 7.34 | Q32: =IFERROR(MAX(Q21:Q25),"") -> 5200 | R32: =IFERROR(MAX(R21:R25),"") -> 0.32098765 | S32: =IFERROR(MAX(S21:S25),"") -> 0 | T32: =IFERROR(MAX(T21:T25),"") -> 0 | U32: =IFERROR(MAX(U21:U25),"") -> 16000 | V32: =IFERROR(MAX(V21:V25),"") -> 0.95503597 | W32: =IFERROR(MAX(W21:W25),"") -> 0.21 | X32: =IFERROR(MAX(X21:X25),"") -> 6.2090436
A34: TIER 3 – SOCIAL MEDIA (Mature-Stage Monetization Anchor) | C34: Mkt | D34: Enterprise
A35: Snap Inc. | B35: NYSE:SNAP | C35: 9550 | D35: 11700 | E35: 5900 | F35: 0.55 | G35: 0.1877 | H35: 0.038 | I35: 0.12 | J35: =IFERROR(D35/E35,"NM") -> 1.9830508 | K35: =IF(OR(G35<=0,E35=0,D35=0),"NM",IF(D35/(E35*G35)>100,"NM",D35/(E35*G35))) -> 10.565002 | M35: 453 | N35: 11.7 | P35: 1.05 | Q35: 3536 | R35: =IFERROR(Q35/(Q35+S35+U35),"") -> 0.27021244 | S35: 0 | T35: =IFERROR(S35/(Q35+S35+U35),"") -> 0 | U35: 9550 | V35: =IFERROR(U35/(Q35+S35+U35),"") -> 0.72978756 | W35: 0.21 | X35: =IFERROR(P35/(1+(Q35/U35)*(1-W35)+S35/U35),"") -> 0.81237483
A36: Pinterest, Inc. | B36: NYSE:PINS | C36: 11580 | D36: 11480 | E36: 4370 | F36: 0.79 | G36: 0.2905 | H36: 0.03 | I36: 0.15 | J36: =IFERROR(D36/E36,"NM") -> 2.6270023 | K36: =IF(OR(G36<=0,E36=0,D36=0),"NM",IF(D36/(E36*G36)>100,"NM",D36/(E36*G36))) -> 9.0430371 | M36: 570 | N36: 5.3 | P36: 0.92 | Q36: 262 | R36: =IFERROR(Q36/(Q36+S36+U36),"") -> 0.022124641 | S36: 0 | T36: =IFERROR(S36/(Q36+S36+U36),"") -> 0 | U36: 11580 | V36: =IFERROR(U36/(Q36+S36+U36),"") -> 0.97787536 | W36: 0.21 | X36: =IFERROR(P36/(1+(Q36/U36)*(1-W36)+S36/U36),"") -> 0.90384475
A37: Reddit, Inc. | B37: NYSE:RDDT | C37: 35400 | D37: 32650 | E37: 2474 | F37: 0.91 | G37: 0.38 | H37: 0.025 | I37: 0.69 | J37: =IFERROR(D37/E37,"NM") -> 13.197251 | K37: =IF(OR(G37<=0,E37=0,D37=0),"NM",IF(D37/(E37*G37)>100,"NM",D37/(E37*G37))) -> 34.729609 | M37: 97 | N37: 25.5 | P37: 0.8 | Q37: 17 | R37: =IFERROR(Q37/(Q37+S37+U37),"") -> 0.00047999548 | S37: 0 | T37: =IFERROR(S37/(Q37+S37+U37),"") -> 0 | U37: 35400 | V37: =IFERROR(U37/(Q37+S37+U37),"") -> 0.99952 | W37: 0.21 | X37: =IFERROR(P37/(1+(Q37/U37)*(1-W37)+S37/U37),"") -> 0.79969661
