Workbook

Sheet Exec Summary
A1: Space Exploration Technologies Corp. (SpaceX) | $SPCX | Pre-IPO Valuation Executive Summary
A2: ="Prepared: "&TEXT(TODAY(),"d-mmm-yyyy")&" | Source: SpaceX S-1 (Filed 20-May-2026) " -> Prepared: 11-Jun-2026 | Source: SpaceX S-1 (Filed 20-May-2026)
A4: INVESTMENT THESIS
A6: SpaceX is pursuing an IPO at $135/share, implying a fully diluted market cap of ~$1.75T. The company operates three segments:
A7: (1) Connectivity (Starlink) — satellite broadband, ~60% of FY2025 revenue, highest margin segment growing 50%+ YoY
A8: (2) Space (Launch + Starship) — launch services and government contracts, ~22% of revenue, steady growth anchored by Falcon 9 cadence
A9: (3) AI (X / xAI / Grok) — social media and AI compute infrastructure, ~17% of revenue, pre-profit but scaling rapidly
A11: Our 3-segment SOTP DCF analysis uses 20-year explicit forecasts per segment with comp-driven WACCs and terminal values.
A12: Two methodologies are applied: (1) Gordon Growth / EV-Revenue and (2) Exit Multiple / Gordon cross-check.
A14: VALUATION CONCLUSION
B15: Method 1 ¹ | C15: Method 2 ² | D15: Average | F15: Notes
A16: Total Enterprise Value ($M) | B16: =SOTP!B11 -> 647687.64 | C16: =SOTP!C11 -> 501724.74 | D16: =SOTP!D11 -> 574706.19 | F16: ¹ Gordon Growth (Conn/Space) + EV/Revenue (AI)
A17: Equity Value ($M) | B17: =SOTP!B20 -> 649148.64 | C17: =SOTP!C20 -> 503185.74 | D17: =SOTP!D20 -> 576167.19 | F17: ² Exit Multiple (Conn/Space) + Gordon (AI cross-check)
A18: Implied Price / Share (fully diluted) | B18: =B17/SOTP!B25 -> 50.08863 | C18: =C17/SOTP!C25 -> 38.82606 | D18: =D17/SOTP!D25 -> 44.457345 | F18: Fully diluted: 12,960M shares (preferred conversion + xAI merger + RSUs + IPO)
A19: IPO Reference Price | B19: =COVER!B5 -> 135 | C19: =B19 -> 135 | D19: =B19 -> 135
A20: Upside / (Downside) to IPO | B20: =B18/B19-1 -> -0.62897311 | C20: =C18/C19-1 -> -0.71239956 | D20: =D18/D19-1 -> -0.67068634
A21: Shares Outstanding — Fully Diluted (M) | B21: =SOTP!B25 -> 12960
A23: SEGMENT VALUATION BREAKDOWN
A25: Segment | B25: Avg EV ($M) | C25: % of SOTP | D25: WACC | E25: Tg | F25: Primary Methodology
A26: Connectivity (Starlink) | B26: =SOTP!D8 -> 436046.2 | C26: =SOTP!E8 -> 0.7587289 | D26: =WACC!B47 -> 0.075445353 | E26: =WACC!C47 -> 0.03 | F26: Gordon Growth perpetuity + EV/EBITDA exit cross-check
A27: Space (Launch + Starship) | B27: =SOTP!D9 -> 91383.931 | C27: =SOTP!E9 -> 0.15900983 | D27: =WACC!B48 -> 0.079328832 | E27: =WACC!C48 -> 0.025 | F27: Gordon Growth perpetuity + EV/EBITDA exit cross-check
A28: AI (X / xAI / Grok) | B28: =SOTP!D10 -> 47276.062 | C28: =SOTP!E10 -> 0.082261271 | D28: =WACC!B49 -> 0.11585358 | E28: =WACC!C49 -> 0.035 | F28: EV/Revenue multiple (primary) — Gordon distorts on loss-making FCF
A29: Total SOTP | B29: =SOTP!D11 -> 574706.19 | C29: =SOTP!E11 -> 1
A31: KEY ASSUMPTIONS (Base Case)
A33: Item | B33: Connectivity | C33: Space | D33: AI | F33: Source
A34: Forecast Horizon | B34: 20 years | C34: 20 years | D34: 20 years | F34: DCF sheet assumptions
A35: WACC | B35: =WACC!B47 -> 0.075445353 | C35: =WACC!B48 -> 0.079328832 | D35: =WACC!B49 -> 0.11585358 | F35: Comp-driven; WACC sheet
A36: Terminal Growth Rate | B36: =WACC!C47 -> 0.03 | C36: =WACC!C48 -> 0.025 | D36: =WACC!C49 -> 0.035 | F36: WACC sheet
A37: Risk-Free Rate | B37: =WACC!B6 -> 0.0435 | F37: 10Y UST, Jun 2026
A38: Equity Risk Premium | B38: =WACC!B7 -> 0.055 | F38: Damodaran implied ERP, Jan 2026
A39: Tax Rate | B39: =WACC!B8 -> 0.21 | F39: US statutory; large NOL carryforwards
A41: FY2025 ACTUALS (S-1 Source)
A43: Metric | B43: FY2025 | C43: YoY | F43: Note
A44: Total Revenue ($M) | B44: =SOTP!D38 -> 18674 | C44: =SOTP!D38/SOTP!C38-1 -> 0.33242954 | F44: Consolidated — 3 segments
A45: Connectivity | B45: =SOTP!D39 -> 11387 | C45: =SOTP!D39/SOTP!C39-1 -> 0.49848664 | F45: 60.9% of total; 63% EBITDA margin
A46: Space | B46: =SOTP!D40 -> 4086 | C46: =SOTP!D40/SOTP!C40-1 -> 0.076396207 | F46: 21.9% of total; Falcon 9 cadence + Starship
A47: AI | B47: =SOTP!D41 -> 3201 | C47: =SOTP!D41/SOTP!C41-1 -> 0.22175573 | F47: 17.1% of total; X ads + xAI compute
A48: Net Income ($M) | B48: =SOTP!D44 -> -4937 | F48: AI segment losses dominate; R&D $8.6B
A49: Operating Cash Flow ($M) | B49: =SOTP!D43 -> 6785 | F49: Cash-generative despite heavy capex cycle
A50: Total Capex ($M) | B50: =SOTP!D42 -> -20737 | F50: AI infra $12.7B = 61% of total capex
A51: Connectivity EBITDA Margin | B51: =SOTP!D45 -> 0.629 | F51: Up from 46.2% in FY2024 — scale leverage
A53: KEY RISKS & SENSITIVITIES
A55: Sensitivity Range (SOTP, fully diluted):
A56: Method 1 (Gordon + EV/Rev): | B56: =B18 -> 50.08863 | C56: per share
A57: Method 2 (Exit Mult + Gordon): | B57: =C18 -> 38.82606 | C57: per share
A58: WACC sensitivity range (±2% Conn WACC): | B58: =TEXT(MIN(SOTP!C52:E56),"$#,##0")&" – "&TEXT(MAX(SOTP!C52:E56),"$#,##0") -> $34 – $89 | C58: per share (Method 1)
A60: Risk | C60: Impact | E60: Segment
A61: AI capex burn exceeds forecasts; xAI margin ramp delayed | C61: High — AI is 45% of avg SOTP EV | E61: AI
A62: Starlink subscriber growth stalls; enterprise adoption slower than modelled | C62: High — Conn is 46% of avg SOTP EV | E62: Connectivity
A63: Regulatory / spectrum risk; international market access restrictions | C63: Medium — affects both Conn & Space | E63: Conn / Space
A64: Method 1 vs Method 2 divergence ($184 vs $56) flags terminal-value sensitivity | C64: High — 3.3x range in implied price | E64: All
A65: Dual-class + Musk governance concentration; key-person dependence | C65: Medium — discount to intrinsic value | E65: All
A66: Starship development delays or cost overruns; launch cadence miss | C66: Medium — capex normalisation thesis | E66: Space
A68: MODEL MAP
A70: Sheet | C70: Purpose
A71: COVER | C71: IPO price input, valuation summary dashboard, scenario selector, upside/downside
A72: SOTP | C72: Sum-of-the-parts roll-up, EV bridge, implied share price, WACC sensitivity tables
A73: Conn DCF | C73: Connectivity (Starlink) 20-year segment DCF — IS, FCF, Gordon + exit multiple
A74: Space DCF | C74: Space (Launch + Starship) 20-year segment DCF — IS, FCF, Gordon + exit multiple
A75: AI DCF | C75: AI (X/xAI/Grok) 20-year segment DCF — IS, FCF, EV/Revenue primary + Gordon cross-check
A76: WACC | C76: Comp-driven betas, CAPM cost of equity, segment WACCs, capital structure
A77: Ratios | C77: Historical financial ratios — profitability, leverage, liquidity, efficiency
A78: Conn/Space/AI Comps | C78: Comparable company data for each segment — trading multiples, betas, benchmarking
A79: Actuals | C79: FY2023–FY2025 actual financials by segment (source: S-1)
A80: Historicals | C80: Extended historical data — balance sheet, cash flow, segment detail from S-1
A82: All financial data sourced from SpaceX S-1 (SEC EDGAR, filed 20-May-2026). Comparable company data from public filings.

Sheet COVER
A1: Space Exploration Technologies Corp. (SpaceX) | $SPCX | Sum-of-the-Parts DCF Valuation
A2: 3-Segment SOTP (Connectivity + Space + AI) | 10-Year Explicit DCF | S-1 Filed May 20, 2026 | $ in Millions (except per share)
A4: ① ENTER PRICE TO SEE UPSIDE / DOWNSIDE
A5: Current / IPO Share Price ($) | B5: 135 | C5: ← Enter the IPO / current trading price here
A7: ② VALUATION SUMMARY (Base Case)
B8: Gordon Growth | C8: Exit Multiple | D8: Average | H8: Note
A9: Total SOTP Enterprise Value ($M) | B9: =SOTP!B11 -> 647687.64 | C9: =SOTP!C11 -> 501724.74 | D9: =SOTP!D11 -> 574706.19
A10: (+) Net Cash (Cash − Total Debt) ($M) | B10: =SOTP!B16+SOTP!B17 -> 1461 | C10: =SOTP!C16+SOTP!C17 -> 1461 | D10: =SOTP!D16+SOTP!D17 -> 1461
A11: Connectivity Segment EV ($M) | B11: =SOTP!B8 -> 524537.59 | C11: =SOTP!C8 -> 347554.8 | D11: =SOTP!D8 -> 436046.2 | H11: 83% of avg SOTP EV
A12: Space Segment EV ($M) | B12: =SOTP!B9 -> 85853.059 | C12: =SOTP!C9 -> 96914.802 | D12: =SOTP!D9 -> 91383.931 | H12: 9% of avg SOTP EV
A13: AI Segment EV ($M) | B13: =SOTP!B10 -> 37296.99 | C13: =SOTP!C10 -> 57255.133 | D13: =SOTP!D10 -> 47276.062 | H13: 8% of avg SOTP EV — wide range
A14: Equity Value ($M) | B14: =SOTP!B20 -> 649148.64 | C14: =SOTP!C20 -> 503185.74 | D14: =SOTP!D20 -> 576167.19 | H14: After debt, cash, pref conversion
A16: Implied Share Price | B16: Gordon Growth | C16: Exit Multiple | D16: Average | H16: Shares Basis
A17: Basic — Common only (5,798M) | B17: =SOTP!B26 -> 111.96079 | C17: =SOTP!C26 -> 86.786088 | D17: =SOTP!D26 -> 99.373437 | H17: Understates: excludes converted pref + xAI shares
A18: Fully Diluted, Post-IPO (12,960M) | B18: =SOTP!B27 -> 50.08863 | C18: =SOTP!C27 -> 38.82606 | D18: =SOTP!D27 -> 44.457345 | H18: ★ Reconciled to actual $135 IPO / $1.75T — primary metric
A20: ③ UPSIDE / (DOWNSIDE) vs. ENTERED PRICE (Fully-Diluted shares — primary)
B21: Gordon Growth | C21: Exit Multiple | D21: Average
A22: Our Implied Price (Fully-Diluted) | B22: =B18 -> 50.08863 | C22: =C18 -> 38.82606 | D22: =D18 -> 44.457345
A23: Current / IPO Price | B23: =IF(B5="","—",B5) -> 135 | C23: =IF(B5="","—",B5) -> 135 | D23: =IF(B5="","—",B5) -> 135
A24: Implied Upside / (Downside) | B24: =IF(B5="","← Enter price",(B18/B5)-1) -> -0.62897311 | C24: =IF(B5="","← Enter price",(C18/B5)-1) -> -0.71239956 | D24: =IF(B5="","← Enter price",(D18/B5)-1) -> -0.67068634
A26: ④ SCENARIO SELECTORS (1=Bear, 2=Base, 3=Bull — changes all 3 segment DCFs simultaneously)
A27: Segment | B27: Scenario (1/2/3) | C27: Selected | D27: WACC | E27: Terminal Growth (Base)
A28: Connectivity (Starlink) | B28: 2 | C28: =IF(B28=1,"◀ BEAR",IF(B28=2,"◀ BASE","◀ BULL")) -> ◀ BASE | D28: =WACC!B43 -> 0.075445353 | E28: =WACC!C47 -> 0.03
A29: Space (Launch + Starship) | B29: 2 | C29: =IF(B29=1,"◀ BEAR",IF(B29=2,"◀ BASE","◀ BULL")) -> ◀ BASE | D29: =WACC!C43 -> 0.079328832 | E29: =WACC!C48 -> 0.025
A30: AI (X / xAI / Grok) | B30: 2 | C30: =IF(B30=1,"◀ BEAR",IF(B30=2,"◀ BASE","◀ BULL")) -> ◀ BASE | D30: =WACC!D43 -> 0.11585358 | E30: =WACC!C49 -> 0.035
A31: ✓ Set scenarios here (B28:B30). 1=Bear, 2=Base, 3=Bull. Segment tabs follow automatically — whole valuation controlled from this page.
A33: ⑤ VALUATION SUMMARY (Implied Price/Share, Basic | Selected Scenario)
A34: Method | B34: Per Share (Basic) | H34: Note
A35: Gordon Growth (Perpetuity) | B35: =SOTP!B26 -> 111.96079 | C35: =SOTP!B26 -> 111.96079 | D35: =SOTP!B26 -> 111.96079 | H35: Changes with Scenario Selector (B28:B30 above)
A36: Exit Multiple | B36: =SOTP!C26 -> 86.786088 | C36: =SOTP!C26 -> 86.786088 | D36: =SOTP!C26 -> 86.786088
A37: Average (Gordon & Exit) | B37: =SOTP!D26 -> 99.373437 | C37: =SOTP!D26 -> 99.373437 | D37: =SOTP!D26 -> 99.373437
A39: ⑥ SENSITIVITY: Implied Price/Share (Fully-Diluted) — Connectivity WACC vs. Terminal Growth Rate (Base Case)
A40: WACC \ Term. Growth | B40: =SOTP!C51 -> 0.02 | C40: =SOTP!D51 -> 0.025 | D40: =SOTP!E51 -> 0.03 | E40: =SOTP!F51 -> 0.035 | F40: =SOTP!G51 -> 0.04
A41: =SOTP!B52 -> 0.055445353 | B41: =SOTP!C52 -> 72.539151 | C41: =SOTP!D52 -> 79.266728 | D41: =SOTP!E52 -> 88.638238 | E41: =SOTP!F52 -> 102.59343 | F41: =SOTP!G52 -> 125.58384
A42: =SOTP!B53 -> 0.065445353 | B42: =SOTP!C53 -> 56.245372 | C42: =SOTP!D53 -> 59.562907 | D42: =SOTP!E53 -> 63.816399 | E42: =SOTP!F53 -> 69.466983 | F42: =SOTP!G53 -> 77.33824
A43: =SOTP!B54 -> 0.075445353 | B43: =SOTP!C54 -> 46.016783 | C43: =SOTP!D54 -> 47.850912 | D43: =SOTP!E54 -> 50.08863 | E43: =SOTP!F54 -> 52.879617 | F43: =SOTP!G54 -> 56.458011
A44: =SOTP!B55 -> 0.085445353 | B44: =SOTP!C55 -> 39.0546 | C44: =SOTP!D55 -> 40.147326 | D44: =SOTP!E55 -> 41.437134 | E44: =SOTP!F55 -> 42.982626 | F44: =SOTP!G55 -> 44.868195
A45: =SOTP!B56 -> 0.095445353 | B45: =SOTP!C56 -> 34.046068 | C45: =SOTP!D56 -> 34.732484 | D45: =SOTP!E56 -> 35.523783 | E45: =SOTP!F56 -> 36.445995 | F45: =SOTP!G56 -> 37.534534
A48: ⑦ KEY SEGMENT FINANCIALS (FY2025 Actuals | Source: SpaceX S-1)
A49: Metric ($M) | B49: FY2023A | C49: FY2024A | D49: FY2025A | E49: Q1 2026A
A50: Total Revenue | C50: 14015 | D50: 18674 | E50: 4694
A51: Connectivity Revenue | B51: 3869 | C51: 7599 | D51: 11387 | E51: 3257
A52: Space Revenue | B52: 3557 | C52: 3796 | D52: 4086 | E52: 619
A53: AI Revenue | B53: 2961 | C53: 2620 | D53: 3201 | E53: 818
A54: Connectivity Op. Income | B54: 469 | C54: 2006 | D54: 4423 | E54: 1188
A55: Space Op. Income | B55: -1 | C55: 21 | D55: -657 | E55: -662
A56: AI Op. Income | B56: -3973 | C56: -1561 | D56: -6355 | E56: -2469
A57: Total Operating Cash Flow | B57: 4520 | C57: 5776 | D57: 6785
A58: Total Capex | B58: -4415 | C58: -11163 | D58: -20737 | E58: -10107
A59: Net Income (Loss) | B59: -4628 | C59: 791 | D59: -4937 | E59: -4276
A62: ⑧ RECONCILIATION BRIDGE — Intrinsic Value → Market Price ($B)
A63: Layer | B63: Value ($B) | C63: Cumulative ($B) | D63: Target Mkt Val ($B) | H63: Note
A64: Our DCF Intrinsic Equity (avg) | B64: =SOTP!D20/1000 -> 576.16719 | C64: =B64 -> 576.16719 | D64: 1750 | H64: 20-yr SOTP DCF, base case — validated by M&I ($429B) & Morningstar ($780B)
A65: (+) AI Optionality | B65: 210 | C65: =C64+B65 -> 786.16719 | H65: xAI/Grok priced at ~$250B in Feb'26 deal vs our ~$64B DCF — market optionality premium
A66: (+) Orbital Data Centers / Compute | B66: 350 | C66: =C65+B66 -> 1136.1672 | H66: S-1 AI compute-in-space thesis; not in our cash-flow base
A67: (+) Mars / Starshield Upside | B67: 250 | C67: =C66+B67 -> 1386.1672 | H67: ARK/Mach33 value Mars by accumulated book value; long-dated optionality
A68: (+) Terafab + Other Future Markets | B68: 120 | C68: =C67+B68 -> 1506.1672 | H68: Semiconductor fab ($119B, Sacra); not modeled in base
A69: (+) Hype / Index-Inclusion / Scarcity | B69: =$D$64-C68 -> 243.83281 | C69: =C68+B69 -> 1750 | H69: Residual — 2x oversubscribed IPO, Nasdaq fast-track, Musk premium
A70: Market IPO Valuation (= total) | B70: =$D$64 -> 1750 | C70: =$D$64 -> 1750 | H70: Reuters: $135/share × ~12.96B shares = $1.75T

Sheet SOTP
A1: SpaceX — Sum-of-the-Parts Valuation
A2: Sum-of-the-Parts DCF Valuation | S-1 Filed May 20, 2026 | $ in Millions (except per share)
A3: Segments: Connectivity (Starlink) + Space (Launch/Starship) + AI (X/xAI/Grok) | 20-Year DCF with Gordon Growth & Exit Multiple cross-check
A5: Scenarios are controlled on the COVER tab (B28:B30). This sheet reflects the selected case live.
A6: SEGMENT ENTERPRISE VALUE SUMMARY ($M)
A7: Segment | B7: Method 1 EV ¹ | C7: Method 2 EV ² | D7: Avg / Selected EV | E7: % of Total SOTP | F7: Comp Data Status
A8: Connectivity (Starlink) | B8: ='Conn DCF'!B88 -> 524537.59 | C8: ='Conn DCF'!C88 -> 347554.8 | D8: =(B8+C8)/2 -> 436046.2 | E8: =D8/$D$11 -> 0.7587289 | F8: =IF(N('Conn Comps'!K57)>0,"✓ LIVE "&TEXT('Conn Comps'!K57,"0.0x")&" EV/EBITDA","⚠ FALLBACK") -> ✓ LIVE 5.9x EV/EBITDA
A9: Space (Launch + Starship) | B9: ='Space DCF'!B88 -> 85853.059 | C9: ='Space DCF'!C88 -> 96914.802 | D9: =(B9+C9)/2 -> 91383.931 | E9: =D9/$D$11 -> 0.15900983 | F9: =IF(N('Space Comps'!K37)>0,"✓ LIVE "&TEXT('Space Comps'!K37,"0.0x")&" EV/EBITDA","⚠ FALLBACK") -> ✓ LIVE 15.1x EV/EBITDA
A10: AI (X / xAI / Grok) | B10: ='AI DCF'!B88 -> 37296.99 | C10: ='AI DCF'!C88 -> 57255.133 | D10: =(B10+C10)/2 -> 47276.062 | E10: =D10/$D$11 -> 0.082261271 | F10: =IF(N('AI Comps'!J47)>0,"✓ LIVE "&TEXT('AI Comps'!J47,"0.0x")&" EV/Rev (Tier 3)","⚠ FALLBACK") -> ✓ LIVE 3.2x EV/Rev (Tier 3)
A11: Total Enterprise Value (SOTP) | B11: =B8+B9+B10 -> 647687.64 | C11: =C8+C9+C10 -> 501724.74 | D11: =D8+D9+D10 -> 574706.19 | E11: =D11/$D$11 -> 1
B14: Gordon Growth | C14: Exit Multiple | D14: Average | F14: Note
A15: Total Enterprise Value (SOTP) | B15: =B11 -> 647687.64 | C15: =C11 -> 501724.74 | D15: =D11 -> 574706.19
A16: (–) Total Debt & Finance Leases | B16: -23286 | C16: =$B$16 -> -23286 | D16: =$B$16 -> -23286 | F16: S-1 Dec'25 BS
A17: (+) Cash & Marketable Securities | B17: 24747 | C17: =$B$17 -> 24747 | D17: =$B$17 -> 24747 | F17: S-1 Dec'25 BS
A18: (–) Redeemable Preferred Stock | B18: -38752 | C18: =$B$18 -> -38752 | D18: =$B$18 -> -38752 | F18: Pre-IPO; converts at IPO
A19: Post-IPO Preferred Conversion Adjustment | B19: 38752 | C19: =$B$19 -> 38752 | D19: =$B$19 -> 38752
A20: Equity Value | B20: =B15+B16+B17+B18+B19 -> 649148.64 | C20: =C15+C16+C17+C18+C19 -> 503185.74 | D20: =D15+D16+D17+D18+D19 -> 576167.19
A22: IMPLIED PRICE PER SHARE (Post-IPO Fully Diluted)
A23: Item | B23: Gordon Growth | C23: Exit Multiple | D23: Average | F23: Note
A24: Common Shares — Basic (Class A+B+C, S-1 Q1'26) | B24: 5798 | C24: =$B$24 -> 5798 | D24: =$B$24 -> 5798 | F24: Cl. A+B+C (S-1 Q1'26)
A25: Total Shares — Fully Diluted, Post-IPO | B25: 12960 | C25: =$B$25 -> 12960 | D25: =$B$25 -> 12960 | F25: $1.75T ÷ $135 reconciled
A26: Implied Price/Share — on Basic (understates) | B26: =B20/$B$24 -> 111.96079 | C26: =C20/$B$24 -> 86.786088 | D26: =D20/$B$24 -> 99.373437
A27: Implied Price/Share — Fully Diluted (primary) | B27: =B20/$B$25 -> 50.08863 | C27: =C20/$B$25 -> 38.82606 | D27: =D20/$B$25 -> 44.457345
A29: SOTP COMPONENT BREAKDOWN ($M)
A30: Segment | B30: EV (Avg) | C30: Per Share (Basic) | D30: % of Total EV | E30: Segment WACC | F30: Key Value Driver
A31: Connectivity (Starlink) | B31: =D8 -> 436046.2 | C31: =B31/$B$24 -> 75.206312 | D31: =B31/$B$34 -> 0.7587289 | E31: ='Conn DCF'!B45 -> 0.075445353 | F31: Subscriber growth + enterprise adoption; 63%+ EBITDA margins
A32: Space (Launch + Starship) | B32: =D9 -> 91383.931 | C32: =B32/$B$24 -> 15.761285 | D32: =B32/$B$34 -> 0.15900983 | E32: ='Space DCF'!B45 -> 0.079328832 | F32: Starship cost curve + reusability; long-term capex normalization
A33: AI (X / xAI) | B33: =D10 -> 47276.062 | C33: =B33/$B$24 -> 8.1538568 | D33: =B33/$B$34 -> 0.082261271 | E33: ='AI DCF'!B45 -> 0.11585358 | F33: Grok monetization + compute infra; margin ramp from -39% to +46%
A34: Total | B34: =D11 -> 574706.19 | C34: =B34/$B$24 -> 99.121454 | D34: 1
A36: KEY METRICS SNAPSHOT (FY2025 Actuals | Source: SpaceX S-1)
A37: Metric | B37: FY2023A | C37: FY2024A | D37: FY2025A | E37: Q1 2026 | F37: Note
A38: Total Revenue ($M) | B38: 10387 | C38: 14015 | D38: 18674 | E38: 4694 | F38: S-1 Consolidated Statements of Operations
A39: Connectivity ($M) | B39: 3869 | C39: 7599 | D39: 11387 | E39: 3257 | F39: Starlink Consumer + Enterprise/Gov't
A40: Space ($M) | B40: 3557 | C40: 3796 | D40: 4086 | E40: 619 | F40: Launch Services + Launch & Development
A41: AI ($M) | B41: 2961 | C41: 2620 | D41: 3201 | E41: 818 | F41: X advertising + AI Solutions & Infrastructure
A42: Total Capex ($M) | B42: -4415 | C42: -11163 | D42: -20737 | E42: -10107 | F42: Massive AI infra build (xAI: $12.7B in 2025)
A43: Operating Cash Flow ($M) | B43: 4520 | C43: 5776 | D43: 6785
A44: Net Income (Loss) ($M) | B44: -4628 | C44: 791 | D44: -4937 | E44: -4276 | F44: R&D ($8.6B) + AI losses dominate 2025
A45: Connectivity EBITDA Margin | B45: 0.5 | C45: 0.462 | D45: 0.629 | E45: 0.641 | F45: From S-1 Segment Adjusted EBITDA disclosure
A46: ¹ Method 1 = Gordon Growth (perpetuity) for Connectivity & Space; EV/Revenue multiple (PRIMARY) for AI — Gordon distorts on AI's loss-making early FCF.
A47: ² Method 2 = EV/EBITDA Exit Multiple for Connectivity & Space; Gordon Growth (cross-check only) for AI.
A48: VALUATION SENSITIVITY ANALYSIS (Method 1: Gordon Growth for Connectivity & Space, EV/Revenue for AI)
A50: Table 1: SOTP Implied Price/Share (Fully-Diluted) — Connectivity WACC vs. Terminal Growth Rate (Base Case)
B51: Terminal Growth Rate → | C51: 0.02 | D51: 0.025 | E51: 0.03 | F51: 0.035 | G51: 0.04
A52: Connectivity WACC ↓ | B52: ='Conn DCF'!B45-0.02 -> 0.055445353 | C52: =((SUMPRODUCT('Conn DCF'!$E$61:$X$61,1/(1+$B52)^'Conn DCF'!$E$66:$X$66)+'Conn DCF'!$X$61*(1+C$51)/($B52-C$51)/(1+$B52)^19.5)+'Space DCF'!$B$88+'AI DCF'!$B$88+$B$16+$B$17+$B$18+$B$19)/$B$25 -> 72.539151 | D52: =((SUMPRODUCT('Conn DCF'!$E$61:$X$61,1/(1+$B52)^'Conn DCF'!$E$66:$X$66)+'Conn DCF'!$X$61*(1+D$51)/($B52-D$51)/(1+$B52)^19.5)+'Space DCF'!$B$88+'AI DCF'!$B$88+$B$16+$B$17+$B$18+$B$19)/$B$25 -> 79.266728 | E52: =((SUMPRODUCT('Conn DCF'!$E$61:$X$61,1/(1+$B52)^'Conn DCF'!$E$66:$X$66)+'Conn DCF'!$X$61*(1+E$51)/($B52-E$51)/(1+$B52)^19.5)+'Space DCF'!$B$88+'AI DCF'!$B$88+$B$16+$B$17+$B$18+$B$19)/$B$25 -> 88.638238 | F52: =((SUMPRODUCT('Conn DCF'!$E$61:$X$61,1/(1+$B52)^'Conn DCF'!$E$66:$X$66)+'Conn DCF'!$X$61*(1+F$51)/($B52-F$51)/(1+$B52)^19.5)+'Space DCF'!$B$88+'AI DCF'!$B$88+$B$16+$B$17+$B$18+$B$19)/$B$25 -> 102.59343 | G52: =((SUMPRODUCT('Conn DCF'!$E$61:$X$61,1/(1+$B52)^'Conn DCF'!$E$66:$X$66)+'Conn DCF'!$X$61*(1+G$51)/($B52-G$51)/(1+$B52)^19.5)+'Space DCF'!$B$88+'AI DCF'!$B$88+$B$16+$B$17+$B$18+$B$19)/$B$25 -> 125.58384
B53: ='Conn DCF'!B45-0.01 -> 0.065445353 | C53: =((SUMPRODUCT('Conn DCF'!$E$61:$X$61,1/(1+$B53)^'Conn DCF'!$E$66:$X$66)+'Conn DCF'!$X$61*(1+C$51)/($B53-C$51)/(1+$B53)^19.5)+'Space DCF'!$B$88+'AI DCF'!$B$88+$B$16+$B$17+$B$18+$B$19)/$B$25 -> 56.245372 | D53: =((SUMPRODUCT('Conn DCF'!$E$61:$X$61,1/(1+$B53)^'Conn DCF'!$E$66:$X$66)+'Conn DCF'!$X$61*(1+D$51)/($B53-D$51)/(1+$B53)^19.5)+'Space DCF'!$B$88+'AI DCF'!$B$88+$B$16+$B$17+$B$18+$B$19)/$B$25 -> 59.562907 | E53: =((SUMPRODUCT('Conn DCF'!$E$61:$X$61,1/(1+$B53)^'Conn DCF'!$E$66:$X$66)+'Conn DCF'!$X$61*(1+E$51)/($B53-E$51)/(1+$B53)^19.5)+'Space DCF'!$B$88+'AI DCF'!$B$88+$B$16+$B$17+$B$18+$B$19)/$B$25 -> 63.816399 | F53: =((SUMPRODUCT('Conn DCF'!$E$61:$X$61,1/(1+$B53)^'Conn DCF'!$E$66:$X$66)+'Conn DCF'!$X$61*(1+F$51)/($B53-F$51)/(1+$B53)^19.5)+'Space DCF'!$B$88+'AI DCF'!$B$88+$B$16+$B$17+$B$18+$B$19)/$B$25 -> 69.466983 | G53: =((SUMPRODUCT('Conn DCF'!$E$61:$X$61,1/(1+$B53)^'Conn DCF'!$E$66:$X$66)+'Conn DCF'!$X$61*(1+G$51)/($B53-G$51)/(1+$B53)^19.5)+'Space DCF'!$B$88+'AI DCF'!$B$88+$B$16+$B$17+$B$18+$B$19)/$B$25 -> 77.33824
B54: ='Conn DCF'!B45 -> 0.075445353 | C54: =((SUMPRODUCT('Conn DCF'!$E$61:$X$61,1/(1+$B54)^'Conn DCF'!$E$66:$X$66)+'Conn DCF'!$X$61*(1+C$51)/($B54-C$51)/(1+$B54)^19.5)+'Space DCF'!$B$88+'AI DCF'!$B$88+$B$16+$B$17+$B$18+$B$19)/$B$25 -> 46.016783 | D54: =((SUMPRODUCT('Conn DCF'!$E$61:$X$61,1/(1+$B54)^'Conn DCF'!$E$66:$X$66)+'Conn DCF'!$X$61*(1+D$51)/($B54-D$51)/(1+$B54)^19.5)+'Space DCF'!$B$88+'AI DCF'!$B$88+$B$16+$B$17+$B$18+$B$19)/$B$25 -> 47.850912 | E54: =((SUMPRODUCT('Conn DCF'!$E$61:$X$61,1/(1+$B54)^'Conn DCF'!$E$66:$X$66)+'Conn DCF'!$X$61*(1+E$51)/($B54-E$51)/(1+$B54)^19.5)+'Space DCF'!$B$88+'AI DCF'!$B$88+$B$16+$B$17+$B$18+$B$19)/$B$25 -> 50.08863 | F54: =((SUMPRODUCT('Conn DCF'!$E$61:$X$61,1/(1+$B54)^'Conn DCF'!$E$66:$X$66)+'Conn DCF'!$X$61*(1+F$51)/($B54-F$51)/(1+$B54)^19.5)+'Space DCF'!$B$88+'AI DCF'!$B$88+$B$16+$B$17+$B$18+$B$19)/$B$25 -> 52.879617 | G54: =((SUMPRODUCT('Conn DCF'!$E$61:$X$61,1/(1+$B54)^'Conn DCF'!$E$66:$X$66)+'Conn DCF'!$X$61*(1+G$51)/($B54-G$51)/(1+$B54)^19.5)+'Space DCF'!$B$88+'AI DCF'!$B$88+$B$16+$B$17+$B$18+$B$19)/$B$25 -> 56.458011
B55: ='Conn DCF'!B45+0.01 -> 0.085445353 | C55: =((SUMPRODUCT('Conn DCF'!$E$61:$X$61,1/(1+$B55)^'Conn DCF'!$E$66:$X$66)+'Conn DCF'!$X$61*(1+C$51)/($B55-C$51)/(1+$B55)^19.5)+'Space DCF'!$B$88+'AI DCF'!$B$88+$B$16+$B$17+$B$18+$B$19)/$B$25 -> 39.0546 | D55: =((SUMPRODUCT('Conn DCF'!$E$61:$X$61,1/(1+$B55)^'Conn DCF'!$E$66:$X$66)+'Conn DCF'!$X$61*(1+D$51)/($B55-D$51)/(1+$B55)^19.5)+'Space DCF'!$B$88+'AI DCF'!$B$88+$B$16+$B$17+$B$18+$B$19)/$B$25 -> 40.147326 | E55: =((SUMPRODUCT('Conn DCF'!$E$61:$X$61,1/(1+$B55)^'Conn DCF'!$E$66:$X$66)+'Conn DCF'!$X$61*(1+E$51)/($B55-E$51)/(1+$B55)^19.5)+'Space DCF'!$B$88+'AI DCF'!$B$88+$B$16+$B$17+$B$18+$B$19)/$B$25 -> 41.437134 | F55: =((SUMPRODUCT('Conn DCF'!$E$61:$X$61,1/(1+$B55)^'Conn DCF'!$E$66:$X$66)+'Conn DCF'!$X$61*(1+F$51)/($B55-F$51)/(1+$B55)^19.5)+'Space DCF'!$B$88+'AI DCF'!$B$88+$B$16+$B$17+$B$18+$B$19)/$B$25 -> 42.982626 | G55: =((SUMPRODUCT('Conn DCF'!$E$61:$X$61,1/(1+$B55)^'Conn DCF'!$E$66:$X$66)+'Conn DCF'!$X$61*(1+G$51)/($B55-G$51)/(1+$B55)^19.5)+'Space DCF'!$B$88+'AI DCF'!$B$88+$B$16+$B$17+$B$18+$B$19)/$B$25 -> 44.868195
B56: ='Conn DCF'!B45+0.02 -> 0.095445353 | C56: =((SUMPRODUCT('Conn DCF'!$E$61:$X$61,1/(1+$B56)^'Conn DCF'!$E$66:$X$66)+'Conn DCF'!$X$61*(1+C$51)/($B56-C$51)/(1+$B56)^19.5)+'Space DCF'!$B$88+'AI DCF'!$B$88+$B$16+$B$17+$B$18+$B$19)/$B$25 -> 34.046068 | D56: =((SUMPRODUCT('Conn DCF'!$E$61:$X$61,1/(1+$B56)^'Conn DCF'!$E$66:$X$66)+'Conn DCF'!$X$61*(1+D$51)/($B56-D$51)/(1+$B56)^19.5)+'Space DCF'!$B$88+'AI DCF'!$B$88+$B$16+$B$17+$B$18+$B$19)/$B$25 -> 34.732484 | E56: =((SUMPRODUCT('Conn DCF'!$E$61:$X$61,1/(1+$B56)^'Conn DCF'!$E$66:$X$66)+'Conn DCF'!$X$61*(1+E$51)/($B56-E$51)/(1+$B56)^19.5)+'Space DCF'!$B$88+'AI DCF'!$B$88+$B$16+$B$17+$B$18+$B$19)/$B$25 -> 35.523783 | F56: =((SUMPRODUCT('Conn DCF'!$E$61:$X$61,1/(1+$B56)^'Conn DCF'!$E$66:$X$66)+'Conn DCF'!$X$61*(1+F$51)/($B56-F$51)/(1+$B56)^19.5)+'Space DCF'!$B$88+'AI DCF'!$B$88+$B$16+$B$17+$B$18+$B$19)/$B$25 -> 36.445995 | G56: =((SUMPRODUCT('Conn DCF'!$E$61:$X$61,1/(1+$B56)^'Conn DCF'!$E$66:$X$66)+'Conn DCF'!$X$61*(1+G$51)/($B56-G$51)/(1+$B56)^19.5)+'Space DCF'!$B$88+'AI DCF'!$B$88+$B$16+$B$17+$B$18+$B$19)/$B$25 -> 37.534534
A60: Table 2: Total SOTP Enterprise Value ($B) — Connectivity WACC vs. Terminal Growth Rate (Base Case)
B61: Terminal Growth Rate → | C61: 0.02 | D61: 0.025 | E61: 0.03 | F61: 0.035 | G61: 0.04
A62: Connectivity WACC ↓ | B62: ='Conn DCF'!B45-0.02 -> 0.055445353 | C62: =(SUMPRODUCT('Conn DCF'!$E$61:$X$61,1/(1+$B62)^'Conn DCF'!$E$66:$X$66)+'Conn DCF'!$X$61*(1+C$61)/($B62-C$61)/(1+$B62)^19.5)+'Space DCF'!$B$88+'AI DCF'!$B$88 -> 938646.4 | D62: =(SUMPRODUCT('Conn DCF'!$E$61:$X$61,1/(1+$B62)^'Conn DCF'!$E$66:$X$66)+'Conn DCF'!$X$61*(1+D$61)/($B62-D$61)/(1+$B62)^19.5)+'Space DCF'!$B$88+'AI DCF'!$B$88 -> 1025835.8 | E62: =(SUMPRODUCT('Conn DCF'!$E$61:$X$61,1/(1+$B62)^'Conn DCF'!$E$66:$X$66)+'Conn DCF'!$X$61*(1+E$61)/($B62-E$61)/(1+$B62)^19.5)+'Space DCF'!$B$88+'AI DCF'!$B$88 -> 1147290.6 | F62: =(SUMPRODUCT('Conn DCF'!$E$61:$X$61,1/(1+$B62)^'Conn DCF'!$E$66:$X$66)+'Conn DCF'!$X$61*(1+F$61)/($B62-F$61)/(1+$B62)^19.5)+'Space DCF'!$B$88+'AI DCF'!$B$88 -> 1328149.9 | G62: =(SUMPRODUCT('Conn DCF'!$E$61:$X$61,1/(1+$B62)^'Conn DCF'!$E$66:$X$66)+'Conn DCF'!$X$61*(1+G$61)/($B62-G$61)/(1+$B62)^19.5)+'Space DCF'!$B$88+'AI DCF'!$B$88 -> 1626105.5
B63: ='Conn DCF'!B45-0.01 -> 0.065445353 | C63: =(SUMPRODUCT('Conn DCF'!$E$61:$X$61,1/(1+$B63)^'Conn DCF'!$E$66:$X$66)+'Conn DCF'!$X$61*(1+C$61)/($B63-C$61)/(1+$B63)^19.5)+'Space DCF'!$B$88+'AI DCF'!$B$88 -> 727479.02 | D63: =(SUMPRODUCT('Conn DCF'!$E$61:$X$61,1/(1+$B63)^'Conn DCF'!$E$66:$X$66)+'Conn DCF'!$X$61*(1+D$61)/($B63-D$61)/(1+$B63)^19.5)+'Space DCF'!$B$88+'AI DCF'!$B$88 -> 770474.27 | E63: =(SUMPRODUCT('Conn DCF'!$E$61:$X$61,1/(1+$B63)^'Conn DCF'!$E$66:$X$66)+'Conn DCF'!$X$61*(1+E$61)/($B63-E$61)/(1+$B63)^19.5)+'Space DCF'!$B$88+'AI DCF'!$B$88 -> 825599.53 | F63: =(SUMPRODUCT('Conn DCF'!$E$61:$X$61,1/(1+$B63)^'Conn DCF'!$E$66:$X$66)+'Conn DCF'!$X$61*(1+F$61)/($B63-F$61)/(1+$B63)^19.5)+'Space DCF'!$B$88+'AI DCF'!$B$88 -> 898831.1 | G63: =(SUMPRODUCT('Conn DCF'!$E$61:$X$61,1/(1+$B63)^'Conn DCF'!$E$66:$X$66)+'Conn DCF'!$X$61*(1+G$61)/($B63-G$61)/(1+$B63)^19.5)+'Space DCF'!$B$88+'AI DCF'!$B$88 -> 1000842.6
B64: ='Conn DCF'!B45 -> 0.075445353 | C64: =(SUMPRODUCT('Conn DCF'!$E$61:$X$61,1/(1+$B64)^'Conn DCF'!$E$66:$X$66)+'Conn DCF'!$X$61*(1+C$61)/($B64-C$61)/(1+$B64)^19.5)+'Space DCF'!$B$88+'AI DCF'!$B$88 -> 594916.51 | D64: =(SUMPRODUCT('Conn DCF'!$E$61:$X$61,1/(1+$B64)^'Conn DCF'!$E$66:$X$66)+'Conn DCF'!$X$61*(1+D$61)/($B64-D$61)/(1+$B64)^19.5)+'Space DCF'!$B$88+'AI DCF'!$B$88 -> 618686.81 | E64: =(SUMPRODUCT('Conn DCF'!$E$61:$X$61,1/(1+$B64)^'Conn DCF'!$E$66:$X$66)+'Conn DCF'!$X$61*(1+E$61)/($B64-E$61)/(1+$B64)^19.5)+'Space DCF'!$B$88+'AI DCF'!$B$88 -> 647687.64 | F64: =(SUMPRODUCT('Conn DCF'!$E$61:$X$61,1/(1+$B64)^'Conn DCF'!$E$66:$X$66)+'Conn DCF'!$X$61*(1+F$61)/($B64-F$61)/(1+$B64)^19.5)+'Space DCF'!$B$88+'AI DCF'!$B$88 -> 683858.84 | G64: =(SUMPRODUCT('Conn DCF'!$E$61:$X$61,1/(1+$B64)^'Conn DCF'!$E$66:$X$66)+'Conn DCF'!$X$61*(1+G$61)/($B64-G$61)/(1+$B64)^19.5)+'Space DCF'!$B$88+'AI DCF'!$B$88 -> 730234.82
B65: ='Conn DCF'!B45+0.01 -> 0.085445353 | C65: =(SUMPRODUCT('Conn DCF'!$E$61:$X$61,1/(1+$B65)^'Conn DCF'!$E$66:$X$66)+'Conn DCF'!$X$61*(1+C$61)/($B65-C$61)/(1+$B65)^19.5)+'Space DCF'!$B$88+'AI DCF'!$B$88 -> 504686.61 | D65: =(SUMPRODUCT('Conn DCF'!$E$61:$X$61,1/(1+$B65)^'Conn DCF'!$E$66:$X$66)+'Conn DCF'!$X$61*(1+D$61)/($B65-D$61)/(1+$B65)^19.5)+'Space DCF'!$B$88+'AI DCF'!$B$88 -> 518848.34 | E65: =(SUMPRODUCT('Conn DCF'!$E$61:$X$61,1/(1+$B65)^'Conn DCF'!$E$66:$X$66)+'Conn DCF'!$X$61*(1+E$61)/($B65-E$61)/(1+$B65)^19.5)+'Space DCF'!$B$88+'AI DCF'!$B$88 -> 535564.25 | F65: =(SUMPRODUCT('Conn DCF'!$E$61:$X$61,1/(1+$B65)^'Conn DCF'!$E$66:$X$66)+'Conn DCF'!$X$61*(1+F$61)/($B65-F$61)/(1+$B65)^19.5)+'Space DCF'!$B$88+'AI DCF'!$B$88 -> 555593.83 | G65: =(SUMPRODUCT('Conn DCF'!$E$61:$X$61,1/(1+$B65)^'Conn DCF'!$E$66:$X$66)+'Conn DCF'!$X$61*(1+G$61)/($B65-G$61)/(1+$B65)^19.5)+'Space DCF'!$B$88+'AI DCF'!$B$88 -> 580030.81
B66: ='Conn DCF'!B45+0.02 -> 0.095445353 | C66: =(SUMPRODUCT('Conn DCF'!$E$61:$X$61,1/(1+$B66)^'Conn DCF'!$E$66:$X$66)+'Conn DCF'!$X$61*(1+C$61)/($B66-C$61)/(1+$B66)^19.5)+'Space DCF'!$B$88+'AI DCF'!$B$88 -> 439776.04 | D66: =(SUMPRODUCT('Conn DCF'!$E$61:$X$61,1/(1+$B66)^'Conn DCF'!$E$66:$X$66)+'Conn DCF'!$X$61*(1+D$61)/($B66-D$61)/(1+$B66)^19.5)+'Space DCF'!$B$88+'AI DCF'!$B$88 -> 448671.99 | E66: =(SUMPRODUCT('Conn DCF'!$E$61:$X$61,1/(1+$B66)^'Conn DCF'!$E$66:$X$66)+'Conn DCF'!$X$61*(1+E$61)/($B66-E$61)/(1+$B66)^19.5)+'Space DCF'!$B$88+'AI DCF'!$B$88 -> 458927.23 | F66: =(SUMPRODUCT('Conn DCF'!$E$61:$X$61,1/(1+$B66)^'Conn DCF'!$E$66:$X$66)+'Conn DCF'!$X$61*(1+F$61)/($B66-F$61)/(1+$B66)^19.5)+'Space DCF'!$B$88+'AI DCF'!$B$88 -> 470879.09 | G66: =(SUMPRODUCT('Conn DCF'!$E$61:$X$61,1/(1+$B66)^'Conn DCF'!$E$66:$X$66)+'Conn DCF'!$X$61*(1+G$61)/($B66-G$61)/(1+$B66)^19.5)+'Space DCF'!$B$88+'AI DCF'!$B$88 -> 484986.56

Sheet Conn DCF
A1: SpaceX — Connectivity Segment DCF (Starlink)
A2: S-1 Filed May 20, 2026 | 20-Year Explicit Forecast FY2026E–FY2045E | $ in Millions
A5: SCENARIO SELECTOR | B5: =COVER!B28 -> 2 | C5: =IF(B5=1,"◀ BEAR",IF(B5=2,"◀ BASE","◀ BULL")) -> ◀ BASE | D5: (1 = Bear | 2 = Base | 3 = Bull)
A7: BEAR CASE ASSUMPTIONS
B8: FY2023A | C8: FY2024A | D8: FY2025A | E8: FY2026E | F8: FY2027E | G8: FY2028E | H8: FY2029E | I8: FY2030E | J8: FY2031E | K8: FY2032E | L8: FY2033E | M8: FY2034E | N8: FY2035E | O8: FY2036E | P8: FY2037E | Q8: FY2038E | R8: FY2039E | S8: FY2040E | T8: FY2041E | U8: FY2042E | V8: FY2043E | W8: FY2044E | X8: FY2045E
A9: Revenue Growth % (YoY) | E9: 0.28 | F9: 0.24 | G9: 0.2 | H9: 0.18 | I9: 0.15 | J9: 0.13 | K9: 0.11 | L9: 0.09 | M9: 0.08 | N9: 0.07 | O9: 0.06 | P9: 0.055 | Q9: 0.05 | R9: 0.045 | S9: 0.04 | T9: 0.038 | U9: 0.035 | V9: 0.032 | W9: 0.03 | X9: 0.025
A10: EBITDA Margin % | E10: 0.6 | F10: 0.61 | G10: 0.62 | H10: 0.63 | I10: 0.64 | J10: 0.64 | K10: 0.65 | L10: 0.65 | M10: 0.65 | N10: 0.65 | O10: 0.655 | P10: 0.655 | Q10: 0.66 | R10: 0.66 | S10: 0.66 | T10: 0.665 | U10: 0.665 | V10: 0.67 | W10: 0.67 | X10: 0.67
A11: D&A % of Revenue | E11: 0.195 | F11: 0.185 | G11: 0.175 | H11: 0.165 | I11: 0.155 | J11: 0.15 | K11: 0.145 | L11: 0.14 | M11: 0.135 | N11: 0.13 | O11: 0.13 | P11: 0.13 | Q11: 0.125 | R11: 0.125 | S11: 0.12 | T11: 0.12 | U11: 0.12 | V11: 0.12 | W11: 0.12 | X11: 0.12
A12: Capex % of Revenue | E12: 0.34 | F12: 0.3 | G12: 0.26 | H12: 0.23 | I12: 0.2 | J12: 0.18 | K12: 0.16 | L12: 0.14 | M12: 0.12 | N12: 0.11 | O12: 0.105 | P12: 0.1 | Q12: 0.1 | R12: 0.095 | S12: 0.095 | T12: 0.09 | U12: 0.09 | V12: 0.09 | W12: 0.09 | X12: 0.09
A13: ΔNW Cap % of ΔRevenue | E13: 0.05 | F13: 0.05 | G13: 0.05 | H13: 0.05 | I13: 0.04 | J13: 0.04 | K13: 0.04 | L13: 0.03 | M13: 0.03 | N13: 0.03 | O13: 0.03 | P13: 0.03 | Q13: 0.03 | R13: 0.025 | S13: 0.025 | T13: 0.025 | U13: 0.025 | V13: 0.025 | W13: 0.025 | X13: 0.025
A14: Terminal Growth Rate | B14: =WACC!D47 -> 0.025
A15: WACC | B15: =WACC!B47 -> 0.075445353
A17: BASE CASE ASSUMPTIONS
B18: FY2023A | C18: FY2024A | D18: FY2025A | E18: FY2026E | F18: FY2027E | G18: FY2028E | H18: FY2029E | I18: FY2030E | J18: FY2031E | K18: FY2032E | L18: FY2033E | M18: FY2034E | N18: FY2035E | O18: FY2036E | P18: FY2037E | Q18: FY2038E | R18: FY2039E | S18: FY2040E | T18: FY2041E | U18: FY2042E | V18: FY2043E | W18: FY2044E | X18: FY2045E
A19: Revenue Growth % (YoY) | E19: 0.38 | F19: 0.32 | G19: 0.26 | H19: 0.22 | I19: 0.18 | J19: 0.15 | K19: 0.13 | L19: 0.11 | M19: 0.09 | N19: 0.08 | O19: 0.07 | P19: 0.065 | Q19: 0.06 | R19: 0.055 | S19: 0.05 | T19: 0.045 | U19: 0.04 | V19: 0.038 | W19: 0.035 | X19: 0.03
A20: EBITDA Margin % | E20: 0.63 | F20: 0.65 | G20: 0.66 | H20: 0.67 | I20: 0.68 | J20: 0.68 | K20: 0.68 | L20: 0.68 | M20: 0.68 | N20: 0.68 | O20: 0.685 | P20: 0.685 | Q20: 0.69 | R20: 0.69 | S20: 0.69 | T20: 0.695 | U20: 0.695 | V20: 0.7 | W20: 0.7 | X20: 0.7
A21: D&A % of Revenue | E21: 0.195 | F21: 0.185 | G21: 0.175 | H21: 0.165 | I21: 0.155 | J21: 0.15 | K21: 0.145 | L21: 0.14 | M21: 0.135 | N21: 0.13 | O21: 0.13 | P21: 0.125 | Q21: 0.125 | R21: 0.12 | S21: 0.12 | T21: 0.12 | U21: 0.115 | V21: 0.115 | W21: 0.115 | X21: 0.115
A22: Capex % of Revenue | E22: 0.32 | F22: 0.27 | G22: 0.23 | H22: 0.2 | I22: 0.17 | J22: 0.15 | K22: 0.13 | L22: 0.12 | M22: 0.11 | N22: 0.1 | O22: 0.095 | P22: 0.09 | Q22: 0.088 | R22: 0.085 | S22: 0.082 | T22: 0.08 | U22: 0.08 | V22: 0.08 | W22: 0.08 | X22: 0.08
A23: ΔNW Cap % of ΔRevenue | E23: 0.04 | F23: 0.04 | G23: 0.04 | H23: 0.04 | I23: 0.03 | J23: 0.03 | K23: 0.03 | L23: 0.03 | M23: 0.02 | N23: 0.02 | O23: 0.02 | P23: 0.02 | Q23: 0.02 | R23: 0.02 | S23: 0.02 | T23: 0.015 | U23: 0.015 | V23: 0.015 | W23: 0.015 | X23: 0.015
A24: Terminal Growth Rate | B24: =WACC!C47 -> 0.03
A25: WACC | B25: =WACC!B47 -> 0.075445353
A27: BULL CASE ASSUMPTIONS
B28: FY2023A | C28: FY2024A | D28: FY2025A | E28: FY2026E | F28: FY2027E | G28: FY2028E | H28: FY2029E | I28: FY2030E | J28: FY2031E | K28: FY2032E | L28: FY2033E | M28: FY2034E | N28: FY2035E | O28: FY2036E | P28: FY2037E | Q28: FY2038E | R28: FY2039E | S28: FY2040E | T28: FY2041E | U28: FY2042E | V28: FY2043E | W28: FY2044E | X28: FY2045E
A29: Revenue Growth % (YoY) | E29: 0.48 | F29: 0.4 | G29: 0.33 | H29: 0.27 | I29: 0.22 | J29: 0.18 | K29: 0.15 | L29: 0.13 | M29: 0.11 | N29: 0.09 | O29: 0.085 | P29: 0.08 | Q29: 0.075 | R29: 0.07 | S29: 0.065 | T29: 0.06 | U29: 0.055 | V29: 0.05 | W29: 0.045 | X29: 0.04
A30: EBITDA Margin % | E30: 0.65 | F30: 0.67 | G30: 0.69 | H30: 0.7 | I30: 0.71 | J30: 0.71 | K30: 0.72 | L30: 0.72 | M30: 0.72 | N30: 0.72 | O30: 0.72 | P30: 0.72 | Q30: 0.725 | R30: 0.725 | S30: 0.73 | T30: 0.73 | U30: 0.73 | V30: 0.73 | W30: 0.73 | X30: 0.73
A31: D&A % of Revenue | E31: 0.195 | F31: 0.185 | G31: 0.175 | H31: 0.165 | I31: 0.155 | J31: 0.15 | K31: 0.145 | L31: 0.14 | M31: 0.135 | N31: 0.13 | O31: 0.13 | P31: 0.125 | Q31: 0.12 | R31: 0.12 | S31: 0.115 | T31: 0.115 | U31: 0.11 | V31: 0.11 | W31: 0.11 | X31: 0.11
A32: Capex % of Revenue | E32: 0.3 | F32: 0.25 | G32: 0.21 | H32: 0.18 | I32: 0.15 | J32: 0.13 | K32: 0.11 | L32: 0.1 | M32: 0.09 | N32: 0.09 | O32: 0.085 | P32: 0.082 | Q32: 0.08 | R32: 0.078 | S32: 0.075 | T32: 0.072 | U32: 0.07 | V32: 0.07 | W32: 0.07 | X32: 0.07
A33: ΔNW Cap % of ΔRevenue | E33: 0.03 | F33: 0.03 | G33: 0.03 | H33: 0.03 | I33: 0.02 | J33: 0.02 | K33: 0.02 | L33: 0.02 | M33: 0.02 | N33: 0.02 | O33: 0.02 | P33: 0.02 | Q33: 0.015 | R33: 0.015 | S33: 0.015 | T33: 0.015 | U33: 0.015 | V33: 0.015 | W33: 0.015 | X33: 0.015
A34: Terminal Growth Rate | B34: =WACC!E47 -> 0.035
A35: WACC | B35: =WACC!B47 -> 0.075445353
A37: SELECTED CASE ASSUMPTIONS (auto-updates with Scenario Selector)
B38: FY2023A | C38: FY2024A | D38: FY2025A | E38: FY2026E | F38: FY2027E | G38: FY2028E | H38: FY2029E | I38: FY2030E | J38: FY2031E | K38: FY2032E | L38: FY2033E | M38: FY2034E | N38: FY2035E | O38: FY2036E | P38: FY2037E | Q38: FY2038E | R38: FY2039E | S38: FY2040E | T38: FY2041E | U38: FY2042E | V38: FY2043E | W38: FY2044E | X38: FY2045E
A39: Revenue Growth % (YoY) | E39: =IF($B$5=1,E9,IF($B$5=2,E19,E29)) -> 0.38 | F39: =IF($B$5=1,F9,IF($B$5=2,F19,F29)) -> 0.32 | G39: =IF($B$5=1,G9,IF($B$5=2,G19,G29)) -> 0.26 | H39: =IF($B$5=1,H9,IF($B$5=2,H19,H29)) -> 0.22 | I39: =IF($B$5=1,I9,IF($B$5=2,I19,I29)) -> 0.18 | J39: =IF($B$5=1,J9,IF($B$5=2,J19,J29)) -> 0.15 | K39: =IF($B$5=1,K9,IF($B$5=2,K19,K29)) -> 0.13 | L39: =IF($B$5=1,L9,IF($B$5=2,L19,L29)) -> 0.11 | ... X39: =IF($B$5=1,X9,IF($B$5=2,X19,X29)) -> 0.03
A40: EBITDA Margin % | E40: =IF($B$5=1,E10,IF($B$5=2,E20,E30)) -> 0.63 | F40: =IF($B$5=1,F10,IF($B$5=2,F20,F30)) -> 0.65 | G40: =IF($B$5=1,G10,IF($B$5=2,G20,G30)) -> 0.66 | H40: =IF($B$5=1,H10,IF($B$5=2,H20,H30)) -> 0.67 | I40: =IF($B$5=1,I10,IF($B$5=2,I20,I30)) -> 0.68 | J40: =IF($B$5=1,J10,IF($B$5=2,J20,J30)) -> 0.68 | K40: =IF($B$5=1,K10,IF($B$5=2,K20,K30)) -> 0.68 | L40: =IF($B$5=1,L10,IF($B$5=2,L20,L30)) -> 0.68 | ... X40: =IF($B$5=1,X10,IF($B$5=2,X20,X30)) -> 0.7
A41: D&A % of Revenue | E41: =IF($B$5=1,E11,IF($B$5=2,E21,E31)) -> 0.195 | F41: =IF($B$5=1,F11,IF($B$5=2,F21,F31)) -> 0.185 | G41: =IF($B$5=1,G11,IF($B$5=2,G21,G31)) -> 0.175 | H41: =IF($B$5=1,H11,IF($B$5=2,H21,H31)) -> 0.165 | I41: =IF($B$5=1,I11,IF($B$5=2,I21,I31)) -> 0.155 | J41: =IF($B$5=1,J11,IF($B$5=2,J21,J31)) -> 0.15 | K41: =IF($B$5=1,K11,IF($B$5=2,K21,K31)) -> 0.145 | L41: =IF($B$5=1,L11,IF($B$5=2,L21,L31)) -> 0.14 | ... X41: =IF($B$5=1,X11,IF($B$5=2,X21,X31)) -> 0.115
A42: Capex % of Revenue | E42: =IF($B$5=1,E12,IF($B$5=2,E22,E32)) -> 0.32 | F42: =IF($B$5=1,F12,IF($B$5=2,F22,F32)) -> 0.27 | G42: =IF($B$5=1,G12,IF($B$5=2,G22,G32)) -> 0.23 | H42: =IF($B$5=1,H12,IF($B$5=2,H22,H32)) -> 0.2 | I42: =IF($B$5=1,I12,IF($B$5=2,I22,I32)) -> 0.17 | J42: =IF($B$5=1,J12,IF($B$5=2,J22,J32)) -> 0.15 | K42: =IF($B$5=1,K12,IF($B$5=2,K22,K32)) -> 0.13 | L42: =IF($B$5=1,L12,IF($B$5=2,L22,L32)) -> 0.12 | ... X42: =IF($B$5=1,X12,IF($B$5=2,X22,X32)) -> 0.08
A43: ΔNW Cap % of ΔRevenue | E43: =IF($B$5=1,E13,IF($B$5=2,E23,E33)) -> 0.04 | F43: =IF($B$5=1,F13,IF($B$5=2,F23,F33)) -> 0.04 | G43: =IF($B$5=1,G13,IF($B$5=2,G23,G33)) -> 0.04 | H43: =IF($B$5=1,H13,IF($B$5=2,H23,H33)) -> 0.04 | I43: =IF($B$5=1,I13,IF($B$5=2,I23,I33)) -> 0.03 | J43: =IF($B$5=1,J13,IF($B$5=2,J23,J33)) -> 0.03 | K43: =IF($B$5=1,K13,IF($B$5=2,K23,K33)) -> 0.03 | L43: =IF($B$5=1,L13,IF($B$5=2,L23,L33)) -> 0.03 | ... X43: =IF($B$5=1,X13,IF($B$5=2,X23,X33)) -> 0.015
A44: Terminal Growth Rate | B44: =IF($B$5=1,B14,IF($B$5=2,B24,B34)) -> 0.03
A45: WACC | B45: =IF($B$5=1,B15,IF($B$5=2,B25,B35)) -> 0.075445353
A47: CONNECTIVITY SEGMENT — INCOME STATEMENT & FREE CASH FLOW ($M)
B48: FY2023A | C48: FY2024A | D48: FY2025A | E48: FY2026E | F48: FY2027E | G48: FY2028E | H48: FY2029E | I48: FY2030E | J48: FY2031E | K48: FY2032E | L48: FY2033E | M48: FY2034E | N48: FY2035E | O48: FY2036E | P48: FY2037E | Q48: FY2038E | R48: FY2039E | S48: FY2040E | T48: FY2041E | U48: FY2042E | V48: FY2043E | W48: FY2044E | X48: FY2045E
A49: Revenue | B49: 3869 | C49: 7599 | D49: =Actuals!D7 -> 11387 | E49: =D49*(1+E39) -> 15714.06 | F49: =E49*(1+F39) -> 20742.559 | G49: =F49*(1+G39) -> 26135.625 | H49: =G49*(1+H39) -> 31885.462 | I49: =H49*(1+I39) -> 37624.845 | J49: =I49*(1+J39) -> 43268.572 | K49: =J49*(1+K39) -> 48893.486 | L49: =K49*(1+L39) -> 54271.77 | ... X49: =W49*(1+X39) -> 102808.69
A50: % YoY Growth | B50: — | C50: =C49/B49-1 -> 0.9640734 | D50: =D49/C49-1 -> 0.49848664 | E50: =E49/D49-1 -> 0.38 | F50: =F49/E49-1 -> 0.32 | G50: =G49/F49-1 -> 0.26 | H50: =H49/G49-1 -> 0.22 | I50: =I49/H49-1 -> 0.18 | J50: =J49/I49-1 -> 0.15 | ... X50: =X49/W49-1 -> 0.03
A51: EBITDA | B51: 1935 | C51: 3514 | D51: =Actuals!D10 -> 7168 | E51: =E49*E40 -> 9899.8578 | F51: =F49*F40 -> 13482.663 | G51: =G49*G40 -> 17249.512 | H51: =H49*H40 -> 21363.26 | I51: =I49*I40 -> 25584.895 | J51: =J49*J40 -> 29422.629 | K51: =K49*K40 -> 33247.571 | L51: =L49*L40 -> 36904.803 | ... X51: =X49*X40 -> 71966.08
A52: EBITDA Margin % | B52: =B51/B49 -> 0.50012923 | C52: =C51/C49 -> 0.46242927 | D52: =D51/D49 -> 0.62948977 | E52: =E51/E49 -> 0.63 | F52: =F51/F49 -> 0.65 | G52: =G51/G49 -> 0.66 | H52: =H51/H49 -> 0.67 | I52: =I51/I49 -> 0.68 | ... X52: =X51/X49 -> 0.7
A53: Depreciation & Amortization | B53: 884 | C53: 1508 | D53: 2376 | E53: =E49*E41 -> 3064.2417 | F53: =F49*F41 -> 3837.3735 | G53: =G49*G41 -> 4573.7343 | H53: =H49*H41 -> 5261.1012 | I53: =I49*I41 -> 5831.851 | J53: =J49*J41 -> 6490.2858 | K53: =K49*K41 -> 7089.5555 | L53: =L49*L41 -> 7598.0478 | ... X53: =X49*X41 -> 11822.999
A54: EBIT (EBITDA − D&A) | B54: =B51-B53 -> 1051 | C54: =C51-C53 -> 2006 | D54: =D51-D53 -> 4792 | E54: =E51-E53 -> 6835.6161 | F54: =F51-F53 -> 9645.29 | G54: =G51-G53 -> 12675.778 | H54: =H51-H53 -> 16102.158 | I54: =I51-I53 -> 19753.044 | ... X54: =X51-X53 -> 60143.081
A55: EBIT Margin % | B55: =B54/B49 -> 0.27164642 | C55: =C54/C49 -> 0.2639821 | D55: =D54/D49 -> 0.42083077 | E55: =E54/E49 -> 0.435 | F55: =F54/F49 -> 0.465 | G55: =G54/G49 -> 0.485 | H55: =H54/H49 -> 0.505 | I55: =I54/I49 -> 0.525 | ... X55: =X54/X49 -> 0.585
A56: (–) Tax on EBIT (NOL-adjusted) | B56: =MAX(B54,0)*WACC!$B$8 -> 220.71 | C56: =MAX(C54,0)*WACC!$B$8 -> 421.26 | D56: =MAX(D54,0)*WACC!$B$8 -> 1006.32 | E56: =MAX(E54,0)*WACC!$B$8 -> 1435.4794 | F56: =MAX(F54,0)*WACC!$B$8 -> 2025.5109 | G56: =MAX(G54,0)*WACC!$B$8 -> 2661.9134 | H56: =MAX(H54,0)*WACC!$B$8 -> 3381.4532 | I56: =MAX(I54,0)*WACC!$B$8 -> 4148.1392 | ... X56: =MAX(X54,0)*WACC!$B$8 -> 12630.047
A57: NOPAT | B57: =B54-B56 -> 830.29 | C57: =C54-C56 -> 1584.74 | D57: =D54-D56 -> 3785.68 | E57: =E54-E56 -> 5400.1367 | F57: =F54-F56 -> 7619.7791 | G57: =G54-G56 -> 10013.865 | H57: =H54-H56 -> 12720.705 | I57: =I54-I56 -> 15604.905 | ... X57: =X54-X56 -> 47513.034
A58: (+) D&A | B58: =B53 -> 884 | C58: =C53 -> 1508 | D58: =D53 -> 2376 | E58: =E53 -> 3064.2417 | F58: =F53 -> 3837.3735 | G58: =G53 -> 4573.7343 | H58: =H53 -> 5261.1012 | I58: =I53 -> 5831.851 | ... X58: =X53 -> 11822.999
A59: (–) Capital Expenditures | B59: -2455 | C59: -3498 | D59: -4178 | E59: =-E49*E42 -> -5028.4992 | F59: =-F49*F42 -> -5600.491 | G59: =-G49*G42 -> -6011.1937 | H59: =-H49*H42 -> -6377.0924 | I59: =-I49*I42 -> -6396.2237 | J59: =-J49*J42 -> -6490.2858 | K59: =-K49*K42 -> -6356.1532 | L59: =-L49*L42 -> -6512.6124 | ... X59: =-X49*X42 -> -8224.6948
A60: (–) Increase in Net Working Capital | B60: 0 | C60: 0 | D60: 0 | E60: =-(E49-D49)*E43 -> -173.0824 | F60: =-(F49-E49)*F43 -> -201.13997 | G60: =-(G49-F49)*G43 -> -215.72262 | H60: =-(H49-G49)*H43 -> -229.9935 | I60: =-(I49-H49)*I43 -> -172.18149 | J60: =-(J49-I49)*J43 -> -169.3118 | K60: =-(K49-J49)*K43 -> -168.74743 | L60: =-(L49-K49)*L43 -> -161.3485 | ... X60: =-(X49-W49)*X43 -> -44.916416
A61: Unlevered Free Cash Flow | B61: =B57+B58+B59+B60 -> -740.71 | C61: =C57+C58+C59+C60 -> -405.26 | D61: =D57+D58+D59+D60 -> 1983.68 | E61: =E57+E58+E59+E60 -> 3262.7968 | F61: =F57+F58+F59+F60 -> 5655.5216 | G61: =G57+G58+G59+G60 -> 8360.6826 | H61: =H57+H58+H59+H60 -> 11374.72 | I61: =I57+I58+I59+I60 -> 14868.35 | ... X61: =X57+X58+X59+X60 -> 51066.421
A62: FCF Margin % | B62: =B61/B49 -> -0.1914474 | C62: =C61/C49 -> -0.053330701 | D62: =D61/D49 -> 0.17420567 | E62: =E61/E49 -> 0.20763551 | F62: =F61/F49 -> 0.27265303 | G62: =G61/G49 -> 0.31989603 | H62: =H61/H49 -> 0.35673689 | I62: =I61/I49 -> 0.39517373 | ... X62: =X61/X49 -> 0.49671311
A64: DCF — DISCOUNT FACTORS & PRESENT VALUES (Mid-Year Convention)
E65: FY2026E | F65: FY2027E | G65: FY2028E | H65: FY2029E | I65: FY2030E | J65: FY2031E | K65: FY2032E | L65: FY2033E | M65: FY2034E | N65: FY2035E | O65: FY2036E | P65: FY2037E | Q65: FY2038E | R65: FY2039E | S65: FY2040E | T65: FY2041E | U65: FY2042E | V65: FY2043E | W65: FY2044E | X65: FY2045E
A66: Discount Period (mid-year) | E66: 0.5 | F66: 1.5 | G66: 2.5 | H66: 3.5 | I66: 4.5 | J66: 5.5 | K66: 6.5 | L66: 7.5 | M66: 8.5 | N66: 9.5 | O66: 10.5 | P66: 11.5 | Q66: 12.5 | R66: 13.5 | S66: 14.5 | T66: 15.5 | U66: 16.5 | V66: 17.5 | W66: 18.5 | X66: 19.5
A67: Discount Factor | E67: =1/(1+$B$45)^E66 -> 0.96428592 | F67: =1/(1+$B$45)^F66 -> 0.8966387 | G67: =1/(1+$B$45)^G66 -> 0.83373711 | H67: =1/(1+$B$45)^H66 -> 0.77524823 | I67: =1/(1+$B$45)^I66 -> 0.72086251 | J67: =1/(1+$B$45)^J66 -> 0.67029208 | K67: =1/(1+$B$45)^K66 -> 0.62326931 | L67: =1/(1+$B$45)^L66 -> 0.57954531 | ... X67: =1/(1+$B$45)^X66 -> 0.24211809
A68: Unlevered FCF ($M) | E68: =E61 -> 3262.7968 | F68: =F61 -> 5655.5216 | G68: =G61 -> 8360.6826 | H68: =H61 -> 11374.72 | I68: =I61 -> 14868.35 | J68: =J61 -> 17947.239 | K68: =K61 -> 21229.487 | L68: =L61 -> 24076.424 | ... X68: =X61 -> 51066.421
A69: PV of FCF ($M) | E69: =E68*E67 -> 3146.269 | F69: =F68*F67 -> 5070.9596 | G69: =G68*G67 -> 6970.6113 | H69: =H68*H67 -> 8818.2319 | I69: =I68*I67 -> 10718.036 | J69: =J68*J67 -> 12029.892 | K69: =K68*K67 -> 13231.688 | L69: =L68*L67 -> 13953.379 | ... X69: =X68*X67 -> 12364.104
A71: TERMINAL VALUE
A72: Gordon Growth Model
A73: Terminal Year FCF ($M) | B73: =X61 -> 51066.421
A74: Terminal FCF × (1+g) | B74: =X61*(1+$B$44) -> 52598.414
A75: Terminal Value (Gordon Growth) | B75: =B74/($B$45-$B$44) -> 1157399.2
A76: PV of Terminal Value (Gordon Growth) | B76: =B75/(1+$B$45)^19.5 -> 280227.27
A78: EV/EBITDA Exit Multiple Method
A79: Exit EV/EBITDA Multiple | B79: =IF(N('Conn Comps'!K57)>0,'Conn Comps'!K57,25) -> 5.9253197 | D79: =IF(N('Conn Comps'!K57)>0,"✓ LIVE — "&TEXT('Conn Comps'!K57,"0.0x")&" from Conn Comps mature tier","⚠ FALLBACK — using 25x default") -> ✓ LIVE — 5.9x from Conn Comps mature tier
A80: Terminal Year EBITDA ($M) | B80: =X51 -> 71966.08
A81: Terminal Value (Exit Multiple) | B81: =B79*B80 -> 426422.03
A82: PV of Terminal Value (Exit Multiple) | B82: =B81/(1+$B$45)^19.5 -> 103244.49
A84: CONNECTIVITY SEGMENT VALUATION SUMMARY
B85: Gordon Growth | C85: Exit Multiple
A86: Sum of PV of FCFs ($M) | B86: =SUM(E69:X69) -> 244310.32 | C86: =SUM(E69:X69) -> 244310.32
A87: PV of Terminal Value ($M) | B87: =B76 -> 280227.27 | C87: =B82 -> 103244.49
A88: Enterprise Value ($M) | B88: =B86+B87 -> 524537.59 | C88: =C86+C87 -> 347554.8
A90: TV % of Enterprise Value | B90: =B87/B88 -> 0.53423678 | C90: =C87/C88 -> 0.29705959
A92: SENSITIVITY ANALYSIS — CONNECTIVITY SEGMENT EV ($M)
A94: Table 1: EV ($M) — WACC vs. Terminal Growth Rate (Gordon Growth)
B96: ↑ WACC \ Terminal g → | C96: =$B$44-0.01 -> 0.02 | D96: =$B$44-0.005 -> 0.025 | E96: =$B$44 -> 0.03 | F96: =$B$44+0.005 -> 0.035 | G96: =$B$44+0.01 -> 0.04
B97: =$B$45-0.02 -> 0.055445353 | C97: =SUMPRODUCT($E$61:$X$61,1/(1+$B97)^$E$66:$X$66)+($X$61*(1+C$96)/($B97-C$96))/(1+$B97)^19.5 -> 815496.35 | D97: =SUMPRODUCT($E$61:$X$61,1/(1+$B97)^$E$66:$X$66)+($X$61*(1+D$96)/($B97-D$96))/(1+$B97)^19.5 -> 902685.75 | E97: =SUMPRODUCT($E$61:$X$61,1/(1+$B97)^$E$66:$X$66)+($X$61*(1+E$96)/($B97-E$96))/(1+$B97)^19.5 -> 1024140.5 | F97: =SUMPRODUCT($E$61:$X$61,1/(1+$B97)^$E$66:$X$66)+($X$61*(1+F$96)/($B97-F$96))/(1+$B97)^19.5 -> 1204999.9 | G97: =SUMPRODUCT($E$61:$X$61,1/(1+$B97)^$E$66:$X$66)+($X$61*(1+G$96)/($B97-G$96))/(1+$B97)^19.5 -> 1502955.5
B98: =$B$45-0.01 -> 0.065445353 | C98: =SUMPRODUCT($E$61:$X$61,1/(1+$B98)^$E$66:$X$66)+($X$61*(1+C$96)/($B98-C$96))/(1+$B98)^19.5 -> 604328.97 | D98: =SUMPRODUCT($E$61:$X$61,1/(1+$B98)^$E$66:$X$66)+($X$61*(1+D$96)/($B98-D$96))/(1+$B98)^19.5 -> 647324.22 | E98: =SUMPRODUCT($E$61:$X$61,1/(1+$B98)^$E$66:$X$66)+($X$61*(1+E$96)/($B98-E$96))/(1+$B98)^19.5 -> 702449.48 | F98: =SUMPRODUCT($E$61:$X$61,1/(1+$B98)^$E$66:$X$66)+($X$61*(1+F$96)/($B98-F$96))/(1+$B98)^19.5 -> 775681.05 | G98: =SUMPRODUCT($E$61:$X$61,1/(1+$B98)^$E$66:$X$66)+($X$61*(1+G$96)/($B98-G$96))/(1+$B98)^19.5 -> 877692.55
B99: =$B$45 -> 0.075445353 | C99: =SUMPRODUCT($E$61:$X$61,1/(1+$B99)^$E$66:$X$66)+($X$61*(1+C$96)/($B99-C$96))/(1+$B99)^19.5 -> 471766.46 | D99: =SUMPRODUCT($E$61:$X$61,1/(1+$B99)^$E$66:$X$66)+($X$61*(1+D$96)/($B99-D$96))/(1+$B99)^19.5 -> 495536.76 | E99: =SUMPRODUCT($E$61:$X$61,1/(1+$B99)^$E$66:$X$66)+($X$61*(1+E$96)/($B99-E$96))/(1+$B99)^19.5 -> 524537.59 | F99: =SUMPRODUCT($E$61:$X$61,1/(1+$B99)^$E$66:$X$66)+($X$61*(1+F$96)/($B99-F$96))/(1+$B99)^19.5 -> 560708.79 | G99: =SUMPRODUCT($E$61:$X$61,1/(1+$B99)^$E$66:$X$66)+($X$61*(1+G$96)/($B99-G$96))/(1+$B99)^19.5 -> 607084.77
B100: =$B$45+0.01 -> 0.085445353 | C100: =SUMPRODUCT($E$61:$X$61,1/(1+$B100)^$E$66:$X$66)+($X$61*(1+C$96)/($B100-C$96))/(1+$B100)^19.5 -> 381536.56 | D100: =SUMPRODUCT($E$61:$X$61,1/(1+$B100)^$E$66:$X$66)+($X$61*(1+D$96)/($B100-D$96))/(1+$B100)^19.5 -> 395698.29 | E100: =SUMPRODUCT($E$61:$X$61,1/(1+$B100)^$E$66:$X$66)+($X$61*(1+E$96)/($B100-E$96))/(1+$B100)^19.5 -> 412414.2 | F100: =SUMPRODUCT($E$61:$X$61,1/(1+$B100)^$E$66:$X$66)+($X$61*(1+F$96)/($B100-F$96))/(1+$B100)^19.5 -> 432443.78 | G100: =SUMPRODUCT($E$61:$X$61,1/(1+$B100)^$E$66:$X$66)+($X$61*(1+G$96)/($B100-G$96))/(1+$B100)^19.5 -> 456880.76
B101: =$B$45+0.02 -> 0.095445353 | C101: =SUMPRODUCT($E$61:$X$61,1/(1+$B101)^$E$66:$X$66)+($X$61*(1+C$96)/($B101-C$96))/(1+$B101)^19.5 -> 316625.99 | D101: =SUMPRODUCT($E$61:$X$61,1/(1+$B101)^$E$66:$X$66)+($X$61*(1+D$96)/($B101-D$96))/(1+$B101)^19.5 -> 325521.94 | E101: =SUMPRODUCT($E$61:$X$61,1/(1+$B101)^$E$66:$X$66)+($X$61*(1+E$96)/($B101-E$96))/(1+$B101)^19.5 -> 335777.18 | F101: =SUMPRODUCT($E$61:$X$61,1/(1+$B101)^$E$66:$X$66)+($X$61*(1+F$96)/($B101-F$96))/(1+$B101)^19.5 -> 347729.04 | G101: =SUMPRODUCT($E$61:$X$61,1/(1+$B101)^$E$66:$X$66)+($X$61*(1+G$96)/($B101-G$96))/(1+$B101)^19.5 -> 361836.51
A104: Table 2: EV ($M) — Terminal EBITDA Margin vs. EV/EBITDA Exit Multiple (Exit Method)
B106: ↑ Term. EBITDA Mgn \ Exit Mult → | C106: =$B$79-10 -> -4.0746803 | D106: =$B$79-5 -> 0.92531974 | E106: =$B$79 -> 5.9253197 | F106: =$B$79+5 -> 10.92532 | G106: =$B$79+10 -> 15.92532
B107: =$X$40-0.06 -> 0.64 | C107: =SUM($E$69:$X$69)+($X$49*$B107*C$106)/(1+$B$45)^19.5 -> 179397.49 | D107: =SUM($E$69:$X$69)+($X$49*$B107*D$106)/(1+$B$45)^19.5 -> 259051.38 | E107: =SUM($E$69:$X$69)+($X$49*$B107*E$106)/(1+$B$45)^19.5 -> 338705.27 | F107: =SUM($E$69:$X$69)+($X$49*$B107*F$106)/(1+$B$45)^19.5 -> 418359.17 | G107: =SUM($E$69:$X$69)+($X$49*$B107*G$106)/(1+$B$45)^19.5 -> 498013.06
B108: =$X$40-0.03 -> 0.67 | C108: =SUM($E$69:$X$69)+($X$49*$B108*C$106)/(1+$B$45)^19.5 -> 176354.7 | D108: =SUM($E$69:$X$69)+($X$49*$B108*D$106)/(1+$B$45)^19.5 -> 259742.37 | E108: =SUM($E$69:$X$69)+($X$49*$B108*E$106)/(1+$B$45)^19.5 -> 343130.04 | F108: =SUM($E$69:$X$69)+($X$49*$B108*F$106)/(1+$B$45)^19.5 -> 426517.71 | G108: =SUM($E$69:$X$69)+($X$49*$B108*G$106)/(1+$B$45)^19.5 -> 509905.38
B109: =$X$40 -> 0.7 | C109: =SUM($E$69:$X$69)+($X$49*$B109*C$106)/(1+$B$45)^19.5 -> 173311.91 | D109: =SUM($E$69:$X$69)+($X$49*$B109*D$106)/(1+$B$45)^19.5 -> 260433.35 | E109: =SUM($E$69:$X$69)+($X$49*$B109*E$106)/(1+$B$45)^19.5 -> 347554.8 | F109: =SUM($E$69:$X$69)+($X$49*$B109*F$106)/(1+$B$45)^19.5 -> 434676.25 | G109: =SUM($E$69:$X$69)+($X$49*$B109*G$106)/(1+$B$45)^19.5 -> 521797.69
B110: =$X$40+0.03 -> 0.73 | C110: =SUM($E$69:$X$69)+($X$49*$B110*C$106)/(1+$B$45)^19.5 -> 170269.12 | D110: =SUM($E$69:$X$69)+($X$49*$B110*D$106)/(1+$B$45)^19.5 -> 261124.34 | E110: =SUM($E$69:$X$69)+($X$49*$B110*E$106)/(1+$B$45)^19.5 -> 351979.56 | F110: =SUM($E$69:$X$69)+($X$49*$B110*F$106)/(1+$B$45)^19.5 -> 442834.79 | G110: =SUM($E$69:$X$69)+($X$49*$B110*G$106)/(1+$B$45)^19.5 -> 533690.01
B111: =$X$40+0.06 -> 0.76 | C111: =SUM($E$69:$X$69)+($X$49*$B111*C$106)/(1+$B$45)^19.5 -> 167226.33 | D111: =SUM($E$69:$X$69)+($X$49*$B111*D$106)/(1+$B$45)^19.5 -> 261815.33 | E111: =SUM($E$69:$X$69)+($X$49*$B111*E$106)/(1+$B$45)^19.5 -> 356404.33 | F111: =SUM($E$69:$X$69)+($X$49*$B111*F$106)/(1+$B$45)^19.5 -> 450993.33 | G111: =SUM($E$69:$X$69)+($X$49*$B111*G$106)/(1+$B$45)^19.5 -> 545582.33
A114: Table 3: EV ($M) — WACC vs. EV/EBITDA Exit Multiple (Exit Method)
B116: ↑ WACC \ Exit Multiple → | C116: =$B$79-10 -> -4.0746803 | D116: =$B$79-5 -> 0.92531974 | E116: =$B$79 -> 5.9253197 | F116: =$B$79+5 -> 10.92532 | G116: =$B$79+10 -> 15.92532
B117: =$B$45-0.02 -> 0.055445353 | C117: =SUMPRODUCT($E$61:$X$61,1/(1+$B117)^$E$66:$X$66)+($X$51*C$116)/(1+$B117)^19.5 -> 200041.24 | D117: =SUMPRODUCT($E$61:$X$61,1/(1+$B117)^$E$66:$X$66)+($X$51*D$116)/(1+$B117)^19.5 -> 325673.36 | E117: =SUMPRODUCT($E$61:$X$61,1/(1+$B117)^$E$66:$X$66)+($X$51*E$116)/(1+$B117)^19.5 -> 451305.47 | F117: =SUMPRODUCT($E$61:$X$61,1/(1+$B117)^$E$66:$X$66)+($X$51*F$116)/(1+$B117)^19.5 -> 576937.59 | G117: =SUMPRODUCT($E$61:$X$61,1/(1+$B117)^$E$66:$X$66)+($X$51*G$116)/(1+$B117)^19.5 -> 702569.71
B118: =$B$45-0.01 -> 0.065445353 | C118: =SUMPRODUCT($E$61:$X$61,1/(1+$B118)^$E$66:$X$66)+($X$51*C$116)/(1+$B118)^19.5 -> 186186.94 | D118: =SUMPRODUCT($E$61:$X$61,1/(1+$B118)^$E$66:$X$66)+($X$51*D$116)/(1+$B118)^19.5 -> 290716.67 | E118: =SUMPRODUCT($E$61:$X$61,1/(1+$B118)^$E$66:$X$66)+($X$51*E$116)/(1+$B118)^19.5 -> 395246.41 | F118: =SUMPRODUCT($E$61:$X$61,1/(1+$B118)^$E$66:$X$66)+($X$51*F$116)/(1+$B118)^19.5 -> 499776.14 | G118: =SUMPRODUCT($E$61:$X$61,1/(1+$B118)^$E$66:$X$66)+($X$51*G$116)/(1+$B118)^19.5 -> 604305.88
B119: =$B$45 -> 0.075445353 | C119: =SUMPRODUCT($E$61:$X$61,1/(1+$B119)^$E$66:$X$66)+($X$51*C$116)/(1+$B119)^19.5 -> 173311.91 | D119: =SUMPRODUCT($E$61:$X$61,1/(1+$B119)^$E$66:$X$66)+($X$51*D$116)/(1+$B119)^19.5 -> 260433.35 | E119: =SUMPRODUCT($E$61:$X$61,1/(1+$B119)^$E$66:$X$66)+($X$51*E$116)/(1+$B119)^19.5 -> 347554.8 | F119: =SUMPRODUCT($E$61:$X$61,1/(1+$B119)^$E$66:$X$66)+($X$51*F$116)/(1+$B119)^19.5 -> 434676.25 | G119: =SUMPRODUCT($E$61:$X$61,1/(1+$B119)^$E$66:$X$66)+($X$51*G$116)/(1+$B119)^19.5 -> 521797.69
B120: =$B$45+0.01 -> 0.085445353 | C120: =SUMPRODUCT($E$61:$X$61,1/(1+$B120)^$E$66:$X$66)+($X$51*C$116)/(1+$B120)^19.5 -> 161382.52 | D120: =SUMPRODUCT($E$61:$X$61,1/(1+$B120)^$E$66:$X$66)+($X$51*D$116)/(1+$B120)^19.5 -> 234117.37 | E120: =SUMPRODUCT($E$61:$X$61,1/(1+$B120)^$E$66:$X$66)+($X$51*E$116)/(1+$B120)^19.5 -> 306852.22 | F120: =SUMPRODUCT($E$61:$X$61,1/(1+$B120)^$E$66:$X$66)+($X$51*F$116)/(1+$B120)^19.5 -> 379587.07 | G120: =SUMPRODUCT($E$61:$X$61,1/(1+$B120)^$E$66:$X$66)+($X$51*G$116)/(1+$B120)^19.5 -> 452321.92
B121: =$B$45+0.02 -> 0.095445353 | C121: =SUMPRODUCT($E$61:$X$61,1/(1+$B121)^$E$66:$X$66)+($X$51*C$116)/(1+$B121)^19.5 -> 150354.31 | D121: =SUMPRODUCT($E$61:$X$61,1/(1+$B121)^$E$66:$X$66)+($X$51*D$116)/(1+$B121)^19.5 -> 211178.85 | E121: =SUMPRODUCT($E$61:$X$61,1/(1+$B121)^$E$66:$X$66)+($X$51*E$116)/(1+$B121)^19.5 -> 272003.4 | F121: =SUMPRODUCT($E$61:$X$61,1/(1+$B121)^$E$66:$X$66)+($X$51*F$116)/(1+$B121)^19.5 -> 332827.94 | G121: =SUMPRODUCT($E$61:$X$61,1/(1+$B121)^$E$66:$X$66)+($X$51*G$116)/(1+$B121)^19.5 -> 393652.49
...

Sheet Space DCF
A1: SpaceX — Space Segment DCF (Launch & Starship)
A2: S-1 Filed May 20, 2026 | 20-Year Explicit Forecast FY2026E–FY2045E | $ in Millions
A5: SCENARIO SELECTOR | B5: =COVER!B29 -> 2 | C5: =IF(B5=1,"◀ BEAR",IF(B5=2,"◀ BASE","◀ BULL")) -> ◀ BASE | D5: (1 = Bear | 2 = Base | 3 = Bull)
A7: BEAR CASE ASSUMPTIONS
B8: FY2023A | C8: FY2024A | D8: FY2025A | E8: FY2026E | F8: FY2027E | G8: FY2028E | H8: FY2029E | I8: FY2030E | J8: FY2031E | K8: FY2032E | L8: FY2033E | M8: FY2034E | N8: FY2035E | O8: FY2036E | P8: FY2037E | Q8: FY2038E | R8: FY2039E | S8: FY2040E | T8: FY2041E | U8: FY2042E | V8: FY2043E | W8: FY2044E | X8: FY2045E
A9: Revenue Growth % (YoY) | E9: 0.06 | F9: 0.08 | G9: 0.1 | H9: 0.12 | I9: 0.15 | J9: 0.15 | K9: 0.13 | L9: 0.12 | M9: 0.1 | N9: 0.08 | O9: 0.07 | P9: 0.06 | Q9: 0.05 | R9: 0.045 | S9: 0.04 | T9: 0.035 | U9: 0.03 | V9: 0.03 | W9: 0.028 | X9: 0.025
A10: EBITDA Margin % | E10: 0.1 | F10: 0.12 | G10: 0.15 | H10: 0.18 | I10: 0.22 | J10: 0.25 | K10: 0.27 | L10: 0.28 | M10: 0.29 | N10: 0.3 | O10: 0.31 | P10: 0.32 | Q10: 0.33 | R10: 0.34 | S10: 0.34 | T10: 0.35 | U10: 0.36 | V10: 0.37 | W10: 0.37 | X10: 0.38
A11: D&A % of Revenue | E11: 0.19 | F11: 0.18 | G11: 0.17 | H11: 0.16 | I11: 0.15 | J11: 0.14 | K11: 0.14 | L11: 0.13 | M11: 0.13 | N11: 0.12 | O11: 0.12 | P11: 0.12 | Q11: 0.115 | R11: 0.115 | S11: 0.11 | T11: 0.11 | U11: 0.11 | V11: 0.11 | W11: 0.11 | X11: 0.11
A12: Capex % of Revenue | E12: 0.85 | F12: 0.75 | G12: 0.65 | H12: 0.55 | I12: 0.45 | J12: 0.38 | K12: 0.32 | L12: 0.28 | M12: 0.24 | N12: 0.22 | O12: 0.21 | P12: 0.2 | Q12: 0.19 | R12: 0.18 | S12: 0.17 | T12: 0.16 | U12: 0.15 | V12: 0.14 | W12: 0.13 | X12: 0.12
A13: ΔNW Cap % of ΔRevenue | E13: 0.06 | F13: 0.06 | G13: 0.05 | H13: 0.05 | I13: 0.05 | J13: 0.04 | K13: 0.04 | L13: 0.03 | M13: 0.03 | N13: 0.03 | O13: 0.03 | P13: 0.03 | Q13: 0.025 | R13: 0.025 | S13: 0.025 | T13: 0.025 | U13: 0.02 | V13: 0.02 | W13: 0.02 | X13: 0.02
A14: Terminal Growth Rate | B14: =WACC!D48 -> 0.02
A15: WACC | B15: =WACC!B48 -> 0.079328832
A17: BASE CASE ASSUMPTIONS
B18: FY2023A | C18: FY2024A | D18: FY2025A | E18: FY2026E | F18: FY2027E | G18: FY2028E | H18: FY2029E | I18: FY2030E | J18: FY2031E | K18: FY2032E | L18: FY2033E | M18: FY2034E | N18: FY2035E | O18: FY2036E | P18: FY2037E | Q18: FY2038E | R18: FY2039E | S18: FY2040E | T18: FY2041E | U18: FY2042E | V18: FY2043E | W18: FY2044E | X18: FY2045E
A19: Revenue Growth % (YoY) | E19: 0.1 | F19: 0.14 | G19: 0.18 | H19: 0.22 | I19: 0.26 | J19: 0.22 | K19: 0.18 | L19: 0.15 | M19: 0.13 | N19: 0.11 | O19: 0.1 | P19: 0.09 | Q19: 0.08 | R19: 0.07 | S19: 0.06 | T19: 0.05 | U19: 0.045 | V19: 0.04 | W19: 0.035 | X19: 0.03
A20: EBITDA Margin % | E20: 0.14 | F20: 0.18 | G20: 0.24 | H20: 0.3 | I20: 0.36 | J20: 0.41 | K20: 0.45 | L20: 0.47 | M20: 0.48 | N20: 0.49 | O20: 0.5 | P20: 0.51 | Q20: 0.52 | R20: 0.52 | S20: 0.53 | T20: 0.54 | U20: 0.54 | V20: 0.55 | W20: 0.55 | X20: 0.56
A21: D&A % of Revenue | E21: 0.19 | F21: 0.18 | G21: 0.17 | H21: 0.16 | I21: 0.15 | J21: 0.14 | K21: 0.14 | L21: 0.13 | M21: 0.13 | N21: 0.12 | O21: 0.12 | P21: 0.115 | Q21: 0.115 | R21: 0.11 | S21: 0.11 | T21: 0.11 | U21: 0.105 | V21: 0.105 | W21: 0.105 | X21: 0.105
A22: Capex % of Revenue | E22: 0.75 | F22: 0.65 | G22: 0.55 | H22: 0.45 | I22: 0.36 | J22: 0.28 | K22: 0.22 | L22: 0.18 | M22: 0.15 | N22: 0.13 | O22: 0.125 | P22: 0.12 | Q22: 0.115 | R22: 0.11 | S22: 0.105 | T22: 0.1 | U22: 0.098 | V22: 0.095 | W22: 0.092 | X22: 0.09
A23: ΔNW Cap % of ΔRevenue | E23: 0.05 | F23: 0.05 | G23: 0.05 | H23: 0.04 | I23: 0.04 | J23: 0.04 | K23: 0.03 | L23: 0.03 | M23: 0.02 | N23: 0.02 | O23: 0.02 | P23: 0.02 | Q23: 0.02 | R23: 0.018 | S23: 0.018 | T23: 0.015 | U23: 0.015 | V23: 0.015 | W23: 0.015 | X23: 0.015
A24: Terminal Growth Rate | B24: =WACC!C48 -> 0.025
A25: WACC | B25: =WACC!B48 -> 0.079328832
A27: BULL CASE ASSUMPTIONS
B28: FY2023A | C28: FY2024A | D28: FY2025A | E28: FY2026E | F28: FY2027E | G28: FY2028E | H28: FY2029E | I28: FY2030E | J28: FY2031E | K28: FY2032E | L28: FY2033E | M28: FY2034E | N28: FY2035E | O28: FY2036E | P28: FY2037E | Q28: FY2038E | R28: FY2039E | S28: FY2040E | T28: FY2041E | U28: FY2042E | V28: FY2043E | W28: FY2044E | X28: FY2045E
A29: Revenue Growth % (YoY) | E29: 0.16 | F29: 0.22 | G29: 0.28 | H29: 0.32 | I29: 0.36 | J29: 0.3 | K29: 0.25 | L29: 0.2 | M29: 0.17 | N29: 0.14 | O29: 0.13 | P29: 0.12 | Q29: 0.11 | R29: 0.1 | S29: 0.09 | T29: 0.08 | U29: 0.07 | V29: 0.06 | W29: 0.05 | X29: 0.04
A30: EBITDA Margin % | E30: 0.18 | F30: 0.24 | G30: 0.32 | H30: 0.4 | I30: 0.46 | J30: 0.5 | K30: 0.52 | L30: 0.53 | M30: 0.54 | N30: 0.55 | O30: 0.56 | P30: 0.57 | Q30: 0.58 | R30: 0.59 | S30: 0.59 | T30: 0.6 | U30: 0.61 | V30: 0.61 | W30: 0.62 | X30: 0.62
A31: D&A % of Revenue | E31: 0.19 | F31: 0.18 | G31: 0.17 | H31: 0.16 | I31: 0.15 | J31: 0.14 | K31: 0.14 | L31: 0.13 | M31: 0.13 | N31: 0.12 | O31: 0.12 | P31: 0.115 | Q31: 0.11 | R31: 0.11 | S31: 0.105 | T31: 0.105 | U31: 0.1 | V31: 0.1 | W31: 0.1 | X31: 0.1
A32: Capex % of Revenue | E32: 0.7 | F32: 0.6 | G32: 0.5 | H32: 0.4 | I32: 0.31 | J32: 0.24 | K32: 0.19 | L32: 0.16 | M32: 0.13 | N32: 0.11 | O32: 0.11 | P32: 0.105 | Q32: 0.1 | R32: 0.098 | S32: 0.095 | T32: 0.092 | U32: 0.09 | V32: 0.088 | W32: 0.085 | X32: 0.08
A33: ΔNW Cap % of ΔRevenue | E33: 0.04 | F33: 0.04 | G33: 0.04 | H33: 0.03 | I33: 0.03 | J33: 0.03 | K33: 0.02 | L33: 0.02 | M33: 0.02 | N33: 0.02 | O33: 0.02 | P33: 0.018 | Q33: 0.018 | R33: 0.015 | S33: 0.015 | T33: 0.015 | U33: 0.012 | V33: 0.012 | W33: 0.012 | X33: 0.012
A34: Terminal Growth Rate | B34: =WACC!E48 -> 0.03
A35: WACC | B35: =WACC!B48 -> 0.079328832
A37: SELECTED CASE ASSUMPTIONS
B38: FY2023A | C38: FY2024A | D38: FY2025A | E38: FY2026E | F38: FY2027E | G38: FY2028E | H38: FY2029E | I38: FY2030E | J38: FY2031E | K38: FY2032E | L38: FY2033E | M38: FY2034E | N38: FY2035E | O38: FY2036E | P38: FY2037E | Q38: FY2038E | R38: FY2039E | S38: FY2040E | T38: FY2041E | U38: FY2042E | V38: FY2043E | W38: FY2044E | X38: FY2045E
A39: Revenue Growth % (YoY) | E39: =IF($B$5=1,E9,IF($B$5=2,E19,E29)) -> 0.1 | F39: =IF($B$5=1,F9,IF($B$5=2,F19,F29)) -> 0.14 | G39: =IF($B$5=1,G9,IF($B$5=2,G19,G29)) -> 0.18 | H39: =IF($B$5=1,H9,IF($B$5=2,H19,H29)) -> 0.22 | I39: =IF($B$5=1,I9,IF($B$5=2,I19,I29)) -> 0.26 | J39: =IF($B$5=1,J9,IF($B$5=2,J19,J29)) -> 0.22 | K39: =IF($B$5=1,K9,IF($B$5=2,K19,K29)) -> 0.18 | L39: =IF($B$5=1,L9,IF($B$5=2,L19,L29)) -> 0.15 | ... X39: =IF($B$5=1,X9,IF($B$5=2,X19,X29)) -> 0.03
A40: EBITDA Margin % | E40: =IF($B$5=1,E10,IF($B$5=2,E20,E30)) -> 0.14 | F40: =IF($B$5=1,F10,IF($B$5=2,F20,F30)) -> 0.18 | G40: =IF($B$5=1,G10,IF($B$5=2,G20,G30)) -> 0.24 | H40: =IF($B$5=1,H10,IF($B$5=2,H20,H30)) -> 0.3 | I40: =IF($B$5=1,I10,IF($B$5=2,I20,I30)) -> 0.36 | J40: =IF($B$5=1,J10,IF($B$5=2,J20,J30)) -> 0.41 | K40: =IF($B$5=1,K10,IF($B$5=2,K20,K30)) -> 0.45 | L40: =IF($B$5=1,L10,IF($B$5=2,L20,L30)) -> 0.47 | ... X40: =IF($B$5=1,X10,IF($B$5=2,X20,X30)) -> 0.56
A41: D&A % of Revenue | E41: =IF($B$5=1,E11,IF($B$5=2,E21,E31)) -> 0.19 | F41: =IF($B$5=1,F11,IF($B$5=2,F21,F31)) -> 0.18 | G41: =IF($B$5=1,G11,IF($B$5=2,G21,G31)) -> 0.17 | H41: =IF($B$5=1,H11,IF($B$5=2,H21,H31)) -> 0.16 | I41: =IF($B$5=1,I11,IF($B$5=2,I21,I31)) -> 0.15 | J41: =IF($B$5=1,J11,IF($B$5=2,J21,J31)) -> 0.14 | K41: =IF($B$5=1,K11,IF($B$5=2,K21,K31)) -> 0.14 | L41: =IF($B$5=1,L11,IF($B$5=2,L21,L31)) -> 0.13 | ... X41: =IF($B$5=1,X11,IF($B$5=2,X21,X31)) -> 0.105
A42: Capex % of Revenue | E42: =IF($B$5=1,E12,IF($B$5=2,E22,E32)) -> 0.75 | F42: =IF($B$5=1,F12,IF($B$5=2,F22,F32)) -> 0.65 | G42: =IF($B$5=1,G12,IF($B$5=2,G22,G32)) -> 0.55 | H42: =IF($B$5=1,H12,IF($B$5=2,H22,H32)) -> 0.45 | I42: =IF($B$5=1,I12,IF($B$5=2,I22,I32)) -> 0.36 | J42: =IF($B$5=1,J12,IF($B$5=2,J22,J32)) -> 0.28 | K42: =IF($B$5=1,K12,IF($B$5=2,K22,K32)) -> 0.22 | L42: =IF($B$5=1,L12,IF($B$5=2,L22,L32)) -> 0.18 | ... X42: =IF($B$5=1,X12,IF($B$5=2,X22,X32)) -> 0.09
A43: ΔNW Cap % of ΔRevenue | E43: =IF($B$5=1,E13,IF($B$5=2,E23,E33)) -> 0.05 | F43: =IF($B$5=1,F13,IF($B$5=2,F23,F33)) -> 0.05 | G43: =IF($B$5=1,G13,IF($B$5=2,G23,G33)) -> 0.05 | H43: =IF($B$5=1,H13,IF($B$5=2,H23,H33)) -> 0.04 | I43: =IF($B$5=1,I13,IF($B$5=2,I23,I33)) -> 0.04 | J43: =IF($B$5=1,J13,IF($B$5=2,J23,J33)) -> 0.04 | K43: =IF($B$5=1,K13,IF($B$5=2,K23,K33)) -> 0.03 | L43: =IF($B$5=1,L13,IF($B$5=2,L23,L33)) -> 0.03 | ... X43: =IF($B$5=1,X13,IF($B$5=2,X23,X33)) -> 0.015
A44: Terminal Growth Rate | B44: =IF($B$5=1,B14,IF($B$5=2,B24,B34)) -> 0.025
A45: WACC | B45: =IF($B$5=1,B15,IF($B$5=2,B25,B35)) -> 0.079328832
A47: SPACE SEGMENT — INCOME STATEMENT & FREE CASH FLOW ($M)
B48: FY2023A | C48: FY2024A | D48: FY2025A | E48: FY2026E | F48: FY2027E | G48: FY2028E | H48: FY2029E | I48: FY2030E | J48: FY2031E | K48: FY2032E | L48: FY2033E | M48: FY2034E | N48: FY2035E | O48: FY2036E | P48: FY2037E | Q48: FY2038E | R48: FY2039E | S48: FY2040E | T48: FY2041E | U48: FY2042E | V48: FY2043E | W48: FY2044E | X48: FY2045E
A49: Revenue | B49: 3557 | C49: 3796 | D49: =Actuals!D8 -> 4086 | E49: =D49*(1+E39) -> 4494.6 | F49: =E49*(1+F39) -> 5123.844 | G49: =F49*(1+G39) -> 6046.1359 | H49: =G49*(1+H39) -> 7376.2858 | I49: =H49*(1+I39) -> 9294.1201 | J49: =I49*(1+J39) -> 11338.827 | K49: =J49*(1+K39) -> 13379.815 | L49: =K49*(1+L39) -> 15386.788 | ... X49: =W49*(1+X39) -> 34482.478
A50: % YoY Growth | C50: =C49/B49-1 -> 0.067191453 | D50: =D49/C49-1 -> 0.076396207 | E50: =E49/D49-1 -> 0.1 | F50: =F49/E49-1 -> 0.14 | G50: =G49/F49-1 -> 0.18 | H50: =H49/G49-1 -> 0.22 | I50: =I49/H49-1 -> 0.26 | J50: =J49/I49-1 -> 0.22 | ... X50: =X49/W49-1 -> 0.03
A51: EBITDA | B51: 570 | C51: 658 | D51: =Actuals!D11 -> 653 | E51: =E49*E40 -> 629.244 | F51: =F49*F40 -> 922.29192 | G51: =G49*G40 -> 1451.0726 | H51: =H49*H40 -> 2212.8857 | I51: =I49*I40 -> 3345.8832 | J51: =J49*J40 -> 4648.9189 | K51: =K49*K40 -> 6020.9169 | L51: =L49*L40 -> 7231.7902 | ... X51: =X49*X40 -> 19310.188
A52: EBITDA Margin % | B52: =B51/B49 -> 0.1602474 | C52: =C51/C49 -> 0.17334036 | D52: =D51/D49 -> 0.159814 | E52: =E51/E49 -> 0.14 | F52: =F51/F49 -> 0.18 | G52: =G51/G49 -> 0.24 | H52: =H51/H49 -> 0.3 | I52: =I51/I49 -> 0.36 | ... X52: =X51/X49 -> 0.56
A53: Depreciation & Amortization | B53: 571 | C53: 637 | D53: 757 | E53: =E49*E41 -> 853.974 | F53: =F49*F41 -> 922.29192 | G53: =G49*G41 -> 1027.8431 | H53: =H49*H41 -> 1180.2057 | I53: =I49*I41 -> 1394.118 | J53: =J49*J41 -> 1587.4357 | K53: =K49*K41 -> 1873.1741 | L53: =L49*L41 -> 2000.2824 | ... X53: =X49*X41 -> 3620.6602
A54: EBIT (EBITDA − D&A) | B54: =B51-B53 -> -1 | C54: =C51-C53 -> 21 | D54: =D51-D53 -> -104 | E54: =E51-E53 -> -224.73 | F54: =F51-F53 -> 0 | G54: =G51-G53 -> 423.22951 | H54: =H51-H53 -> 1032.68 | I54: =I51-I53 -> 1951.7652 | ... X54: =X51-X53 -> 15689.527
A55: EBIT Margin % | B55: =B54/B49 -> -0.00028113579 | C55: =C54/C49 -> 0.0055321391 | D55: =D54/D49 -> -0.025452766 | E55: =E54/E49 -> -0.05 | F55: =F54/F49 -> 0 | G55: =G54/G49 -> 0.07 | H55: =H54/H49 -> 0.14 | I55: =I54/I49 -> 0.21 | ... X55: =X54/X49 -> 0.455
A56: (–) Tax on EBIT | B56: =MAX(B54,0)*WACC!$B$8 -> 0 | C56: =MAX(C54,0)*WACC!$B$8 -> 4.41 | D56: =MAX(D54,0)*WACC!$B$8 -> 0 | E56: =MAX(E54,0)*WACC!$B$8 -> 0 | F56: =MAX(F54,0)*WACC!$B$8 -> 0 | G56: =MAX(G54,0)*WACC!$B$8 -> 88.878198 | H56: =MAX(H54,0)*WACC!$B$8 -> 216.8628 | I56: =MAX(I54,0)*WACC!$B$8 -> 409.8707 | ... X56: =MAX(X54,0)*WACC!$B$8 -> 3294.8008
A57: NOPAT | B57: =B54-B56 -> -1 | C57: =C54-C56 -> 16.59 | D57: =D54-D56 -> -104 | E57: =E54-E56 -> -224.73 | F57: =F54-F56 -> 0 | G57: =G54-G56 -> 334.35132 | H57: =H54-H56 -> 815.81721 | I57: =I54-I56 -> 1541.8945 | ... X57: =X54-X56 -> 12394.727
A58: (+) D&A | B58: =B53 -> 571 | C58: =C53 -> 637 | D58: =D53 -> 757 | E58: =E53 -> 853.974 | F58: =F53 -> 922.29192 | G58: =G53 -> 1027.8431 | H58: =H53 -> 1180.2057 | I58: =I53 -> 1394.118 | ... X58: =X53 -> 3620.6602
A59: (–) Capital Expenditures | B59: -1497 | C59: -2032 | D59: -3832 | E59: =-E49*E42 -> -3370.95 | F59: =-F49*F42 -> -3330.4986 | G59: =-G49*G42 -> -3325.3748 | H59: =-H49*H42 -> -3319.3286 | I59: =-I49*I42 -> -3345.8832 | J59: =-J49*J42 -> -3174.8714 | K59: =-K49*K42 -> -2943.5594 | L59: =-L49*L42 -> -2769.6218 | ... X59: =-X49*X42 -> -3103.423
A60: (–) Increase in Net Working Capital | B60: 0 | C60: 0 | D60: 0 | E60: =-(E49-D49)*E43 -> -20.43 | F60: =-(F49-E49)*F43 -> -31.4622 | G60: =-(G49-F49)*G43 -> -46.114596 | H60: =-(H49-G49)*H43 -> -53.205996 | I60: =-(I49-H49)*I43 -> -76.713373 | J60: =-(J49-I49)*J43 -> -81.788257 | K60: =-(K49-J49)*K43 -> -61.229663 | L60: =-(L49-K49)*L43 -> -60.209169 | ... X60: =-(X49-W49)*X43 -> -15.06516
A61: Unlevered Free Cash Flow | B61: =B57+B58+B59+B60 -> -927 | C61: =C57+C58+C59+C60 -> -1378.41 | D61: =D57+D58+D59+D60 -> -3179 | E61: =E57+E58+E59+E60 -> -2762.136 | F61: =F57+F58+F59+F60 -> -2439.6689 | G61: =G57+G58+G59+G60 -> -2009.2949 | H61: =H57+H58+H59+H60 -> -1376.5117 | I61: =I57+I58+I59+I60 -> -486.58407 | ... X61: =X57+X58+X59+X60 -> 12896.899
A62: FCF Margin % | B62: =B61/B49 -> -0.26061288 | C62: =C61/C49 -> -0.36312171 | D62: =D61/D49 -> -0.77802252 | E62: =E61/E49 -> -0.61454545 | F62: =F61/F49 -> -0.47614035 | G62: =G61/G49 -> -0.33232712 | H62: =H61/H49 -> -0.18661311 | I62: =I61/I49 -> -0.052353968 | ... X62: =X61/X49 -> 0.37401311
A64: DCF — DISCOUNT FACTORS & PRESENT VALUES (Mid-Year Convention)
E65: FY2026E | F65: FY2027E | G65: FY2028E | H65: FY2029E | I65: FY2030E | J65: FY2031E | K65: FY2032E | L65: FY2033E | M65: FY2034E | N65: FY2035E | O65: FY2036E | P65: FY2037E | Q65: FY2038E | R65: FY2039E | S65: FY2040E | T65: FY2041E | U65: FY2042E | V65: FY2043E | W65: FY2044E | X65: FY2045E
A66: Discount Period (mid-year) | E66: 0.5 | F66: 1.5 | G66: 2.5 | H66: 3.5 | I66: 4.5 | J66: 5.5 | K66: 6.5 | L66: 7.5 | M66: 8.5 | N66: 9.5 | O66: 10.5 | P66: 11.5 | Q66: 12.5 | R66: 13.5 | S66: 14.5 | T66: 15.5 | U66: 16.5 | V66: 17.5 | W66: 18.5 | X66: 19.5
A67: Discount Factor | E67: =1/(1+$B$45)^E66 -> 0.96254958 | F67: =1/(1+$B$45)^F66 -> 0.89180383 | G67: =1/(1+$B$45)^G66 -> 0.82625777 | H67: =1/(1+$B$45)^H66 -> 0.76552923 | I67: =1/(1+$B$45)^I66 -> 0.70926413 | J67: =1/(1+$B$45)^J66 -> 0.65713442 | K67: =1/(1+$B$45)^K66 -> 0.60883616 | L67: =1/(1+$B$45)^L66 -> 0.56408774 | ... X67: =1/(1+$B$45)^X66 -> 0.22568429
A68: Unlevered FCF ($M) | E68: =E61 -> -2762.136 | F68: =F61 -> -2439.6689 | G68: =G61 -> -2009.2949 | H68: =H61 -> -1376.5117 | I68: =I61 -> -486.58407 | J68: =J61 -> 749.34773 | K68: =K61 -> 2145.1019 | L68: =L61 -> 3303.3426 | ... X68: =X61 -> 12896.899
A69: PV of FCF ($M) | E69: =E68*E67 -> -2658.6929 | F69: =F68*F67 -> -2175.706 | G69: =G68*G67 -> -1660.1955 | H69: =H68*H67 -> -1053.7599 | I69: =I68*I67 -> -345.11663 | J69: =J68*J67 -> 492.42219 | K69: =K68*K67 -> 1306.0156 | L69: =L68*L67 -> 1863.3751 | ... X69: =X68*X67 -> 2910.6274
A71: TERMINAL VALUE
A72: Gordon Growth Model
A73: Terminal FCF ($M) | B73: =X61 -> 12896.899
A74: Terminal FCF × (1+g) | B74: =X61*(1+$B$44) -> 13219.321
A75: Terminal Value (Gordon Growth) | B75: =B74/($B$45-$B$44) -> 243320.55
A76: PV of Terminal Value (Gordon Growth) | B76: =B75/(1+$B$45)^19.5 -> 54913.624
A78: EV/EBITDA Exit Multiple Method
A79: Exit EV/EBITDA Multiple | B79: =IF(N('Space Comps'!K37)>0,'Space Comps'!K37,18) -> 15.138889 | D79: =IF(N('Space Comps'!K37)>0,"✓ LIVE — "&TEXT('Space Comps'!K37,"0.0x")&" from Space Comps mature tier","⚠ FALLBACK — using 18x default") -> ✓ LIVE — 15.1x from Space Comps mature tier
A80: Terminal Year EBITDA ($M) | B80: =X51 -> 19310.188
A81: Terminal Value (Exit Multiple) | B81: =B79*B80 -> 292334.79
A82: PV of Terminal Value (Exit Multiple) | B82: =B81/(1+$B$45)^19.5 -> 65975.367
A84: SPACE SEGMENT VALUATION SUMMARY
B85: Gordon Growth | C85: Exit Multiple
A86: Sum of PV of FCFs ($M) | B86: =SUM(E69:X69) -> 30939.435 | C86: =SUM(E69:X69) -> 30939.435
A87: PV of Terminal Value ($M) | B87: =B76 -> 54913.624 | C87: =B82 -> 65975.367
A88: Enterprise Value ($M) | B88: =B86+B87 -> 85853.059 | C88: =C86+C87 -> 96914.802
A90: TV % of Enterprise Value | B90: =B87/B88 -> 0.63962338 | C90: =C87/C88 -> 0.68075635
A92: SENSITIVITY ANALYSIS — SPACE SEGMENT EV ($M)
A94: Table 1: EV ($M) — WACC vs. Terminal Growth Rate (Gordon Growth)
B96: ↑ WACC \ Tg → | C96: =$B$44-0.01 -> 0.015 | D96: =$B$44-0.005 -> 0.02 | E96: =$B$44 -> 0.025 | F96: =$B$44+0.005 -> 0.03 | G96: =$B$44+0.01 -> 0.035
B97: =$B$45-0.02 -> 0.059328832 | C97: =SUMPRODUCT($E$61:$X$61,1/(1+$B97)^$E$66:$X$66)+($X$61*(1+C$96)/($B97-C$96))/(1+$B97)^19.5 -> 137925.2 | D97: =SUMPRODUCT($E$61:$X$61,1/(1+$B97)^$E$66:$X$66)+($X$61*(1+D$96)/($B97-D$96))/(1+$B97)^19.5 -> 150659.89 | E97: =SUMPRODUCT($E$61:$X$61,1/(1+$B97)^$E$66:$X$66)+($X$61*(1+E$96)/($B97-E$96))/(1+$B97)^19.5 -> 167104.19 | F97: =SUMPRODUCT($E$61:$X$61,1/(1+$B97)^$E$66:$X$66)+($X$61*(1+F$96)/($B97-F$96))/(1+$B97)^19.5 -> 189155.37 | G97: =SUMPRODUCT($E$61:$X$61,1/(1+$B97)^$E$66:$X$66)+($X$61*(1+G$96)/($B97-G$96))/(1+$B97)^19.5 -> 220270.36
B98: =$B$45-0.01 -> 0.069328832 | C98: =SUMPRODUCT($E$61:$X$61,1/(1+$B98)^$E$66:$X$66)+($X$61*(1+C$96)/($B98-C$96))/(1+$B98)^19.5 -> 101233.35 | D98: =SUMPRODUCT($E$61:$X$61,1/(1+$B98)^$E$66:$X$66)+($X$61*(1+D$96)/($B98-D$96))/(1+$B98)^19.5 -> 108195.86 | E98: =SUMPRODUCT($E$61:$X$61,1/(1+$B98)^$E$66:$X$66)+($X$61*(1+E$96)/($B98-E$96))/(1+$B98)^19.5 -> 116729.01 | F98: =SUMPRODUCT($E$61:$X$61,1/(1+$B98)^$E$66:$X$66)+($X$61*(1+F$96)/($B98-F$96))/(1+$B98)^19.5 -> 127431.86 | G98: =SUMPRODUCT($E$61:$X$61,1/(1+$B98)^$E$66:$X$66)+($X$61*(1+G$96)/($B98-G$96))/(1+$B98)^19.5 -> 141252.45
B99: =$B$45 -> 0.079328832 | C99: =SUMPRODUCT($E$61:$X$61,1/(1+$B99)^$E$66:$X$66)+($X$61*(1+C$96)/($B99-C$96))/(1+$B99)^19.5 -> 76864.205 | D99: =SUMPRODUCT($E$61:$X$61,1/(1+$B99)^$E$66:$X$66)+($X$61*(1+D$96)/($B99-D$96))/(1+$B99)^19.5 -> 80979.86 | E99: =SUMPRODUCT($E$61:$X$61,1/(1+$B99)^$E$66:$X$66)+($X$61*(1+E$96)/($B99-E$96))/(1+$B99)^19.5 -> 85853.059 | F99: =SUMPRODUCT($E$61:$X$61,1/(1+$B99)^$E$66:$X$66)+($X$61*(1+F$96)/($B99-F$96))/(1+$B99)^19.5 -> 91714.16 | G99: =SUMPRODUCT($E$61:$X$61,1/(1+$B99)^$E$66:$X$66)+($X$61*(1+G$96)/($B99-G$96))/(1+$B99)^19.5 -> 98897.448
B100: =$B$45+0.01 -> 0.089328832 | C100: =SUMPRODUCT($E$61:$X$61,1/(1+$B100)^$E$66:$X$66)+($X$61*(1+C$96)/($B100-C$96))/(1+$B100)^19.5 -> 59748.859 | D100: =SUMPRODUCT($E$61:$X$61,1/(1+$B100)^$E$66:$X$66)+($X$61*(1+D$96)/($B100-D$96))/(1+$B100)^19.5 -> 62318.915 | E100: =SUMPRODUCT($E$61:$X$61,1/(1+$B100)^$E$66:$X$66)+($X$61*(1+E$96)/($B100-E$96))/(1+$B100)^19.5 -> 65288.49 | F100: =SUMPRODUCT($E$61:$X$61,1/(1+$B100)^$E$66:$X$66)+($X$61*(1+F$96)/($B100-F$96))/(1+$B100)^19.5 -> 68758.593 | G100: =SUMPRODUCT($E$61:$X$61,1/(1+$B100)^$E$66:$X$66)+($X$61*(1+G$96)/($B100-G$96))/(1+$B100)^19.5 -> 72867.418
B101: =$B$45+0.02 -> 0.099328832 | C101: =SUMPRODUCT($E$61:$X$61,1/(1+$B101)^$E$66:$X$66)+($X$61*(1+C$96)/($B101-C$96))/(1+$B101)^19.5 -> 47234.39 | D101: =SUMPRODUCT($E$61:$X$61,1/(1+$B101)^$E$66:$X$66)+($X$61*(1+D$96)/($B101-D$96))/(1+$B101)^19.5 -> 48906.201 | E101: =SUMPRODUCT($E$61:$X$61,1/(1+$B101)^$E$66:$X$66)+($X$61*(1+E$96)/($B101-E$96))/(1+$B101)^19.5 -> 50802.933 | F101: =SUMPRODUCT($E$61:$X$61,1/(1+$B101)^$E$66:$X$66)+($X$61*(1+F$96)/($B101-F$96))/(1+$B101)^19.5 -> 52973.25 | G101: =SUMPRODUCT($E$61:$X$61,1/(1+$B101)^$E$66:$X$66)+($X$61*(1+G$96)/($B101-G$96))/(1+$B101)^19.5 -> 55480.945
A104: Table 2: EV ($M) — WACC vs. EV/EBITDA Exit Multiple
B106: ↑ WACC \ Multiple → | C106: =$B$79-8 -> 7.1388889 | D106: =$B$79-4 -> 11.138889 | E106: =$B$79 -> 15.138889 | F106: =$B$79+4 -> 19.138889 | G106: =$B$79+8 -> 23.138889
B107: =$B$45-0.02 -> 0.059328832 | C107: =SUMPRODUCT($E$61:$X$61,1/(1+$B107)^$E$66:$X$66)+($X$51*C$106)/(1+$B107)^19.5 -> 86752.759 | D107: =SUMPRODUCT($E$61:$X$61,1/(1+$B107)^$E$66:$X$66)+($X$51*D$106)/(1+$B107)^19.5 -> 111856.94 | E107: =SUMPRODUCT($E$61:$X$61,1/(1+$B107)^$E$66:$X$66)+($X$51*E$106)/(1+$B107)^19.5 -> 136961.12 | F107: =SUMPRODUCT($E$61:$X$61,1/(1+$B107)^$E$66:$X$66)+($X$51*F$106)/(1+$B107)^19.5 -> 162065.3 | G107: =SUMPRODUCT($E$61:$X$61,1/(1+$B107)^$E$66:$X$66)+($X$51*G$106)/(1+$B107)^19.5 -> 187169.48
B108: =$B$45-0.01 -> 0.069328832 | C108: =SUMPRODUCT($E$61:$X$61,1/(1+$B108)^$E$66:$X$66)+($X$51*C$106)/(1+$B108)^19.5 -> 73336.13 | D108: =SUMPRODUCT($E$61:$X$61,1/(1+$B108)^$E$66:$X$66)+($X$51*D$106)/(1+$B108)^19.5 -> 94237.589 | E108: =SUMPRODUCT($E$61:$X$61,1/(1+$B108)^$E$66:$X$66)+($X$51*E$106)/(1+$B108)^19.5 -> 115139.05 | F108: =SUMPRODUCT($E$61:$X$61,1/(1+$B108)^$E$66:$X$66)+($X$51*F$106)/(1+$B108)^19.5 -> 136040.51 | G108: =SUMPRODUCT($E$61:$X$61,1/(1+$B108)^$E$66:$X$66)+($X$51*G$106)/(1+$B108)^19.5 -> 156941.96
B109: =$B$45 -> 0.079328832 | C109: =SUMPRODUCT($E$61:$X$61,1/(1+$B109)^$E$66:$X$66)+($X$51*C$106)/(1+$B109)^19.5 -> 62050.755 | D109: =SUMPRODUCT($E$61:$X$61,1/(1+$B109)^$E$66:$X$66)+($X$51*D$106)/(1+$B109)^19.5 -> 79482.779 | E109: =SUMPRODUCT($E$61:$X$61,1/(1+$B109)^$E$66:$X$66)+($X$51*E$106)/(1+$B109)^19.5 -> 96914.802 | F109: =SUMPRODUCT($E$61:$X$61,1/(1+$B109)^$E$66:$X$66)+($X$51*F$106)/(1+$B109)^19.5 -> 114346.83 | G109: =SUMPRODUCT($E$61:$X$61,1/(1+$B109)^$E$66:$X$66)+($X$51*G$106)/(1+$B109)^19.5 -> 131778.85
B110: =$B$45+0.01 -> 0.089328832 | C110: =SUMPRODUCT($E$61:$X$61,1/(1+$B110)^$E$66:$X$66)+($X$51*C$106)/(1+$B110)^19.5 -> 52535.239 | D110: =SUMPRODUCT($E$61:$X$61,1/(1+$B110)^$E$66:$X$66)+($X$51*D$106)/(1+$B110)^19.5 -> 67098.077 | E110: =SUMPRODUCT($E$61:$X$61,1/(1+$B110)^$E$66:$X$66)+($X$51*E$106)/(1+$B110)^19.5 -> 81660.915 | F110: =SUMPRODUCT($E$61:$X$61,1/(1+$B110)^$E$66:$X$66)+($X$51*F$106)/(1+$B110)^19.5 -> 96223.752 | G110: =SUMPRODUCT($E$61:$X$61,1/(1+$B110)^$E$66:$X$66)+($X$51*G$106)/(1+$B110)^19.5 -> 110786.59
B111: =$B$45+0.02 -> 0.099328832 | C111: =SUMPRODUCT($E$61:$X$61,1/(1+$B111)^$E$66:$X$66)+($X$51*C$106)/(1+$B111)^19.5 -> 44492.97 | D111: =SUMPRODUCT($E$61:$X$61,1/(1+$B111)^$E$66:$X$66)+($X$51*D$106)/(1+$B111)^19.5 -> 56678.879 | E111: =SUMPRODUCT($E$61:$X$61,1/(1+$B111)^$E$66:$X$66)+($X$51*E$106)/(1+$B111)^19.5 -> 68864.788 | F111: =SUMPRODUCT($E$61:$X$61,1/(1+$B111)^$E$66:$X$66)+($X$51*F$106)/(1+$B111)^19.5 -> 81050.697 | G111: =SUMPRODUCT($E$61:$X$61,1/(1+$B111)^$E$66:$X$66)+($X$51*G$106)/(1+$B111)^19.5 -> 93236.606
A124: SPACE — BOTTOM-UP OPERATING DRIVERS (launch-based, cross-check vs top-down revenue above)
A125: Driver | D125: FY2025A | E125: FY2026E | F125: FY2027E | G125: FY2028E | H125: FY2029E | I125: FY2030E | J125: FY2031E | K125: FY2032E | L125: FY2033E | M125: FY2034E | N125: FY2035E | O125: FY2036E | P125: FY2037E | Q125: FY2038E | R125: FY2039E | S125: FY2040E | T125: FY2041E | U125: FY2042E | V125: FY2043E | W125: FY2044E | X125: FY2045E
A126: External Launches per Day | D126: 0.1 | E126: 0.16 | F126: 0.21 | G126: 0.27 | H126: 0.32 | I126: 0.38 | J126: 0.43 | K126: 0.49 | L126: 0.54 | M126: 0.6 | N126: 0.65 | O126: 0.7 | P126: 0.76 | Q126: 0.82 | R126: 0.87 | S126: 0.92 | T126: 0.98 | U126: 1.03 | V126: 1.09 | W126: 1.15 | X126: 1.2
A127: External Launches per Year | D127: =D126*365 -> 36.5 | E127: =E126*365 -> 58.4 | F127: =F126*365 -> 76.65 | G127: =G126*365 -> 98.55 | H127: =H126*365 -> 116.8 | I127: =I126*365 -> 138.7 | J127: =J126*365 -> 156.95 | K127: =K126*365 -> 178.85 | ... X127: =X126*365 -> 438
A128: Revenue per Launch ($M) | D128: 60 | E128: 61 | F128: 62 | G128: 62 | H128: 63 | I128: 64 | J128: 65 | K128: 65 | L128: 66 | M128: 67 | N128: 68 | O128: 68 | P128: 69 | Q128: 70 | R128: 71 | S128: 71 | T128: 72 | U128: 73 | V128: 74 | W128: 74 | X128: 75
A129: Launch Services Revenue ($M) | D129: =D127*D128 -> 2190 | E129: =E127*E128 -> 3562.4 | F129: =F127*F128 -> 4752.3 | G129: =G127*G128 -> 6110.1 | H129: =H127*H128 -> 7358.4 | I129: =I127*I128 -> 8876.8 | J129: =J127*J128 -> 10201.75 | K129: =K127*K128 -> 11625.25 | ... X129: =X127*X128 -> 32850
A130: Dragon + Dev Contracts Rev ($M) | D130: 1510 | E130: =D130*(1+E131) -> 1661 | F130: =E130*(1+F131) -> 1793.88 | G130: =F130*(1+G131) -> 1919.4516 | H130: =G130*(1+H131) -> 2034.6187 | I130: =H130*(1+I131) -> 2136.3496 | J130: =I130*(1+J131) -> 2243.1671 | K130: =J130*(1+K131) -> 2332.8938 | L130: =K130*(1+L131) -> 2426.2095 | ... X130: =W130*(1+X131) -> 3492.7791
...

Sheet AI DCF
A1: SpaceX — AI Segment DCF (X / xAI / Grok)
A2: S-1 Filed May 20, 2026 | 20-Year Explicit Forecast FY2026E–FY2045E | $ in Millions
A3: ⚠ AI segment includes X (social/advertising), xAI (Grok/models), and compute infrastructure. Op losses reflect heavy investment phase; TV captures mature-state value.
A5: SCENARIO SELECTOR | B5: =COVER!B30 -> 2 | C5: =IF(B5=1,"◀ BEAR",IF(B5=2,"◀ BASE","◀ BULL")) -> ◀ BASE | D5: (1 = Bear | 2 = Base | 3 = Bull)
A7: BEAR CASE ASSUMPTIONS
B8: FY2023A | C8: FY2024A | D8: FY2025A | E8: FY2026E | F8: FY2027E | G8: FY2028E | H8: FY2029E | I8: FY2030E | J8: FY2031E | K8: FY2032E | L8: FY2033E | M8: FY2034E | N8: FY2035E | O8: FY2036E | P8: FY2037E | Q8: FY2038E | R8: FY2039E | S8: FY2040E | T8: FY2041E | U8: FY2042E | V8: FY2043E | W8: FY2044E | X8: FY2045E
A9: Revenue Growth % (YoY) | E9: 0.15 | F9: 0.2 | G9: 0.25 | H9: 0.28 | I9: 0.3 | J9: 0.28 | K9: 0.25 | L9: 0.22 | M9: 0.18 | N9: 0.15 | O9: 0.14 | P9: 0.13 | Q9: 0.12 | R9: 0.1 | S9: 0.09 | T9: 0.08 | U9: 0.07 | V9: 0.06 | W9: 0.05 | X9: 0.04
A10: EBITDA Margin % | E10: -0.3 | F10: -0.15 | G10: 0 | H10: 0.1 | I10: 0.18 | J10: 0.23 | K10: 0.27 | L10: 0.3 | M10: 0.32 | N10: 0.34 | O10: 0.36 | P10: 0.38 | Q10: 0.39 | R10: 0.4 | S10: 0.41 | T10: 0.42 | U10: 0.42 | V10: 0.43 | W10: 0.43 | X10: 0.44
A11: D&A % of Revenue | E11: 1.05 | F11: 0.9 | G11: 0.75 | H11: 0.62 | I11: 0.52 | J11: 0.44 | K11: 0.38 | L11: 0.33 | M11: 0.29 | N11: 0.26 | O11: 0.24 | P11: 0.22 | Q11: 0.2 | R11: 0.19 | S11: 0.18 | T11: 0.17 | U11: 0.16 | V11: 0.16 | W11: 0.15 | X11: 0.15
A12: Capex % of Revenue | E12: 3.6 | F12: 2.8 | G12: 2.1 | H12: 1.6 | I12: 1.2 | J12: 0.95 | K12: 0.78 | L12: 0.65 | M12: 0.55 | N12: 0.48 | O12: 0.44 | P12: 0.4 | Q12: 0.36 | R12: 0.33 | S12: 0.3 | T12: 0.27 | U12: 0.24 | V12: 0.22 | W12: 0.2 | X12: 0.18
A13: ΔNW Cap % of ΔRevenue | E13: 0.08 | F13: 0.07 | G13: 0.06 | H13: 0.06 | I13: 0.05 | J13: 0.05 | K13: 0.04 | L13: 0.04 | M13: 0.03 | N13: 0.03 | O13: 0.03 | P13: 0.03 | Q13: 0.025 | R13: 0.025 | S13: 0.025 | T13: 0.02 | U13: 0.02 | V13: 0.02 | W13: 0.02 | X13: 0.02
A14: Terminal Growth Rate | B14: =WACC!D49 -> 0.025
A15: WACC | B15: =WACC!B49 -> 0.11585358
A17: BASE CASE ASSUMPTIONS
B18: FY2023A | C18: FY2024A | D18: FY2025A | E18: FY2026E | F18: FY2027E | G18: FY2028E | H18: FY2029E | I18: FY2030E | J18: FY2031E | K18: FY2032E | L18: FY2033E | M18: FY2034E | N18: FY2035E | O18: FY2036E | P18: FY2037E | Q18: FY2038E | R18: FY2039E | S18: FY2040E | T18: FY2041E | U18: FY2042E | V18: FY2043E | W18: FY2044E | X18: FY2045E
A19: Revenue Growth % (YoY) | E19: 0.28 | F19: 0.38 | G19: 0.45 | H19: 0.48 | I19: 0.45 | J19: 0.38 | K19: 0.32 | L19: 0.27 | M19: 0.22 | N19: 0.18 | O19: 0.16 | P19: 0.15 | Q19: 0.13 | R19: 0.12 | S19: 0.1 | T19: 0.09 | U19: 0.08 | V19: 0.07 | W19: 0.06 | X19: 0.05
A20: EBITDA Margin % | E20: -0.15 | F20: 0.02 | G20: 0.12 | H20: 0.22 | I20: 0.3 | J20: 0.36 | K20: 0.4 | L20: 0.43 | M20: 0.45 | N20: 0.46 | O20: 0.48 | P20: 0.5 | Q20: 0.51 | R20: 0.52 | S20: 0.53 | T20: 0.54 | U20: 0.55 | V20: 0.56 | W20: 0.57 | X20: 0.58
A21: D&A % of Revenue | E21: 1.05 | F21: 0.9 | G21: 0.75 | H21: 0.62 | I21: 0.52 | J21: 0.44 | K21: 0.38 | L21: 0.33 | M21: 0.29 | N21: 0.26 | O21: 0.24 | P21: 0.22 | Q21: 0.2 | R21: 0.19 | S21: 0.18 | T21: 0.17 | U21: 0.16 | V21: 0.16 | W21: 0.15 | X21: 0.15
A22: Capex % of Revenue | E22: 3.2 | F22: 2.4 | G22: 1.8 | H22: 1.35 | I22: 1 | J22: 0.8 | K22: 0.65 | L22: 0.54 | M22: 0.46 | N22: 0.4 | O22: 0.36 | P22: 0.33 | Q22: 0.3 | R22: 0.27 | S22: 0.25 | T22: 0.22 | U22: 0.2 | V22: 0.18 | W22: 0.16 | X22: 0.15
A23: ΔNW Cap % of ΔRevenue | E23: 0.06 | F23: 0.06 | G23: 0.05 | H23: 0.05 | I23: 0.04 | J23: 0.04 | K23: 0.03 | L23: 0.03 | M23: 0.03 | N23: 0.02 | O23: 0.02 | P23: 0.02 | Q23: 0.02 | R23: 0.018 | S23: 0.018 | T23: 0.015 | U23: 0.015 | V23: 0.015 | W23: 0.015 | X23: 0.015
A24: Terminal Growth Rate | B24: =WACC!C49 -> 0.035
A25: WACC | B25: =WACC!B49 -> 0.11585358
A27: BULL CASE ASSUMPTIONS
B28: FY2023A | C28: FY2024A | D28: FY2025A | E28: FY2026E | F28: FY2027E | G28: FY2028E | H28: FY2029E | I28: FY2030E | J28: FY2031E | K28: FY2032E | L28: FY2033E | M28: FY2034E | N28: FY2035E | O28: FY2036E | P28: FY2037E | Q28: FY2038E | R28: FY2039E | S28: FY2040E | T28: FY2041E | U28: FY2042E | V28: FY2043E | W28: FY2044E | X28: FY2045E
A29: Revenue Growth % (YoY) | E29: 0.45 | F29: 0.6 | G29: 0.7 | H29: 0.7 | I29: 0.6 | J29: 0.5 | K29: 0.42 | L29: 0.35 | M29: 0.28 | N29: 0.22 | O29: 0.2 | P29: 0.18 | Q29: 0.16 | R29: 0.14 | S29: 0.12 | T29: 0.11 | U29: 0.1 | V29: 0.09 | W29: 0.07 | X29: 0.06
A30: EBITDA Margin % | E30: -0.1 | F30: -0.05 | G30: 0.05 | H30: 0.12 | I30: 0.2 | J30: 0.28 | K30: 0.35 | L30: 0.42 | M30: 0.48 | N30: 0.55 | O30: 0.57 | P30: 0.59 | Q30: 0.6 | R30: 0.61 | S30: 0.62 | T30: 0.63 | U30: 0.64 | V30: 0.65 | W30: 0.65 | X30: 0.66
A31: D&A % of Revenue | E31: 1.05 | F31: 0.9 | G31: 0.75 | H31: 0.62 | I31: 0.52 | J31: 0.44 | K31: 0.38 | L31: 0.33 | M31: 0.29 | N31: 0.26 | O31: 0.24 | P31: 0.22 | Q31: 0.2 | R31: 0.18 | S31: 0.17 | T31: 0.16 | U31: 0.15 | V31: 0.15 | W31: 0.14 | X31: 0.14
A32: Capex % of Revenue | E32: 2.9 | F32: 2.1 | G32: 1.55 | H32: 1.15 | I32: 0.85 | J32: 0.68 | K32: 0.55 | L32: 0.46 | M32: 0.39 | N32: 0.34 | O32: 0.3 | P32: 0.27 | Q32: 0.25 | R32: 0.22 | S32: 0.2 | T32: 0.18 | U32: 0.16 | V32: 0.15 | W32: 0.14 | X32: 0.13
A33: ΔNW Cap % of ΔRevenue | E33: 0.05 | F33: 0.05 | G33: 0.04 | H33: 0.04 | I33: 0.03 | J33: 0.03 | K33: 0.03 | L33: 0.02 | M33: 0.02 | N33: 0.02 | O33: 0.02 | P33: 0.018 | Q33: 0.018 | R33: 0.015 | S33: 0.015 | T33: 0.015 | U33: 0.012 | V33: 0.012 | W33: 0.012 | X33: 0.012
A34: Terminal Growth Rate | B34: =WACC!E49 -> 0.04
A35: WACC | B35: =WACC!B49 -> 0.11585358
A37: SELECTED CASE ASSUMPTIONS
B38: FY2023A | C38: FY2024A | D38: FY2025A | E38: FY2026E | F38: FY2027E | G38: FY2028E | H38: FY2029E | I38: FY2030E | J38: FY2031E | K38: FY2032E | L38: FY2033E | M38: FY2034E | N38: FY2035E | O38: FY2036E | P38: FY2037E | Q38: FY2038E | R38: FY2039E | S38: FY2040E | T38: FY2041E | U38: FY2042E | V38: FY2043E | W38: FY2044E | X38: FY2045E
A39: Revenue Growth % (YoY) | E39: =IF($B$5=1,E9,IF($B$5=2,E19,E29)) -> 0.28 | F39: =IF($B$5=1,F9,IF($B$5=2,F19,F29)) -> 0.38 | G39: =IF($B$5=1,G9,IF($B$5=2,G19,G29)) -> 0.45 | H39: =IF($B$5=1,H9,IF($B$5=2,H19,H29)) -> 0.48 | I39: =IF($B$5=1,I9,IF($B$5=2,I19,I29)) -> 0.45 | J39: =IF($B$5=1,J9,IF($B$5=2,J19,J29)) -> 0.38 | K39: =IF($B$5=1,K9,IF($B$5=2,K19,K29)) -> 0.32 | L39: =IF($B$5=1,L9,IF($B$5=2,L19,L29)) -> 0.27 | ... X39: =IF($B$5=1,X9,IF($B$5=2,X19,X29)) -> 0.05
A40: EBITDA Margin % | E40: =IF($B$5=1,E10,IF($B$5=2,E20,E30)) -> -0.15 | F40: =IF($B$5=1,F10,IF($B$5=2,F20,F30)) -> 0.02 | G40: =IF($B$5=1,G10,IF($B$5=2,G20,G30)) -> 0.12 | H40: =IF($B$5=1,H10,IF($B$5=2,H20,H30)) -> 0.22 | I40: =IF($B$5=1,I10,IF($B$5=2,I20,I30)) -> 0.3 | J40: =IF($B$5=1,J10,IF($B$5=2,J20,J30)) -> 0.36 | K40: =IF($B$5=1,K10,IF($B$5=2,K20,K30)) -> 0.4 | L40: =IF($B$5=1,L10,IF($B$5=2,L20,L30)) -> 0.43 | ... X40: =IF($B$5=1,X10,IF($B$5=2,X20,X30)) -> 0.58
A41: D&A % of Revenue | E41: =IF($B$5=1,E11,IF($B$5=2,E21,E31)) -> 1.05 | F41: =IF($B$5=1,F11,IF($B$5=2,F21,F31)) -> 0.9 | G41: =IF($B$5=1,G11,IF($B$5=2,G21,G31)) -> 0.75 | H41: =IF($B$5=1,H11,IF($B$5=2,H21,H31)) -> 0.62 | I41: =IF($B$5=1,I11,IF($B$5=2,I21,I31)) -> 0.52 | J41: =IF($B$5=1,J11,IF($B$5=2,J21,J31)) -> 0.44 | K41: =IF($B$5=1,K11,IF($B$5=2,K21,K31)) -> 0.38 | L41: =IF($B$5=1,L11,IF($B$5=2,L21,L31)) -> 0.33 | ... X41: =IF($B$5=1,X11,IF($B$5=2,X21,X31)) -> 0.15
A42: Capex % of Revenue | E42: =IF($B$5=1,E12,IF($B$5=2,E22,E32)) -> 3.2 | F42: =IF($B$5=1,F12,IF($B$5=2,F22,F32)) -> 2.4 | G42: =IF($B$5=1,G12,IF($B$5=2,G22,G32)) -> 1.8 | H42: =IF($B$5=1,H12,IF($B$5=2,H22,H32)) -> 1.35 | I42: =IF($B$5=1,I12,IF($B$5=2,I22,I32)) -> 1 | J42: =IF($B$5=1,J12,IF($B$5=2,J22,J32)) -> 0.8 | K42: =IF($B$5=1,K12,IF($B$5=2,K22,K32)) -> 0.65 | L42: =IF($B$5=1,L12,IF($B$5=2,L22,L32)) -> 0.54 | ... X42: =IF($B$5=1,X12,IF($B$5=2,X22,X32)) -> 0.15
A43: ΔNW Cap % of ΔRevenue | E43: =IF($B$5=1,E13,IF($B$5=2,E23,E33)) -> 0.06 | F43: =IF($B$5=1,F13,IF($B$5=2,F23,F33)) -> 0.06 | G43: =IF($B$5=1,G13,IF($B$5=2,G23,G33)) -> 0.05 | H43: =IF($B$5=1,H13,IF($B$5=2,H23,H33)) -> 0.05 | I43: =IF($B$5=1,I13,IF($B$5=2,I23,I33)) -> 0.04 | J43: =IF($B$5=1,J13,IF($B$5=2,J23,J33)) -> 0.04 | K43: =IF($B$5=1,K13,IF($B$5=2,K23,K33)) -> 0.03 | L43: =IF($B$5=1,L13,IF($B$5=2,L23,L33)) -> 0.03 | ... X43: =IF($B$5=1,X13,IF($B$5=2,X23,X33)) -> 0.015
A44: Terminal Growth Rate | B44: =IF($B$5=1,B14,IF($B$5=2,B24,B34)) -> 0.035
A45: WACC | B45: =IF($B$5=1,B15,IF($B$5=2,B25,B35)) -> 0.11585358
A47: AI SEGMENT — INCOME STATEMENT & FREE CASH FLOW ($M)
B48: FY2023A | C48: FY2024A | D48: FY2025A | E48: FY2026E | F48: FY2027E | G48: FY2028E | H48: FY2029E | I48: FY2030E | J48: FY2031E | K48: FY2032E | L48: FY2033E | M48: FY2034E | N48: FY2035E | O48: FY2036E | P48: FY2037E | Q48: FY2038E | R48: FY2039E | S48: FY2040E | T48: FY2041E | U48: FY2042E | V48: FY2043E | W48: FY2044E | X48: FY2045E
A49: Revenue | B49: 2961 | C49: 2620 | D49: =Actuals!D9 -> 3201 | E49: =D49*(1+E39) -> 4097.28 | F49: =E49*(1+F39) -> 5654.2464 | G49: =F49*(1+G39) -> 8198.6573 | H49: =G49*(1+H39) -> 12134.013 | I49: =H49*(1+I39) -> 17594.319 | J49: =I49*(1+J39) -> 24280.16 | K49: =J49*(1+K39) -> 32049.811 | L49: =K49*(1+L39) -> 40703.259 | ... X49: =W49*(1+X39) -> 152561.59
A50: % YoY Growth | C50: =C49/B49-1 -> -0.1151638 | D50: =D49/C49-1 -> 0.22175573 | E50: =E49/D49-1 -> 0.28 | F50: =F49/E49-1 -> 0.38 | G50: =G49/F49-1 -> 0.45 | H50: =H49/G49-1 -> 0.48 | I50: =I49/H49-1 -> 0.45 | J50: =J49/I49-1 -> 0.38 | ... X50: =X49/W49-1 -> 0.05
A51: EBITDA | B51: -793 | C51: 118 | D51: =Actuals!D12 -> -1237 | E51: =E49*E40 -> -614.592 | F51: =F49*F40 -> 113.08493 | G51: =G49*G40 -> 983.83887 | H51: =H49*H40 -> 2669.4828 | I51: =I49*I40 -> 5278.2956 | J51: =J49*J40 -> 8740.8574 | K51: =K49*K40 -> 12819.924 | L51: =L49*L40 -> 17502.402 | ... X51: =X49*X40 -> 88485.722
A52: EBITDA Margin % | B52: =B51/B49 -> -0.26781493 | C52: =C51/C49 -> 0.045038168 | D52: =D51/D49 -> -0.38644174 | E52: =E51/E49 -> -0.15 | F52: =F51/F49 -> 0.02 | G52: =G51/G49 -> 0.12 | H52: =H51/H49 -> 0.22 | I52: =I51/I49 -> 0.3 | ... X52: =X51/X49 -> 0.58
A53: Depreciation & Amortization | B53: 1180 | C53: 1679 | D53: 3568 | E53: =E49*E41 -> 4302.144 | F53: =F49*F41 -> 5088.8218 | G53: =G49*G41 -> 6148.993 | H53: =H49*H41 -> 7523.0879 | I53: =I49*I41 -> 9149.0456 | J53: =J49*J41 -> 10683.27 | K53: =K49*K41 -> 12178.928 | L53: =L49*L41 -> 13432.076 | ... X53: =X49*X41 -> 22884.238
A54: EBIT (EBITDA − D&A) | B54: =B51-B53 -> -1973 | C54: =C51-C53 -> -1561 | D54: =D51-D53 -> -4805 | E54: =E51-E53 -> -4916.736 | F54: =F51-F53 -> -4975.7368 | G54: =G51-G53 -> -5165.1541 | H54: =H51-H53 -> -4853.6051 | I54: =I51-I53 -> -3870.7501 | ... X54: =X51-X53 -> 65601.483
A55: EBIT Margin % | B55: =B54/B49 -> -0.66632894 | C55: =C54/C49 -> -0.59580153 | D55: =D54/D49 -> -1.5010934 | E55: =E54/E49 -> -1.2 | F55: =F54/F49 -> -0.88 | G55: =G54/G49 -> -0.63 | H55: =H54/H49 -> -0.4 | I55: =I54/I49 -> -0.22 | ... X55: =X54/X49 -> 0.43
A56: (–) Tax on EBIT | B56: =MAX(B54,0)*WACC!$B$8 -> 0 | C56: =MAX(C54,0)*WACC!$B$8 -> 0 | D56: =MAX(D54,0)*WACC!$B$8 -> 0 | E56: =MAX(E54,0)*WACC!$B$8 -> 0 | F56: =MAX(F54,0)*WACC!$B$8 -> 0 | G56: =MAX(G54,0)*WACC!$B$8 -> 0 | H56: =MAX(H54,0)*WACC!$B$8 -> 0 | I56: =MAX(I54,0)*WACC!$B$8 -> 0 | ... X56: =MAX(X54,0)*WACC!$B$8 -> 13776.311
A57: NOPAT | B57: =B54-B56 -> -1973 | C57: =C54-C56 -> -1561 | D57: =D54-D56 -> -4805 | E57: =E54-E56 -> -4916.736 | F57: =F54-F56 -> -4975.7368 | G57: =G54-G56 -> -5165.1541 | H57: =H54-H56 -> -4853.6051 | I57: =I54-I56 -> -3870.7501 | ... X57: =X54-X56 -> 51825.172
A58: (+) D&A | B58: =B53 -> 1180 | C58: =C53 -> 1679 | D58: =D53 -> 3568 | E58: =E53 -> 4302.144 | F58: =F53 -> 5088.8218 | G58: =G53 -> 6148.993 | H58: =H53 -> 7523.0879 | I58: =I53 -> 9149.0456 | ... X58: =X53 -> 22884.238
A59: (–) Capital Expenditures | B59: -463 | C59: -5633 | D59: -12727 | E59: =-E49*E42 -> -13111.296 | F59: =-F49*F42 -> -13570.191 | G59: =-G49*G42 -> -14757.583 | H59: =-H49*H42 -> -16380.917 | I59: =-I49*I42 -> -17594.319 | J59: =-J49*J42 -> -19424.128 | K59: =-K49*K42 -> -20832.377 | L59: =-L49*L42 -> -21979.76 | ... X59: =-X49*X42 -> -22884.238
A60: (–) Increase in Net Working Capital | B60: 0 | C60: 0 | D60: 0 | E60: =-(E49-D49)*E43 -> -53.7768 | F60: =-(F49-E49)*F43 -> -93.417984 | G60: =-(G49-F49)*G43 -> -127.22054 | H60: =-(H49-G49)*H43 -> -196.76777 | I60: =-(I49-H49)*I43 -> -218.41223 | J60: =-(J49-I49)*J43 -> -267.43364 | K60: =-(K49-J49)*K43 -> -233.08953 | L60: =-(L49-K49)*L43 -> -259.60347 | ... X60: =-(X49-W49)*X43 -> -108.97256
A61: Unlevered Free Cash Flow | B61: =B57+B58+B59+B60 -> -1256 | C61: =C57+C58+C59+C60 -> -5515 | D61: =D57+D58+D59+D60 -> -13964 | E61: =E57+E58+E59+E60 -> -13779.665 | F61: =F57+F58+F59+F60 -> -13550.524 | G61: =G57+G58+G59+G60 -> -13900.965 | H61: =H57+H58+H59+H60 -> -13908.202 | I61: =I57+I58+I59+I60 -> -12534.435 | ... X61: =X57+X58+X59+X60 -> 51716.199
A62: FCF Margin % | B62: =B61/B49 -> -0.42418102 | C62: =C61/C49 -> -2.1049618 | D62: =D61/D49 -> -4.3623868 | E62: =E61/E49 -> -3.363125 | F62: =F61/F49 -> -2.3965217 | G62: =G61/G49 -> -1.6955172 | H62: =H61/H49 -> -1.1462162 | I62: =I61/I49 -> -0.71241379 | ... X62: =X61/X49 -> 0.33898571
A64: DCF — DISCOUNT FACTORS & PRESENT VALUES (Mid-Year Convention)
E65: FY2026E | F65: FY2027E | G65: FY2028E | H65: FY2029E | I65: FY2030E | J65: FY2031E | K65: FY2032E | L65: FY2033E | M65: FY2034E | N65: FY2035E | O65: FY2036E | P65: FY2037E | Q65: FY2038E | R65: FY2039E | S65: FY2040E | T65: FY2041E | U65: FY2042E | V65: FY2043E | W65: FY2044E | X65: FY2045E
A66: Discount Period (mid-year) | E66: 0.5 | F66: 1.5 | G66: 2.5 | H66: 3.5 | I66: 4.5 | J66: 5.5 | K66: 6.5 | L66: 7.5 | M66: 8.5 | N66: 9.5 | O66: 10.5 | P66: 11.5 | Q66: 12.5 | R66: 13.5 | S66: 14.5 | T66: 15.5 | U66: 16.5 | V66: 17.5 | W66: 18.5 | X66: 19.5
A67: Discount Factor | E67: =1/(1+$B$45)^E66 -> 0.94666516 | F67: =1/(1+$B$45)^F66 -> 0.84837758 | G67: =1/(1+$B$45)^G66 -> 0.76029472 | H67: =1/(1+$B$45)^H66 -> 0.68135706 | I67: =1/(1+$B$45)^I66 -> 0.61061511 | J67: =1/(1+$B$45)^J66 -> 0.54721796 | K67: =1/(1+$B$45)^K66 -> 0.49040301 | L67: =1/(1+$B$45)^L66 -> 0.43948688 | ... X67: =1/(1+$B$45)^X66 -> 0.11793953
A68: Unlevered FCF ($M) | E68: =E61 -> -13779.665 | F68: =F61 -> -13550.524 | G68: =G61 -> -13900.965 | H68: =H61 -> -13908.202 | I68: =I61 -> -12534.435 | J68: =J61 -> -10950.704 | K68: =K61 -> -8380.1514 | L68: =L61 -> -5591.7305 | ... X68: =X61 -> 51716.199
A69: PV of FCF ($M) | E69: =E68*E67 -> -13044.729 | F69: =F68*F67 -> -11495.961 | G69: =G68*G67 -> -10568.83 | H69: =H68*H67 -> -9476.4518 | I69: =I68*I67 -> -7653.7156 | J69: =J68*J67 -> -5992.4218 | K69: =K68*K67 -> -4109.6515 | L69: =L68*L67 -> -2457.4922 | ... X69: =X68*X67 -> 6099.3841
A71: TERMINAL VALUE
A72: Gordon Growth Model
A73: Terminal FCF ($M) | B73: =X61 -> 51716.199
A74: Terminal FCF × (1+g) | B74: =X61*(1+$B$44) -> 53526.266
A75: Terminal Value (Gordon Growth) | B75: =B74/($B$45-$B$44) -> 662014.79
A76: PV of Terminal Value (Gordon Growth) | B76: =B75/(1+$B$45)^19.5 -> 78077.712
A78: EV/Revenue Exit Multiple Method (preferred for pre-profit businesses)
A79: Exit EV/Revenue Multiple (= Tier 3 Social Media comp median, fallback 6.0x) | B79: =IF(N('AI Comps'!J47)>0,'AI Comps'!J47,6) -> 3.2301136 | D79: =IF(N('AI Comps'!J47)>0,"✓ LIVE — "&TEXT('AI Comps'!J47,"0.0x")&" from AI Comps Tier 3 (Social Media)","⚠ FALLBACK — using 6.0x default") -> ✓ LIVE — 3.2x from AI Comps Tier 3 (Social Media)
A80: Terminal Year Revenue ($M) | B80: =X49 -> 152561.59
A81: Terminal Value (Exit EV/Rev) | B81: =B79*B80 -> 492791.27
A82: PV of Terminal Value (Exit EV/Rev) | B82: =B81/(1+$B$45)^19.5 -> 58119.569
A84: AI SEGMENT VALUATION SUMMARY
B85: EV/Revenue (Primary) | C85: Gordon (Cross-Check)
A86: Sum of PV of FCFs ($M) | B86: =SUM(E69:X69) -> -20822.579 | C86: =SUM(E69:X69) -> -20822.579
A87: PV of Terminal Value ($M) | B87: =B82 -> 58119.569 | C87: =B76 -> 78077.712
A88: Enterprise Value ($M) | B88: =B86+B87 -> 37296.99 | C88: =C86+C87 -> 57255.133
A90: TV % of Enterprise Value | B90: =B87/B88 -> 1.5582911 | C90: =C87/C88 -> 1.3636806
A92: SENSITIVITY ANALYSIS — AI SEGMENT EV ($M)
A94: Table 1: EV ($M) — WACC vs. Terminal Growth Rate (Gordon Growth)
B96: ↑ WACC \ Tg → | C96: =$B$44-0.01 -> 0.025 | D96: =$B$44-0.005 -> 0.03 | E96: =$B$44 -> 0.035 | F96: =$B$44+0.005 -> 0.04 | G96: =$B$44+0.01 -> 0.045
B97: =$B$45-0.02 -> 0.09585358 | C97: =SUMPRODUCT($E$61:$X$61,1/(1+$B97)^$E$66:$X$66)+($X$61*(1+C$96)/($B97-C$96))/(1+$B97)^19.5 -> 115952.83 | D97: =SUMPRODUCT($E$61:$X$61,1/(1+$B97)^$E$66:$X$66)+($X$61*(1+D$96)/($B97-D$96))/(1+$B97)^19.5 -> 126144.23 | E97: =SUMPRODUCT($E$61:$X$61,1/(1+$B97)^$E$66:$X$66)+($X$61*(1+E$96)/($B97-E$96))/(1+$B97)^19.5 -> 138010.36 | F97: =SUMPRODUCT($E$61:$X$61,1/(1+$B97)^$E$66:$X$66)+($X$61*(1+F$96)/($B97-F$96))/(1+$B97)^19.5 -> 152001 | G97: =SUMPRODUCT($E$61:$X$61,1/(1+$B97)^$E$66:$X$66)+($X$61*(1+G$96)/($B97-G$96))/(1+$B97)^19.5 -> 168742.81
B98: =$B$45-0.01 -> 0.10585358 | C98: =SUMPRODUCT($E$61:$X$61,1/(1+$B98)^$E$66:$X$66)+($X$61*(1+C$96)/($B98-C$96))/(1+$B98)^19.5 -> 76407.654 | D98: =SUMPRODUCT($E$61:$X$61,1/(1+$B98)^$E$66:$X$66)+($X$61*(1+D$96)/($B98-D$96))/(1+$B98)^19.5 -> 82961.786 | E98: =SUMPRODUCT($E$61:$X$61,1/(1+$B98)^$E$66:$X$66)+($X$61*(1+E$96)/($B98-E$96))/(1+$B98)^19.5 -> 90440.942 | F98: =SUMPRODUCT($E$61:$X$61,1/(1+$B98)^$E$66:$X$66)+($X$61*(1+F$96)/($B98-F$96))/(1+$B98)^19.5 -> 99055.823 | G98: =SUMPRODUCT($E$61:$X$61,1/(1+$B98)^$E$66:$X$66)+($X$61*(1+G$96)/($B98-G$96))/(1+$B98)^19.5 -> 109086.38
B99: =$B$45 -> 0.11585358 | C99: =SUMPRODUCT($E$61:$X$61,1/(1+$B99)^$E$66:$X$66)+($X$61*(1+C$96)/($B99-C$96))/(1+$B99)^19.5 -> 47989.995 | D99: =SUMPRODUCT($E$61:$X$61,1/(1+$B99)^$E$66:$X$66)+($X$61*(1+D$96)/($B99-D$96))/(1+$B99)^19.5 -> 52352.769 | E99: =SUMPRODUCT($E$61:$X$61,1/(1+$B99)^$E$66:$X$66)+($X$61*(1+E$96)/($B99-E$96))/(1+$B99)^19.5 -> 57255.133 | F99: =SUMPRODUCT($E$61:$X$61,1/(1+$B99)^$E$66:$X$66)+($X$61*(1+F$96)/($B99-F$96))/(1+$B99)^19.5 -> 62803.79 | G99: =SUMPRODUCT($E$61:$X$61,1/(1+$B99)^$E$66:$X$66)+($X$61*(1+G$96)/($B99-G$96))/(1+$B99)^19.5 -> 69135.563
B100: =$B$45+0.01 -> 0.12585358 | C100: =SUMPRODUCT($E$61:$X$61,1/(1+$B100)^$E$66:$X$66)+($X$61*(1+C$96)/($B100-C$96))/(1+$B100)^19.5 -> 27109.008 | D100: =SUMPRODUCT($E$61:$X$61,1/(1+$B100)^$E$66:$X$66)+($X$61*(1+D$96)/($B100-D$96))/(1+$B100)^19.5 -> 30093.577 | E100: =SUMPRODUCT($E$61:$X$61,1/(1+$B100)^$E$66:$X$66)+($X$61*(1+E$96)/($B100-E$96))/(1+$B100)^19.5 -> 33406.648 | F100: =SUMPRODUCT($E$61:$X$61,1/(1+$B100)^$E$66:$X$66)+($X$61*(1+F$96)/($B100-F$96))/(1+$B100)^19.5 -> 37105.618 | G100: =SUMPRODUCT($E$61:$X$61,1/(1+$B100)^$E$66:$X$66)+($X$61*(1+G$96)/($B100-G$96))/(1+$B100)^19.5 -> 41262.077
B101: =$B$45+0.02 -> 0.13585358 | C101: =SUMPRODUCT($E$61:$X$61,1/(1+$B101)^$E$66:$X$66)+($X$61*(1+C$96)/($B101-C$96))/(1+$B101)^19.5 -> 11506.038 | D101: =SUMPRODUCT($E$61:$X$61,1/(1+$B101)^$E$66:$X$66)+($X$61*(1+D$96)/($B101-D$96))/(1+$B101)^19.5 -> 13593.785 | E101: =SUMPRODUCT($E$61:$X$61,1/(1+$B101)^$E$66:$X$66)+($X$61*(1+E$96)/($B101-E$96))/(1+$B101)^19.5 -> 15888.539 | F101: =SUMPRODUCT($E$61:$X$61,1/(1+$B101)^$E$66:$X$66)+($X$61*(1+F$96)/($B101-F$96))/(1+$B101)^19.5 -> 18422.696 | G101: =SUMPRODUCT($E$61:$X$61,1/(1+$B101)^$E$66:$X$66)+($X$61*(1+G$96)/($B101-G$96))/(1+$B101)^19.5 -> 21235.78
A104: Table 2: EV ($M) — WACC vs. EV/Revenue Exit Multiple
B106: ↑ WACC \ EV/Rev → | C106: =$B$79-4 -> -0.76988636 | D106: =$B$79-2 -> 1.2301136 | E106: =$B$79 -> 3.2301136 | F106: =$B$79+2 -> 5.2301136 | G106: =$B$79+4 -> 7.2301136
B107: =$B$45-0.02 -> 0.09585358 | C107: =SUMPRODUCT($E$61:$X$61,1/(1+$B107)^$E$66:$X$66)+($X$49*C$106)/(1+$B107)^19.5 -> -29306.967 | D107: =SUMPRODUCT($E$61:$X$61,1/(1+$B107)^$E$66:$X$66)+($X$49*D$106)/(1+$B107)^19.5 -> 21896.675 | E107: =SUMPRODUCT($E$61:$X$61,1/(1+$B107)^$E$66:$X$66)+($X$49*E$106)/(1+$B107)^19.5 -> 73100.316 | F107: =SUMPRODUCT($E$61:$X$61,1/(1+$B107)^$E$66:$X$66)+($X$49*F$106)/(1+$B107)^19.5 -> 124303.96 | G107: =SUMPRODUCT($E$61:$X$61,1/(1+$B107)^$E$66:$X$66)+($X$49*G$106)/(1+$B107)^19.5 -> 175507.6
B108: =$B$45-0.01 -> 0.10585358 | C108: =SUMPRODUCT($E$61:$X$61,1/(1+$B108)^$E$66:$X$66)+($X$49*C$106)/(1+$B108)^19.5 -> -32264.205 | D108: =SUMPRODUCT($E$61:$X$61,1/(1+$B108)^$E$66:$X$66)+($X$49*D$106)/(1+$B108)^19.5 -> 10627.317 | E108: =SUMPRODUCT($E$61:$X$61,1/(1+$B108)^$E$66:$X$66)+($X$49*E$106)/(1+$B108)^19.5 -> 53518.838 | F108: =SUMPRODUCT($E$61:$X$61,1/(1+$B108)^$E$66:$X$66)+($X$49*F$106)/(1+$B108)^19.5 -> 96410.359 | G108: =SUMPRODUCT($E$61:$X$61,1/(1+$B108)^$E$66:$X$66)+($X$49*G$106)/(1+$B108)^19.5 -> 139301.88
B109: =$B$45 -> 0.11585358 | C109: =SUMPRODUCT($E$61:$X$61,1/(1+$B109)^$E$66:$X$66)+($X$49*C$106)/(1+$B109)^19.5 -> -34675.177 | D109: =SUMPRODUCT($E$61:$X$61,1/(1+$B109)^$E$66:$X$66)+($X$49*D$106)/(1+$B109)^19.5 -> 1310.9068 | E109: =SUMPRODUCT($E$61:$X$61,1/(1+$B109)^$E$66:$X$66)+($X$49*E$106)/(1+$B109)^19.5 -> 37296.99 | F109: =SUMPRODUCT($E$61:$X$61,1/(1+$B109)^$E$66:$X$66)+($X$49*F$106)/(1+$B109)^19.5 -> 73283.074 | G109: =SUMPRODUCT($E$61:$X$61,1/(1+$B109)^$E$66:$X$66)+($X$49*G$106)/(1+$B109)^19.5 -> 109269.16
B110: =$B$45+0.01 -> 0.12585358 | C110: =SUMPRODUCT($E$61:$X$61,1/(1+$B110)^$E$66:$X$66)+($X$49*C$106)/(1+$B110)^19.5 -> -36622.467 | D110: =SUMPRODUCT($E$61:$X$61,1/(1+$B110)^$E$66:$X$66)+($X$49*D$106)/(1+$B110)^19.5 -> -6382.738 | E110: =SUMPRODUCT($E$61:$X$61,1/(1+$B110)^$E$66:$X$66)+($X$49*E$106)/(1+$B110)^19.5 -> 23856.991 | F110: =SUMPRODUCT($E$61:$X$61,1/(1+$B110)^$E$66:$X$66)+($X$49*F$106)/(1+$B110)^19.5 -> 54096.72 | G110: =SUMPRODUCT($E$61:$X$61,1/(1+$B110)^$E$66:$X$66)+($X$49*G$106)/(1+$B110)^19.5 -> 84336.449
B111: =$B$45+0.02 -> 0.13585358 | C111: =SUMPRODUCT($E$61:$X$61,1/(1+$B111)^$E$66:$X$66)+($X$49*C$106)/(1+$B111)^19.5 -> -38176.288 | D111: =SUMPRODUCT($E$61:$X$61,1/(1+$B111)^$E$66:$X$66)+($X$49*D$106)/(1+$B111)^19.5 -> -12726.196 | E111: =SUMPRODUCT($E$61:$X$61,1/(1+$B111)^$E$66:$X$66)+($X$49*E$106)/(1+$B111)^19.5 -> 12723.895 | F111: =SUMPRODUCT($E$61:$X$61,1/(1+$B111)^$E$66:$X$66)+($X$49*F$106)/(1+$B111)^19.5 -> 38173.987 | G111: =SUMPRODUCT($E$61:$X$61,1/(1+$B111)^$E$66:$X$66)+($X$49*G$106)/(1+$B111)^19.5 -> 63624.079
A124: AI — BOTTOM-UP OPERATING DRIVERS (capacity-based, cross-check vs top-down revenue above)
A125: Driver | D125: FY2025A | E125: FY2026E | F125: FY2027E | G125: FY2028E | H125: FY2029E | I125: FY2030E | J125: FY2031E | K125: FY2032E | L125: FY2033E | M125: FY2034E | N125: FY2035E | O125: FY2036E | P125: FY2037E | Q125: FY2038E | R125: FY2039E | S125: FY2040E | T125: FY2041E | U125: FY2042E | V125: FY2043E | W125: FY2044E | X125: FY2045E
A126: Global AI Data-Center Capacity (GW) | D126: 31 | E126: 34.8 | F126: 39.1 | G126: 43.8 | H126: 49.2 | I126: 55.2 | J126: 62 | K126: 69.6 | L126: 78.1 | M126: 87.6 | N126: 98.3 | O126: 110.4 | P126: 123.9 | Q126: 139.1 | R126: 156.1 | S126: 175.2 | T126: 196.6 | U126: 220.7 | V126: 247.7 | W126: 278 | X126: 312
A127: SpaceX Market Share % | D127: 0.005 | E127: 0.008 | F127: 0.011 | G127: 0.015 | H127: 0.019 | I127: 0.024 | J127: 0.029 | K127: 0.034 | L127: 0.04 | M127: 0.045 | N127: 0.05 | O127: 0.055 | P127: 0.06 | Q127: 0.064 | R127: 0.068 | S127: 0.071 | T127: 0.074 | U127: 0.076 | V127: 0.078 | W127: 0.079 | X127: 0.08
A128: SpaceX Capacity (MW) | D128: =D126*1000*D127 -> 155 | E128: =E126*1000*E127 -> 278.4 | F128: =F126*1000*F127 -> 430.1 | G128: =G126*1000*G127 -> 657 | H128: =H126*1000*H127 -> 934.8 | I128: =I126*1000*I127 -> 1324.8 | J128: =J126*1000*J127 -> 1798 | K128: =K126*1000*K127 -> 2366.4 | ... X128: =X126*1000*X127 -> 24960
A129: Compute Revenue per MW ($M/yr) | D129: 1.5 | E129: 1.55 | F129: 1.6 | G129: 1.65 | H129: 1.7 | I129: 1.75 | J129: 1.8 | K129: 1.82 | L129: 1.85 | M129: 1.87 | N129: 1.9 | O129: 1.92 | P129: 1.94 | Q129: 1.96 | R129: 1.98 | S129: 2 | T129: 2 | U129: 2 | V129: 2 | W129: 2 | X129: 2
...

Sheet WACC
A1: SpaceX — Weighted Average Cost of Capital
A2: May 2026 | Sum-of-the-Parts Segment WACCs | $M
A4: MACRO INPUTS
A5: Item | B5: Value | F5: Note
A6: Risk-Free Rate (10Y US Treasury) | B6: 0.0435 | F6: US Treasury, Jun 2026
A7: Equity Risk Premium | B7: 0.055 | F7: Damodaran Jan 2026 (US ERP)
A8: Tax Rate | B8: 0.21 | F8: US statutory; SpaceX has large NOL carryforwards
A9: Specific Risk Premium (Size / Illiquidity) | B9: 0.025 | F9: Pre-IPO illiquidity + size/execution risk; 2–3% typical for late-stage private
A11: COMPARABLE COMPANY BETA DERIVATION
A12: Company | B12: Levered β | C12: D/E Ratio | D12: Tax Rate | E12: Unlevered β | F12: Segment
A13: Iridium Communications (IRDM) | B13: 0.82 | C13: 0.35 | D13: 0.21 | E13: =B13/(1+(1-D13)*C13) -> 0.64238151 | F13: Space / Connectivity
A14: Viasat (VSAT) | B14: 1.15 | C14: 0.88 | D14: 0.21 | E14: =B14/(1+(1-D14)*C14) -> 0.67838603 | F14: Space / Connectivity
A15: Maxar Technologies | B15: 1.25 | C15: 0.75 | D15: 0.21 | E15: =B15/(1+(1-D15)*C15) -> 0.78492936 | F15: Space
A16: Rocket Lab (RKLB) | B16: 1.42 | C16: 0.18 | D16: 0.21 | E16: =B16/(1+(1-D16)*C16) -> 1.2432148 | F16: Space / Launch
A17: Meta Platforms (META) | B17: 1.28 | C17: 0.02 | D17: 0.21 | E17: =B17/(1+(1-D17)*C17) -> 1.2600906 | F17: AI / Social
A18: Alphabet (GOOGL) | B18: 1.05 | C18: 0 | D18: 0.21 | E18: =B18/(1+(1-D18)*C18) -> 1.05 | F18: AI / Infrastructure
A19: CoreWeave (CRWV) | B19: 1.65 | C19: 1.2 | D19: 0.21 | E19: =B19/(1+(1-D19)*C19) -> 0.84702259 | F19: AI Infrastructure
A21: UNLEVERED BETA BY SEGMENT (Comp-Driven — mature-stage tier median)
A22: Segment | B22: Selected Unlevered β | F22: Rationale
A23: Connectivity (Starlink) | B23: =IF(N('Conn Comps'!X57)>0,'Conn Comps'!X57,0.85) -> 0.20833333 | F23: Mature Wireless comp median unlevered β (fallback 0.85)
A24: Space (Launch) | B24: =IF(N('Space Comps'!X37)>0,'Space Comps'!X37,1.1) -> 0.26644722 | F24: Big-5 Defense comp median unlevered β (fallback 1.10)
A25: AI (X + xAI) | B25: =IF(N('AI Comps'!X47)>0,'AI Comps'!X47,1.35) -> 0.90384475 | F25: Social Media comp median unlevered β (fallback 1.35); excludes high-β neoclouds
A27: COST OF EQUITY BY SEGMENT
B28: Connectivity | C28: Space | D28: AI | F28: Formula
A29: Target D/E (post-IPO est.) | B29: 0.3 | C29: 0.45 | D29: 0.25 | F29: Based on Dec 2025 debt / est. post-IPO market cap by seg
A30: Relevered β | B30: =B23*(1+(1-$B$8)*B29) -> 0.25770833 | C30: =B24*(1+(1-$B$8)*C29) -> 0.3611692 | D30: =B25*(1+(1-$B$8)*D29) -> 1.0823541 | F30: βL = βU × (1 + (1-t) × D/E)
A31: Cost of Equity (CAPM) | B31: =$B$6+B30*$B$7+$B$9 -> 0.082673958 | C31: =$B$6+C30*$B$7+$B$9 -> 0.088364306 | D31: =$B$6+D30*$B$7+$B$9 -> 0.12802947 | F31: Ke = Rf + βL × ERP + SRP
A33: COST OF DEBT
B34: Connectivity | C34: Space | D34: AI | F34: Note
A35: Pre-Tax Cost of Debt | B35: 0.065 | C35: 0.075 | D35: 0.085 | F35: Based on SpaceX credit facility + X debt yields, Jun 2026
A36: After-Tax Cost of Debt | B36: =B35*(1-$B$8) -> 0.05135 | C36: =C35*(1-$B$8) -> 0.05925 | D36: =D35*(1-$B$8) -> 0.06715 | F36: Kd × (1-t)
A39: WACC CALCULATION
B40: Connectivity | C40: Space | D40: AI
A41: Equity Weight | B41: =1/(1+B29) -> 0.76923077 | C41: =1/(1+C29) -> 0.68965517 | D41: =1/(1+D29) -> 0.8 | F41: E/(E+D) = 1/(1+D/E)
A42: Debt Weight | B42: =B29/(1+B29) -> 0.23076923 | C42: =C29/(1+C29) -> 0.31034483 | D42: =D29/(1+D29) -> 0.2 | F42: D/(E+D) = (D/E)/(1+D/E)
A43: WACC | B43: =B31*B41+B36*B42 -> 0.075445353 | C43: =C31*C41+C36*C42 -> 0.079328832 | D43: =D31*D41+D36*D42 -> 0.11585358 | F43: WACC = Ke×We + Kd×Wd
A45: WACC SUMMARY (referenced by DCF sheets)
A46: Segment | B46: WACC | C46: Tg (Base) | D46: Tg (Bear) | E46: Tg (Bull)
A47: Connectivity | B47: =B43 -> 0.075445353 | C47: 0.03 | D47: 0.025 | E47: 0.035
A48: Space | B48: =C43 -> 0.079328832 | C48: 0.025 | D48: 0.02 | E48: 0.03
A49: AI | B49: =D43 -> 0.11585358 | C49: 0.035 | D49: 0.025 | E49: 0.04

Sheet Ratios
A1: SpaceX — Financial Ratios & Credit Metrics
A2: Multiples at our intrinsic value vs. $135 IPO | $ in Millions | FY2025A actuals from S-1
A4: MARKET & VALUATION INPUTS
A5: Our Intrinsic Equity Value (avg, $M) | B5: =SOTP!D20 -> 576167.19
A6: Our Intrinsic EV (avg, $M) | B6: =SOTP!D11 -> 574706.19
A7: IPO Price / Share ($) | B7: =COVER!B5 -> 135
A8: Fully-Diluted Shares (M) | B8: =SOTP!B25 -> 12960
A9: IPO Market Cap ($M) | B9: =B7*B8 -> 1749600
A10: Net Debt ($M) | B10: =SOTP!B16+SOTP!B17 -> 1461
A11: IPO Enterprise Value ($M) | B11: =B9-B10 -> 1748139
A13: FY2025A FINANCIALS (S-1 actuals)
A14: Total Revenue ($M) | B14: =Actuals!D6 -> 18674
A15: Connectivity Revenue ($M) | B15: =Actuals!D7 -> 11387
A16: Space Revenue ($M) | B16: =Actuals!D8 -> 4086
A17: AI Revenue ($M) | B17: =Actuals!D9 -> 3201
A18: Consolidated Adj. EBITDA ($M) | B18: 6600
A19: Connectivity EBITDA ($M) | B19: =Actuals!D10 -> 7168
A20: Net Income (Loss) ($M) | B20: =Actuals!D15 -> -4937
A22: VALUATION MULTIPLES — Our Intrinsic vs. $135 IPO
A23: Multiple | B23: At Our Intrinsic | C23: At $135 IPO | E23: Comp Benchmark
A24: EV / Revenue (trailing) | B24: =B6/B14 -> 30.775741 | C24: =B11/B14 -> 93.613527 | E24: RKLB 118x | PLTR 81x | TSLA 17x
A25: EV / Connectivity Rev | B25: =SOTP!D8/B15 -> 38.293334 | C25: =B11/B15 -> 153.52059 | E25: (blended proxy)
A26: EV / EBITDA (Connectivity) | B26: =SOTP!D8/B19 -> 60.832338 | C26: =B11/B19 -> 243.881 | E26: Telecom 7-10x
A27: EV / EBITDA (consolidated) | B27: =B6/B18 -> 87.076695 | C27: =B11/B18 -> 264.86955 | E27: N/M if EBITDA low
A28: P / E | B28: N/M — net loss | C28: N/M — net loss | E28: SpaceX FY25 net loss $(4.9)B
A29: Market Cap / Revenue | B29: =B5/B14 -> 30.853978 | C29: =B9/B14 -> 93.691764 | E29: —
A31: BALANCE SHEET (Dec 2025, S-1 actuals)
A32: Cash & Marketable Securities ($M) | B32: 24747
A33: Total Current Assets ($M) | B33: 30952
A34: Total Assets ($M) | B34: 92079
A35: Total Current Liabilities ($M) | B35: 21400
A36: Total Debt & Finance Leases ($M) | B36: 23286
A37: Total Liabilities ($M) | B37: 50754
A38: Total Shareholders' Equity ($M) | B38: 2573
A40: FINANCIAL HEALTH RATIOS
A41: Ratio | B41: Value | E41: Note
A42: Current Ratio | B42: =B33/B35 -> 1.4463551 | E42: Current assets / current liabilities
A43: Quick Ratio (approx) | B43: =(B32)/B35 -> 1.1564019 | E43: Cash & securities / current liab
A44: Debt / Equity | B44: =B36/B38 -> 9.050136 | E44: Total debt / shareholders' equity
A45: Debt / EBITDA | B45: =B36/B18 -> 3.5281818 | E45: Leverage vs consolidated adj. EBITDA
A46: Net Debt / EBITDA | B46: =B10/B18 -> 0.22136364 | E46: Net debt / consolidated adj. EBITDA
A47: Total Liabilities / Assets | B47: =B37/B34 -> 0.5512006 | E47: Balance sheet leverage
A48: Return on Equity (ROE) | B48: =B20/B38 -> -1.9187719 | E48: Net loss / equity — negative
A49: Return on Assets (ROA) | B49: =B20/B34 -> -0.053617003 | E49: Net loss / assets — negative
A50: Net Margin | B50: =B20/B14 -> -0.26437828 | E50: Net loss / revenue
A51: EBITDA Margin (consolidated) | B51: =B18/B14 -> 0.35343258 | E51: Adj. EBITDA / revenue

Sheet Graphs
A1: SpaceX — Exhibits & Charts
T3: Segment EV Contribution ($B) | W3: Valuation Comparison — All Sources ($B)
T4: Segment | U4: Avg EV ($B) | W4: Source | X4: Equity/EV Value ($B)
T5: Connectivity | U5: =SOTP!D8/1000 -> 436.0462 | W5: IPO ($135) | X5: 1750
T6: Space | U6: =SOTP!D9/1000 -> 91.383931 | W6: ARK (2030 FV) | X6: 2500
T7: AI | U7: =SOTP!D10/1000 -> 47.276062 | W7: Morningstar | X7: 780
W8: M&I SOTP | X8: 429
W9: Rifat's DCF (Gordon) | X9: =SOTP!B20/1000 -> 649.14864
W10: Rifat's DCF (Avg) | X10: =SOTP!D20/1000 -> 576.16719

Sheet Conn Comps
A1: SpaceX — Connectivity Comparable Companies
A2: Comparable Public Companies by Maturity & Industry | Satellite Broadband + Telecom Infrastructure | $ in Millions
A3: Current-stage anchor = Satellite / LEO Broadband • Mature-stage anchor = Telecom Infrastructure. Input cells (blue) to be populated from terminal (CapIQ/Bloomberg).
A5: TIER 1 — PUBLIC SATELLITE OPERATORS (current-stage anchor)
A6: Name | B6: Ticker | C6: Mkt Cap | D6: Enterprise | E6: LTM | F6: Gross | G6: EBITDA | H6: Capex % | I6: 3-Yr Ann. | J6: TEV / | K6: TEV / | M6: # Subs | N6: ARPU | P6: Levered | Q6: Debt | R6: % Debt | S6: Preferred | T6: % Pref | U6: Equity | V6: % Equity | W6: Tax | X6: Unlevered
C7: ($M) | D7: Value ($M) | E7: Revenue ($M) | F7: Margin | G7: Margin | H7: Revenue | I7: Rev Growth | J7: Revenue | K7: EBITDA | M7: (M) | N7: ($) | P7: Beta | Q7: ($M) | S7: Stock ($M) | U7: Value ($M) | W7: Rate | X7: Beta
A8: Iridium Communications | B8: NasdaqGS:IRDM | C8: 3200 | D8: 4600 | E8: 830 | F8: 0.7195 | G8: 0.62 | H8: 0.045 | I8: 0.05 | J8: =IFERROR(IF(D8=0,"NM",D8/E8),"NM") -> 5.5421687 | K8: =IF(OR(G8<=0,E8=0,D8=0),"NM",IF(D8/(E8*G8)>100,"NM",D8/(E8*G8))) -> 8.9389817 | M8: 2.555 | N8: 27 | P8: 0.6 | Q8: 1810 | R8: =IFERROR(Q8/(Q8+S8+U8),"") -> 0.25138889 | S8: 0 | T8: =IFERROR(S8/($Q8+$S8+$U8),"") -> 0 | U8: 5390 | V8: =IFERROR(U8/(Q8+S8+U8),"") -> 0.74861111 | W8: 0.21 | X8: =IFERROR(P8/(1+(Q8/U8)*(1-W8)+S8/U8),"") -> 0.4742005
A9: EchoStar Corporation | B9: NasdaqGS:SATS | C9: 36100 | D9: 61430 | E9: 14800 | F9: 0.37 | G9: 0.37 | H9: 0.115 | I9: 0.11 | J9: =IFERROR(IF(D9=0,"NM",D9/E9),"NM") -> 4.1506757 | K9: =IF(OR(G9<=0,E9=0,D9=0),"NM",IF(D9/(E9*G9)>100,"NM",D9/(E9*G9))) -> 11.218042 | M9: 29.2 | N9: 40 | P9: 0.96 | Q9: 29240 | R9: =IFERROR(Q9/(Q9+S9+U9),"") -> 0.47130883 | S9: 0 | T9: =IFERROR(S9/($Q9+$S9+$U9),"") -> 0 | U9: 32800 | V9: =IFERROR(U9/(Q9+S9+U9),"") -> 0.52869117 | W9: 0.21 | X9: =IFERROR(P9/(1+(Q9/U9)*(1-W9)+S9/U9),"") -> 0.56329562
A10: Globalstar, Inc. | B10: NasdaqGS:GSAT | C10: 3000 | D10: 3500 | E10: 250 | F10: 0.6381 | G10: 0.4 | H10: 0.8 | I10: 0.1 | J10: =IFERROR(IF(D10=0,"NM",D10/E10),"NM") -> 14 | K10: =IF(OR(G10<=0,E10=0,D10=0),"NM",IF(D10/(E10*G10)>100,"NM",D10/(E10*G10))) -> 35 | M10: NM | N10: NM | P10: 2.6 | Q10: 546 | R10: =IFERROR(Q10/(Q10+S10+U10),"") -> 0.044953071 | S10: 0 | T10: =IFERROR(S10/($Q10+$S10+$U10),"") -> 0 | U10: 11600 | V10: =IFERROR(U10/(Q10+S10+U10),"") -> 0.95504693 | W10: 0.21 | X10: =IFERROR(P10/(1+(Q10/U10)*(1-W10)+S10/U10),"") -> 2.5067864
A11: AST SpaceMobile, Inc. | B11: NasdaqGS:ASTS | C11: 15600 | D11: 15100 | E11: 71 | F11: 0.4482 | G11: -2 | H11: 5 | I11: 0.15 | J11: =IFERROR(IF(D11=0,"NM",D11/E11),"NM") -> 212.67606 | K11: =IF(OR(G11<=0,E11=0,D11=0),"NM",IF(D11/(E11*G11)>100,"NM",D11/(E11*G11))) -> NM | M11: NM | N11: NM | P11: 2.6 | Q11: 2990 | R11: =IFERROR(Q11/(Q11+S11+U11),"") -> 0.096607431 | S11: 0 | T11: =IFERROR(S11/($Q11+$S11+$U11),"") -> 0 | U11: 27960 | V11: =IFERROR(U11/(Q11+S11+U11),"") -> 0.90339257 | W11: 0.21 | X11: =IFERROR(P11/(1+(Q11/U11)*(1-W11)+S11/U11),"") -> 2.3974593
A12: Viasat, Inc. | B12: NasdaqGS:VSAT | C12: 6640 | D12: 12000 | E12: 4500 | F12: 0.332 | G12: 0.3 | H12: 0.199 | I12: 0.08 | J12: =IFERROR(IF(D12=0,"NM",D12/E12),"NM") -> 2.6666667 | K12: =IF(OR(G12<=0,E12=0,D12=0),"NM",IF(D12/(E12*G12)>100,"NM",D12/(E12*G12))) -> 8.8888889 | M12: NM | N12: NM | P12: 1.37 | Q12: 7080 | R12: =IFERROR(Q12/(Q12+S12+U12),"") -> 0.43839009 | S12: 0 | T12: =IFERROR(S12/($Q12+$S12+$U12),"") -> 0 | U12: 9070 | V12: =IFERROR(U12/(Q12+S12+U12),"") -> 0.56160991 | W12: 0.21 | X12: =IFERROR(P12/(1+(Q12/U12)*(1-W12)+S12/U12),"") -> 0.84742075
A13: SES S.A. | B13: ENXTPA:SESG | C13: 6300 | D13: 12560 | E13: 2850 | F13: 0.6 | G13: 0.43 | H13: 0.5 | I13: 0.05 | J13: =IFERROR(IF(D13=0,"NM",D13/E13),"NM") -> 4.4070175 | K13: =IF(OR(G13<=0,E13=0,D13=0),"NM",IF(D13/(E13*G13)>100,"NM",D13/(E13*G13))) -> 10.248878 | M13: NM | N13: NM | P13: 0.51 | Q13: 3400 | R13: =IFERROR(Q13/(Q13+S13+U13),"") -> 0.57627119 | S13: 0 | T13: =IFERROR(S13/($Q13+$S13+$U13),"") -> 0 | U13: 2500 | V13: =IFERROR(U13/(Q13+S13+U13),"") -> 0.42372881 | W13: 0.21 | X13: =IFERROR(P13/(1+(Q13/U13)*(1-W13)+S13/U13),"") -> 0.24585422
A14: Eutelsat Communications | B14: ENXTPA:ETL | C14: 3840 | D14: 4810 | E14: 1230 | F14: 0.5 | G14: 0.3 | H14: 0.45 | I14: 0.08 | J14: =IFERROR(IF(D14=0,"NM",D14/E14),"NM") -> 3.9105691 | K14: =IF(OR(G14<=0,E14=0,D14=0),"NM",IF(D14/(E14*G14)>100,"NM",D14/(E14*G14))) -> 13.03523 | M14: NM | N14: NM | P14: 0.9 | Q14: 7300 | R14: =IFERROR(Q14/(Q14+S14+U14),"") -> 0.72277228 | S14: 0 | T14: =IFERROR(S14/($Q14+$S14+$U14),"") -> 0 | U14: 2800 | V14: =IFERROR(U14/(Q14+S14+U14),"") -> 0.27722772 | W14: 0.25 | X14: =IFERROR(P14/(1+(Q14/U14)*(1-W14)+S14/U14),"") -> 0.30453172
A15: Telesat Corporation | B15: NasdaqGS:TSAT | C15: 2460 | D15: 5500 | E15: 279 | F15: 0.65 | G15: 0.65 | H15: 0.35 | I15: 0.05 | J15: =IFERROR(IF(D15=0,"NM",D15/E15),"NM") -> 19.713262 | K15: =IF(OR(G15<=0,E15=0,D15=0),"NM",IF(D15/(E15*G15)>100,"NM",D15/(E15*G15))) -> 30.328095 | M15: NM | N15: NM | P15: 2 | Q15: 4200 | R15: =IFERROR(Q15/(Q15+S15+U15),"") -> 0.87318087 | S15: 0 | T15: =IFERROR(S15/($Q15+$S15+$U15),"") -> 0 | U15: 610 | V15: =IFERROR(U15/(Q15+S15+U15),"") -> 0.12681913 | W15: 0.265 | X15: =IFERROR(P15/(1+(Q15/U15)*(1-W15)+S15/U15),"") -> 0.3299973
A17: Min: | C17: =IFERROR(MIN(C8:C15),"") -> 2460 | D17: =IFERROR(MIN(D8:D15),"") -> 3500 | E17: =IFERROR(MIN(E8:E15),"") -> 71 | F17: =IFERROR(MIN(F8:F15),"") -> 0.332 | G17: =IFERROR(MIN(G8:G15),"") -> -2 | H17: =IFERROR(MIN(H8:H15),"") -> 0.045 | I17: =IFERROR(MIN(I8:I15),"") -> 0.05 | J17: =IFERROR(_xlfn.AGGREGATE(5,6,J8:J15),"") -> 2.6666667 | K17: =IFERROR(MIN(K8:K15),"") -> 8.8888889 | M17: =IFERROR(IF(COUNTA(M8:M15)=0,"",MIN(M8:M15)),"") -> 2.555 | N17: =IFERROR(IF(COUNTA(N8:N15)=0,"",MIN(N8:N15)),"") -> 27 | P17: =IFERROR(MIN(P8:P15),"") -> 0.51 | Q17: =IFERROR(MIN(Q8:Q15),"") -> 546 | R17: =IFERROR(MIN(R8:R15),"") -> 0.044953071 | S17: =IFERROR(MIN(S8:S15),"") -> 0 | T17: =IFERROR(MIN(T8:T15),"") -> 0 | U17: =IFERROR(MIN(U8:U15),"") -> 610 | V17: =IFERROR(MIN(V8:V15),"") -> 0.12681913 | W17: =IFERROR(MIN(W8:W15),"") -> 0.21 | X17: =IFERROR(MIN(X8:X15),"") -> 0.24585422
A18: 25th Pctl: | C18: =IFERROR(QUARTILE(C8:C15,1),"") -> 3150 | D18: =IFERROR(QUARTILE(D8:D15,1),"") -> 4757.5 | E18: =IFERROR(QUARTILE(E8:E15,1),"") -> 271.75 | F18: =IFERROR(QUARTILE(F8:F15,1),"") -> 0.42865 | G18: =IFERROR(QUARTILE(G8:G15,1),"") -> 0.3 | H18: =IFERROR(QUARTILE(H8:H15,1),"") -> 0.178 | I18: =IFERROR(QUARTILE(I8:I15,1),"") -> 0.05 | J18: =IFERROR(QUARTILE(J8:J15,1),"") -> 4.090649 | K18: =QUARTILE((K8,K9,K10,K12,K13,K14,K15),1) -> 9.5939299 | M18: =IFERROR(QUARTILE(M8:M15,1),"") -> 9.21625 | N18: =IFERROR(QUARTILE(N8:N15,1),"") -> 30.25 | P18: =IFERROR(QUARTILE(P8:P15,1),"") -> 0.825 | Q18: =IFERROR(QUARTILE(Q8:Q15,1),"") -> 2695 | R18: =IFERROR(QUARTILE(R8:R15,1),"") -> 0.21269352 | S18: =IFERROR(QUARTILE(S8:S15,1),"") -> 0 | T18: =IFERROR(QUARTILE(T8:T15,1),"") -> 0 | U18: =IFERROR(QUARTILE(U8:U15,1),"") -> 2725 | V18: =IFERROR(QUARTILE(V8:V15,1),"") -> 0.38710354 | W18: =IFERROR(QUARTILE(W8:W15,1),"") -> 0.21 | X18: =IFERROR(QUARTILE(X8:X15,1),"") -> 0.3236309
A19: Median: | C19: =IFERROR(MEDIAN(C8:C15),"") -> 5070 | D19: =IFERROR(MEDIAN(D8:D15),"") -> 8750 | E19: =IFERROR(MEDIAN(E8:E15),"") -> 1030 | F19: =IFERROR(MEDIAN(F8:F15),"") -> 0.55 | G19: =IFERROR(MEDIAN(G8:G15),"") -> 0.385 | H19: =IFERROR(MEDIAN(H8:H15),"") -> 0.4 | I19: =IFERROR(MEDIAN(I8:I15),"") -> 0.08 | J19: =IFERROR(QUARTILE(J8:J15,2),"") -> 4.9745931 | K19: =QUARTILE((K8,K9,K10,K12,K13,K14,K15),2) -> 11.218042 | M19: =IFERROR(MEDIAN(M8:M15),"") -> 15.8775 | N19: =IFERROR(MEDIAN(N8:N15),"") -> 33.5 | P19: =IFERROR(MEDIAN(P8:P15),"") -> 1.165 | Q19: =IFERROR(MEDIAN(Q8:Q15),"") -> 3800 | R19: =IFERROR(MEDIAN(R8:R15),"") -> 0.45484946 | S19: =IFERROR(MEDIAN(S8:S15),"") -> 0 | T19: =IFERROR(MEDIAN(T8:T15),"") -> 0 | U19: =IFERROR(MEDIAN(U8:U15),"") -> 7230 | V19: =IFERROR(MEDIAN(V8:V15),"") -> 0.54515054 | W19: =IFERROR(MEDIAN(W8:W15),"") -> 0.21 | X19: =IFERROR(MEDIAN(X8:X15),"") -> 0.51874806
A20: Mean: | C20: =IFERROR(AVERAGE(C8:C15),"") -> 9642.5 | D20: =IFERROR(AVERAGE(D8:D15),"") -> 14937.5 | E20: =IFERROR(AVERAGE(E8:E15),"") -> 3101.25 | F20: =IFERROR(AVERAGE(F8:F15),"") -> 0.532225 | G20: =IFERROR(AVERAGE(G8:G15),"") -> 0.13375 | H20: =IFERROR(AVERAGE(H8:H15),"") -> 0.932375 | I20: =IFERROR(AVERAGE(I8:I15),"") -> 0.08375 | J20: =IFERROR(_xlfn.AGGREGATE(1,6,J8:J15),"") -> 33.383302 | K20: =IFERROR(AVERAGE(K8:K15),"") -> 16.808302 | M20: =IFERROR(AVERAGE(M8:M15),"") -> 15.8775 | N20: =IFERROR(AVERAGE(N8:N15),"") -> 33.5 | P20: =IFERROR(AVERAGE(P8:P15),"") -> 1.4425 | Q20: =IFERROR(AVERAGE(Q8:Q15),"") -> 7070.75 | R20: =IFERROR(AVERAGE(R8:R15),"") -> 0.43435908 | S20: =IFERROR(AVERAGE(S8:S15),"") -> 0 | T20: =IFERROR(AVERAGE(T8:T15),"") -> 0 | U20: =IFERROR(AVERAGE(U8:U15),"") -> 11591.25 | V20: =IFERROR(AVERAGE(V8:V15),"") -> 0.56564092 | W20: =IFERROR(AVERAGE(W8:W15),"") -> 0.221875 | X20: =IFERROR(AVERAGE(X8:X15),"") -> 0.95869323
A21: 75th Pctl: | C21: =IFERROR(QUARTILE(C8:C15,3),"") -> 8880 | D21: =IFERROR(QUARTILE(D8:D15,3),"") -> 13195 | E21: =IFERROR(QUARTILE(E8:E15,3),"") -> 3262.5 | F21: =IFERROR(QUARTILE(F8:F15,3),"") -> 0.641075 | G21: =IFERROR(QUARTILE(G8:G15,3),"") -> 0.4775 | H21: =IFERROR(QUARTILE(H8:H15,3),"") -> 0.575 | I21: =IFERROR(QUARTILE(I8:I15,3),"") -> 0.1025 | J21: =IFERROR(QUARTILE(J8:J15,3),"") -> 15.428315 | K21: =QUARTILE((K8,K9,K10,K12,K13,K14,K15),3) -> 21.681663 | M21: =IFERROR(QUARTILE(M8:M15,3),"") -> 22.53875 | N21: =IFERROR(QUARTILE(N8:N15,3),"") -> 36.75 | P21: =IFERROR(QUARTILE(P8:P15,3),"") -> 2.15 | Q21: =IFERROR(QUARTILE(Q8:Q15,3),"") -> 7135 | R21: =IFERROR(QUARTILE(R8:R15,3),"") -> 0.61289646 | S21: =IFERROR(QUARTILE(S8:S15,3),"") -> 0 | T21: =IFERROR(QUARTILE(T8:T15,3),"") -> 0 | U21: =IFERROR(QUARTILE(U8:U15,3),"") -> 15690 | V21: =IFERROR(QUARTILE(V8:V15,3),"") -> 0.78730648 | W21: =IFERROR(QUARTILE(W8:W15,3),"") -> 0.22 | X21: =IFERROR(QUARTILE(X8:X15,3),"") -> 1.2349304
A22: Max: | C22: =IFERROR(MAX(C8:C15),"") -> 36100 | D22: =IFERROR(MAX(D8:D15),"") -> 61430 | E22: =IFERROR(MAX(E8:E15),"") -> 14800 | F22: =IFERROR(MAX(F8:F15),"") -> 0.7195 | G22: =IFERROR(MAX(G8:G15),"") -> 0.65 | H22: =IFERROR(MAX(H8:H15),"") -> 5 | I22: =IFERROR(MAX(I8:I15),"") -> 0.15 | J22: =IFERROR(_xlfn.AGGREGATE(4,6,J8:J15),"") -> 212.67606 | K22: =IFERROR(MAX(K8:K15),"") -> 35 | M22: =IFERROR(IF(COUNTA(M8:M15)=0,"",MAX(M8:M15)),"") -> 29.2 | N22: =IFERROR(IF(COUNTA(N8:N15)=0,"",MAX(N8:N15)),"") -> 40 | P22: =IFERROR(MAX(P8:P15),"") -> 2.6 | Q22: =IFERROR(MAX(Q8:Q15),"") -> 29240 | R22: =IFERROR(MAX(R8:R15),"") -> 0.87318087 | S22: =IFERROR(MAX(S8:S15),"") -> 0 | T22: =IFERROR(MAX(T8:T15),"") -> 0 | U22: =IFERROR(MAX(U8:U15),"") -> 32800 | V22: =IFERROR(MAX(V8:V15),"") -> 0.95504693 | W22: =IFERROR(MAX(W8:W15),"") -> 0.265 | X22: =IFERROR(MAX(X8:X15),"") -> 2.5067864
A24: TIER 2 — EMERGING-MARKETS TELECOM / WIRELESS (>10% Projected Organic Revenue Growth)
A25: Name | B25: Ticker | C25: Mkt Cap | D25: Enterprise | E25: LTM | F25: Gross | G25: EBITDA | H25: Capex % | I25: 3-Yr Ann. | J25: TEV / | K25: TEV / | M25: # Subs | N25: ARPU | P25: Levered | Q25: Debt | R25: % Debt | S25: Preferred | T25: % Pref | U25: Equity | V25: % Equity | W25: Tax | X25: Unlevered
C26: ($M) | D26: Value ($M) | E26: Revenue ($M) | F26: Margin | G26: Margin | H26: Revenue | I26: Rev Growth | J26: Revenue | K26: EBITDA | M26: (M) | N26: ($) | P26: Beta | Q26: ($M) | S26: Stock ($M) | U26: Value ($M) | W26: Rate | X26: Beta
A27: Bharti Airtel Limited | B27: BSE:532454 | C27: 116130 | D27: 137956 | E27: 23300 | F27: 0.5 | G27: 0.38 | H27: 0.22 | I27: 0.22 | J27: =IF(OR(D27="",D27=0,E27="",E27=0),"NM",D27/E27) -> 5.9208584 | K27: =IF(OR(G27<=0,E27=0,D27=0),"NM",IF(D27/(E27*G27)>100,"NM",D27/(E27*G27))) -> 15.581206 | M27: 478 | N27: 3 | P27: 0.5 | Q27: 14000 | R27: =IFERROR(Q27/(Q27+S27+U27),"") -> 0.11070694 | S27: 0 | T27: =IFERROR(S27/(Q27+S27+U27),"") -> 0 | U27: 112460 | V27: =IFERROR(U27/(Q27+S27+U27),"") -> 0.88929306 | W27: 0.25 | X27: =IFERROR(P27/(1+(Q27/U27)*(1-W27)+S27/U27),"") -> 0.45730319
A28: MTN Group Limited | B28: JSE:MTN | C28: 21828 | D28: 24074 | E28: 10010 | F28: 0.45 | G28: 0.44 | H28: 0.19 | I28: 0.08 | J28: =IF(OR(D28="",D28=0,E28="",E28=0),"NM",D28/E28) -> 2.404995 | K28: =IF(OR(G28<=0,E28=0,D28=0),"NM",IF(D28/(E28*G28)>100,"NM",D28/(E28*G28))) -> 5.4658977 | M28: 307 | N28: 3.5 | P28: 0.97 | Q28: 8100 | R28: =IFERROR(Q28/(Q28+S28+U28),"") -> 0.29454545 | S28: 0 | T28: =IFERROR(S28/(Q28+S28+U28),"") -> 0 | U28: 19400 | V28: =IFERROR(U28/(Q28+S28+U28),"") -> 0.70545455 | W28: 0.28 | X28: =IFERROR(P28/(1+(Q28/U28)*(1-W28)+S28/U28),"") -> 0.74579899
A29: Vodacom Group Limited | B29: JSE:VOD | C29: 17080 | D29: 20380 | E29: 8860 | F29: 0.55 | G29: 0.4 | H29: 0.18 | I29: 0.12 | J29: =IF(OR(D29="",D29=0,E29="",E29=0),"NM",D29/E29) -> 2.3002257 | K29: =IF(OR(G29<=0,E29=0,D29=0),"NM",IF(D29/(E29*G29)>100,"NM",D29/(E29*G29))) -> 5.7505643 | M29: 83 | N29: 7 | P29: 0.42 | Q29: 4400 | R29: =IFERROR(Q29/(Q29+S29+U29),"") -> 0.19634092 | S29: 0 | T29: =IFERROR(S29/(Q29+S29+U29),"") -> 0 | U29: 18010 | V29: =IFERROR(U29/(Q29+S29+U29),"") -> 0.80365908 | W29: 0.28 | X29: =IFERROR(P29/(1+(Q29/U29)*(1-W29)+S29/U29),"") -> 0.35717254
A30: Vodafone Idea Limited | B30: NSEI:IDEA | C30: 15293 | D30: 36374 | E30: 4000 | F30: 0.3 | G30: 0.27 | H30: 0.25 | I30: 0.05 | J30: =IF(OR(D30="",D30=0,E30="",E30=0),"NM",D30/E30) -> 9.0935 | K30: =IF(OR(G30<=0,E30=0,D30=0),"NM",IF(D30/(E30*G30)>100,"NM",D30/(E30*G30))) -> 33.67963 | M30: 198 | N30: 2 | P30: 1.1 | Q30: 23000 | R30: =IFERROR(Q30/(Q30+S30+U30),"") -> 0.71875 | S30: 0 | T30: =IFERROR(S30/(Q30+S30+U30),"") -> 0 | U30: 9000 | V30: =IFERROR(U30/(Q30+S30+U30),"") -> 0.28125 | W30: 0.25 | X30: =IFERROR(P30/(1+(Q30/U30)*(1-W30)+S30/U30),"") -> 0.37714286
A31: VEON Ltd. | B31: NasdaqGS:VEON | C31: 3630 | D31: 5130 | E31: 4400 | F31: 0.88 | G31: 0.43 | H31: 0.2 | I31: 0.14 | J31: =IF(OR(D31="",D31=0,E31="",E31=0),"NM",D31/E31) -> 1.1659091 | K31: =IF(OR(G31<=0,E31=0,D31=0),"NM",IF(D31/(E31*G31)>100,"NM",D31/(E31*G31))) -> 2.7114165 | M31: 150.5 | N31: 2.3 | P31: 1.61 | Q31: 5150 | R31: =IFERROR(Q31/(Q31+S31+U31),"") -> 0.56593407 | S31: 0 | T31: =IFERROR(S31/(Q31+S31+U31),"") -> 0 | U31: 3950 | V31: =IFERROR(U31/(Q31+S31+U31),"") -> 0.43406593 | W31: 0.2 | X31: =IFERROR(P31/(1+(Q31/U31)*(1-W31)+S31/U31),"") -> 0.78804213
A32: Mobile Telecom Co. (Zain) | B32: KWSE:ZAIN | C32: 7612 | D32: 9717 | E32: 5500 | F32: 0.55 | G32: 0.34 | H32: 0.16 | I32: 0.08 | J32: =IF(OR(D32="",D32=0,E32="",E32=0),"NM",D32/E32) -> 1.7667273 | K32: =IF(OR(G32<=0,E32=0,D32=0),"NM",IF(D32/(E32*G32)>100,"NM",D32/(E32*G32))) -> 5.1962567 | M32: 51.2 | N32: 12 | P32: 0.65 | Q32: 3500 | R32: =IFERROR(Q32/(Q32+S32+U32),"") -> 0.24475524 | S32: 0 | T32: =IFERROR(S32/(Q32+S32+U32),"") -> 0 | U32: 10800 | V32: =IFERROR(U32/(Q32+S32+U32),"") -> 0.75524476 | W32: 0.15 | X32: =IFERROR(P32/(1+(Q32/U32)*(1-W32)+S32/U32),"") -> 0.50961887
A33: Safaricom PLC | B33: NASE:SCOM | C33: 9815 | D33: 11440 | E33: 3080 | F33: 0.6 | G33: 0.44 | H33: 0.21 | I33: 0.11 | J33: =IF(OR(D33="",D33=0,E33="",E33=0),"NM",D33/E33) -> 3.7142857 | K33: =IF(OR(G33<=0,E33=0,D33=0),"NM",IF(D33/(E33*G33)>100,"NM",D33/(E33*G33))) -> 8.4415584 | M33: 46 | N33: 3 | P33: 0.5 | Q33: 1200 | R33: =IFERROR(Q33/(Q33+S33+U33),"") -> 0.11650485 | S33: 0 | T33: =IFERROR(S33/(Q33+S33+U33),"") -> 0 | U33: 9100 | V33: =IFERROR(U33/(Q33+S33+U33),"") -> 0.88349515 | W33: 0.3 | X33: =IFERROR(P33/(1+(Q33/U33)*(1-W33)+S33/U33),"") -> 0.45774648
A34: PT XLSMART Telecom | B34: IDX:EXCL | C34: 3255 | D34: 4037 | E34: 1500 | F34: 0.52 | G34: 0.3 | H34: 0.22 | I34: 0.1 | J34: =IF(OR(D34="",D34=0,E34="",E34=0),"NM",D34/E34) -> 2.6913333 | K34: =IF(OR(G34<=0,E34=0,D34=0),"NM",IF(D34/(E34*G34)>100,"NM",D34/(E34*G34))) -> 8.9711111 | M34: 94.5 | N34: 1.5 | P34: 1 | Q34: 1800 | R34: =IFERROR(Q34/(Q34+S34+U34),"") -> 0.36 | S34: 0 | T34: =IFERROR(S34/(Q34+S34+U34),"") -> 0 | U34: 3200 | V34: =IFERROR(U34/(Q34+S34+U34),"") -> 0.64 | W34: 0.22 | X34: =IFERROR(P34/(1+(Q34/U34)*(1-W34)+S34/U34),"") -> 0.69504778
A36: Min: | C36: =IFERROR(IF(COUNTA(C27:C34)=0,"",MIN(C27:C34)),"") -> 3255 | D36: =IFERROR(IF(COUNTA(D27:D34)=0,"",MIN(D27:D34)),"") -> 4037 | E36: =IFERROR(MIN(E27:E34),"") -> 1500 | F36: =MIN(F27:F34) -> 0.3 | G36: =IFERROR(MIN(G27:G34),"") -> 0.27 | H36: =IFERROR(MIN(H27:H34),"") -> 0.16 | I36: =IFERROR(IF(COUNTA(I27:I34)=0,"",MIN(I27:I34)),"") -> 0.05 | J36: =IFERROR(IF(COUNTA(D27:D34)=0,"",_xlfn.AGGREGATE(5,6,J27:J34)),"") -> 1.1659091 | K36: =IFERROR(IF(COUNTA(G27:G34)=0,"",_xlfn.AGGREGATE(5,6,K27:K34)),"") -> 2.7114165 | M36: =IFERROR(IF(COUNTA(M27:M34)=0,"",MIN(M27:M34)),"") -> 46 | N36: =IFERROR(IF(COUNTA(N27:N34)=0,"",MIN(N27:N34)),"") -> 1.5 | P36: =IFERROR(MIN(P27:P34),"") -> 0.42 | Q36: =MIN(Q27:Q34) -> 1200 | R36: =IFERROR(MIN(R27:R34),"") -> 0.11070694 | S36: =MIN(S27:S34) -> 0 | T36: =IFERROR(MIN(T27:T34),"") -> 0 | U36: =MIN(U27:U34) -> 3200 | V36: =IFERROR(MIN(V27:V34),"") -> 0.28125 | W36: =IFERROR(MIN(W27:W34),"") -> 0.15 | X36: =IFERROR(MIN(X27:X34),"") -> 0.35717254
A37: 25th Pctl: | C37: =IFERROR(IF(COUNTA(C27:C34)=0,"",QUARTILE(C27:C34,1)),"") -> 6616.5 | D37: =IFERROR(IF(COUNTA(D27:D34)=0,"",QUARTILE(D27:D34,1)),"") -> 8570.25 | E37: =IFERROR(QUARTILE(E27:E34,1),"") -> 3770 | F37: =PERCENTILE(F27:F34,0.25) -> 0.4875 | G37: =IFERROR(QUARTILE(G27:G34,1),"") -> 0.33 | H37: =IFERROR(QUARTILE(H27:H34,1),"") -> 0.1875 | I37: =IFERROR(IF(COUNTA(I27:I34)=0,"",QUARTILE(I27:I34,1)),"") -> 0.08 | J37: =QUARTILE(J27:J34,1) -> 2.1668511 | K37: =QUARTILE(K27:K34,1) -> 5.3984875 | M37: =QUARTILE(M27:M34,1) -> 75.05 | N37: =QUARTILE(N27:N34,1) -> 2.225 | P37: =IFERROR(QUARTILE(P27:P34,1),"") -> 0.5 | Q37: =PERCENTILE(Q27:Q34,0.25) -> 3075 | R37: =IFERROR(QUARTILE(R27:R34,1),"") -> 0.1763819 | S37: =PERCENTILE(S27:S34,0.25) -> 0 | T37: =IFERROR(QUARTILE(T27:T34,1),"") -> 0 | U37: =PERCENTILE(U27:U34,0.25) -> 7737.5 | V37: =IFERROR(QUARTILE(V27:V34,1),"") -> 0.58851648 | W37: =IFERROR(QUARTILE(W27:W34,1),"") -> 0.215 | X37: =IFERROR(QUARTILE(X27:X34,1),"") -> 0.43726311
A38: Median: | C38: =IFERROR(IF(COUNTA(C27:C34)=0,"",MEDIAN(C27:C34)),"") -> 12554 | D38: =IFERROR(IF(COUNTA(D27:D34)=0,"",MEDIAN(D27:D34)),"") -> 15910 | E38: =IFERROR(MEDIAN(E27:E34),"") -> 4950 | F38: =MEDIAN(F27:F34) -> 0.535 | G38: =IFERROR(MEDIAN(G27:G34),"") -> 0.39 | H38: =IFERROR(MEDIAN(H27:H34),"") -> 0.205 | I38: =IFERROR(IF(COUNTA(I27:I34)=0,"",MEDIAN(I27:I34)),"") -> 0.105 | J38: =QUARTILE(J27:J34,2) -> 2.5481642 | K38: =QUARTILE(K27:K34,2) -> 7.0960614 | M38: =QUARTILE(M27:M34,2) -> 122.5 | N38: =QUARTILE(N27:N34,2) -> 3 | P38: =IFERROR(MEDIAN(P27:P34),"") -> 0.81 | Q38: =MEDIAN(Q27:Q34) -> 4775 | R38: =IFERROR(MEDIAN(R27:R34),"") -> 0.26965035 | S38: =MEDIAN(S27:S34) -> 0 | T38: =IFERROR(MEDIAN(T27:T34),"") -> 0 | U38: =MEDIAN(U27:U34) -> 9950 | V38: =IFERROR(MEDIAN(V27:V34),"") -> 0.73034965 | W38: =IFERROR(MEDIAN(W27:W34),"") -> 0.25 | X38: =IFERROR(MEDIAN(X27:X34),"") -> 0.48368268
A39: Mean: | C39: =IFERROR(IF(COUNTA(C27:C34)=0,"",AVERAGE(C27:C34)),"") -> 24330.375 | D39: =IFERROR(IF(COUNTA(D27:D34)=0,"",AVERAGE(D27:D34)),"") -> 31138.5 | E39: =IFERROR(AVERAGE(E27:E34),"") -> 7581.25 | F39: =AVERAGE(F27:F34) -> 0.54375 | G39: =IFERROR(AVERAGE(G27:G34),"") -> 0.375 | H39: =IFERROR(AVERAGE(H27:H34),"") -> 0.20375 | I39: =IFERROR(IF(COUNTA(I27:I34)=0,"",AVERAGE(I27:I34)),"") -> 0.1125 | J39: =IFERROR(IF(COUNTA(D27:D34)=0,"",_xlfn.AGGREGATE(1,6,J27:J34)),"") -> 3.6322293 | K39: =IFERROR(IF(COUNTA(G27:G34)=0,"",_xlfn.AGGREGATE(1,6,K27:K34)),"") -> 10.724705 | M39: =IFERROR(IF(COUNTA(I27:I34)=0,"",_xlfn.AGGREGATE(1,6,M27:M34)),"") -> 176.025 | N39: =IFERROR(IF(COUNTA(J27:J34)=0,"",_xlfn.AGGREGATE(1,6,N27:N34)),"") -> 4.2875 | P39: =IFERROR(AVERAGE(P27:P34),"") -> 0.84375 | Q39: =AVERAGE(Q27:Q34) -> 7643.75 | R39: =IFERROR(AVERAGE(R27:R34),"") -> 0.32594219 | S39: =AVERAGE(S27:S34) -> 0 | T39: =IFERROR(AVERAGE(T27:T34),"") -> 0 | U39: =AVERAGE(U27:U34) -> 23240 | V39: =IFERROR(AVERAGE(V27:V34),"") -> 0.67405781 | W39: =IFERROR(AVERAGE(W27:W34),"") -> 0.24125 | X39: =IFERROR(AVERAGE(X27:X34),"") -> 0.5484841
A40: 75th Pctl: | C40: =IFERROR(IF(COUNTA(C27:C34)=0,"",QUARTILE(C27:C34,3)),"") -> 18267 | D40: =IFERROR(IF(COUNTA(D27:D34)=0,"",QUARTILE(D27:D34,3)),"") -> 27149 | E40: =IFERROR(QUARTILE(E27:E34,3),"") -> 9147.5 | F40: =PERCENTILE(F27:F34,0.75) -> 0.5625 | G40: =IFERROR(QUARTILE(G27:G34,3),"") -> 0.4325 | H40: =IFERROR(QUARTILE(H27:H34,3),"") -> 0.22 | I40: =IFERROR(IF(COUNTA(I27:I34)=0,"",QUARTILE(I27:I34,3)),"") -> 0.125 | J40: =QUARTILE(J27:J34,3) -> 4.2659289 | K40: =QUARTILE(K27:K34,3) -> 10.623635 | M40: =QUARTILE(M27:M34,3) -> 225.25 | N40: =QUARTILE(N27:N34,3) -> 4.375 | P40: =IFERROR(QUARTILE(P27:P34,3),"") -> 1.025 | Q40: =PERCENTILE(Q27:Q34,0.75) -> 9575 | R40: =IFERROR(QUARTILE(R27:R34,3),"") -> 0.41148352 | S40: =PERCENTILE(S27:S34,0.75) -> 0 | T40: =IFERROR(QUARTILE(T27:T34,3),"") -> 0 | U40: =PERCENTILE(U27:U34,0.75) -> 18357.5 | V40: =IFERROR(QUARTILE(V27:V34,3),"") -> 0.8236181 | W40: =IFERROR(QUARTILE(W27:W34,3),"") -> 0.28 | X40: =IFERROR(QUARTILE(X27:X34,3),"") -> 0.70773558
A41: Max: | C41: =IFERROR(IF(COUNTA(C27:C34)=0,"",MAX(C27:C34)),"") -> 116130 | D41: =IFERROR(IF(COUNTA(D27:D34)=0,"",MAX(D27:D34)),"") -> 137956 | E41: =IFERROR(MAX(E27:E34),"") -> 23300 | F41: =MAX(F27:F34) -> 0.88 | G41: =IFERROR(MAX(G27:G34),"") -> 0.44 | H41: =IFERROR(MAX(H27:H34),"") -> 0.25 | I41: =IFERROR(IF(COUNTA(I27:I34)=0,"",MAX(I27:I34)),"") -> 0.22 | J41: =IFERROR(IF(COUNTA(D27:D34)=0,"",_xlfn.AGGREGATE(4,6,J27:J34)),"") -> 9.0935 | K41: =IFERROR(IF(COUNTA(G27:G34)=0,"",_xlfn.AGGREGATE(4,6,K27:K34)),"") -> 33.67963 | M41: =IFERROR(IF(COUNTA(M27:M34)=0,"",MAX(M27:M34)),"") -> 478 | N41: =IFERROR(IF(COUNTA(N27:N34)=0,"",MAX(N27:N34)),"") -> 12 | P41: =IFERROR(MAX(P27:P34),"") -> 1.61 | Q41: =MAX(Q27:Q34) -> 23000 | R41: =IFERROR(MAX(R27:R34),"") -> 0.71875 | S41: =MAX(S27:S34) -> 0 | T41: =IFERROR(MAX(T27:T34),"") -> 0 | U41: =MAX(U27:U34) -> 112460 | V41: =IFERROR(MAX(V27:V34),"") -> 0.88929306 | W41: =IFERROR(MAX(W27:W34),"") -> 0.3 | X41: =IFERROR(MAX(X27:X34),"") -> 0.78804213
A43: TIER 3 — LARGE, MATURE WIRELESS (>$10B Revenue — Mature-Stage Anchor)
A44: Name | B44: Ticker | C44: Mkt Cap | D44: Enterprise | E44: LTM | F44: Gross | G44: EBITDA | H44: Capex % | I44: 3-Yr Ann. | J44: TEV / | K44: TEV / | M44: # Subs | N44: ARPU | P44: Levered | Q44: Debt | R44: % Debt | S44: Preferred | T44: % Pref | U44: Equity | V44: % Equity | W44: Tax | X44: Unlevered
C45: ($M) | D45: Value ($M) | E45: Revenue ($M) | F45: Margin | G45: Margin | H45: Revenue | I45: Rev Growth | J45: Revenue | K45: EBITDA | M45: (M) | N45: ($) | P45: Beta | Q45: ($M) | S45: Stock ($M) | U45: Value ($M) | W45: Rate | X45: Beta
A46: América Móvil | B46: BMV:AMX B | C46: 76000 | D46: 121230 | E46: 45430 | F46: 0.434 | G46: 0.3973 | H46: 0.155 | I46: 0.07 | J46: =IF(OR(D46="",D46=0,E46="",E46=0),"NM",D46/E46) -> 2.668501 | K46: =IF(OR(G46<=0,E46=0,D46=0),"NM",IF(D46/(E46*G46)>100,"NM",D46/(E46*G46))) -> 6.7165895 | M46: 329 | N46: 11 | P46: 0.28 | Q46: 119500 | R46: =IFERROR(Q46/(Q46+S46+U46),"") -> 0.82698962 | S46: 0 | T46: =IFERROR(S46/(Q46+S46+U46),"") -> 0 | U46: 25000 | V46: =IFERROR(U46/(Q46+S46+U46),"") -> 0.17301038 | W46: 0.28 | X46: =IFERROR(P46/(1+(Q46/U46)*(1-W46)+S46/U46),"") -> 0.063040346
A47: China Mobile Limited | B47: SEHK:941 | C47: 224000 | D47: 186000 | E47: 144000 | F47: 0.284 | G47: 0.35 | H47: 0.16 | I47: 0.03 | J47: =IF(OR(D47="",D47=0,E47="",E47=0),"NM",D47/E47) -> 1.2916667 | K47: =IF(OR(G47<=0,E47=0,D47=0),"NM",IF(D47/(E47*G47)>100,"NM",D47/(E47*G47))) -> 3.6904762 | M47: 1009 | N47: 6.7 | P47: 0.23 | Q47: 0 | R47: =IFERROR(Q47/(Q47+S47+U47),"") -> 0 | S47: 0 | T47: =IFERROR(S47/(Q47+S47+U47),"") -> 0 | U47: 82000 | V47: =IFERROR(U47/(Q47+S47+U47),"") -> 1 | W47: 0.3 | X47: =IFERROR(P47/(1+(Q47/U47)*(1-W47)+S47/U47),"") -> 0.23
A48: T-Mobile US, Inc. | B48: NasdaqGS:TMUS | C48: 202950 | D48: 321560 | E48: 90530 | F48: 0.638 | G48: 0.38 | H48: 0.13 | I48: 0.1 | J48: =IF(OR(D48="",D48=0,E48="",E48=0),"NM",D48/E48) -> 3.5519717 | K48: =IF(OR(G48<=0,E48=0,D48=0),"NM",IF(D48/(E48*G48)>100,"NM",D48/(E48*G48))) -> 9.347294 | M48: 142.4 | N48: 48 | P48: 0.32 | Q48: 86000 | R48: =IFERROR(Q48/(Q48+S48+U48),"") -> 0.29122926 | S48: 0 | T48: =IFERROR(S48/(Q48+S48+U48),"") -> 0 | U48: 209300 | V48: =IFERROR(U48/(Q48+S48+U48),"") -> 0.70877074 | W48: 0.21 | X48: =IFERROR(P48/(1+(Q48/U48)*(1-W48)+S48/U48),"") -> 0.2415813
A49: China Unicom | B49: SHSE:600050 | C49: 80000 | D49: 110000 | E49: 43000 | F49: 0.55 | G49: 0.285 | H49: 0.22 | I49: 0.02 | J49: =IF(OR(D49="",D49=0,E49="",E49=0),"NM",D49/E49) -> 2.5581395 | K49: =IF(OR(G49<=0,E49=0,D49=0),"NM",IF(D49/(E49*G49)>100,"NM",D49/(E49*G49))) -> 8.9759282 | M49: 335 | N49: 5.5 | P49: 0.5 | Q49: 97310 | R49: =IFERROR(Q49/(Q49+S49+U49),"") -> 0.80950004 | S49: 0 | T49: =IFERROR(S49/(Q49+S49+U49),"") -> 0 | U49: 22900 | V49: =IFERROR(U49/(Q49+S49+U49),"") -> 0.19049996 | W49: 0.25 | X49: =IFERROR(P49/(1+(Q49/U49)*(1-W49)+S49/U49),"") -> 0.11941699
A50: Charter Communications | B50: NasdaqGS:CHTR | C50: 27710 | D50: 124500 | E50: 54636 | F50: 0.553 | G50: 0.4 | H50: 0.18 | I50: -0.01 | J50: =IF(OR(D50="",D50=0,E50="",E50=0),"NM",D50/E50) -> 2.2787173 | K50: =IF(OR(G50<=0,E50=0,D50=0),"NM",IF(D50/(E50*G50)>100,"NM",D50/(E50*G50))) -> 5.6967933 | M50: 32 | N50: 114 | P50: 1.05 | Q50: 97310 | R50: =IFERROR(Q50/(Q50+S50+U50),"") -> 0.80950004 | S50: 0 | T50: =IFERROR(S50/(Q50+S50+U50),"") -> 0 | U50: 22900 | V50: =IFERROR(U50/(Q50+S50+U50),"") -> 0.19049996 | W50: 0.21 | X50: =IFERROR(P50/(1+(Q50/U50)*(1-W50)+S50/U50),"") -> 0.24099247
A51: SoftBank Corp. | B51: TSE:9434 | C51: 28000 | D51: 63000 | E51: 49000 | F51: 0.44 | G51: 0.32 | H51: 0.15 | I51: 0.05 | J51: =IF(OR(D51="",D51=0,E51="",E51=0),"NM",D51/E51) -> 1.2857143 | K51: =IF(OR(G51<=0,E51=0,D51=0),"NM",IF(D51/(E51*G51)>100,"NM",D51/(E51*G51))) -> 4.0178571 | M51: 44 | N51: 41 | P51: 0.35 | Q51: 35000 | R51: =IFERROR(Q51/(Q51+S51+U51),"") -> 0.55555556 | S51: 0 | T51: =IFERROR(S51/(Q51+S51+U51),"") -> 0 | U51: 28000 | V51: =IFERROR(U51/(Q51+S51+U51),"") -> 0.44444444 | W51: 0.3 | X51: =IFERROR(P51/(1+(Q51/U51)*(1-W51)+S51/U51),"") -> 0.18666667
A52: Vodafone Group plc | B52: LSE:VOD | C52: 34460 | D52: 98000 | E52: 45500 | F52: 0.33 | G52: 0.35 | H52: 0.12 | I52: 0.03 | J52: =IF(OR(D52="",D52=0,E52="",E52=0),"NM",D52/E52) -> 2.1538462 | K52: =IF(OR(G52<=0,E52=0,D52=0),"NM",IF(D52/(E52*G52)>100,"NM",D52/(E52*G52))) -> 6.1538462 | M52: 270 | N52: 5 | P52: 0.34 | Q52: 63250 | R52: =IFERROR(Q52/(Q52+S52+U52),"") -> 0.64732371 | S52: 0 | T52: =IFERROR(S52/(Q52+S52+U52),"") -> 0 | U52: 34460 | V52: =IFERROR(U52/(Q52+S52+U52),"") -> 0.35267629 | W52: 0.19 | X52: =IFERROR(P52/(1+(Q52/U52)*(1-W52)+S52/U52),"") -> 0.13672608
A53: KDDI Corporation | B53: TSE:9433 | C53: 56000 | D53: 74000 | E53: 42000 | F53: 0.45 | G53: 0.33 | H53: 0.18 | I53: 0.04 | J53: =IF(OR(D53="",D53=0,E53="",E53=0),"NM",D53/E53) -> 1.7619048 | K53: =IF(OR(G53<=0,E53=0,D53=0),"NM",IF(D53/(E53*G53)>100,"NM",D53/(E53*G53))) -> 5.3391053 | M53: 55 | N53: 54 | P53: 0.4 | Q53: 18000 | R53: =IFERROR(Q53/(Q53+S53+U53),"") -> 0.24324324 | S53: 0 | T53: =IFERROR(S53/(Q53+S53+U53),"") -> 0 | U53: 56000 | V53: =IFERROR(U53/(Q53+S53+U53),"") -> 0.75675676 | W53: 0.3 | X53: =IFERROR(P53/(1+(Q53/U53)*(1-W53)+S53/U53),"") -> 0.32653061
A55: Min: | C55: =IFERROR(MIN(C46:C53),"") -> 27710 | D55: =IFERROR(MIN(D46:D53),"") -> 63000 | E55: =IFERROR(MIN(E46:E53),"") -> 42000 | F55: =MIN(F46:F53) -> 0.284 | G55: =IFERROR(MIN(G46:G53),"") -> 0.285 | H55: =IFERROR(MIN(H46:H53),"") -> 0.12 | I55: =IFERROR(MIN(I46:I53),"") -> -0.01 | J55: =IFERROR(_xlfn.AGGREGATE(5,5,J46:J53),"NM") -> 1.2857143 | K55: =IFERROR(MIN(K46:K53),"") -> 3.6904762 | M55: =IFERROR(IF(COUNTA(M46:M53)=0,"",MIN(M46:M53)),"") -> 32 | N55: =IFERROR(IF(COUNTA(N46:N53)=0,"",MIN(N46:N53)),"") -> 5 | P55: =IFERROR(MIN(P46:P53),"") -> 0.23 | Q55: =MIN(Q46:Q53) -> 0 | R55: =IFERROR(MIN(R46:R53),"") -> 0 | S55: =MIN(S46:S53) -> 0 | T55: =IFERROR(MIN(T46:T53),"") -> 0 | U55: =MIN(U46:U53) -> 22900 | V55: =IFERROR(MIN(V46:V53),"") -> 0.17301038 | W55: =IFERROR(MIN(W46:W53),"") -> 0.19 | X55: =IFERROR(MIN(X46:X53),"") -> 0.063040346
A56: 25th Pctl: | C56: =IFERROR(QUARTILE(C46:C53,1),"") -> 32845 | D56: =IFERROR(QUARTILE(D46:D53,1),"") -> 92000 | E56: =IFERROR(QUARTILE(E46:E53,1),"") -> 44822.5 | F56: =PERCENTILE(F46:F53,0.25) -> 0.408 | G56: =IFERROR(QUARTILE(G46:G53,1),"") -> 0.3275 | H56: =IFERROR(QUARTILE(H46:H53,1),"") -> 0.145 | I56: =IFERROR(QUARTILE(I46:I53,1),"") -> 0.0275 | J56: =IFERROR(PERCENTILE(J46:J53,0.25),"NM") -> 1.6443452 | K56: =IFERROR(QUARTILE(K46:K53,1),"") -> 5.0087933 | M56: =IFERROR(QUARTILE(M46:M53,1),"") -> 52.25 | N56: =IFERROR(QUARTILE(N46:N53,1),"") -> 6.4 | P56: =IFERROR(QUARTILE(P46:P53,1),"") -> 0.31 | Q56: =PERCENTILE(Q46:Q53,0.25) -> 30750 | R56: =IFERROR(QUARTILE(R46:R53,1),"") -> 0.27923275 | S56: =PERCENTILE(S46:S53,0.25) -> 0 | T56: =IFERROR(QUARTILE(T46:T53,1),"") -> 0 | U56: =PERCENTILE(U46:U53,0.25) -> 24475 | V56: =IFERROR(QUARTILE(V46:V53,1),"") -> 0.19049996 | W56: =IFERROR(QUARTILE(W46:W53,1),"") -> 0.21 | X56: =IFERROR(QUARTILE(X46:X53,1),"") -> 0.13239881
A57: Median: | C57: =IFERROR(MEDIAN(C46:C53),"") -> 66000 | D57: =IFERROR(MEDIAN(D46:D53),"") -> 115615 | E57: =IFERROR(MEDIAN(E46:E53),"") -> 47250 | F57: =MEDIAN(F46:F53) -> 0.445 | G57: =IFERROR(MEDIAN(G46:G53),"") -> 0.35 | H57: =IFERROR(MEDIAN(H46:H53),"") -> 0.1575 | I57: =IFERROR(MEDIAN(I46:I53),"") -> 0.035 | J57: =IFERROR(PERCENTILE(J46:J53,0.5),"NM") -> 2.2162817 | K57: =IFERROR(MEDIAN(K46:K53),"") -> 5.9253197 | M57: =IFERROR(MEDIAN(M46:M53),"") -> 206.2 | N57: =IFERROR(MEDIAN(N46:N53),"") -> 26 | P57: =IFERROR(MEDIAN(P46:P53),"") -> 0.345 | Q57: =MEDIAN(Q46:Q53) -> 74625 | R57: =IFERROR(MEDIAN(R46:R53),"") -> 0.60143963 | S57: =MEDIAN(S46:S53) -> 0 | T57: =IFERROR(MEDIAN(T46:T53),"") -> 0 | U57: =MEDIAN(U46:U53) -> 31230 | V57: =IFERROR(MEDIAN(V46:V53),"") -> 0.39856037 | W57: =IFERROR(MEDIAN(W46:W53),"") -> 0.265 | X57: =IFERROR(MEDIAN(X46:X53),"") -> 0.20833333
A58: Mean: | C58: =IFERROR(AVERAGE(C46:C53),"") -> 91140 | D58: =IFERROR(AVERAGE(D46:D53),"") -> 137286.25 | E58: =IFERROR(AVERAGE(E46:E53),"") -> 64262 | F58: =AVERAGE(F46:F53) -> 0.459875 | G58: =IFERROR(AVERAGE(G46:G53),"") -> 0.3515375 | H58: =IFERROR(AVERAGE(H46:H53),"") -> 0.161875 | I58: =IFERROR(AVERAGE(I46:I53),"") -> 0.04125 | J58: =IFERROR(_xlfn.AGGREGATE(1,5,J46:J53),"NM") -> 2.1938077 | K58: =IFERROR(AVERAGE(K46:K53),"") -> 6.2422362 | M58: =IFERROR(AVERAGE(M46:M53),"") -> 277.05 | N58: =IFERROR(AVERAGE(N46:N53),"") -> 35.65 | P58: =IFERROR(AVERAGE(P46:P53),"") -> 0.43375 | Q58: =AVERAGE(Q46:Q53) -> 64546.25 | R58: =IFERROR(AVERAGE(R46:R53),"") -> 0.52291768 | S58: =AVERAGE(S46:S53) -> 0 | T58: =IFERROR(AVERAGE(T46:T53),"") -> 0 | U58: =AVERAGE(U46:U53) -> 60070 | V58: =IFERROR(AVERAGE(V46:V53),"") -> 0.47708232 | W58: =IFERROR(AVERAGE(W46:W53),"") -> 0.255 | X58: =IFERROR(AVERAGE(X46:X53),"") -> 0.19311931
A59: 75th Pctl: | C59: =IFERROR(QUARTILE(C46:C53,3),"") -> 110737.5 | D59: =IFERROR(QUARTILE(D46:D53,3),"") -> 139875 | E59: =IFERROR(QUARTILE(E46:E53,3),"") -> 63609.5 | F59: =PERCENTILE(F46:F53,0.75) -> 0.55075 | G59: =IFERROR(QUARTILE(G46:G53,3),"") -> 0.384325 | H59: =IFERROR(QUARTILE(H46:H53,3),"") -> 0.18 | I59: =IFERROR(QUARTILE(I46:I53,3),"") -> 0.055 | J59: =IFERROR(PERCENTILE(J46:J53,0.75),"NM") -> 2.5857299 | K59: =IFERROR(QUARTILE(K46:K53,3),"") -> 7.2814241 | M59: =IFERROR(QUARTILE(M46:M53,3),"") -> 330.5 | N59: =IFERROR(QUARTILE(N46:N53,3),"") -> 49.5 | P59: =IFERROR(QUARTILE(P46:P53,3),"") -> 0.425 | Q59: =PERCENTILE(Q46:Q53,0.75) -> 97310 | R59: =IFERROR(QUARTILE(R46:R53,3),"") -> 0.80950004 | S59: =PERCENTILE(S46:S53,0.75) -> 0 | T59: =IFERROR(QUARTILE(T46:T53,3),"") -> 0 | U59: =PERCENTILE(U46:U53,0.75) -> 62500 | V59: =IFERROR(QUARTILE(V46:V53,3),"") -> 0.72076725 | W59: =IFERROR(QUARTILE(W46:W53,3),"") -> 0.3 | X59: =IFERROR(QUARTILE(X46:X53,3),"") -> 0.24113968
A60: Max: | C60: =IFERROR(MAX(C46:C53),"") -> 224000 | D60: =IFERROR(MAX(D46:D53),"") -> 321560 | E60: =IFERROR(MAX(E46:E53),"") -> 144000 | F60: =MAX(F46:F53) -> 0.638 | G60: =IFERROR(MAX(G46:G53),"") -> 0.4 | H60: =IFERROR(MAX(H46:H53),"") -> 0.22 | I60: =IFERROR(MAX(I46:I53),"") -> 0.1 | J60: =IFERROR(_xlfn.AGGREGATE(4,5,J46:J53),"NM") -> 3.5519717 | K60: =IFERROR(MAX(K46:K53),"") -> 9.347294 | M60: =IFERROR(IF(COUNTA(M46:M53)=0,"",MAX(M46:M53)),"") -> 1009 | N60: =IFERROR(IF(COUNTA(N46:N53)=0,"",MAX(N46:N53)),"") -> 114 | P60: =IFERROR(MAX(P46:P53),"") -> 1.05 | Q60: =MAX(Q46:Q53) -> 119500 | R60: =IFERROR(MAX(R46:R53),"") -> 0.82698962 | S60: =MAX(S46:S53) -> 0 | T60: =IFERROR(MAX(T46:T53),"") -> 0 | U60: =MAX(U46:U53) -> 209300 | V60: =IFERROR(MAX(V46:V53),"") -> 1 | W60: =IFERROR(MAX(W46:W53),"") -> 0.3 | X60: =IFERROR(MAX(X46:X53),"") -> 0.32653061

Sheet Space Comps
A1: SpaceX — Space Comparable Companies
A2: Comparable Public Companies by Maturity & Industry | Launch Services + Defense / Aerospace | $ in Millions
A3: Current-stage anchor = Launch Services / NewSpace • Mature-stage anchor = Big-5 Defense Primes. Input cells (blue) to be populated from terminal (CapIQ/Bloomberg).
A5: TIER 1 — SMALLER-SCALE ROCKET / SPACE TECH (Current-Stage Anchor)
A6: Name | B6: Ticker | C6: Mkt Cap | D6: Enterprise | E6: LTM | F6: Gross | G6: EBITDA | H6: Capex % | I6: 3-Yr Ann. | J6: TEV / | K6: TEV / | M6: Backlog | N6: Backlog / | P6: Levered | Q6: Debt | R6: % Debt | S6: Preferred | T6: % Pref | U6: Equity | V6: % Equity | W6: Tax | X6: Unlevered
C7: ($M) | D7: Value ($M) | E7: Revenue ($M) | F7: Margin | G7: Margin | H7: Revenue | I7: Rev Growth | J7: Revenue | K7: EBITDA | M7: ($M) | N7: Rev (x) | P7: Beta | Q7: ($M) | S7: Stock ($M) | U7: Value ($M) | W7: Rate | X7: Beta
A8: Rocket Lab Corporation | B8: NasdaqGS:RKLB | C8: 74950 | D8: 73700 | E8: 602 | F8: 0.317 | G8: -0.15 | H8: 0.256 | I8: 0.38 | J8: =IFERROR(D8/E8,"NM") -> 122.42525 | K8: =IF(OR(G8<=0,E8=0,D8=0),"NM",IF(D8/(E8*G8)>100,"NM",D8/(E8*G8))) -> NM | M8: 2200 | N8: =IFERROR(M8/E8,"NM") -> 3.654485 | P8: 2.31 | Q8: 139 | R8: =IFERROR(Q8/(Q8+S8+U8),"") -> 0.0021766705 | S8: 0 | T8: =IFERROR(S8/(Q8+S8+U8),"") -> 0 | U8: 63720 | V8: =IFERROR(U8/(Q8+S8+U8),"") -> 0.99782333 | W8: 0.21 | X8: =IFERROR(P8/(1+(Q8/U8)*(1-W8)+S8/U8),"") -> 2.306026
A9: AeroVironment, Inc. | B9: NasdaqGS:AVAV | C9: 9410 | D9: 9650 | E9: 821 | F9: 0.25 | G9: 0.1 | H9: 0.034 | I9: 0.3 | J9: =IFERROR(D9/E9,"NM") -> 11.753959 | K9: =IF(OR(G9<=0,E9=0,D9=0),"NM",IF(D9/(E9*G9)>100,"NM",D9/(E9*G9))) -> NM | M9: 1100 | N9: =IFERROR(M9/E9,"NM") -> 1.3398295 | P9: 1.4 | Q9: 826 | R9: =IFERROR(Q9/(Q9+S9+U9),"") -> 0.080695584 | S9: 0 | T9: =IFERROR(S9/(Q9+S9+U9),"") -> 0 | U9: 9410 | V9: =IFERROR(U9/(Q9+S9+U9),"") -> 0.91930442 | W9: 0.21 | X9: =IFERROR(P9/(1+(Q9/U9)*(1-W9)+S9/U9),"") -> 1.3092122
A10: Kratos Defense & Security | B10: NasdaqGS:KTOS | C10: 10970 | D10: 10860 | E10: 1350 | F10: 0.28 | G10: 0.08 | H10: 0.04 | I10: 0.19 | J10: =IFERROR(D10/E10,"NM") -> 8.0444444 | K10: =IF(OR(G10<=0,E10=0,D10=0),"NM",IF(D10/(E10*G10)>100,"NM",D10/(E10*G10))) -> NM | M10: 2000 | N10: =IFERROR(M10/E10,"NM") -> 1.4814815 | P10: 1.15 | Q10: 280 | R10: =IFERROR(Q10/(Q10+S10+U10),"") -> 0.024888889 | S10: 0 | T10: =IFERROR(S10/(Q10+S10+U10),"") -> 0 | U10: 10970 | V10: =IFERROR(U10/(Q10+S10+U10),"") -> 0.97511111 | W10: 0.21 | X10: =IFERROR(P10/(1+(Q10/U10)*(1-W10)+S10/U10),"") -> 1.1272696
A11: Redwire Corporation | B11: NYSE:RDW | C11: 4000 | D11: 4080 | E11: 469 | F11: 0.092 | G11: -0.1 | H11: 0.062 | I11: 0.41 | J11: =IFERROR(D11/E11,"NM") -> 8.6993603 | K11: =IF(OR(G11<=0,E11=0,D11=0),"NM",IF(D11/(E11*G11)>100,"NM",D11/(E11*G11))) -> NM | M11: 498 | N11: =IFERROR(M11/E11,"NM") -> 1.0618337 | P11: 2.5 | Q11: 80 | R11: =IFERROR(Q11/(Q11+S11+U11),"") -> 0.019607843 | S11: 0 | T11: =IFERROR(S11/(Q11+S11+U11),"") -> 0 | U11: 4000 | V11: =IFERROR(U11/(Q11+S11+U11),"") -> 0.98039216 | W11: 0.21 | X11: =IFERROR(P11/(1+(Q11/U11)*(1-W11)+S11/U11),"") -> 2.4611144
A12: MDA Space Ltd. | B12: TSX:MDA | C12: 5390 | D12: 5230 | E12: 1250 | F12: 0.287 | G12: 0.18 | H12: 0.163 | I12: 0.3 | J12: =IFERROR(D12/E12,"NM") -> 4.184 | K12: =IF(OR(G12<=0,E12=0,D12=0),"NM",IF(D12/(E12*G12)>100,"NM",D12/(E12*G12))) -> 23.244444 | M12: 1500 | N12: =IFERROR(M12/E12,"NM") -> 1.2 | P12: 0.12 | Q12: 273 | R12: =IFERROR(Q12/(Q12+S12+U12),"") -> 0.048207664 | S12: 0 | T12: =IFERROR(S12/(Q12+S12+U12),"") -> 0 | U12: 5390 | V12: =IFERROR(U12/(Q12+S12+U12),"") -> 0.95179234 | W12: 0.265 | X12: =IFERROR(P12/(1+(Q12/U12)*(1-W12)+S12/U12),"") -> 0.11569306
A13: York Space Systems | B13: NYSE:YSS | C13: 3950 | D13: 4150 | E13: 420 | F13: 0.19 | G13: -0.1 | H13: 0.05 | I13: 0.48 | J13: =IFERROR(D13/E13,"NM") -> 9.8809524 | K13: =IF(OR(G13<=0,E13=0,D13=0),"NM",IF(D13/(E13*G13)>100,"NM",D13/(E13*G13))) -> NM | M13: 450 | N13: =IFERROR(M13/E13,"NM") -> 1.0714286 | P13: 2 | Q13: 200 | R13: =IFERROR(Q13/(Q13+S13+U13),"") -> 0.048192771 | S13: 0 | T13: =IFERROR(S13/(Q13+S13+U13),"") -> 0 | U13: 3950 | V13: =IFERROR(U13/(Q13+S13+U13),"") -> 0.95180723 | W13: 0.21 | X13: =IFERROR(P13/(1+(Q13/U13)*(1-W13)+S13/U13),"") -> 1.9230769
A14: Intuitive Machines | B14: NasdaqGM:LUNR | C14: 2500 | D14: 2300 | E14: 230 | F14: 0.18 | G14: -0.2 | H14: 0.5 | I14: 0.5 | J14: =IFERROR(D14/E14,"NM") -> 10 | K14: =IF(OR(G14<=0,E14=0,D14=0),"NM",IF(D14/(E14*G14)>100,"NM",D14/(E14*G14))) -> NM | M14: 1100 | N14: =IFERROR(M14/E14,"NM") -> 4.7826087 | P14: 1.47 | Q14: 336 | R14: =IFERROR(Q14/(Q14+S14+U14),"") -> 0.061617458 | S14: 7 | T14: =IFERROR(S14/(Q14+S14+U14),"") -> 0.001283697 | U14: 5110 | V14: =IFERROR(U14/(Q14+S14+U14),"") -> 0.93709884 | W14: 0.21 | X14: =IFERROR(P14/(1+(Q14/U14)*(1-W14)+S14/U14),"") -> 1.3955938
A15: Firefly Aerospace Inc. | B15: NasdaqGM:FLY | C15: 6000 | D15: 5500 | E15: 185 | F15: 0.248 | G15: -0.3 | H15: 0.25 | I15: 0.55 | J15: =IFERROR(D15/E15,"NM") -> 29.72973 | K15: =IF(OR(G15<=0,E15=0,D15=0),"NM",IF(D15/(E15*G15)>100,"NM",D15/(E15*G15))) -> NM | M15: 1300 | N15: =IFERROR(M15/E15,"NM") -> 7.027027 | P15: 3 | Q15: 53 | R15: =IFERROR(Q15/(Q15+S15+U15),"") -> 0.0087559888 | S15: 0 | T15: =IFERROR(S15/(Q15+S15+U15),"") -> 0 | U15: 6000 | V15: =IFERROR(U15/(Q15+S15+U15),"") -> 0.99124401 | W15: 0.21 | X15: =IFERROR(P15/(1+(Q15/U15)*(1-W15)+S15/U15),"") -> 2.9792101
A16: Voyager Technologies | B16: NYSE:VOYG | C16: 2800 | D16: 2850 | E16: 166 | F16: 0.179 | G16: -0.25 | H16: 0.366 | I16: 0.4 | J16: =IFERROR(D16/E16,"NM") -> 17.168675 | K16: =IF(OR(G16<=0,E16=0,D16=0),"NM",IF(D16/(E16*G16)>100,"NM",D16/(E16*G16))) -> NM | M16: 275 | N16: =IFERROR(M16/E16,"NM") -> 1.6566265 | P16: 2.5 | Q16: 50 | R16: =IFERROR(Q16/(Q16+S16+U16),"") -> 0.01754386 | S16: 0 | T16: =IFERROR(S16/(Q16+S16+U16),"") -> 0 | U16: 2800 | V16: =IFERROR(U16/(Q16+S16+U16),"") -> 0.98245614 | W16: 0.21 | X16: =IFERROR(P16/(1+(Q16/U16)*(1-W16)+S16/U16),"") -> 2.4652228
A18: Min: | C18: =IFERROR(MIN(C8:C16),"") -> 2500 | D18: =IFERROR(MIN(D8:D16),"") -> 2300 | E18: =IFERROR(MIN(E8:E16),"") -> 166 | F18: =IFERROR(MIN(F8:F16),"") -> 0.092 | G18: =IFERROR(MIN(G8:G16),"") -> -0.3 | H18: =IFERROR(MIN(H8:H16),"") -> 0.034 | I18: =IFERROR(MIN(I8:I16),"") -> 0.19 | J18: =IFERROR(MIN(J8:J16),"") -> 4.184 | K18: =IFERROR(_xlfn.AGGREGATE(15,6,K8:K16,1),"NM") -> 23.244444 | M18: =IFERROR(MIN(M8:M16),"") -> 275 | N18: =IFERROR(MIN(N8:N16),"") -> 1.0618337 | P18: =IFERROR(MIN(P8:P16),"") -> 0.12 | Q18: =IFERROR(MIN(Q8:Q16),"") -> 50 | R18: =IFERROR(MIN(R8:R16),"") -> 0.0021766705 | S18: =IFERROR(MIN(S8:S16),"") -> 0 | T18: =IFERROR(MIN(T8:T16),"") -> 0 | U18: =IFERROR(MIN(U8:U16),"") -> 2800 | V18: =IFERROR(MIN(V8:V16),"") -> 0.91930442 | W18: =IFERROR(MIN(W8:W16),"") -> 0.21 | X18: =IFERROR(MIN(X8:X16),"") -> 0.11569306
A19: 25th Pctl: | C19: =IFERROR(QUARTILE(C8:C16,1),"") -> 3950 | D19: =IFERROR(QUARTILE(D8:D16,1),"") -> 4080 | E19: =IFERROR(QUARTILE(E8:E16,1),"") -> 230 | F19: =IFERROR(QUARTILE(F8:F16,1),"") -> 0.18 | G19: =IFERROR(QUARTILE(G8:G16,1),"") -> -0.2 | H19: =IFERROR(QUARTILE(H8:H16,1),"") -> 0.05 | I19: =IFERROR(QUARTILE(I8:I16,1),"") -> 0.3 | J19: =IFERROR(QUARTILE(J8:J16,1),"") -> 8.6993603 | K19: =IFERROR(_xlfn.AGGREGATE(16,6,K8:K16,0.25),"NM") -> 23.244444 | M19: =IFERROR(QUARTILE(M8:M16,1),"") -> 498 | N19: =IFERROR(QUARTILE(N8:N16,1),"") -> 1.2 | P19: =IFERROR(QUARTILE(P8:P16,1),"") -> 1.4 | Q19: =IFERROR(QUARTILE(Q8:Q16,1),"") -> 80 | R19: =IFERROR(QUARTILE(R8:R16,1),"") -> 0.01754386 | S19: =IFERROR(QUARTILE(S8:S16,1),"") -> 0 | T19: =IFERROR(QUARTILE(T8:T16,1),"") -> 0 | U19: =IFERROR(QUARTILE(U8:U16,1),"") -> 4000 | V19: =IFERROR(QUARTILE(V8:V16,1),"") -> 0.95179234 | W19: =IFERROR(QUARTILE(W8:W16,1),"") -> 0.21 | X19: =IFERROR(QUARTILE(X8:X16,1),"") -> 1.3092122
A20: Median: | C20: =IFERROR(MEDIAN(C8:C16),"") -> 5390 | D20: =IFERROR(MEDIAN(D8:D16),"") -> 5230 | E20: =IFERROR(MEDIAN(E8:E16),"") -> 469 | F20: =IFERROR(MEDIAN(F8:F16),"") -> 0.248 | G20: =IFERROR(MEDIAN(G8:G16),"") -> -0.1 | H20: =IFERROR(MEDIAN(H8:H16),"") -> 0.163 | I20: =IFERROR(MEDIAN(I8:I16),"") -> 0.4 | J20: =IFERROR(MEDIAN(J8:J16),"") -> 10 | K20: =IFERROR(_xlfn.AGGREGATE(16,6,K8:K16,0.5),"NM") -> 23.244444 | M20: =IFERROR(MEDIAN(M8:M16),"") -> 1100 | N20: =IFERROR(MEDIAN(N8:N16),"") -> 1.4814815 | P20: =IFERROR(MEDIAN(P8:P16),"") -> 2 | Q20: =IFERROR(MEDIAN(Q8:Q16),"") -> 200 | R20: =IFERROR(MEDIAN(R8:R16),"") -> 0.024888889 | S20: =IFERROR(MEDIAN(S8:S16),"") -> 0 | T20: =IFERROR(MEDIAN(T8:T16),"") -> 0 | U20: =IFERROR(MEDIAN(U8:U16),"") -> 5390 | V20: =IFERROR(MEDIAN(V8:V16),"") -> 0.97511111 | W20: =IFERROR(MEDIAN(W8:W16),"") -> 0.21 | X20: =IFERROR(MEDIAN(X8:X16),"") -> 1.9230769
A21: Mean: | C21: =IFERROR(AVERAGE(C8:C16),"") -> 13330 | D21: =IFERROR(AVERAGE(D8:D16),"") -> 13146.667 | E21: =IFERROR(AVERAGE(E8:E16),"") -> 610.33333 | F21: =IFERROR(AVERAGE(F8:F16),"") -> 0.22477778 | G21: =IFERROR(AVERAGE(G8:G16),"") -> -0.082222222 | H21: =IFERROR(AVERAGE(H8:H16),"") -> 0.19122222 | I21: =IFERROR(AVERAGE(I8:I16),"") -> 0.39 | J21: =IFERROR(AVERAGE(J8:J16),"") -> 24.654041 | K21: =IFERROR(_xlfn.AGGREGATE(1,6,K8:K16),"NM") -> 23.244444 | M21: =IFERROR(AVERAGE(M8:M16),"") -> 1158.1111 | N21: =IFERROR(AVERAGE(N8:N16),"") -> 2.5861467 | P21: =IFERROR(AVERAGE(P8:P16),"") -> 1.8277778 | Q21: =IFERROR(AVERAGE(Q8:Q16),"") -> 248.55556 | R21: =IFERROR(AVERAGE(R8:R16),"") -> 0.034631859 | S21: =IFERROR(AVERAGE(S8:S16),"") -> 0.77777778 | T21: =IFERROR(AVERAGE(T8:T16),"") -> 0.00014263301 | U21: =IFERROR(AVERAGE(U8:U16),"") -> 12372.222 | V21: =IFERROR(AVERAGE(V8:V16),"") -> 0.96522551 | W21: =IFERROR(AVERAGE(W8:W16),"") -> 0.21611111 | X21: =IFERROR(AVERAGE(X8:X16),"") -> 1.7869354
A22: 75th Pctl: | C22: =IFERROR(QUARTILE(C8:C16,3),"") -> 9410 | D22: =IFERROR(QUARTILE(D8:D16,3),"") -> 9650 | E22: =IFERROR(QUARTILE(E8:E16,3),"") -> 821 | F22: =IFERROR(QUARTILE(F8:F16,3),"") -> 0.28 | G22: =IFERROR(QUARTILE(G8:G16,3),"") -> 0.08 | H22: =IFERROR(QUARTILE(H8:H16,3),"") -> 0.256 | I22: =IFERROR(QUARTILE(I8:I16,3),"") -> 0.48 | J22: =IFERROR(QUARTILE(J8:J16,3),"") -> 17.168675 | K22: =IFERROR(_xlfn.AGGREGATE(16,6,K8:K16,0.75),"NM") -> 23.244444 | M22: =IFERROR(QUARTILE(M8:M16,3),"") -> 1500 | N22: =IFERROR(QUARTILE(N8:N16,3),"") -> 3.654485 | P22: =IFERROR(QUARTILE(P8:P16,3),"") -> 2.5 | Q22: =IFERROR(QUARTILE(Q8:Q16,3),"") -> 280 | R22: =IFERROR(QUARTILE(R8:R16,3),"") -> 0.048207664 | S22: =IFERROR(QUARTILE(S8:S16,3),"") -> 0 | T22: =IFERROR(QUARTILE(T8:T16,3),"") -> 0 | U22: =IFERROR(QUARTILE(U8:U16,3),"") -> 9410 | V22: =IFERROR(QUARTILE(V8:V16,3),"") -> 0.98245614 | W22: =IFERROR(QUARTILE(W8:W16,3),"") -> 0.21 | X22: =IFERROR(QUARTILE(X8:X16,3),"") -> 2.4611144
A23: Max: | C23: =IFERROR(MAX(C8:C16),"") -> 74950 | D23: =IFERROR(MAX(D8:D16),"") -> 73700 | E23: =IFERROR(MAX(E8:E16),"") -> 1350 | F23: =IFERROR(MAX(F8:F16),"") -> 0.317 | G23: =IFERROR(MAX(G8:G16),"") -> 0.18 | H23: =IFERROR(MAX(H8:H16),"") -> 0.5 | I23: =IFERROR(MAX(I8:I16),"") -> 0.55 | J23: =IFERROR(MAX(J8:J16),"") -> 122.42525 | K23: =IFERROR(_xlfn.AGGREGATE(14,6,K8:K16,1),"NM") -> 23.244444 | M23: =IFERROR(MAX(M8:M16),"") -> 2200 | N23: =IFERROR(MAX(N8:N16),"") -> 7.027027 | P23: =IFERROR(MAX(P8:P16),"") -> 3 | Q23: =IFERROR(MAX(Q8:Q16),"") -> 826 | R23: =IFERROR(MAX(R8:R16),"") -> 0.080695584 | S23: =IFERROR(MAX(S8:S16),"") -> 7 | T23: =IFERROR(MAX(T8:T16),"") -> 0.001283697 | U23: =IFERROR(MAX(U8:U16),"") -> 63720 | V23: =IFERROR(MAX(V8:V16),"") -> 0.99782333 | W23: =IFERROR(MAX(W8:W16),"") -> 0.265 | X23: =IFERROR(MAX(X8:X16),"") -> 2.9792101
A26: TIER 2 — "BIG 5" U.S. DEFENSE CONTRACTORS (Mature-Stage Anchor)
A27: Name | B27: Ticker | C27: Mkt Cap | D27: Enterprise | E27: LTM | F27: Gross | G27: EBITDA | H27: Capex % | I27: 3-Yr Ann. | J27: TEV / | K27: TEV / | M27: Backlog | N27: Backlog / | P27: Levered | Q27: Debt | R27: % Debt | S27: Preferred | T27: % Pref | U27: Equity | V27: % Equity | W27: Tax | X27: Unlevered
C28: ($M) | D28: Value ($M) | E28: Revenue ($M) | F28: Margin | G28: Margin | H28: Revenue | I28: Rev Growth | J28: Revenue | K28: EBITDA | M28: ($M) | N28: Rev (x) | P28: Beta | Q28: ($M) | S28: Stock ($M) | U28: Value ($M) | W28: Rate | X28: Beta
A29: The Boeing Company | B29: NYSE:BA | C29: 170000 | D29: 196150 | E29: 92184 | F29: 0.048 | G29: 0.045 | H29: 0.017 | I29: 0.11 | J29: =IFERROR(D29/E29,"NM") -> 2.1278096 | K29: =IF(OR(G29<=0,E29=0,D29=0),"NM",IF(D29/(E29*G29)>100,"NM",D29/(E29*G29))) -> 47.284658 | M29: 516000 | N29: =IFERROR(M29/E29,"NM") -> 5.5975007 | P29: 1.21 | Q29: 44354 | R29: =IFERROR(Q29/(Q29+S29+U29),"") -> 0.20113004 | S29: 5750 | T29: =IFERROR(S29/(Q29+S29+U29),"") -> 0.026074259 | U29: 170420 | V29: =IFERROR(U29/(Q29+S29+U29),"") -> 0.7727957 | W29: 0.21 | X29: =IFERROR(P29/(1+(Q29/U29)*(1-W29)+S29/U29),"") -> 0.97631993
A30: RTX Corporation | B30: NYSE:RTX | C30: 238380 | D30: 247000 | E30: 90373 | F30: 0.202 | G30: 0.145 | H30: 0.029 | I30: 0.1 | J30: =IFERROR(D30/E30,"NM") -> 2.7331172 | K30: =IF(OR(G30<=0,E30=0,D30=0),"NM",IF(D30/(E30*G30)>100,"NM",D30/(E30*G30))) -> 18.849084 | M30: 217000 | N30: =IFERROR(M30/E30,"NM") -> 2.4011596 | P30: 0.3 | Q30: 38940 | R30: =IFERROR(Q30/(Q30+S30+U30),"") -> 0.13748544 | S30: 0 | T30: =IFERROR(S30/(Q30+S30+U30),"") -> 0 | U30: 244290 | V30: =IFERROR(U30/(Q30+S30+U30),"") -> 0.86251456 | W30: 0.21 | X30: =IFERROR(P30/(1+(Q30/U30)*(1-W30)+S30/U30),"") -> 0.26644722
A31: Lockheed Martin | B31: NYSE:LMT | C31: 121000 | D31: 141700 | E31: 72000 | F31: 0.11 | G31: 0.13 | H31: 0.016 | I31: 0.04 | J31: =IFERROR(D31/E31,"NM") -> 1.9680556 | K31: =IF(OR(G31<=0,E31=0,D31=0),"NM",IF(D31/(E31*G31)>100,"NM",D31/(E31*G31))) -> 15.138889 | M31: 160000 | N31: =IFERROR(M31/E31,"NM") -> 2.2222222 | P31: 0.2 | Q31: 20530 | R31: =IFERROR(Q31/(Q31+S31+U31),"") -> 0.14530398 | S31: 0 | T31: =IFERROR(S31/(Q31+S31+U31),"") -> 0 | U31: 120760 | V31: =IFERROR(U31/(Q31+S31+U31),"") -> 0.85469602 | W31: 0.21 | X31: =IFERROR(P31/(1+(Q31/U31)*(1-W31)+S31/U31),"") -> 0.17631938
A32: General Dynamics | B32: NYSE:GD | C32: 92350 | D32: 99000 | E32: 53810 | F32: 0.152 | G32: 0.13 | H32: 0.013 | I32: 0.1 | J32: =IFERROR(D32/E32,"NM") -> 1.8398067 | K32: =IF(OR(G32<=0,E32=0,D32=0),"NM",IF(D32/(E32*G32)>100,"NM",D32/(E32*G32))) -> 14.152359 | M32: 100000 | N32: =IFERROR(M32/E32,"NM") -> 1.8583906 | P32: 0.5 | Q32: 12800 | R32: =IFERROR(Q32/(Q32+S32+U32),"") -> 0.12019908 | S32: 0 | T32: =IFERROR(S32/(Q32+S32+U32),"") -> 0 | U32: 93690 | V32: =IFERROR(U32/(Q32+S32+U32),"") -> 0.87980092 | W32: 0.21 | X32: =IFERROR(P32/(1+(Q32/U32)*(1-W32)+S32/U32),"") -> 0.45129188
A33: Northrop Grumman | B33: NYSE:NOC | C33: 79800 | D33: 94000 | E33: 42000 | F33: 0.2 | G33: 0.16 | H33: 0.016 | I33: 0.03 | J33: =IFERROR(D33/E33,"NM") -> 2.2380952 | K33: =IF(OR(G33<=0,E33=0,D33=0),"NM",IF(D33/(E33*G33)>100,"NM",D33/(E33*G33))) -> 13.988095 | M33: 90000 | N33: =IFERROR(M33/E33,"NM") -> 2.1428571 | P33: 0.05 | Q33: 14600 | R33: =IFERROR(Q33/(Q33+S33+U33),"") -> 0.15883377 | S33: 0 | T33: =IFERROR(S33/(Q33+S33+U33),"") -> 0 | U33: 77320 | V33: =IFERROR(U33/(Q33+S33+U33),"") -> 0.84116623 | W33: 0.21 | X33: =IFERROR(P33/(1+(Q33/U33)*(1-W33)+S33/U33),"") -> 0.043509578
A35: Min: | C35: =IFERROR(MIN(C29:C33),"") -> 79800 | D35: =IFERROR(MIN(D29:D33),"") -> 94000 | E35: =IFERROR(MIN(E29:E33),"") -> 42000 | F35: =IFERROR(MIN(F29:F33),"") -> 0.048 | G35: =IFERROR(MIN(G29:G33),"") -> 0.045 | H35: =IFERROR(MIN(H29:H33),"") -> 0.013 | I35: =IFERROR(MIN(I29:I33),"") -> 0.03 | J35: =IFERROR(MIN(J29:J33),"") -> 1.8398067 | K35: =IFERROR(MIN(K29:K33),"") -> 13.988095 | M35: =IFERROR(MIN(M29:M33),"") -> 90000 | N35: =IFERROR(MIN(N29:N33),"") -> 1.8583906 | P35: =IFERROR(MIN(P29:P33),"") -> 0.05 | Q35: =IFERROR(MIN(Q29:Q33),"") -> 12800 | R35: =IFERROR(MIN(R29:R33),"") -> 0.12019908 | S35: =IFERROR(MIN(S29:S33),"") -> 0 | T35: =IFERROR(MIN(T29:T33),"") -> 0 | U35: =IFERROR(MIN(U29:U33),"") -> 77320 | V35: =IFERROR(MIN(V29:V33),"") -> 0.7727957 | W35: =IFERROR(MIN(W29:W33),"") -> 0.21 | X35: =IFERROR(MIN(X29:X33),"") -> 0.043509578
A36: 25th Pctl: | C36: =IFERROR(QUARTILE(C29:C33,1),"") -> 92350 | D36: =IFERROR(QUARTILE(D29:D33,1),"") -> 99000 | E36: =IFERROR(QUARTILE(E29:E33,1),"") -> 53810 | F36: =IFERROR(QUARTILE(F29:F33,1),"") -> 0.11 | G36: =IFERROR(QUARTILE(G29:G33,1),"") -> 0.13 | H36: =IFERROR(QUARTILE(H29:H33,1),"") -> 0.016 | I36: =IFERROR(QUARTILE(I29:I33,1),"") -> 0.04 | J36: =IFERROR(QUARTILE(J29:J33,1),"") -> 1.9680556 | K36: =IFERROR(QUARTILE(K29:K33,1),"") -> 14.152359 | M36: =IFERROR(QUARTILE(M29:M33,1),"") -> 100000 | N36: =IFERROR(QUARTILE(N29:N33,1),"") -> 2.1428571 | P36: =IFERROR(QUARTILE(P29:P33,1),"") -> 0.2 | Q36: =IFERROR(QUARTILE(Q29:Q33,1),"") -> 14600 | R36: =IFERROR(QUARTILE(R29:R33,1),"") -> 0.13748544 | S36: =IFERROR(QUARTILE(S29:S33,1),"") -> 0 | T36: =IFERROR(QUARTILE(T29:T33,1),"") -> 0 | U36: =IFERROR(QUARTILE(U29:U33,1),"") -> 93690 | V36: =IFERROR(QUARTILE(V29:V33,1),"") -> 0.84116623 | W36: =IFERROR(QUARTILE(W29:W33,1),"") -> 0.21 | X36: =IFERROR(QUARTILE(X29:X33,1),"") -> 0.17631938
A37: Median: | C37: =IFERROR(MEDIAN(C29:C33),"") -> 121000 | D37: =IFERROR(MEDIAN(D29:D33),"") -> 141700 | E37: =IFERROR(MEDIAN(E29:E33),"") -> 72000 | F37: =IFERROR(MEDIAN(F29:F33),"") -> 0.152 | G37: =IFERROR(MEDIAN(G29:G33),"") -> 0.13 | H37: =IFERROR(MEDIAN(H29:H33),"") -> 0.016 | I37: =IFERROR(MEDIAN(I29:I33),"") -> 0.1 | J37: =IFERROR(MEDIAN(J29:J33),"") -> 2.1278096 | K37: =IFERROR(MEDIAN(K29:K33),"") -> 15.138889 | M37: =IFERROR(MEDIAN(M29:M33),"") -> 160000 | N37: =IFERROR(MEDIAN(N29:N33),"") -> 2.2222222 | P37: =IFERROR(MEDIAN(P29:P33),"") -> 0.3 | Q37: =IFERROR(MEDIAN(Q29:Q33),"") -> 20530 | R37: =IFERROR(MEDIAN(R29:R33),"") -> 0.14530398 | S37: =IFERROR(MEDIAN(S29:S33),"") -> 0 | T37: =IFERROR(MEDIAN(T29:T33),"") -> 0 | U37: =IFERROR(MEDIAN(U29:U33),"") -> 120760 | V37: =IFERROR(MEDIAN(V29:V33),"") -> 0.85469602 | W37: =IFERROR(MEDIAN(W29:W33),"") -> 0.21 | X37: =IFERROR(MEDIAN(X29:X33),"") -> 0.26644722
A38: Mean: | C38: =IFERROR(AVERAGE(C29:C33),"") -> 140306 | D38: =IFERROR(AVERAGE(D29:D33),"") -> 155570 | E38: =IFERROR(AVERAGE(E29:E33),"") -> 70073.4 | F38: =IFERROR(AVERAGE(F29:F33),"") -> 0.1424 | G38: =IFERROR(AVERAGE(G29:G33),"") -> 0.122 | H38: =IFERROR(AVERAGE(H29:H33),"") -> 0.0182 | I38: =IFERROR(AVERAGE(I29:I33),"") -> 0.076 | J38: =IFERROR(AVERAGE(J29:J33),"") -> 2.1813769 | K38: =IFERROR(AVERAGE(K29:K33),"") -> 21.882617 | M38: =IFERROR(AVERAGE(M29:M33),"") -> 216600 | N38: =IFERROR(AVERAGE(N29:N33),"") -> 2.8444261 | P38: =IFERROR(AVERAGE(P29:P33),"") -> 0.452 | Q38: =IFERROR(AVERAGE(Q29:Q33),"") -> 26244.8 | R38: =IFERROR(AVERAGE(R29:R33),"") -> 0.15259046 | S38: =IFERROR(AVERAGE(S29:S33),"") -> 1150 | T38: =IFERROR(AVERAGE(T29:T33),"") -> 0.0052148519 | U38: =IFERROR(AVERAGE(U29:U33),"") -> 141296 | V38: =IFERROR(AVERAGE(V29:V33),"") -> 0.84219469 | W38: =IFERROR(AVERAGE(W29:W33),"") -> 0.21 | X38: =IFERROR(AVERAGE(X29:X33),"") -> 0.3827776
A39: 75th Pctl: | C39: =IFERROR(QUARTILE(C29:C33,3),"") -> 170000 | D39: =IFERROR(QUARTILE(D29:D33,3),"") -> 196150 | E39: =IFERROR(QUARTILE(E29:E33,3),"") -> 90373 | F39: =IFERROR(QUARTILE(F29:F33,3),"") -> 0.2 | G39: =IFERROR(QUARTILE(G29:G33,3),"") -> 0.145 | H39: =IFERROR(QUARTILE(H29:H33,3),"") -> 0.017 | I39: =IFERROR(QUARTILE(I29:I33,3),"") -> 0.1 | J39: =IFERROR(QUARTILE(J29:J33,3),"") -> 2.2380952 | K39: =IFERROR(QUARTILE(K29:K33,3),"") -> 18.849084 | M39: =IFERROR(QUARTILE(M29:M33,3),"") -> 217000 | N39: =IFERROR(QUARTILE(N29:N33,3),"") -> 2.4011596 | P39: =IFERROR(QUARTILE(P29:P33,3),"") -> 0.5 | Q39: =IFERROR(QUARTILE(Q29:Q33,3),"") -> 38940 | R39: =IFERROR(QUARTILE(R29:R33,3),"") -> 0.15883377 | S39: =IFERROR(QUARTILE(S29:S33,3),"") -> 0 | T39: =IFERROR(QUARTILE(T29:T33,3),"") -> 0 | U39: =IFERROR(QUARTILE(U29:U33,3),"") -> 170420 | V39: =IFERROR(QUARTILE(V29:V33,3),"") -> 0.86251456 | W39: =IFERROR(QUARTILE(W29:W33,3),"") -> 0.21 | X39: =IFERROR(QUARTILE(X29:X33,3),"") -> 0.45129188
A40: Max: | C40: =IFERROR(MAX(C29:C33),"") -> 238380 | D40: =IFERROR(MAX(D29:D33),"") -> 247000 | E40: =IFERROR(MAX(E29:E33),"") -> 92184 | F40: =IFERROR(MAX(F29:F33),"") -> 0.202 | G40: =IFERROR(MAX(G29:G33),"") -> 0.16 | H40: =IFERROR(MAX(H29:H33),"") -> 0.029 | I40: =IFERROR(MAX(I29:I33),"") -> 0.11 | J40: =IFERROR(MAX(J29:J33),"") -> 2.7331172 | K40: =IFERROR(MAX(K29:K33),"") -> 47.284658 | M40: =IFERROR(MAX(M29:M33),"") -> 516000 | N40: =IFERROR(MAX(N29:N33),"") -> 5.5975007 | P40: =IFERROR(MAX(P29:P33),"") -> 1.21 | Q40: =IFERROR(MAX(Q29:Q33),"") -> 44354 | R40: =IFERROR(MAX(R29:R33),"") -> 0.20113004 | S40: =IFERROR(MAX(S29:S33),"") -> 5750 | T40: =IFERROR(MAX(T29:T33),"") -> 0.026074259 | U40: =IFERROR(MAX(U29:U33),"") -> 244290 | V40: =IFERROR(MAX(V29:V33),"") -> 0.87980092 | W40: =IFERROR(MAX(W29:W33),"") -> 0.21 | X40: =IFERROR(MAX(X29:X33),"") -> 0.97631993

Sheet AI Comps
A1: SpaceX — AI Comparable Companies
A2: Comparable Public Companies by Maturity & Industry | Compute Infrastructure + Social Media | $ in Millions
A3: Current-stage anchor = GPU Neoclouds / Infra Hosting • Mature-stage anchor = Social Media. Input cells (blue) to be populated from terminal (CapIQ/Bloomberg).
A5: TIER 1 — GPU-FIRST NEOCLOUDS (Current-Stage Anchor)
A6: Name | B6: Ticker | C6: Mkt Cap | D6: Enterprise | E6: LTM | F6: Gross | G6: EBITDA | H6: CapEx / | I6: 3-Yr Ann. | J6: TEV / | K6: TEV / | M6: Power | N6: Rev / | P6: Levered | Q6: Debt | R6: % Debt | S6: Preferred | T6: % Pref | U6: Equity | V6: % Equity | W6: Tax | X6: Unlevered
C7: ($M) | D7: Value ($M) | E7: Revenue ($M) | F7: Margin | G7: Margin | H7: Revenue | I7: Rev Growth | J7: Revenue | K7: EBITDA | M7: (MW) | N7: MW ($M) | P7: Beta | Q7: ($M) | S7: Stock ($M) | U7: Value ($M) | W7: Rate | X7: Beta
A8: CoreWeave, Inc. | B8: NasdaqGS:CRWV | C8: 55470 | D8: 88930 | E8: 6230 | F8: -0.29 | G8: -0.29 | H8: 5 | I8: 1.12 | J8: =IFERROR(D8/E8,"NM") -> 14.274478 | K8: =IF(OR(G8<=0,E8=0,D8=0),"NM",IF(D8/(E8*G8)>100,"NM",D8/(E8*G8))) -> NM | M8: 470 | N8: =IFERROR(E8/M8,"NM") -> 13.255319 | P8: 1.8 | Q8: 35150 | R8: =IFERROR(Q8/(Q8+S8+U8),"") -> 0.38788347 | S8: 0 | T8: =IFERROR(S8/(Q8+S8+U8),"") -> 0 | U8: 55470 | V8: =IFERROR(U8/(Q8+S8+U8),"") -> 0.61211653 | W8: 0.21 | X8: =IFERROR(P8/(1+(Q8/U8)*(1-W8)+S8/U8),"") -> 1.1995171
A9: Nebius Group N.V. | B9: NasdaqGS:NBIS | C9: 56000 | D9: 58040 | E9: 878 | F9: 0.45 | G9: 0.45 | H9: 2.5 | I9: 6.84 | J9: =IFERROR(D9/E9,"NM") -> 66.104784 | K9: =IF(OR(G9<=0,E9=0,D9=0),"NM",IF(D9/(E9*G9)>100,"NM",D9/(E9*G9))) -> NM | M9: 300 | N9: =IFERROR(E9/M9,"NM") -> 2.9266667 | P9: 2.8 | Q9: 7800 | R9: =IFERROR(Q9/(Q9+S9+U9),"") -> 0.12225705 | S9: 0 | T9: =IFERROR(S9/(Q9+S9+U9),"") -> 0 | U9: 56000 | V9: =IFERROR(U9/(Q9+S9+U9),"") -> 0.87774295 | W9: 0.25 | X9: =IFERROR(P9/(1+(Q9/U9)*(1-W9)+S9/U9),"") -> 2.5351657
A11: Min: | C11: =IFERROR(MIN(C8:C9),"") -> 55470 | D11: =IFERROR(MIN(D8:D9),"") -> 58040 | E11: =IFERROR(MIN(E8:E9),"") -> 878 | F11: =IFERROR(MIN(F8:F9),"") -> -0.29 | G11: =IFERROR(MIN(G8:G9),"") -> -0.29 | H11: =IFERROR(MIN(H8:H9),"") -> 2.5 | I11: =IFERROR(MIN(I8:I9),"") -> 1.12 | J11: =IFERROR(MIN(J8:J9),"") -> 14.274478 | K11: =IFERROR(_xlfn.AGGREGATE(15,6,K8:K9,1),"NM") -> NM | M11: =IFERROR(MIN(M8:M9),"") -> 300 | N11: =IFERROR(MIN(N8:N9),"") -> 2.9266667 | P11: =IFERROR(MIN(P8:P9),"") -> 1.8 | Q11: =IFERROR(MIN(Q8:Q9),"") -> 7800 | R11: =IFERROR(MIN(R8:R9),"") -> 0.12225705 | S11: =IFERROR(MIN(S8:S9),"") -> 0 | T11: =IFERROR(MIN(T8:T9),"") -> 0 | U11: =IFERROR(MIN(U8:U9),"") -> 55470 | V11: =IFERROR(MIN(V8:V9),"") -> 0.61211653 | W11: =IFERROR(MIN(W8:W9),"") -> 0.21 | X11: =IFERROR(MIN(X8:X9),"") -> 1.1995171
A12: 25th Pctl: | C12: =IFERROR(QUARTILE(C8:C9,1),"") -> 55602.5 | D12: =IFERROR(QUARTILE(D8:D9,1),"") -> 65762.5 | E12: =IFERROR(QUARTILE(E8:E9,1),"") -> 2216 | F12: =IFERROR(QUARTILE(F8:F9,1),"") -> -0.105 | G12: =IFERROR(QUARTILE(G8:G9,1),"") -> -0.105 | H12: =IFERROR(QUARTILE(H8:H9,1),"") -> 3.125 | I12: =IFERROR(QUARTILE(I8:I9,1),"") -> 2.55 | J12: =IFERROR(QUARTILE(J8:J9,1),"") -> 27.232055 | K12: =IFERROR(_xlfn.AGGREGATE(16,6,K8:K9,0.25),"NM") -> NM | M12: =IFERROR(QUARTILE(M8:M9,1),"") -> 342.5 | N12: =IFERROR(QUARTILE(N8:N9,1),"") -> 5.5088298 | P12: =IFERROR(QUARTILE(P8:P9,1),"") -> 2.05 | Q12: =IFERROR(QUARTILE(Q8:Q9,1),"") -> 14637.5 | R12: =IFERROR(QUARTILE(R8:R9,1),"") -> 0.18866366 | S12: =IFERROR(QUARTILE(S8:S9,1),"") -> 0 | T12: =IFERROR(QUARTILE(T8:T9,1),"") -> 0 | U12: =IFERROR(QUARTILE(U8:U9,1),"") -> 55602.5 | V12: =IFERROR(QUARTILE(V8:V9,1),"") -> 0.67852313 | W12: =IFERROR(QUARTILE(W8:W9,1),"") -> 0.22 | X12: =IFERROR(QUARTILE(X8:X9,1),"") -> 1.5334292
A13: Median: | C13: =IFERROR(MEDIAN(C8:C9),"") -> 55735 | D13: =IFERROR(MEDIAN(D8:D9),"") -> 73485 | E13: =IFERROR(MEDIAN(E8:E9),"") -> 3554 | F13: =IFERROR(MEDIAN(F8:F9),"") -> 0.08 | G13: =IFERROR(MEDIAN(G8:G9),"") -> 0.08 | H13: =IFERROR(MEDIAN(H8:H9),"") -> 3.75 | I13: =IFERROR(MEDIAN(I8:I9),"") -> 3.98 | J13: =IFERROR(MEDIAN(J8:J9),"") -> 40.189631 | K13: =IFERROR(_xlfn.AGGREGATE(16,6,K8:K9,0.5),"NM") -> NM | M13: =IFERROR(MEDIAN(M8:M9),"") -> 385 | N13: =IFERROR(MEDIAN(N8:N9),"") -> 8.0909929 | P13: =IFERROR(MEDIAN(P8:P9),"") -> 2.3 | Q13: =IFERROR(MEDIAN(Q8:Q9),"") -> 21475 | R13: =IFERROR(MEDIAN(R8:R9),"") -> 0.25507026 | S13: =IFERROR(MEDIAN(S8:S9),"") -> 0 | T13: =IFERROR(MEDIAN(T8:T9),"") -> 0 | U13: =IFERROR(MEDIAN(U8:U9),"") -> 55735 | V13: =IFERROR(MEDIAN(V8:V9),"") -> 0.74492974 | W13: =IFERROR(MEDIAN(W8:W9),"") -> 0.23 | X13: =IFERROR(MEDIAN(X8:X9),"") -> 1.8673414
A14: Mean: | C14: =IFERROR(AVERAGE(C8:C9),"") -> 55735 | D14: =IFERROR(AVERAGE(D8:D9),"") -> 73485 | E14: =IFERROR(AVERAGE(E8:E9),"") -> 3554 | F14: =IFERROR(AVERAGE(F8:F9),"") -> 0.08 | G14: =IFERROR(AVERAGE(G8:G9),"") -> 0.08 | H14: =IFERROR(AVERAGE(H8:H9),"") -> 3.75 | I14: =IFERROR(AVERAGE(I8:I9),"") -> 3.98 | J14: =IFERROR(AVERAGE(J8:J9),"") -> 40.189631 | K14: =IFERROR(_xlfn.AGGREGATE(1,6,K8:K9),"NM") -> NM | M14: =IFERROR(AVERAGE(M8:M9),"") -> 385 | N14: =IFERROR(AVERAGE(N8:N9),"") -> 8.0909929 | P14: =IFERROR(AVERAGE(P8:P9),"") -> 2.3 | Q14: =IFERROR(AVERAGE(Q8:Q9),"") -> 21475 | R14: =IFERROR(AVERAGE(R8:R9),"") -> 0.25507026 | S14: =IFERROR(AVERAGE(S8:S9),"") -> 0 | T14: =IFERROR(AVERAGE(T8:T9),"") -> 0 | U14: =IFERROR(AVERAGE(U8:U9),"") -> 55735 | V14: =IFERROR(AVERAGE(V8:V9),"") -> 0.74492974 | W14: =IFERROR(AVERAGE(W8:W9),"") -> 0.23 | X14: =IFERROR(AVERAGE(X8:X9),"") -> 1.8673414
A15: 75th Pctl: | C15: =IFERROR(QUARTILE(C8:C9,3),"") -> 55867.5 | D15: =IFERROR(QUARTILE(D8:D9,3),"") -> 81207.5 | E15: =IFERROR(QUARTILE(E8:E9,3),"") -> 4892 | F15: =IFERROR(QUARTILE(F8:F9,3),"") -> 0.265 | G15: =IFERROR(QUARTILE(G8:G9,3),"") -> 0.265 | H15: =IFERROR(QUARTILE(H8:H9,3),"") -> 4.375 | I15: =IFERROR(QUARTILE(I8:I9,3),"") -> 5.41 | J15: =IFERROR(QUARTILE(J8:J9,3),"") -> 53.147207 | K15: =IFERROR(_xlfn.AGGREGATE(16,6,K8:K9,0.75),"NM") -> NM | M15: =IFERROR(QUARTILE(M8:M9,3),"") -> 427.5 | N15: =IFERROR(QUARTILE(N8:N9,3),"") -> 10.673156 | P15: =IFERROR(QUARTILE(P8:P9,3),"") -> 2.55 | Q15: =IFERROR(QUARTILE(Q8:Q9,3),"") -> 28312.5 | R15: =IFERROR(QUARTILE(R8:R9,3),"") -> 0.32147687 | S15: =IFERROR(QUARTILE(S8:S9,3),"") -> 0 | T15: =IFERROR(QUARTILE(T8:T9,3),"") -> 0 | U15: =IFERROR(QUARTILE(U8:U9,3),"") -> 55867.5 | V15: =IFERROR(QUARTILE(V8:V9,3),"") -> 0.81133634 | W15: =IFERROR(QUARTILE(W8:W9,3),"") -> 0.24 | X15: =IFERROR(QUARTILE(X8:X9,3),"") -> 2.2012536
A16: Max: | C16: =IFERROR(MAX(C8:C9),"") -> 56000 | D16: =IFERROR(MAX(D8:D9),"") -> 88930 | E16: =IFERROR(MAX(E8:E9),"") -> 6230 | F16: =IFERROR(MAX(F8:F9),"") -> 0.45 | G16: =IFERROR(MAX(G8:G9),"") -> 0.45 | H16: =IFERROR(MAX(H8:H9),"") -> 5 | I16: =IFERROR(MAX(I8:I9),"") -> 6.84 | J16: =IFERROR(MAX(J8:J9),"") -> 66.104784 | K16: =IFERROR(_xlfn.AGGREGATE(14,6,K8:K9,1),"NM") -> NM | M16: =IFERROR(MAX(M8:M9),"") -> 470 | N16: =IFERROR(MAX(N8:N9),"") -> 13.255319 | P16: =IFERROR(MAX(P8:P9),"") -> 2.8 | Q16: =IFERROR(MAX(Q8:Q9),"") -> 35150 | R16: =IFERROR(MAX(R8:R9),"") -> 0.38788347 | S16: =IFERROR(MAX(S8:S9),"") -> 0 | T16: =IFERROR(MAX(T8:T9),"") -> 0 | U16: =IFERROR(MAX(U8:U9),"") -> 56000 | V16: =IFERROR(MAX(V8:V9),"") -> 0.87774295 | W16: =IFERROR(MAX(W8:W9),"") -> 0.25 | X16: =IFERROR(MAX(X8:X9),"") -> 2.5351657
A19: TIER 2 — INFRASTRUCTURE-FIRST HOSTING (No GPUs) | C19: Mkt | D19: Enterprise
A20: Name | B20: Ticker | C20: Mkt Cap | D20: Enterprise | E20: LTM | F20: Gross | G20: EBITDA | H20: CapEx / | I20: 3-Yr Ann. | J20: TEV / | K20: TEV / | M20: Power | N20: Rev / | P20: Levered | Q20: Debt | R20: % Debt | S20: Preferred | T20: % Pref | U20: Equity | V20: % Equity | W20: Tax | X20: Unlevered
C21: ($M) | D21: Value ($M) | E21: Revenue ($M) | F21: Margin | G21: Margin | H21: Revenue | I21: Rev Growth | J21: Revenue | K21: EBITDA | M21: (MW) | N21: MW ($M) | P21: Beta | Q21: ($M) | S21: Stock ($M) | U21: Value ($M) | W21: Rate | X21: Beta
A22: WhiteFiber, Inc. | B22: NasdaqCM:WYFI | C22: 898 | D22: 1070 | E22: 84 | F22: 0.45 | G22: -0.25 | H22: 2 | I22: 0.79 | J22: =IFERROR(D22/E22,"NM") -> 12.738095 | K22: =IF(OR(G22<=0,E22=0,D22=0),"NM",IF(D22/(E22*G22)>100,"NM",D22/(E22*G22))) -> NM | M22: 54 | N22: 1.2 | P22: 1.5 | Q22: 230 | R22: =IFERROR(Q22/(Q22+S22+U22),"") -> 0.20390071 | S22: 0 | T22: =IFERROR(S22/(Q22+S22+U22),"") -> 0 | U22: 898 | V22: =IFERROR(U22/(Q22+S22+U22),"") -> 0.79609929 | W22: 0.21 | X22: =IFERROR(P22/(1+(Q22/U22)*(1-W22)+S22/U22),"") -> 1.2475688
A23: IREN Limited | B23: NasdaqGS:IREN | C23: 16000 | D23: 17750 | E23: 757 | F23: 0.5 | G23: -0.33 | H23: 5 | I23: 1.07 | J23: =IFERROR(D23/E23,"NM") -> 23.44782 | K23: =IF(OR(G23<=0,E23=0,D23=0),"NM",IF(D23/(E23*G23)>100,"NM",D23/(E23*G23))) -> NM | M23: 480 | N23: 1.58 | P23: 4.18 | Q23: 3960 | R23: =IFERROR(Q23/(Q23+S23+U23),"") -> 0.19839679 | S23: 0 | T23: =IFERROR(S23/(Q23+S23+U23),"") -> 0 | U23: 16000 | V23: =IFERROR(U23/(Q23+S23+U23),"") -> 0.80160321 | W23: 0.21 | X23: =IFERROR(P23/(1+(Q23/U23)*(1-W23)+S23/U23),"") -> 3.4963719
A24: Applied Digital Corp. | B24: NasdaqGS:APLD | C24: 11320 | D24: 13235 | E24: 264 | F24: 0.5 | G24: -0.48 | H24: 4 | I24: 0.52 | J24: =IFERROR(D24/E24,"NM") -> 50.132576 | K24: =IF(OR(G24<=0,E24=0,D24=0),"NM",IF(D24/(E24*G24)>100,"NM",D24/(E24*G24))) -> NM | M24: 300 | N24: 0.88 | P24: 7.34 | Q24: 2610 | R24: =IFERROR(Q24/(Q24+S24+U24),"") -> 0.1873654 | S24: 0 | T24: =IFERROR(S24/(Q24+S24+U24),"") -> 0 | U24: 11320 | V24: =IFERROR(U24/(Q24+S24+U24),"") -> 0.8126346 | W24: 0.21 | X24: =IFERROR(P24/(1+(Q24/U24)*(1-W24)+S24/U24),"") -> 6.2090436
A25: TeraWulf Inc. | B25: NasdaqCM:WULF | C25: 11000 | D25: 14930 | E25: 168 | F25: 0.55 | G25: -3.93 | H25: 5 | I25: 0.73 | J25: =IFERROR(D25/E25,"NM") -> 88.869048 | K25: =IF(OR(G25<=0,E25=0,D25=0),"NM",IF(D25/(E25*G25)>100,"NM",D25/(E25*G25))) -> NM | M25: 480 | N25: 0.35 | P25: 4.3 | Q25: 5200 | R25: =IFERROR(Q25/(Q25+S25+U25),"") -> 0.32098765 | S25: 0 | T25: =IFERROR(S25/(Q25+S25+U25),"") -> 0 | U25: 11000 | V25: =IFERROR(U25/(Q25+S25+U25),"") -> 0.67901235 | W25: 0.21 | X25: =IFERROR(P25/(1+(Q25/U25)*(1-W25)+S25/U25),"") -> 3.1307916
A26: Cipher Mining Inc. | B26: NasdaqGS:CIFR | C26: 10620 | D26: 10440 | E26: 224 | F26: 0.637 | G26: -3.67 | H26: 3 | I26: 0.65 | J26: =IFERROR(D26/E26,"NM") -> 46.607143 | K26: =IF(OR(G26<=0,E26=0,D26=0),"NM",IF(D26/(E26*G26)>100,"NM",D26/(E26*G26))) -> NM | M26: 495 | N26: 0.45 | P26: 2.89 | Q26: 500 | R26: =IFERROR(Q26/(Q26+S26+U26),"") -> 0.044964029 | S26: 0 | T26: =IFERROR(S26/(Q26+S26+U26),"") -> 0 | U26: 10620 | V26: =IFERROR(U26/(Q26+S26+U26),"") -> 0.95503597 | W26: 0.21 | X26: =IFERROR(P26/(1+(Q26/U26)*(1-W26)+S26/U26),"") -> 2.786364
A28: Min: | C28: =IFERROR(MIN(C22:C26),"") -> 898 | D28: =IFERROR(MIN(D22:D26),"") -> 1070 | E28: =IFERROR(MIN(E22:E26),"") -> 84 | F28: =IFERROR(MIN(F22:F26),"") -> 0.45 | G28: =IFERROR(MIN(G22:G26),"") -> -3.93 | H28: =IFERROR(MIN(H22:H26),"") -> 2 | I28: =IFERROR(MIN(I22:I26),"") -> 0.52 | J28: =IFERROR(MIN(J22:J26),"") -> 12.738095 | K28: =IFERROR(_xlfn.AGGREGATE(15,6,K22:K26,1),"NM") -> NM | M28: =IFERROR(MIN(M22:M26),"") -> 54 | N28: =IFERROR(MIN(N22:N26),"") -> 0.35 | P28: =IFERROR(MIN(P22:P26),"") -> 1.5 | Q28: =IFERROR(MIN(Q22:Q26),"") -> 230 | R28: =IFERROR(MIN(R22:R26),"") -> 0.044964029 | S28: =IFERROR(MIN(S22:S26),"") -> 0 | T28: =IFERROR(MIN(T22:T26),"") -> 0 | U28: =IFERROR(MIN(U22:U26),"") -> 898 | V28: =IFERROR(MIN(V22:V26),"") -> 0.67901235 | W28: =IFERROR(MIN(W22:W26),"") -> 0.21 | X28: =IFERROR(MIN(X22:X26),"") -> 1.2475688
A29: 25th Pctl: | C29: =IFERROR(QUARTILE(C22:C26,1),"") -> 10620 | D29: =IFERROR(QUARTILE(D22:D26,1),"") -> 10440 | E29: =IFERROR(QUARTILE(E22:E26,1),"") -> 168 | F29: =IFERROR(QUARTILE(F22:F26,1),"") -> 0.5 | G29: =IFERROR(QUARTILE(G22:G26,1),"") -> -3.67 | H29: =IFERROR(QUARTILE(H22:H26,1),"") -> 3 | I29: =IFERROR(QUARTILE(I22:I26,1),"") -> 0.65 | J29: =IFERROR(QUARTILE(J22:J26,1),"") -> 23.44782 | K29: =IFERROR(_xlfn.AGGREGATE(16,6,K22:K26,0.25),"NM") -> NM | M29: =IFERROR(QUARTILE(M22:M26,1),"") -> 300 | N29: =IFERROR(QUARTILE(N22:N26,1),"") -> 0.45 | P29: =IFERROR(QUARTILE(P22:P26,1),"") -> 2.89 | Q29: =IFERROR(QUARTILE(Q22:Q26,1),"") -> 500 | R29: =IFERROR(QUARTILE(R22:R26,1),"") -> 0.1873654 | S29: =IFERROR(QUARTILE(S22:S26,1),"") -> 0 | T29: =IFERROR(QUARTILE(T22:T26,1),"") -> 0 | U29: =IFERROR(QUARTILE(U22:U26,1),"") -> 10620 | V29: =IFERROR(QUARTILE(V22:V26,1),"") -> 0.79609929 | W29: =IFERROR(QUARTILE(W22:W26,1),"") -> 0.21 | X29: =IFERROR(QUARTILE(X22:X26,1),"") -> 2.786364
A30: Median: | C30: =IFERROR(MEDIAN(C22:C26),"") -> 11000 | D30: =IFERROR(MEDIAN(D22:D26),"") -> 13235 | E30: =IFERROR(MEDIAN(E22:E26),"") -> 224 | F30: =IFERROR(MEDIAN(F22:F26),"") -> 0.5 | G30: =IFERROR(MEDIAN(G22:G26),"") -> -0.48 | H30: =IFERROR(MEDIAN(H22:H26),"") -> 4 | I30: =IFERROR(MEDIAN(I22:I26),"") -> 0.73 | J30: =IFERROR(MEDIAN(J22:J26),"") -> 46.607143 | K30: =IFERROR(_xlfn.AGGREGATE(16,6,K22:K26,0.5),"NM") -> NM | M30: =IFERROR(MEDIAN(M22:M26),"") -> 480 | N30: =IFERROR(MEDIAN(N22:N26),"") -> 0.88 | P30: =IFERROR(MEDIAN(P22:P26),"") -> 4.18 | Q30: =IFERROR(MEDIAN(Q22:Q26),"") -> 2610 | R30: =IFERROR(MEDIAN(R22:R26),"") -> 0.19839679 | S30: =IFERROR(MEDIAN(S22:S26),"") -> 0 | T30: =IFERROR(MEDIAN(T22:T26),"") -> 0 | U30: =IFERROR(MEDIAN(U22:U26),"") -> 11000 | V30: =IFERROR(MEDIAN(V22:V26),"") -> 0.80160321 | W30: =IFERROR(MEDIAN(W22:W26),"") -> 0.21 | X30: =IFERROR(MEDIAN(X22:X26),"") -> 3.1307916
A31: Mean: | C31: =IFERROR(AVERAGE(C22:C26),"") -> 9967.6 | D31: =IFERROR(AVERAGE(D22:D26),"") -> 11485 | E31: =IFERROR(AVERAGE(E22:E26),"") -> 299.4 | F31: =IFERROR(AVERAGE(F22:F26),"") -> 0.5274 | G31: =IFERROR(AVERAGE(G22:G26),"") -> -1.732 | H31: =IFERROR(AVERAGE(H22:H26),"") -> 3.8 | I31: =IFERROR(AVERAGE(I22:I26),"") -> 0.752 | J31: =IFERROR(AVERAGE(J22:J26),"") -> 44.358936 | K31: =IFERROR(_xlfn.AGGREGATE(1,6,K22:K26),"NM") -> NM | M31: =IFERROR(AVERAGE(M22:M26),"") -> 361.8 | N31: =IFERROR(AVERAGE(N22:N26),"") -> 0.892 | P31: =IFERROR(AVERAGE(P22:P26),"") -> 4.042 | Q31: =IFERROR(AVERAGE(Q22:Q26),"") -> 2500 | R31: =IFERROR(AVERAGE(R22:R26),"") -> 0.19112292 | S31: =IFERROR(AVERAGE(S22:S26),"") -> 0 | T31: =IFERROR(AVERAGE(T22:T26),"") -> 0 | U31: =IFERROR(AVERAGE(U22:U26),"") -> 9967.6 | V31: =IFERROR(AVERAGE(V22:V26),"") -> 0.80887708 | W31: =IFERROR(AVERAGE(W22:W26),"") -> 0.21 | X31: =IFERROR(AVERAGE(X22:X26),"") -> 3.374028
A32: 75th Pctl: | C32: =IFERROR(QUARTILE(C22:C26,3),"") -> 11320 | D32: =IFERROR(QUARTILE(D22:D26,3),"") -> 14930 | E32: =IFERROR(QUARTILE(E22:E26,3),"") -> 264 | F32: =IFERROR(QUARTILE(F22:F26,3),"") -> 0.55 | G32: =IFERROR(QUARTILE(G22:G26,3),"") -> -0.33 | H32: =IFERROR(QUARTILE(H22:H26,3),"") -> 5 | I32: =IFERROR(QUARTILE(I22:I26,3),"") -> 0.79 | J32: =IFERROR(QUARTILE(J22:J26,3),"") -> 50.132576 | K32: =IFERROR(_xlfn.AGGREGATE(16,6,K22:K26,0.75),"NM") -> NM | M32: =IFERROR(QUARTILE(M22:M26,3),"") -> 480 | N32: =IFERROR(QUARTILE(N22:N26,3),"") -> 1.2 | P32: =IFERROR(QUARTILE(P22:P26,3),"") -> 4.3 | Q32: =IFERROR(QUARTILE(Q22:Q26,3),"") -> 3960 | R32: =IFERROR(QUARTILE(R22:R26,3),"") -> 0.20390071 | S32: =IFERROR(QUARTILE(S22:S26,3),"") -> 0 | T32: =IFERROR(QUARTILE(T22:T26,3),"") -> 0 | U32: =IFERROR(QUARTILE(U22:U26,3),"") -> 11320 | V32: =IFERROR(QUARTILE(V22:V26,3),"") -> 0.8126346 | W32: =IFERROR(QUARTILE(W22:W26,3),"") -> 0.21 | X32: =IFERROR(QUARTILE(X22:X26,3),"") -> 3.4963719
A33: Max: | C33: =IFERROR(MAX(C22:C26),"") -> 16000 | D33: =IFERROR(MAX(D22:D26),"") -> 17750 | E33: =IFERROR(MAX(E22:E26),"") -> 757 | F33: =IFERROR(MAX(F22:F26),"") -> 0.637 | G33: =IFERROR(MAX(G22:G26),"") -> -0.25 | H33: =IFERROR(MAX(H22:H26),"") -> 5 | I33: =IFERROR(MAX(I22:I26),"") -> 1.07 | J33: =IFERROR(MAX(J22:J26),"") -> 88.869048 | K33: =IFERROR(_xlfn.AGGREGATE(14,6,K22:K26,1),"NM") -> NM | M33: =IFERROR(MAX(M22:M26),"") -> 495 | N33: =IFERROR(MAX(N22:N26),"") -> 1.58 | P33: =IFERROR(MAX(P22:P26),"") -> 7.34 | Q33: =IFERROR(MAX(Q22:Q26),"") -> 5200 | R33: =IFERROR(MAX(R22:R26),"") -> 0.32098765 | S33: =IFERROR(MAX(S22:S26),"") -> 0 | T33: =IFERROR(MAX(T22:T26),"") -> 0 | U33: =IFERROR(MAX(U22:U26),"") -> 16000 | V33: =IFERROR(MAX(V22:V26),"") -> 0.95503597 | W33: =IFERROR(MAX(W22:W26),"") -> 0.21 | X33: =IFERROR(MAX(X22:X26),"") -> 6.2090436
A36: TIER 3 — SOCIAL MEDIA (Mature-Stage Monetization Anchor) | C36: Mkt | D36: Enterprise
A37: Name | B37: Ticker | C37: Mkt Cap | D37: Enterprise | E37: LTM | F37: Gross | G37: EBITDA | H37: Capex % | I37: 3-Yr Ann. | J37: TEV / | K37: TEV / | M37: MAU / DAU | N37: ARPU | P37: Levered | Q37: Debt | R37: % Debt | S37: Preferred | T37: % Pref | U37: Equity | V37: % Equity | W37: Tax | X37: Unlevered
C38: ($M) | D38: Value ($M) | E38: Revenue ($M) | F38: Margin | G38: Margin | H38: Revenue | I38: Rev Growth | J38: Revenue | K38: EBITDA | M38: (M) | N38: ($) | P38: Beta | Q38: ($M) | S38: Stock ($M) | U38: Value ($M) | W38: Rate | X38: Beta
A39: Snap Inc. | B39: NYSE:SNAP | C39: 9550 | D39: 11700 | E39: 5900 | F39: 0.55 | G39: 0.1877 | H39: 0.038 | I39: 0.12 | J39: =IFERROR(D39/E39,"NM") -> 1.9830508 | K39: =IF(OR(G39<=0,E39=0,D39=0),"NM",IF(D39/(E39*G39)>100,"NM",D39/(E39*G39))) -> 10.565002 | M39: 453 | N39: 11.7 | P39: 1.05 | Q39: 3536 | R39: =IFERROR(Q39/(Q39+S39+U39),"") -> 0.27021244 | S39: 0 | T39: =IFERROR(S39/(Q39+S39+U39),"") -> 0 | U39: 9550 | V39: =IFERROR(U39/(Q39+S39+U39),"") -> 0.72978756 | W39: 0.21 | X39: =IFERROR(P39/(1+(Q39/U39)*(1-W39)+S39/U39),"") -> 0.81237483
A40: Pinterest, Inc. | B40: NYSE:PINS | C40: 11580 | D40: 11480 | E40: 4370 | F40: 0.79 | G40: 0.2905 | H40: 0.03 | I40: 0.15 | J40: =IFERROR(D40/E40,"NM") -> 2.6270023 | K40: =IF(OR(G40<=0,E40=0,D40=0),"NM",IF(D40/(E40*G40)>100,"NM",D40/(E40*G40))) -> 9.0430371 | M40: 570 | N40: 5.3 | P40: 0.92 | Q40: 262 | R40: =IFERROR(Q40/(Q40+S40+U40),"") -> 0.022124641 | S40: 0 | T40: =IFERROR(S40/(Q40+S40+U40),"") -> 0 | U40: 11580 | V40: =IFERROR(U40/(Q40+S40+U40),"") -> 0.97787536 | W40: 0.21 | X40: =IFERROR(P40/(1+(Q40/U40)*(1-W40)+S40/U40),"") -> 0.90384475
A41: Reddit, Inc. | B41: NYSE:RDDT | C41: 35400 | D41: 32650 | E41: 2474 | F41: 0.91 | G41: 0.38 | H41: 0.025 | I41: 0.69 | J41: =IFERROR(D41/E41,"NM") -> 13.197251 | K41: =IF(OR(G41<=0,E41=0,D41=0),"NM",IF(D41/(E41*G41)>100,"NM",D41/(E41*G41))) -> 34.729609 | M41: 97 | N41: 25.5 | P41: 0.8 | Q41: 17 | R41: =IFERROR(Q41/(Q41+S41+U41),"") -> 0.00047999548 | S41: 0 | T41: =IFERROR(S41/(Q41+S41+U41),"") -> 0 | U41: 35400 | V41: =IFERROR(U41/(Q41+S41+U41),"") -> 0.99952 | W41: 0.21 | X41: =IFERROR(P41/(1+(Q41/U41)*(1-W41)+S41/U41),"") -> 0.79969661
A42: Meta Platforms, Inc. | B42: NasdaqGS:META | C42: 1449000 | D42: 1450000 | E42: 214963 | F42: 0.82 | G42: 0.509 | H42: 0.2 | I42: 0.2 | J42: =IFERROR(D42/E42,"NM") -> 6.7453469 | K42: =IFERROR(IF(G42<=0,"NM",D42/(E42*G42)),"NM") -> 13.252155 | M42: 3430 | N42: 62.7 | P42: 1.24 | Q42: 83900 | R42: =IFERROR(Q42/(Q42+S42+U42),"") -> 0.054732859 | S42: 0 | T42: =IFERROR(S42/(Q42+S42+U42),"") -> 0 | U42: 1449000 | V42: =IFERROR(U42/(Q42+S42+U42),"") -> 0.94526714 | W42: 0.15 | X42: =IFERROR(P42/(1+(Q42/U42)*(1-W42)+S42/U42),"") -> 1.181834
A43: Match Group, Inc. | B43: NasdaqGS:MTCH | C43: 8360 | D43: 11370 | E43: 3520 | F43: 0.74 | G43: 0.38 | H43: 0.04 | I43: 0.02 | J43: =IFERROR(D43/E43,"NM") -> 3.2301136 | K43: =IF(OR(G43<=0,E43=0,D43=0),"NM",IF(D43/(E43*G43)>100,"NM",D43/(E43*G43))) -> 8.500299 | M43: 65 | N43: 54.2 | P43: 1.36 | Q43: 4000 | R43: =IFERROR(Q43/(Q43+S43+U43),"") -> 0.3236246 | S43: 0 | T43: =IFERROR(S43/(Q43+S43+U43),"") -> 0 | U43: 8360 | V43: =IFERROR(U43/(Q43+S43+U43),"") -> 0.6763754 | W43: 0.23 | X43: =IFERROR(P43/(1+(Q43/U43)*(1-W43)+S43/U43),"") -> 0.99384615
A45: Min: | C45: =IFERROR(MIN(C39:C43),"") -> 8360 | D45: =IFERROR(MIN(D39:D43),"") -> 11370 | E45: =IFERROR(MIN(E39:E43),"") -> 2474 | F45: =IFERROR(MIN(F39:F43),"") -> 0.55 | G45: =IFERROR(MIN(G39:G43),"") -> 0.1877 | H45: =IFERROR(MIN(H39:H43),"") -> 0.025 | I45: =IFERROR(MIN(I39:I43),"") -> 0.02 | J45: =IFERROR(MIN(J39:J43),"") -> 1.9830508 | K45: =IFERROR(MIN(K39:K43),"") -> 8.500299 | M45: =IFERROR(MIN(M39:M43),"") -> 65 | N45: =IFERROR(MIN(N39:N43),"") -> 5.3 | P45: =IFERROR(MIN(P39:P43),"") -> 0.8 | Q45: =IFERROR(MIN(Q39:Q43),"") -> 17 | R45: =IFERROR(MIN(R39:R43),"") -> 0.00047999548 | S45: =IFERROR(MIN(S39:S43),"") -> 0 | T45: =IFERROR(MIN(T39:T43),"") -> 0 | U45: =IFERROR(MIN(U39:U43),"") -> 8360 | V45: =IFERROR(MIN(V39:V43),"") -> 0.6763754 | W45: =IFERROR(MIN(W39:W43),"") -> 0.15 | X45: =IFERROR(MIN(X39:X43),"") -> 0.79969661
A46: 25th Pctl: | C46: =IFERROR(QUARTILE(C39:C43,1),"") -> 9550 | D46: =IFERROR(QUARTILE(D39:D43,1),"") -> 11480 | E46: =IFERROR(QUARTILE(E39:E43,1),"") -> 3520 | F46: =IFERROR(QUARTILE(F39:F43,1),"") -> 0.74 | G46: =IFERROR(QUARTILE(G39:G43,1),"") -> 0.2905 | H46: =IFERROR(QUARTILE(H39:H43,1),"") -> 0.03 | I46: =IFERROR(QUARTILE(I39:I43,1),"") -> 0.12 | J46: =IFERROR(QUARTILE(J39:J43,1),"") -> 2.6270023 | K46: =IFERROR(QUARTILE(K39:K43,1),"") -> 9.0430371 | M46: =IFERROR(QUARTILE(M39:M43,1),"") -> 97 | N46: =IFERROR(QUARTILE(N39:N43,1),"") -> 11.7 | P46: =IFERROR(QUARTILE(P39:P43,1),"") -> 0.92 | Q46: =IFERROR(QUARTILE(Q39:Q43,1),"") -> 262 | R46: =IFERROR(QUARTILE(R39:R43,1),"") -> 0.022124641 | S46: =IFERROR(QUARTILE(S39:S43,1),"") -> 0 | T46: =IFERROR(QUARTILE(T39:T43,1),"") -> 0 | U46: =IFERROR(QUARTILE(U39:U43,1),"") -> 9550 | V46: =IFERROR(QUARTILE(V39:V43,1),"") -> 0.72978756 | W46: =IFERROR(QUARTILE(W39:W43,1),"") -> 0.21 | X46: =IFERROR(QUARTILE(X39:X43,1),"") -> 0.81237483
A47: Median: | C47: =IFERROR(MEDIAN(C39:C43),"") -> 11580 | D47: =IFERROR(MEDIAN(D39:D43),"") -> 11700 | E47: =IFERROR(MEDIAN(E39:E43),"") -> 4370 | F47: =IFERROR(MEDIAN(F39:F43),"") -> 0.79 | G47: =IFERROR(MEDIAN(G39:G43),"") -> 0.38 | H47: =IFERROR(MEDIAN(H39:H43),"") -> 0.038 | I47: =IFERROR(MEDIAN(I39:I43),"") -> 0.15 | J47: =IFERROR(MEDIAN(J39:J43),"") -> 3.2301136 | K47: =IFERROR(MEDIAN(K39:K43),"") -> 10.565002 | M47: =IFERROR(MEDIAN(M39:M43),"") -> 453 | N47: =IFERROR(MEDIAN(N39:N43),"") -> 25.5 | P47: =IFERROR(MEDIAN(P39:P43),"") -> 1.05 | Q47: =IFERROR(MEDIAN(Q39:Q43),"") -> 3536 | R47: =IFERROR(MEDIAN(R39:R43),"") -> 0.054732859 | S47: =IFERROR(MEDIAN(S39:S43),"") -> 0 | T47: =IFERROR(MEDIAN(T39:T43),"") -> 0 | U47: =IFERROR(MEDIAN(U39:U43),"") -> 11580 | V47: =IFERROR(MEDIAN(V39:V43),"") -> 0.94526714 | W47: =IFERROR(MEDIAN(W39:W43),"") -> 0.21 | X47: =IFERROR(MEDIAN(X39:X43),"") -> 0.90384475
A48: Mean: | C48: =IFERROR(AVERAGE(C39:C43),"") -> 302778 | D48: =IFERROR(AVERAGE(D39:D43),"") -> 303440 | E48: =IFERROR(AVERAGE(E39:E43),"") -> 46245.4 | F48: =IFERROR(AVERAGE(F39:F43),"") -> 0.762 | G48: =IFERROR(AVERAGE(G39:G43),"") -> 0.34944 | H48: =IFERROR(AVERAGE(H39:H43),"") -> 0.0666 | I48: =IFERROR(AVERAGE(I39:I43),"") -> 0.236 | J48: =IFERROR(AVERAGE(J39:J43),"") -> 5.556553 | K48: =IFERROR(AVERAGE(K39:K43),"") -> 15.21802 | M48: =IFERROR(AVERAGE(M39:M43),"") -> 923 | N48: =IFERROR(AVERAGE(N39:N43),"") -> 31.88 | P48: =IFERROR(AVERAGE(P39:P43),"") -> 1.074 | Q48: =IFERROR(AVERAGE(Q39:Q43),"") -> 18343 | R48: =IFERROR(AVERAGE(R39:R43),"") -> 0.13423491 | S48: =IFERROR(AVERAGE(S39:S43),"") -> 0 | T48: =IFERROR(AVERAGE(T39:T43),"") -> 0 | U48: =IFERROR(AVERAGE(U39:U43),"") -> 302778 | V48: =IFERROR(AVERAGE(V39:V43),"") -> 0.86576509 | W48: =IFERROR(AVERAGE(W39:W43),"") -> 0.202 | X48: =IFERROR(AVERAGE(X39:X43),"") -> 0.93831928
A49: 75th Pctl: | C49: =IFERROR(QUARTILE(C39:C43,3),"") -> 35400 | D49: =IFERROR(QUARTILE(D39:D43,3),"") -> 32650 | E49: =IFERROR(QUARTILE(E39:E43,3),"") -> 5900 | F49: =IFERROR(QUARTILE(F39:F43,3),"") -> 0.82 | G49: =IFERROR(QUARTILE(G39:G43,3),"") -> 0.38 | H49: =IFERROR(QUARTILE(H39:H43,3),"") -> 0.04 | I49: =IFERROR(QUARTILE(I39:I43,3),"") -> 0.2 | J49: =IFERROR(QUARTILE(J39:J43,3),"") -> 6.7453469 | K49: =IFERROR(QUARTILE(K39:K43,3),"") -> 13.252155 | M49: =IFERROR(QUARTILE(M39:M43,3),"") -> 570 | N49: =IFERROR(QUARTILE(N39:N43,3),"") -> 54.2 | P49: =IFERROR(QUARTILE(P39:P43,3),"") -> 1.24 | Q49: =IFERROR(QUARTILE(Q39:Q43,3),"") -> 4000 | R49: =IFERROR(QUARTILE(R39:R43,3),"") -> 0.27021244 | S49: =IFERROR(QUARTILE(S39:S43,3),"") -> 0 | T49: =IFERROR(QUARTILE(T39:T43,3),"") -> 0 | U49: =IFERROR(QUARTILE(U39:U43,3),"") -> 35400 | V49: =IFERROR(QUARTILE(V39:V43,3),"") -> 0.97787536 | W49: =IFERROR(QUARTILE(W39:W43,3),"") -> 0.21 | X49: =IFERROR(QUARTILE(X39:X43,3),"") -> 0.99384615
A50: Max: | C50: =IFERROR(MAX(C39:C43),"") -> 1449000 | D50: =IFERROR(MAX(D39:D43),"") -> 1450000 | E50: =IFERROR(MAX(E39:E43),"") -> 214963 | F50: =IFERROR(MAX(F39:F43),"") -> 0.91 | G50: =IFERROR(MAX(G39:G43),"") -> 0.509 | H50: =IFERROR(MAX(H39:H43),"") -> 0.2 | I50: =IFERROR(MAX(I39:I43),"") -> 0.69 | J50: =IFERROR(MAX(J39:J43),"") -> 13.197251 | K50: =IFERROR(MAX(K39:K43),"") -> 34.729609 | M50: =IFERROR(MAX(M39:M43),"") -> 3430 | N50: =IFERROR(MAX(N39:N43),"") -> 62.7 | P50: =IFERROR(MAX(P39:P43),"") -> 1.36 | Q50: =IFERROR(MAX(Q39:Q43),"") -> 83900 | R50: =IFERROR(MAX(R39:R43),"") -> 0.3236246 | S50: =IFERROR(MAX(S39:S43),"") -> 0 | T50: =IFERROR(MAX(T39:T43),"") -> 0 | U50: =IFERROR(MAX(U39:U43),"") -> 1449000 | V50: =IFERROR(MAX(V39:V43),"") -> 0.99952 | W50: =IFERROR(MAX(W39:W43),"") -> 0.23 | X50: =IFERROR(MAX(X39:X43),"") -> 1.181834

Sheet Actuals
A1: SpaceX — Segment Actuals & Estimates
A2: DCF stays annual (refreshed ~yearly). Quarterly actuals tracked vs explicit quarterly estimates. $ in Millions. Source: SpaceX S-1.
A4: ANNUAL — ACTUALS (FY23–FY25) + DCF FORECAST (FY26–FY28)
A5: Line Item ($M) | B5: FY2023A | C5: FY2024A | D5: FY2025A | E5: FY2026E | F5: FY2027E | G5: FY2028E
A6: Total Revenue | B6: 10387 | C6: 14015 | D6: 18674 | E6: ='Conn DCF'!E49+'Space DCF'!E49+'AI DCF'!E49 -> 24305.94 | F6: ='Conn DCF'!F49+'Space DCF'!F49+'AI DCF'!F49 -> 31520.65 | G6: ='Conn DCF'!G49+'Space DCF'!G49+'AI DCF'!G49 -> 40380.418
A7: Connectivity Revenue | B7: 3869 | C7: 7599 | D7: 11387 | E7: ='Conn DCF'!E49 -> 15714.06 | F7: ='Conn DCF'!F49 -> 20742.559 | G7: ='Conn DCF'!G49 -> 26135.625
A8: Space Revenue | B8: 3557 | C8: 3796 | D8: 4086 | E8: ='Space DCF'!E49 -> 4494.6 | F8: ='Space DCF'!F49 -> 5123.844 | G8: ='Space DCF'!G49 -> 6046.1359
A9: AI Revenue | B9: 2961 | C9: 2620 | D9: 3201 | E9: ='AI DCF'!E49 -> 4097.28 | F9: ='AI DCF'!F49 -> 5654.2464 | G9: ='AI DCF'!G49 -> 8198.6573
A10: Connectivity EBITDA | B10: 469 | C10: 2006 | D10: 7168 | E10: ='Conn DCF'!E51 -> 9899.8578 | F10: ='Conn DCF'!F51 -> 13482.663 | G10: ='Conn DCF'!G51 -> 17249.512
A11: Space EBITDA | B11: -1 | C11: 21 | D11: 653 | E11: ='Space DCF'!E51 -> 629.244 | F11: ='Space DCF'!F51 -> 922.29192 | G11: ='Space DCF'!G51 -> 1451.0726
A12: AI EBITDA | B12: -3973 | C12: -1561 | D12: -1237 | E12: ='AI DCF'!E51 -> -614.592 | F12: ='AI DCF'!F51 -> 113.08493 | G12: ='AI DCF'!G51 -> 983.83887
A13: Total D&A | B13: 2635 | C13: 3824 | D13: 6701 | E13: ='Conn DCF'!E53+'Space DCF'!E53+'AI DCF'!E53 -> 8220.3597 | F13: ='Conn DCF'!F53+'Space DCF'!F53+'AI DCF'!F53 -> 9848.4871 | G13: ='Conn DCF'!G53+'Space DCF'!G53+'AI DCF'!G53 -> 11750.57
A14: Total Capex | B14: -4415 | C14: -11163 | D14: -20737 | E14: ='Conn DCF'!E59+'Space DCF'!E59+'AI DCF'!E59 -> -21510.745 | F14: ='Conn DCF'!F59+'Space DCF'!F59+'AI DCF'!F59 -> -22501.181 | G14: ='Conn DCF'!G59+'Space DCF'!G59+'AI DCF'!G59 -> -24094.152
A15: Net Income (Loss) | B15: -4628 | C15: 791 | D15: -4937 | E15: n/a | F15: n/a | G15: n/a
A18: QUARTERLY — ACTUALS & ESTIMATES (Q1 2026A from S-1; Q2–Q4 2026E phased from annual FY26E)
A19: Line Item ($M) | B19: Q1 2026A | C19: Q2 2026E | D19: Q3 2026E | E19: Q4 2026E | F19: FY2026E (check)
A20: Total Revenue | B20: 4694 | C20: =(E6-B20)*C$24 -> 6275.8208 | D20: =(E6-B20)*D$24 -> 6668.0596 | E20: =(E6-B20)*E$24 -> 6668.0596 | F20: =B20+C20+D20+E20 -> 24305.94
A21: Connectivity Revenue | B21: 3257 | C21: =(E7-B21)*C$24 -> 3986.2592 | D21: =(E7-B21)*D$24 -> 4235.4004 | E21: =(E7-B21)*E$24 -> 4235.4004 | F21: =B21+C21+D21+E21 -> 15714.06
A22: Space Revenue | B22: 619 | C22: =(E8-B22)*C$24 -> 1240.192 | D22: =(E8-B22)*D$24 -> 1317.704 | E22: =(E8-B22)*E$24 -> 1317.704 | F22: =B22+C22+D22+E22 -> 4494.6
A23: AI Revenue | B23: 818 | C23: =(E9-B23)*C$24 -> 1049.3696 | D23: =(E9-B23)*D$24 -> 1114.9552 | E23: =(E9-B23)*E$24 -> 1114.9552 | F23: =B23+C23+D23+E23 -> 4097.28
A24: Phasing Weight (%) | C24: 0.32 | D24: 0.34 | E24: 0.34
A26: ANNUAL VARIANCE — Model Forecast vs Full-Year Actual (enter actual when FY reports)
A27: FY2026 Metric | B27: Forecast | C27: Actual (enter) | D27: Var % | E27: Status
A28: Total Revenue | B28: =E6 -> 24305.94 | D28: =IF(C28="","—",C28/B28-1) -> —
A29: Connectivity Rev | B29: =E7 -> 15714.06 | D29: =IF(C29="","—",C29/B29-1) -> — | E29: =IF(C29="","(awaiting)",IF(ABS(D29)<0.05,"On track",IF(D29>0,"Beat","Miss"))) -> (awaiting)
A30: Space Rev | B30: =E8 -> 4494.6 | D30: =IF(C30="","—",C30/B30-1) -> — | E30: =IF(C30="","(awaiting)",IF(ABS(D30)<0.05,"On track",IF(D30>0,"Beat","Miss"))) -> (awaiting)
A31: AI Rev | B31: =E9 -> 4097.28 | D31: =IF(C31="","—",C31/B31-1) -> — | E31: =IF(C31="","(awaiting)",IF(ABS(D31)<0.05,"On track",IF(D31>0,"Beat","Miss"))) -> (awaiting)
A32: Connectivity EBITDA | B32: =E10 -> 9899.8578 | D32: =IF(C32="","—",C32/B32-1) -> — | E32: =IF(C32="","(awaiting)",IF(ABS(D32)<0.05,"On track",IF(D32>0,"Beat","Miss"))) -> (awaiting)
A33: Space EBITDA | B33: =E11 -> 629.244 | D33: =IF(C33="","—",C33/B33-1) -> — | E33: =IF(C33="","(awaiting)",IF(ABS(D33)<0.05,"On track",IF(D33>0,"Beat","Miss"))) -> (awaiting)
A34: AI EBITDA | B34: =E12 -> -614.592 | D34: =IF(C34="","—",C34/B34-1) -> — | E34: =IF(C34="","(awaiting)",IF(ABS(D34)<0.05,"On track",IF(D34>0,"Beat","Miss"))) -> (awaiting)
A35: Total Capex | B35: =E14 -> -21510.745 | D35: =IF(C35="","—",C35/B35-1) -> — | E35: =IF(C35="","(awaiting)",IF(ABS(D35)<0.05,"On track",IF(D35>0,"Beat","Miss"))) -> (awaiting)
A36: Total Unlevered FCF | B36: ='Conn DCF'!E61+'Space DCF'!E61+'AI DCF'!E61 -> -13279.004 | D36: =IF(C36="","—",C36/B36-1) -> — | E36: =IF(C36="","(awaiting)",IF(ABS(D36)<0.05,"On track",IF(D36>0,"Beat","Miss"))) -> (awaiting)
A38: QUARTERLY VARIANCE — Estimate vs Actual (enter Q actual as reported)
A39: Q2 2026 Metric | B39: Estimate | C39: Actual (enter) | D39: Var % | E39: Status
A40: Total Revenue | B40: =C20 -> 6275.8208 | D40: =IF(C40="","—",C40/B40-1) -> — | E40: =IF(C40="","(awaiting)",IF(ABS(D40)<0.05,"On track",IF(D40>0,"Beat","Miss"))) -> (awaiting)
A41: Connectivity Rev | B41: =C21 -> 3986.2592 | D41: =IF(C41="","—",C41/B41-1) -> — | E41: =IF(C41="","(awaiting)",IF(ABS(D41)<0.05,"On track",IF(D41>0,"Beat","Miss"))) -> (awaiting)
A42: Space Rev | B42: =C22 -> 1240.192 | D42: =IF(C42="","—",C42/B42-1) -> — | E42: =IF(C42="","(awaiting)",IF(ABS(D42)<0.05,"On track",IF(D42>0,"Beat","Miss"))) -> (awaiting)
A43: AI Rev | B43: =C23 -> 1049.3696 | D43: =IF(C43="","—",C43/B43-1) -> — | E43: =IF(C43="","(awaiting)",IF(ABS(D43)<0.05,"On track",IF(D43>0,"Beat","Miss"))) -> (awaiting)
A46: HOW TO UPDATE (maintenance playbook)
A47: STRUCTURE: Line items run DOWN rows; periods run ACROSS columns (JPM/IB convention). Actuals = blue, forecast links = green, formulas = black.
A48: WHEN A QUARTER REPORTS: enter the actual into the Quarterly Variance 'Actual' column (C35:C38). Var% + Beat/Miss computes automatically. Then roll the estimate row (Q2→Q3) by re-pointing B35:B38 to the next quarter's estimate column (D20→E20).
A49: WHEN A FULL YEAR REPORTS: (1) enter the actual into Annual Variance 'Actual' col (C28:C31); (2) append the new FYxxA as a column in the annual block; (3) ask me to RE-BASE the DCF (shift forecast one year, repoint segment base-year links) — that's a structural change.
A50: SEGMENT D&A & CAPEX: this tab carries only TOTAL D&A/capex. Segment-level D&A/capex base values live as blue hardcodes on each segment DCF (row 53 / row 59).
A51: SINGLE SOURCE OF TRUTH: segment revenue & EBITDA base year (FY2025A) live HERE (D7-D12); segment DCFs link to them. Don't hardcode them on the segment tabs.

Sheet Historicals
A1: SpaceX — Historical Financial Statements
A2: Historical Financial Statements | Source: S-1 (SEC EDGAR, Filed May 20, 2026) | $ in Millions
A3: Segments: Space + Connectivity (Starlink) + AI (X / xAI / Grok) | FY2023-FY2025 Audited | Q1 2025-Q1 2026 Unaudited
B5: FY2023 | C5: FY2024 | D5: FY2025 | E5: Q1 2025 | F5: Q1 2026
A6: CONSOLIDATED INCOME STATEMENT
A7: Revenue | B7: 10387 | C7: 14015 | D7: 18674 | E7: 4067 | F7: 4694
A8: Cost of revenue | B8: -6110 | C8: -7996 | D8: -9451 | E8: -1962 | F8: -2388
A9: Gross Profit | B9: =B7+B8 -> 4277 | C9: =C7+C8 -> 6019 | D9: =D7+D8 -> 9223 | E9: =E7+E8 -> 2105 | F9: =F7+F8 -> 2306
A10: Gross Margin % | B10: =B9/B7 -> 0.41176471 | C10: =C9/C7 -> 0.42946843 | D10: =D9/D7 -> 0.49389526 | E10: =E9/E7 -> 0.51758053 | F10: =F9/F7 -> 0.49126545
A11: Research and development | B11: -2105 | C11: -3464 | D11: -8643 | E11: -1557 | F11: -3514
A12: Selling, general & administrative | B12: -1665 | C12: -1813 | D12: -2644 | E12: -493 | F12: -746
A13: Restructuring charges | B13: -237 | C13: -213 | D13: -487 | E13: -4 | F13: 11
A14: Impairment | B14: -3775 | C14: -63 | D14: -38 | E14: -24 | F14: 0
A15: Total costs and expenses | B15: =B8+B11+B12+B13+B14 -> -13892 | C15: =C8+C11+C12+C13+C14 -> -13549 | D15: =D8+D11+D12+D13+D14 -> -21263 | E15: =E8+E11+E12+E13+E14 -> -4040 | F15: =F8+F11+F12+F13+F14 -> -6637
A17: Income (loss) from operations | B17: =B7+B15 -> -3505 | C17: =C7+C15 -> 466 | D17: =D7+D15 -> -2589 | E17: =E7+E15 -> 27 | F17: =F7+F15 -> -1943
A18: Operating Margin % | B18: =B17/B7 -> -0.33744103 | C18: =C17/C7 -> 0.033250089 | D18: =D17/D7 -> -0.13864196 | E18: =E17/E7 -> 0.0066388001 | F18: =F17/F7 -> -0.41393268
A19: Interest expense | B19: -1693 | C19: -1580 | D19: -1945 | E19: -447 | F19: -664
A20: Interest income | B20: 249 | C20: 371 | D20: 492 | E20: 117 | F20: 213
A21: Other income (expense), net | B21: -42 | C21: 985 | D21: -177 | E21: -211 | F21: -1876
A22: Income (loss) before taxes | B22: =B17+B19+B20+B21 -> -4991 | C22: =C17+C19+C20+C21 -> 242 | D22: =D17+D19+D20+D21 -> -4219 | E22: =E17+E19+E20+E21 -> -514 | F22: =F17+F19+F20+F21 -> -4270
A23: Provision for (benefit from) taxes | B23: 363 | C23: 549 | D23: -718 | E23: -14 | F23: -6
A24: Net income (loss) | B24: =B22+B23 -> -4628 | C24: =C22+C23 -> 791 | D24: =D22+D23 -> -4937 | E24: =E22+E23 -> -528 | F24: =F22+F23 -> -4276
A25: Net Margin % | B25: =B24/B7 -> -0.44555695 | C25: =C24/C7 -> 0.056439529 | D25: =D24/D7 -> -0.26437828 | E25: =E24/E7 -> -0.12982542 | F25: =F24/F7 -> -0.91095015
A27: SEGMENT REVENUE BREAKDOWN
A28: Space segment | B28: 3557 | C28: 3796 | D28: 4086 | E28: 865 | F28: 619
A29: Launch Services | B29: 1964 | C29: 2584 | D29: 2576
A30: Launch & Development | B30: 1593 | C30: 1212 | D30: 1510
A31: Connectivity segment | B31: 3869 | C31: 7599 | D31: 11387 | E31: 2475 | F31: 3257
A32: Consumer | B32: 2817 | C32: 4830 | D32: 7208
A33: Enterprise & Government | B33: 1052 | C33: 2769 | D33: 4179
A34: AI segment | B34: 2961 | C34: 2620 | D34: 3201 | E34: 727 | F34: 818
A35: Advertising (X) | B35: 2323 | C35: 1728 | D35: 1844
A36: AI Solutions & Infrastructure | B36: 638 | C36: 892 | D36: 1357
A37: Total Revenue (check) | B37: =B28+B31+B34 -> 10387 | C37: =C28+C31+C34 -> 14015 | D37: =D28+D31+D34 -> 18674 | E37: =E28+E31+E34 -> 4067 | F37: =F28+F31+F34 -> 4694
A39: SEGMENT OPERATING PERFORMANCE
A40: Segment Income (Loss) from Operations
A41: Space | B41: -1 | C41: 21 | D41: -657 | E41: -70 | F41: -662
